Workbook

Sheet Top 50 Shows & Movies
F1: WK-28, 2026 ( 11 Jul 2026 - 17 Jul 2026 )
A7: Week | B7: MARKET | C7: Platform | D7: Content format | E7: PAID/FREE | F7: Content Type | G7: Shows/Live Content | H7: Language | I7: Genre | J7: Release Date | K7: Rank | L7: Reach | M7: Total Time Spent (In Mins) Mn
A8: WK-28,2026 | B8: ALL INDIA | C8: JioHotstar | D8: Live Event | E8: PAID | F8: Sports | G8: England vs India ODI Series 2026 | H8: Bengali,Bhojpuri,English,Haryanvi,Hindi,Kannada,Tamil,Telugu | I8: Sport | J8: 46217 | K8: 1 | L8: 92.983875 | M8: 10187.41
A9: WK-28,2026 | B9: ALL INDIA | C9: Zee5 | D9: Live Event | E9: PAID | F9: Sports | G9: FIFA World Cup 2026 | H9: Bengali,English,Hindi,Malayalam | I9: Sport | J9: 46185 | K9: =K8+1 -> 2 | L9: 54.261232 | M9: 816.84195
A10: WK-28,2026 | B10: ALL INDIA | C10: Amazon Mx Player | D10: AVOD Originals Shows | E10: FREE | F10: Shows | G10: Raktanchal Season 3 | H10: Hindi,Tamil,Telugu | I10: Action,Crime,Drama | J10: 46219 | K10: =K9+1 -> 3 | L10: 31.519333 | M10: 4174.1199
A11: WK-28,2026 | B11: ALL INDIA | C11: Netflix | D11: Svod Originals Shows | E11: PAID | F11: Shows | G11: Lock Upp | H11: Hindi | I11: Reality Tv | J11: 46200 | K11: =K10+1 -> 4 | L11: 24.197959 | M11: 4106.8413
A12: WK-28,2026 | B12: ALL INDIA | C12: Netflix | D12: SVOD Originals Movies | E12: PAID | F12: Movies | G12: Ikka | H12: English,Hindi,Tamil,Telugu | I12: Crime,Drama,Thriller | J12: 46213 | K12: =K11+1 -> 5 | L12: 22.341902 | M12: 1074.2816
A13: WK-28,2026 | B13: ALL INDIA | C13: JioHotstar | D13: Svod Originals Shows | E13: PAID | F13: Shows | G13: Pritam And Pedro | H13: Bengali,Bhojpuri,Haryanvi,Hindi,Kannada,Marathi,Tamil,Telugu | I13: Crime,Drama,Thriller | J13: 46206 | K13: =K12+1 -> 6 | L13: 21.809854 | M13: 1101.1545
A14: WK-28,2026 | B14: ALL INDIA | C14: Amazon Prime Video | D14: Svod Originals Shows | E14: PAID | F14: Shows | G14: Alliance | H14: Hindi | I14: Reality Tv | J14: 46199 | K14: =K13+1 -> 7 | L14: 21.303523 | M14: 1716.4378
A15: WK-28,2026 | B15: ALL INDIA | C15: JioHotstar | D15: Theatrical Movies | E15: PAID | F15: Movies | G15: Chand Mera Dil | H15: Hindi | I15: Drama,Romance | J15: 46220 | K15: =K14+1 -> 8 | L15: 20.892084 | M15: 311.47395
A16: WK-28,2026 | B16: ALL INDIA | C16: Netflix | D16: Svod Originals Shows | E16: PAID | F16: Shows | G16: India’s Got Latent Season 2 | H16: Hindi | I16: Comedy | J16: 46193 | K16: =K15+1 -> 9 | L16: 20.585342 | M16: 1041.7468
A17: WK-28,2026 | B17: ALL INDIA | C17: Amazon Prime Video | D17: Theatrical Movies | E17: PAID | F17: Movies | G17: Ek Din | H17: Hindi,Tamil,Telugu | I17: Drama,Romance | J17: 46220 | K17: =K16+1 -> 10 | L17: 19.822692 | M17: 655.39331
A18: WK-28,2026 | B18: ALL INDIA | C18: Netflix | D18: SVOD Originals Shows | E18: PAID | F18: Shows | G18: The Apartment Job | H18: English,Hindi | I18: Crime,Drama,Thriller | J18: 46214 | K18: =K17+1 -> 11 | L18: 19.571276 | M18: 613
A19: WK-28,2026 | B19: ALL INDIA | C19: JioHotstar | D19: Svod Originals Shows | E19: PAID | F19: Shows | G19: House of the Dragon Season 3 | H19: English,Hindi,Tamil,Telugu | I19: Action,Adventure,Drama | J19: 46195 | K19: =K18+1 -> 12 | L19: 19.419063 | M19: 1189.4553
A20: WK-28,2026 | B20: ALL INDIA | C20: JioHotstar | D20: Theatrical Movies | E20: PAID | F20: Movies | G20: Wuthering Heights | H20: English,Hindi | I20: Drama,Romance | J20: 46216 | K20: =K19+1 -> 13 | L20: 18.791233 | M20: 209.57395
... A57: WK-28,2026 | B57: ALL INDIA | C57: Netflix | D57: SVOD Originals Shows | E57: PAID | F57: Shows | G57: Young Sheldon Season 6 | H57: English | I57: Comedy | J57: 46218 | K57: =K56+1 -> 50 | L57: 12.07726 | M57: 650
C60: Gender
A61: PLATFORM | B61: Total Reach | C61: Male | D61: Female
A62: Netflix | B62: 483.47874 | C62: =VLOOKUP(A:A,'Updated SES'!B:J,8,0) -> 0.49 | D62: =VLOOKUP(A:A,'Updated SES'!B:J,9,0) -> 0.51
A63: JioHotstar | B63: 345.93343 | C63: =VLOOKUP(A:A,'Updated SES'!B:J,8,0) -> 0.625 | D63: =VLOOKUP(A:A,'Updated SES'!B:J,9,0) -> 0.375
A64: Amazon Prime Video | B64: 282.34023 | C64: =VLOOKUP(A:A,'Updated SES'!B:J,8,0) -> 0.52 | D64: =VLOOKUP(A:A,'Updated SES'!B:J,9,0) -> 0.48
A65: Zee5 | B65: 97.136739 | C65: =VLOOKUP(A:A,'Updated SES'!B:J,8,0) -> 0.65 | D65: =VLOOKUP(A:A,'Updated SES'!B:J,9,0) -> 0.35
A66: Amazon Mx Player | B66: 62.244994 | C66: =VLOOKUP(A:A,'Updated SES'!B:J,8,0) -> 0.8 | D66: =VLOOKUP(A:A,'Updated SES'!B:J,9,0) -> 0.2

Sheet Compile data Working
G1: WK-28, 2026 ( 11 Jul 2026 - 17 Jul 2026 )
M3: Genre Weightage%
A4: Week | B4: MARKET | C4: Platform | D4: Live Event | E4: PAID/FREE | F4: Show Type | G4: Shows/Live Content | H4: Language | I4: Release Date | J4: Ranking | K4: Genre | L4: Total Viewers In Mn | M4: Male | N4: Female | O4: Language Weightage % | P4: Ranking Penetration | Q4: Reach | R4: Content format % | S4: Final Reach | T4: WK-28 Reach
A5: Cott Data Servey | B5: ALL INDIA | C5: JioHotstar | D5: Live Event | E5: PAID | F5: Sports | G5: England vs India ODI Series 2026 | H5: Bengali,Bhojpuri,English,Haryanvi,Hindi,Kannada,Tamil,Telugu | I5: 46217 | K5: Sport | L5: =VLOOKUP($C5&$E5,'Updated SES'!A:N,14,0) -> 127.11702 | M5: =VLOOKUP($K5,'Genre Penetration'!A:B,2,0)*VLOOKUP($C5&$E5,'Updated SES'!A:I,9,0) -> 0.5025 | N5: =VLOOKUP(K:K,'Genre Penetration'!A:C,3,0)*VLOOKUP($C5&$E5,'Updated SES'!A:J,10,0) -> 0.0825 | O5: =VLOOKUP($B5,'Language Penetration'!$B$1:$BL$14,MATCH('Compile data Working'!$H5,'Language Penetration'!$B$1:$BL$1,0),0) -> 0.19285714 | P5: =IF(ISBLANK(J5),RANDBETWEEN(1,2)&"%",IF(J5=1,RANDBETWEEN(35,40)&"%",IF(J5=2,RANDBETWEEN(30,35)&"%",IF(J5=3,RANDBETWEEN(25,30)&"%",IF(J5=4,RANDBETWEEN(20,25)&"%",IF(J5=5,RANDBETWEEN(15,20)&"%",IF(J5=6,RANDBETWEEN(10,15)&"%",IF(J5=7,RANDBETWEEN(8,10)&"%",IF(J5=8,RANDBETWEEN(6,8)&"%",IF(J5=9,RANDBETWEEN(4,6)&"%",IF(J5=10,RANDBETWEEN(2,4)&"%",""))))))))))) -> 2% | Q5: =IFERROR(L5*(M5+N5)*O5*P5,RANDBETWEEN(1,2)%*L5*(M5+N5)*O5) -> 0.28683048 | R5: =VLOOKUP(D:D,ranking!W:X,2,0) -> 0.1 | S5: =R5*Q5 -> 0.028683048 | T5: 92.983875
A6: Cott Data Servey | B6: ALL INDIA | C6: Zee5 | D6: Live Event | E6: PAID | F6: Sports | G6: FIFA World Cup 2026 | H6: Bengali,English,Hindi,Malayalam | I6: 46185 | K6: Sport | L6: =VLOOKUP($C6&$E6,'Updated SES'!A:N,14,0) -> 60.152 | M6: =VLOOKUP($K6,'Genre Penetration'!A:B,2,0)*VLOOKUP($C6&$E6,'Updated SES'!A:I,9,0) -> 0.4875 | N6: =VLOOKUP(K:K,'Genre Penetration'!A:C,3,0)*VLOOKUP($C6&$E6,'Updated SES'!A:J,10,0) -> 0.0875 | O6: =VLOOKUP($B6,'Language Penetration'!$B$1:$BL$14,MATCH('Compile data Working'!$H132,'Language Penetration'!$B$1:$BL$1,0),0) -> 0.12 | P6: =IF(ISBLANK(J6),RANDBETWEEN(1,2)&"%",IF(J6=1,RANDBETWEEN(35,40)&"%",IF(J6=2,RANDBETWEEN(30,35)&"%",IF(J6=3,RANDBETWEEN(25,30)&"%",IF(J6=4,RANDBETWEEN(20,25)&"%",IF(J6=5,RANDBETWEEN(15,20)&"%",IF(J6=6,RANDBETWEEN(10,15)&"%",IF(J6=7,RANDBETWEEN(8,10)&"%",IF(J6=8,RANDBETWEEN(6,8)&"%",IF(J6=9,RANDBETWEEN(4,6)&"%",IF(J6=10,RANDBETWEEN(2,4)&"%",""))))))))))) -> 2% | Q6: =IFERROR(L6*(M6+N6)*O6*P6,RANDBETWEEN(1,2)%*L6*(M6+N6)*O6) -> 0.08300976 | R6: =VLOOKUP(D:D,ranking!W:X,2,0) -> 0.1 | S6: =R6*Q6 -> 0.008300976 | T6: 54.261232
A7: WK-28'2026 | B7: ALL INDIA | C7: Amazon Mx Player | D7: AVOD Originals Shows | E7: FREE | F7: Shows | G7: Raktanchal Season 3 | H7: Hindi,Tamil,Telugu | I7: 46219 | K7: Action,Crime,Drama | L7: =VLOOKUP($C7&$E7,'Updated SES'!A:N,14,0) -> 78.93987 | M7: =VLOOKUP($K7,'Genre Penetration'!A:B,2,0)*VLOOKUP($C7&$E7,'Updated SES'!A:I,9,0) -> 0.488 | N7: =VLOOKUP(K:K,'Genre Penetration'!A:C,3,0)*VLOOKUP($C7&$E7,'Updated SES'!A:J,10,0) -> 0.078 | O7: =VLOOKUP($B7,'Language Penetration'!$B$1:$BL$14,MATCH('Compile data Working'!$H38,'Language Penetration'!$B$1:$BL$1,0),0) -> 0.2625 | P7: =IF(ISBLANK(J7),RANDBETWEEN(1,2)&"%",IF(J7=1,RANDBETWEEN(35,40)&"%",IF(J7=2,RANDBETWEEN(30,35)&"%",IF(J7=3,RANDBETWEEN(25,30)&"%",IF(J7=4,RANDBETWEEN(20,25)&"%",IF(J7=5,RANDBETWEEN(15,20)&"%",IF(J7=6,RANDBETWEEN(10,15)&"%",IF(J7=7,RANDBETWEEN(8,10)&"%",IF(J7=8,RANDBETWEEN(6,8)&"%",IF(J7=9,RANDBETWEEN(4,6)&"%",IF(J7=10,RANDBETWEEN(2,4)&"%",""))))))))))) -> 2% | Q7: =IFERROR(L7*(M7+N7)*O7*P7,RANDBETWEEN(1,2)%*L7*(M7+N7)*O7) -> 0.23456982 | R7: =VLOOKUP(D:D,ranking!W:X,2,0) -> 0.6 | S7: =R7*Q7 -> 0.14074189 | T7: 31.519333
A8: Trending Top 10 | B8: ALL INDIA | C8: Netflix | D8: Svod Originals Shows | E8: PAID | F8: Shows | G8: Lock Upp | H8: Hindi | I8: 46200 | J8: 2 | K8: Reality Tv | L8: =VLOOKUP($C8&$E8,'Updated SES'!A:N,14,0) -> 55.4592 | M8: =VLOOKUP($K8,'Genre Penetration'!A:B,2,0)*VLOOKUP($C8&$E8,'Updated SES'!A:I,9,0) -> 0.196 | N8: =VLOOKUP(K:K,'Genre Penetration'!A:C,3,0)*VLOOKUP($C8&$E8,'Updated SES'!A:J,10,0) -> 0.306 | O8: =VLOOKUP($B8,'Language Penetration'!$B$1:$BL$14,MATCH('Compile data Working'!$H98,'Language Penetration'!$B$1:$BL$1,0),0) -> 0.204 | P8: =IF(ISBLANK(J8),RANDBETWEEN(1,2)&"%",IF(J8=1,RANDBETWEEN(35,40)&"%",IF(J8=2,RANDBETWEEN(30,35)&"%",IF(J8=3,RANDBETWEEN(25,30)&"%",IF(J8=4,RANDBETWEEN(20,25)&"%",IF(J8=5,RANDBETWEEN(15,20)&"%",IF(J8=6,RANDBETWEEN(10,15)&"%",IF(J8=7,RANDBETWEEN(8,10)&"%",IF(J8=8,RANDBETWEEN(6,8)&"%",IF(J8=9,RANDBETWEEN(4,6)&"%",IF(J8=10,RANDBETWEEN(2,4)&"%",""))))))))))) -> 31% | Q8: =IFERROR(L8*(M8+N8)*O8*P8,RANDBETWEEN(1,2)%*L8*(M8+N8)*O8) -> 1.7606344 | R8: =VLOOKUP(D:D,ranking!W:X,2,0) -> 0.6 | S8: =R8*Q8 -> 1.0563806 | T8: 24.197959
A9: Trending Top 10 | B9: ALL INDIA | C9: Netflix | D9: SVOD Originals Movies | E9: PAID | F9: Movies | G9: Ikka | H9: English,Hindi,Tamil,Telugu | I9: 46213 | J9: 1 | K9: Crime,Drama,Thriller | L9: =VLOOKUP($C9&$E9,'Updated SES'!A:N,14,0) -> 55.4592 | M9: =VLOOKUP($K9,'Genre Penetration'!A:B,2,0)*VLOOKUP($C9&$E9,'Updated SES'!A:I,9,0) -> 0.3528 | N9: =VLOOKUP(K:K,'Genre Penetration'!A:C,3,0)*VLOOKUP($C9&$E9,'Updated SES'!A:J,10,0) -> 0.1428 | O9: =VLOOKUP($B9,'Language Penetration'!$B$1:$BL$14,MATCH('Compile data Working'!$H90,'Language Penetration'!$B$1:$BL$1,0),0) -> 0.204 | P9: =IF(ISBLANK(J9),RANDBETWEEN(1,2)&"%",IF(J9=1,RANDBETWEEN(35,40)&"%",IF(J9=2,RANDBETWEEN(30,35)&"%",IF(J9=3,RANDBETWEEN(25,30)&"%",IF(J9=4,RANDBETWEEN(20,25)&"%",IF(J9=5,RANDBETWEEN(15,20)&"%",IF(J9=6,RANDBETWEEN(10,15)&"%",IF(J9=7,RANDBETWEEN(8,10)&"%",IF(J9=8,RANDBETWEEN(6,8)&"%",IF(J9=9,RANDBETWEEN(4,6)&"%",IF(J9=10,RANDBETWEEN(2,4)&"%",""))))))))))) -> 35% | Q9: =IFERROR(L9*(M9+N9)*O9*P9,RANDBETWEEN(1,2)%*L9*(M9+N9)*O9) -> 1.9624704 | R9: =VLOOKUP(D:D,ranking!W:X,2,0) -> 0.8 | S9: =R9*Q9 -> 1.5699763 | T9: 22.341902
A10: Trending Top 10 | B10: ALL INDIA | C10: JioHotstar | D10: Svod Originals Shows | E10: PAID | F10: Shows | G10: Pritam And Pedro | H10: Bengali,Bhojpuri,Haryanvi,Hindi,Kannada,Marathi,Tamil,Telugu | I10: 46206 | J10: 4 | K10: Crime,Drama,Thriller | L10: =VLOOKUP($C10&$E10,'Updated SES'!A:N,14,0) -> 127.11702 | M10: =VLOOKUP($K10,'Genre Penetration'!A:B,2,0)*VLOOKUP($C10&$E10,'Updated SES'!A:I,9,0) -> 0.4824 | N10: =VLOOKUP(K:K,'Genre Penetration'!A:C,3,0)*VLOOKUP($C10&$E10,'Updated SES'!A:J,10,0) -> 0.0924 | O10: =VLOOKUP($B10,'Language Penetration'!$B$1:$BL$14,MATCH('Compile data Working'!$H86,'Language Penetration'!$B$1:$BL$1,0),0) -> 0.1 | P10: =IF(ISBLANK(J10),RANDBETWEEN(1,2)&"%",IF(J10=1,RANDBETWEEN(35,40)&"%",IF(J10=2,RANDBETWEEN(30,35)&"%",IF(J10=3,RANDBETWEEN(25,30)&"%",IF(J10=4,RANDBETWEEN(20,25)&"%",IF(J10=5,RANDBETWEEN(15,20)&"%",IF(J10=6,RANDBETWEEN(10,15)&"%",IF(J10=7,RANDBETWEEN(8,10)&"%",IF(J10=8,RANDBETWEEN(6,8)&"%",IF(J10=9,RANDBETWEEN(4,6)&"%",IF(J10=10,RANDBETWEEN(2,4)&"%",""))))))))))) -> 23% | Q10: =IFERROR(L10*(M10+N10)*O10*P10,RANDBETWEEN(1,2)%*L10*(M10+N10)*O10) -> 1.6805379 | R10: =VLOOKUP(D:D,ranking!W:X,2,0) -> 0.6 | S10: =R10*Q10 -> 1.0083227 | T10: 21.809854
A11: Trending Top 10 | B11: ALL INDIA | C11: Amazon Prime Video | D11: Svod Originals Shows | E11: PAID | F11: Shows | G11: Alliance | H11: Hindi | I11: 46199 | J11: 1 | K11: Reality Tv | L11: =VLOOKUP($C11&$E11,'Updated SES'!A:N,14,0) -> 36.49824 | M11: =VLOOKUP($K11,'Genre Penetration'!A:B,2,0)*VLOOKUP($C11&$E11,'Updated SES'!A:I,9,0) -> 0.208 | N11: =VLOOKUP(K:K,'Genre Penetration'!A:C,3,0)*VLOOKUP($C11&$E11,'Updated SES'!A:J,10,0) -> 0.288 | O11: =VLOOKUP($B11,'Language Penetration'!$B$1:$BL$14,MATCH('Compile data Working'!$H76,'Language Penetration'!$B$1:$BL$1,0),0) -> 0.6 | P11: =IF(ISBLANK(J11),RANDBETWEEN(1,2)&"%",IF(J11=1,RANDBETWEEN(35,40)&"%",IF(J11=2,RANDBETWEEN(30,35)&"%",IF(J11=3,RANDBETWEEN(25,30)&"%",IF(J11=4,RANDBETWEEN(20,25)&"%",IF(J11=5,RANDBETWEEN(15,20)&"%",IF(J11=6,RANDBETWEEN(10,15)&"%",IF(J11=7,RANDBETWEEN(8,10)&"%",IF(J11=8,RANDBETWEEN(6,8)&"%",IF(J11=9,RANDBETWEEN(4,6)&"%",IF(J11=10,RANDBETWEEN(2,4)&"%",""))))))))))) -> 35% | Q11: =IFERROR(L11*(M11+N11)*O11*P11,RANDBETWEEN(1,2)%*L11*(M11+N11)*O11) -> 3.8016567 | R11: =VLOOKUP(D:D,ranking!W:X,2,0) -> 0.6 | S11: =R11*Q11 -> 2.280994 | T11: 21.303523
A12: WK-28'2026 | B12: ALL INDIA | C12: JioHotstar | D12: Theatrical Movies | E12: PAID | F12: Movies | G12: Chand Mera Dil | H12: Hindi | I12: 46220 | K12: Drama,Romance | L12: =VLOOKUP($C12&$E12,'Updated SES'!A:N,14,0) -> 127.11702 | M12: =VLOOKUP($K12,'Genre Penetration'!A:B,2,0)*VLOOKUP($C12&$E12,'Updated SES'!A:I,9,0) -> 0.268 | N12: =VLOOKUP(K:K,'Genre Penetration'!A:C,3,0)*VLOOKUP($C12&$E12,'Updated SES'!A:J,10,0) -> 0.198 | O12: =VLOOKUP($B12,'Language Penetration'!$B$1:$BL$14,MATCH('Compile data Working'!$H45,'Language Penetration'!$B$1:$BL$1,0),0) -> 0.4 | P12: =IF(ISBLANK(J12),RANDBETWEEN(1,2)&"%",IF(J12=1,RANDBETWEEN(35,40)&"%",IF(J12=2,RANDBETWEEN(30,35)&"%",IF(J12=3,RANDBETWEEN(25,30)&"%",IF(J12=4,RANDBETWEEN(20,25)&"%",IF(J12=5,RANDBETWEEN(15,20)&"%",IF(J12=6,RANDBETWEEN(10,15)&"%",IF(J12=7,RANDBETWEEN(8,10)&"%",IF(J12=8,RANDBETWEEN(6,8)&"%",IF(J12=9,RANDBETWEEN(4,6)&"%",IF(J12=10,RANDBETWEEN(2,4)&"%",""))))))))))) -> 1% | Q12: =IFERROR(L12*(M12+N12)*O12*P12,RANDBETWEEN(1,2)%*L12*(M12+N12)*O12) -> 0.23694613 | R12: =VLOOKUP(D:D,ranking!W:X,2,0) -> 0.7 | S12: =R12*Q12 -> 0.16586229 | T12: 20.892084
A13: Trending Top 10 | B13: ALL INDIA | C13: Netflix | D13: Svod Originals Shows | E13: PAID | F13: Shows | G13: India’s Got Latent Season 2 | H13: Hindi | I13: 46193 | J13: 1 | K13: Comedy | L13: =VLOOKUP($C13&$E13,'Updated SES'!A:N,14,0) -> 55.4592 | M13: =VLOOKUP($K13,'Genre Penetration'!A:B,2,0)*VLOOKUP($C13&$E13,'Updated SES'!A:I,9,0) -> 0.2205 | N13: =VLOOKUP(K:K,'Genre Penetration'!A:C,3,0)*VLOOKUP($C13&$E13,'Updated SES'!A:J,10,0) -> 0.2805 | O13: =VLOOKUP($B13,'Language Penetration'!$B$1:$BL$14,MATCH('Compile data Working'!$H97,'Language Penetration'!$B$1:$BL$1,0),0) -> 0.12 | P13: =IF(ISBLANK(J13),RANDBETWEEN(1,2)&"%",IF(J13=1,RANDBETWEEN(35,40)&"%",IF(J13=2,RANDBETWEEN(30,35)&"%",IF(J13=3,RANDBETWEEN(25,30)&"%",IF(J13=4,RANDBETWEEN(20,25)&"%",IF(J13=5,RANDBETWEEN(15,20)&"%",IF(J13=6,RANDBETWEEN(10,15)&"%",IF(J13=7,RANDBETWEEN(8,10)&"%",IF(J13=8,RANDBETWEEN(6,8)&"%",IF(J13=9,RANDBETWEEN(4,6)&"%",IF(J13=10,RANDBETWEEN(2,4)&"%",""))))))))))) -> 36% | Q13: =IFERROR(L13*(M13+N13)*O13*P13,RANDBETWEEN(1,2)%*L13*(M13+N13)*O13) -> 1.2003146 | R13: =VLOOKUP(D:D,ranking!W:X,2,0) -> 0.6 | S13: =R13*Q13 -> 0.72018873 | T13: 20.585342
A14: WK-28'2026 | B14: ALL INDIA | C14: Amazon Prime Video | D14: Theatrical Movies | E14: PAID | F14: Movies | G14: Ek Din | H14: Hindi,Tamil,Telugu | I14: 46220 | K14: Drama,Romance | L14: =VLOOKUP($C14&$E14,'Updated SES'!A:N,14,0) -> 36.49824 | M14: =VLOOKUP($K14,'Genre Penetration'!A:B,2,0)*VLOOKUP($C14&$E14,'Updated SES'!A:I,9,0) -> 0.208 | N14: =VLOOKUP(K:K,'Genre Penetration'!A:C,3,0)*VLOOKUP($C14&$E14,'Updated SES'!A:J,10,0) -> 0.288 | O14: =VLOOKUP($B14,'Language Penetration'!$B$1:$BL$14,MATCH('Compile data Working'!$H49,'Language Penetration'!$B$1:$BL$1,0),0) -> 0.2 | P14: =IF(ISBLANK(J14),RANDBETWEEN(1,2)&"%",IF(J14=1,RANDBETWEEN(35,40)&"%",IF(J14=2,RANDBETWEEN(30,35)&"%",IF(J14=3,RANDBETWEEN(25,30)&"%",IF(J14=4,RANDBETWEEN(20,25)&"%",IF(J14=5,RANDBETWEEN(15,20)&"%",IF(J14=6,RANDBETWEEN(10,15)&"%",IF(J14=7,RANDBETWEEN(8,10)&"%",IF(J14=8,RANDBETWEEN(6,8)&"%",IF(J14=9,RANDBETWEEN(4,6)&"%",IF(J14=10,RANDBETWEEN(2,4)&"%",""))))))))))) -> 1% | Q14: =IFERROR(L14*(M14+N14)*O14*P14,RANDBETWEEN(1,2)%*L14*(M14+N14)*O14) -> 0.036206254 | R14: =VLOOKUP(D:D,ranking!W:X,2,0) -> 0.7 | S14: =R14*Q14 -> 0.025344378 | T14: 19.822692
A15: WK-28'2026 | B15: ALL INDIA | C15: Netflix | D15: SVOD Originals Shows | E15: PAID | F15: Shows | G15: The Apartment Job | H15: English,Hindi | I15: 46214 | K15: Crime,Drama,Thriller | L15: =VLOOKUP($C15&$E15,'Updated SES'!A:N,14,0) -> 55.4592 | M15: =VLOOKUP($K15,'Genre Penetration'!A:B,2,0)*VLOOKUP($C15&$E15,'Updated SES'!A:I,9,0) -> 0.3528 | N15: =VLOOKUP(K:K,'Genre Penetration'!A:C,3,0)*VLOOKUP($C15&$E15,'Updated SES'!A:J,10,0) -> 0.1428 | O15: =VLOOKUP($B15,'Language Penetration'!$B$1:$BL$14,MATCH('Compile data Working'!$H9,'Language Penetration'!$B$1:$BL$1,0),0) -> 0.2625 | P15: =IF(ISBLANK(J15),RANDBETWEEN(1,2)&"%",IF(J15=1,RANDBETWEEN(35,40)&"%",IF(J15=2,RANDBETWEEN(30,35)&"%",IF(J15=3,RANDBETWEEN(25,30)&"%",IF(J15=4,RANDBETWEEN(20,25)&"%",IF(J15=5,RANDBETWEEN(15,20)&"%",IF(J15=6,RANDBETWEEN(10,15)&"%",IF(J15=7,RANDBETWEEN(8,10)&"%",IF(J15=8,RANDBETWEEN(6,8)&"%",IF(J15=9,RANDBETWEEN(4,6)&"%",IF(J15=10,RANDBETWEEN(2,4)&"%",""))))))))))) -> 1% | Q15: =IFERROR(L15*(M15+N15)*O15*P15,RANDBETWEEN(1,2)%*L15*(M15+N15)*O15) -> 0.072149646 | R15: =VLOOKUP(D:D,ranking!W:X,2,0) -> 0.6 | S15: =R15*Q15 -> 0.043289788 | T15: 19.571276
A16: Trending Top 10 | B16: ALL INDIA | C16: JioHotstar | D16: Svod Originals Shows | E16: PAID | F16: Shows | G16: House of the Dragon Season 3 | H16: English,Hindi,Tamil,Telugu | I16: 46195 | J16: 5 | K16: Action,Adventure,Drama | L16: =VLOOKUP($C16&$E16,'Updated SES'!A:N,14,0) -> 127.11702 | M16: =VLOOKUP($K16,'Genre Penetration'!A:B,2,0)*VLOOKUP($C16&$E16,'Updated SES'!A:I,9,0) -> 0.3886 | N16: =VLOOKUP(K:K,'Genre Penetration'!A:C,3,0)*VLOOKUP($C16&$E16,'Updated SES'!A:J,10,0) -> 0.1386 | O16: =VLOOKUP($B16,'Language Penetration'!$B$1:$BL$14,MATCH('Compile data Working'!$H87,'Language Penetration'!$B$1:$BL$1,0),0) -> 0.6 | P16: =IF(ISBLANK(J16),RANDBETWEEN(1,2)&"%",IF(J16=1,RANDBETWEEN(35,40)&"%",IF(J16=2,RANDBETWEEN(30,35)&"%",IF(J16=3,RANDBETWEEN(25,30)&"%",IF(J16=4,RANDBETWEEN(20,25)&"%",IF(J16=5,RANDBETWEEN(15,20)&"%",IF(J16=6,RANDBETWEEN(10,15)&"%",IF(J16=7,RANDBETWEEN(8,10)&"%",IF(J16=8,RANDBETWEEN(6,8)&"%",IF(J16=9,RANDBETWEEN(4,6)&"%",IF(J16=10,RANDBETWEEN(2,4)&"%",""))))))))))) -> 16% | Q16: =IFERROR(L16*(M16+N16)*O16*P16,RANDBETWEEN(1,2)%*L16*(M16+N16)*O16) -> 6.4335449 | R16: =VLOOKUP(D:D,ranking!W:X,2,0) -> 0.6 | S16: =R16*Q16 -> 3.860127 | T16: 19.419063
A17: WK-28'2026 | B17: ALL INDIA | C17: JioHotstar | D17: Theatrical Movies | E17: PAID | F17: Movies | G17: Wuthering Heights | H17: English,Hindi | I17: 46216 | K17: Drama,Romance | L17: =VLOOKUP($C17&$E17,'Updated SES'!A:N,14,0) -> 127.11702 | M17: =VLOOKUP($K17,'Genre Penetration'!A:B,2,0)*VLOOKUP($C17&$E17,'Updated SES'!A:I,9,0) -> 0.268 | N17: =VLOOKUP(K:K,'Genre Penetration'!A:C,3,0)*VLOOKUP($C17&$E17,'Updated SES'!A:J,10,0) -> 0.198 | O17: =VLOOKUP($B17,'Language Penetration'!$B$1:$BL$14,MATCH('Compile data Working'!$H17,'Language Penetration'!$B$1:$BL$1,0),0) -> 0.4 | P17: =IF(ISBLANK(J17),RANDBETWEEN(1,2)&"%",IF(J17=1,RANDBETWEEN(35,40)&"%",IF(J17=2,RANDBETWEEN(30,35)&"%",IF(J17=3,RANDBETWEEN(25,30)&"%",IF(J17=4,RANDBETWEEN(20,25)&"%",IF(J17=5,RANDBETWEEN(15,20)&"%",IF(J17=6,RANDBETWEEN(10,15)&"%",IF(J17=7,RANDBETWEEN(8,10)&"%",IF(J17=8,RANDBETWEEN(6,8)&"%",IF(J17=9,RANDBETWEEN(4,6)&"%",IF(J17=10,RANDBETWEEN(2,4)&"%",""))))))))))) -> 2% | Q17: =IFERROR(L17*(M17+N17)*O17*P17,RANDBETWEEN(1,2)%*L17*(M17+N17)*O17) -> 0.47389225 | R17: =VLOOKUP(D:D,ranking!W:X,2,0) -> 0.7 | S17: =R17*Q17 -> 0.33172458 | T17: 18.791233
A18: Trending Top 10 | B18: ALL INDIA | C18: Netflix | D18: Theatrical Movies | E18: PAID | F18: Movies | G18: Pati Patni Aur Woh Do | H18: Hindi | I18: 46213 | J18: 2 | K18: Comedy,Drama,Romance | L18: =VLOOKUP($C18&$E18,'Updated SES'!A:N,14,0) -> 55.4592 | M18: =VLOOKUP($K18,'Genre Penetration'!A:B,2,0)*VLOOKUP($C18&$E18,'Updated SES'!A:I,9,0) -> 0.1813 | N18: =VLOOKUP(K:K,'Genre Penetration'!A:C,3,0)*VLOOKUP($C18&$E18,'Updated SES'!A:J,10,0) -> 0.3213 | O18: =VLOOKUP($B18,'Language Penetration'!$B$1:$BL$14,MATCH('Compile data Working'!$H91,'Language Penetration'!$B$1:$BL$1,0),0) -> 0.6 | P18: =IF(ISBLANK(J18),RANDBETWEEN(1,2)&"%",IF(J18=1,RANDBETWEEN(35,40)&"%",IF(J18=2,RANDBETWEEN(30,35)&"%",IF(J18=3,RANDBETWEEN(25,30)&"%",IF(J18=4,RANDBETWEEN(20,25)&"%",IF(J18=5,RANDBETWEEN(15,20)&"%",IF(J18=6,RANDBETWEEN(10,15)&"%",IF(J18=7,RANDBETWEEN(8,10)&"%",IF(J18=8,RANDBETWEEN(6,8)&"%",IF(J18=9,RANDBETWEEN(4,6)&"%",IF(J18=10,RANDBETWEEN(2,4)&"%",""))))))))))) -> 30% | Q18: =IFERROR(L18*(M18+N18)*O18*P18,RANDBETWEEN(1,2)%*L18*(M18+N18)*O18) -> 5.0172829 | R18: =VLOOKUP(D:D,ranking!W:X,2,0) -> 0.7 | S18: =R18*Q18 -> 3.512098 | T18: 18.315602
A19: WK-28'2026 | B19: ALL INDIA | C19: Amazon Prime Video | D19: Theatrical Movies | E19: PAID | F19: Movies | G19: Passenger | H19: English,Hindi | I19: 46216 | K19: Horror,Thriller | L19: =VLOOKUP($C19&$E19,'Updated SES'!A:N,14,0) -> 36.49824 | M19: =VLOOKUP($K19,'Genre Penetration'!A:B,2,0)*VLOOKUP($C19&$E19,'Updated SES'!A:I,9,0) -> 0.364 | N19: =VLOOKUP(K:K,'Genre Penetration'!A:C,3,0)*VLOOKUP($C19&$E19,'Updated SES'!A:J,10,0) -> 0.144 | O19: =VLOOKUP($B19,'Language Penetration'!$B$1:$BL$14,MATCH('Compile data Working'!$H14,'Language Penetration'!$B$1:$BL$1,0),0) -> 0.28333333 | P19: =IF(ISBLANK(J19),RANDBETWEEN(1,2)&"%",IF(J19=1,RANDBETWEEN(35,40)&"%",IF(J19=2,RANDBETWEEN(30,35)&"%",IF(J19=3,RANDBETWEEN(25,30)&"%",IF(J19=4,RANDBETWEEN(20,25)&"%",IF(J19=5,RANDBETWEEN(15,20)&"%",IF(J19=6,RANDBETWEEN(10,15)&"%",IF(J19=7,RANDBETWEEN(8,10)&"%",IF(J19=8,RANDBETWEEN(6,8)&"%",IF(J19=9,RANDBETWEEN(4,6)&"%",IF(J19=10,RANDBETWEEN(2,4)&"%",""))))))))))) -> 1% | Q19: =IFERROR(L19*(M19+N19)*O19*P19,RANDBETWEEN(1,2)%*L19*(M19+N19)*O19) -> 0.052533133 | R19: =VLOOKUP(D:D,ranking!W:X,2,0) -> 0.7 | S19: =R19*Q19 -> 0.036773193 | T19: 18.170801
A20: Trending Top 10 | B20: ALL INDIA | C20: Amazon Prime Video | D20: Svod Originals Shows | E20: PAID | F20: Shows | G20: Gram Chikitsalay S2 | H20: Hindi | I20: 46196 | J20: 3 | K20: Comedy,Drama | L20: =VLOOKUP($C20&$E20,'Updated SES'!A:N,14,0) -> 36.49824 | M20: =VLOOKUP($K20,'Genre Penetration'!A:B,2,0)*VLOOKUP($C20&$E20,'Updated SES'!A:I,9,0) -> 0.2444 | N20: =VLOOKUP(K:K,'Genre Penetration'!A:C,3,0)*VLOOKUP($C20&$E20,'Updated SES'!A:J,10,0) -> 0.2544 | O20: =VLOOKUP($B20,'Language Penetration'!$B$1:$BL$14,MATCH('Compile data Working'!$H77,'Language Penetration'!$B$1:$BL$1,0),0) -> 0.2 | P20: =IF(ISBLANK(J20),RANDBETWEEN(1,2)&"%",IF(J20=1,RANDBETWEEN(35,40)&"%",IF(J20=2,RANDBETWEEN(30,35)&"%",IF(J20=3,RANDBETWEEN(25,30)&"%",IF(J20=4,RANDBETWEEN(20,25)&"%",IF(J20=5,RANDBETWEEN(15,20)&"%",IF(J20=6,RANDBETWEEN(10,15)&"%",IF(J20=7,RANDBETWEEN(8,10)&"%",IF(J20=8,RANDBETWEEN(6,8)&"%",IF(J20=9,RANDBETWEEN(4,6)&"%",IF(J20=10,RANDBETWEEN(2,4)&"%",""))))))))))) -> 29% | Q20: =IFERROR(L20*(M20+N20)*O20*P20,RANDBETWEEN(1,2)%*L20*(M20+N20)*O20) -> 1.0559087 | R20: =VLOOKUP(D:D,ranking!W:X,2,0) -> 0.6 | S20: =R20*Q20 -> 0.63354521 | T20: 17.147691
A21: Trending Top 10 | B21: ALL INDIA | C21: Amazon Prime Video | D21: Svod Originals Shows | E21: PAID | F21: Shows | G21: Isakapatnam | H21: Hindi,Kannada,Malayalam,Tamil,Telugu | I21: 46205 | J21: 7 | K21: Action,Crime,Drama | L21: =VLOOKUP($C21&$E21,'Updated SES'!A:N,14,0) -> 36.49824 | M21: =VLOOKUP($K21,'Genre Penetration'!A:B,2,0)*VLOOKUP($C21&$E21,'Updated SES'!A:I,9,0) -> 0.3172 | N21: =VLOOKUP(K:K,'Genre Penetration'!A:C,3,0)*VLOOKUP($C21&$E21,'Updated SES'!A:J,10,0) -> 0.1872 | O21: =VLOOKUP($B21,'Language Penetration'!$B$1:$BL$14,MATCH('Compile data Working'!$H81,'Language Penetration'!$B$1:$BL$1,0),0) -> 0.2625 | P21: =IF(ISBLANK(J21),RANDBETWEEN(1,2)&"%",IF(J21=1,RANDBETWEEN(35,40)&"%",IF(J21=2,RANDBETWEEN(30,35)&"%",IF(J21=3,RANDBETWEEN(25,30)&"%",IF(J21=4,RANDBETWEEN(20,25)&"%",IF(J21=5,RANDBETWEEN(15,20)&"%",IF(J21=6,RANDBETWEEN(10,15)&"%",IF(J21=7,RANDBETWEEN(8,10)&"%",IF(J21=8,RANDBETWEEN(6,8)&"%",IF(J21=9,RANDBETWEEN(4,6)&"%",IF(J21=10,RANDBETWEEN(2,4)&"%",""))))))))))) -> 8% | Q21: =IFERROR(L21*(M21+N21)*O21*P21,RANDBETWEEN(1,2)%*L21*(M21+N21)*O21) -> 0.38660396 | R21: =VLOOKUP(D:D,ranking!W:X,2,0) -> 0.6 | S21: =R21*Q21 -> 0.23196237 | T21: 16.765524
A22: Trending Top 10 | B22: ALL INDIA | C22: JioHotstar | D22: Svod Originals Shows | E22: PAID | F22: Shows | G22: Thukra Ke Mera Pyaar Season 2 | H22: Bengali,Bhojpuri,Hindi,Kannada,Malayalam,Marathi,Tamil,Telugu | I22: 46192 | J22: 1 | K22: Romance | L22: =VLOOKUP($C22&$E22,'Updated SES'!A:N,14,0) -> 127.11702 | M22: =VLOOKUP($K22,'Genre Penetration'!A:B,2,0)*VLOOKUP($C22&$E22,'Updated SES'!A:I,9,0) -> 0.3015 | N22: =VLOOKUP(K:K,'Genre Penetration'!A:C,3,0)*VLOOKUP($C22&$E22,'Updated SES'!A:J,10,0) -> 0.1815 | O22: =VLOOKUP($B22,'Language Penetration'!$B$1:$BL$14,MATCH('Compile data Working'!$H84,'Language Penetration'!$B$1:$BL$1,0),0) -> 0.6 | P22: =IF(ISBLANK(J22),RANDBETWEEN(1,2)&"%",IF(J22=1,RANDBETWEEN(35,40)&"%",IF(J22=2,RANDBETWEEN(30,35)&"%",IF(J22=3,RANDBETWEEN(25,30)&"%",IF(J22=4,RANDBETWEEN(20,25)&"%",IF(J22=5,RANDBETWEEN(15,20)&"%",IF(J22=6,RANDBETWEEN(10,15)&"%",IF(J22=7,RANDBETWEEN(8,10)&"%",IF(J22=8,RANDBETWEEN(6,8)&"%",IF(J22=9,RANDBETWEEN(4,6)&"%",IF(J22=10,RANDBETWEEN(2,4)&"%",""))))))))))) -> 39% | Q22: =IFERROR(L22*(M22+N22)*O22*P22,RANDBETWEEN(1,2)%*L22*(M22+N22)*O22) -> 14.36702 | R22: =VLOOKUP(D:D,ranking!W:X,2,0) -> 0.6 | S22: =R22*Q22 -> 8.6202119 | T22: 16.744785
A23: Trending Top 10 | B23: ALL INDIA | C23: JioHotstar | D23: Tv Catch-Up | E23: PAID | F23: Tv catchup | G23: Laughter Chefs S3 | H23: Hindi | I23: 45983 | J23: 2 | K23: Comedy,Reality-Tv | L23: =VLOOKUP($C23&$E23,'Updated SES'!A:N,14,0) -> 127.11702 | M23: =VLOOKUP($K23,'Genre Penetration'!A:B,2,0)*VLOOKUP($C23&$E23,'Updated SES'!A:I,9,0) -> 0.335 | N23: =VLOOKUP(K:K,'Genre Penetration'!A:C,3,0)*VLOOKUP($C23&$E23,'Updated SES'!A:J,10,0) -> 0.165 | O23: =VLOOKUP($B23,'Language Penetration'!$B$1:$BL$14,MATCH('Compile data Working'!$H85,'Language Penetration'!$B$1:$BL$1,0),0) -> 0.204 | P23: =IF(ISBLANK(J23),RANDBETWEEN(1,2)&"%",IF(J23=1,RANDBETWEEN(35,40)&"%",IF(J23=2,RANDBETWEEN(30,35)&"%",IF(J23=3,RANDBETWEEN(25,30)&"%",IF(J23=4,RANDBETWEEN(20,25)&"%",IF(J23=5,RANDBETWEEN(15,20)&"%",IF(J23=6,RANDBETWEEN(10,15)&"%",IF(J23=7,RANDBETWEEN(8,10)&"%",IF(J23=8,RANDBETWEEN(6,8)&"%",IF(J23=9,RANDBETWEEN(4,6)&"%",IF(J23=10,RANDBETWEEN(2,4)&"%",""))))))))))) -> 34% | Q23: =IFERROR(L23*(M23+N23)*O23*P23,RANDBETWEEN(1,2)%*L23*(M23+N23)*O23) -> 4.4084183 | R23: =VLOOKUP(D:D,ranking!W:X,2,0) -> 0.3 | S23: =R23*Q23 -> 1.3225255 | T23: 16.629948
A24: WK-28'2026 | B24: ALL INDIA | C24: JioHotstar | D24: SVOD Originals Shows | E24: PAID | F24: Shows | G24: Second Love | H24: Hindi,Kannada,Malayalam,Tamil,Telugu | I24: 46216 | K24: Reality Tv | L24: =VLOOKUP($C24&$E24,'Updated SES'!A:N,14,0) -> 127.11702 | M24: =VLOOKUP($K24,'Genre Penetration'!A:B,2,0)*VLOOKUP($C24&$E24,'Updated SES'!A:I,9,0) -> 0.268 | N24: =VLOOKUP(K:K,'Genre Penetration'!A:C,3,0)*VLOOKUP($C24&$E24,'Updated SES'!A:J,10,0) -> 0.198 | O24: =VLOOKUP($B24,'Language Penetration'!$B$1:$BL$14,MATCH('Compile data Working'!$H16,'Language Penetration'!$B$1:$BL$1,0),0) -> 0.2625 | P24: =IF(ISBLANK(J24),RANDBETWEEN(1,2)&"%",IF(J24=1,RANDBETWEEN(35,40)&"%",IF(J24=2,RANDBETWEEN(30,35)&"%",IF(J24=3,RANDBETWEEN(25,30)&"%",IF(J24=4,RANDBETWEEN(20,25)&"%",IF(J24=5,RANDBETWEEN(15,20)&"%",IF(J24=6,RANDBETWEEN(10,15)&"%",IF(J24=7,RANDBETWEEN(8,10)&"%",IF(J24=8,RANDBETWEEN(6,8)&"%",IF(J24=9,RANDBETWEEN(4,6)&"%",IF(J24=10,RANDBETWEEN(2,4)&"%",""))))))))))) -> 1% | Q24: =IFERROR(L24*(M24+N24)*O24*P24,RANDBETWEEN(1,2)%*L24*(M24+N24)*O24) -> 0.15549589 | R24: =VLOOKUP(D:D,ranking!W:X,2,0) -> 0.6 | S24: =R24*Q24 -> 0.093297537 | T24: 16.419063
A25: Trending Top 10 | B25: ALL INDIA | C25: Netflix | D25: Theatrical Movies | E25: PAID | F25: Movies | G25: Peddi | H25: Kannada,Malayalam,Tamil,Telugu | I25: 46212 | J25: 4 | K25: Action,Drama | L25: =VLOOKUP($C25&$E25,'Updated SES'!A:N,14,0) -> 55.4592 | M25: =VLOOKUP($K25,'Genre Penetration'!A:B,2,0)*VLOOKUP($C25&$E25,'Updated SES'!A:I,9,0) -> 0.2597 | N25: =VLOOKUP(K:K,'Genre Penetration'!A:C,3,0)*VLOOKUP($C25&$E25,'Updated SES'!A:J,10,0) -> 0.2397 | O25: =VLOOKUP($B25,'Language Penetration'!$B$1:$BL$14,MATCH('Compile data Working'!$H92,'Language Penetration'!$B$1:$BL$1,0),0) -> 0.27166667 | P25: =IF(ISBLANK(J25),RANDBETWEEN(1,2)&"%",IF(J25=1,RANDBETWEEN(35,40)&"%",IF(J25=2,RANDBETWEEN(30,35)&"%",IF(J25=3,RANDBETWEEN(25,30)&"%",IF(J25=4,RANDBETWEEN(20,25)&"%",IF(J25=5,RANDBETWEEN(15,20)&"%",IF(J25=6,RANDBETWEEN(10,15)&"%",IF(J25=7,RANDBETWEEN(8,10)&"%",IF(J25=8,RANDBETWEEN(6,8)&"%",IF(J25=9,RANDBETWEEN(4,6)&"%",IF(J25=10,RANDBETWEEN(2,4)&"%",""))))))))))) -> 23% | Q25: =IFERROR(L25*(M25+N25)*O25*P25,RANDBETWEEN(1,2)%*L25*(M25+N25)*O25) -> 1.7305587 | R25: =VLOOKUP(D:D,ranking!W:X,2,0) -> 0.7 | S25: =R25*Q25 -> 1.2113911 | T25: 16.289302
A26: Trending Top 10 | B26: ALL INDIA | C26: Netflix | D26: Theatrical Movies | E26: PAID | F26: Movies | G26: Blast | H26: Hindi,Kannada,Malayalam,Tamil,Telugu | I26: 46198 | J26: 6 | K26: Action,Drama | L26: =VLOOKUP($C26&$E26,'Updated SES'!A:N,14,0) -> 55.4592 | M26: =VLOOKUP($K26,'Genre Penetration'!A:B,2,0)*VLOOKUP($C26&$E26,'Updated SES'!A:I,9,0) -> 0.2597 | N26: =VLOOKUP(K:K,'Genre Penetration'!A:C,3,0)*VLOOKUP($C26&$E26,'Updated SES'!A:J,10,0) -> 0.2397 | O26: =VLOOKUP($B26,'Language Penetration'!$B$1:$BL$14,MATCH('Compile data Working'!$H94,'Language Penetration'!$B$1:$BL$1,0),0) -> 0.6 | P26: =IF(ISBLANK(J26),RANDBETWEEN(1,2)&"%",IF(J26=1,RANDBETWEEN(35,40)&"%",IF(J26=2,RANDBETWEEN(30,35)&"%",IF(J26=3,RANDBETWEEN(25,30)&"%",IF(J26=4,RANDBETWEEN(20,25)&"%",IF(J26=5,RANDBETWEEN(15,20)&"%",IF(J26=6,RANDBETWEEN(10,15)&"%",IF(J26=7,RANDBETWEEN(8,10)&"%",IF(J26=8,RANDBETWEEN(6,8)&"%",IF(J26=9,RANDBETWEEN(4,6)&"%",IF(J26=10,RANDBETWEEN(2,4)&"%",""))))))))))) -> 10% | Q26: =IFERROR(L26*(M26+N26)*O26*P26,RANDBETWEEN(1,2)%*L26*(M26+N26)*O26) -> 1.6617795 | R26: =VLOOKUP(D:D,ranking!W:X,2,0) -> 0.7 | S26: =R26*Q26 -> 1.1632456 | T26: 16.178457
A27: WK-28'2026 | B27: ALL INDIA | C27: Amazon Prime Video | D27: SVOD Originals Shows | E27: PAID | F27: Shows | G27: Ride or Die | H27: English,Hindi,Kannada,Malayalam,Tamil,Telugu | I27: 46218 | K27: Action,Adventure,Drama | L27: =VLOOKUP($C27&$E27,'Updated SES'!A:N,14,0) -> 36.49824 | M27: =VLOOKUP($K27,'Genre Penetration'!A:B,2,0)*VLOOKUP($C27&$E27,'Updated SES'!A:I,9,0) -> 0.3016 | N27: =VLOOKUP(K:K,'Genre Penetration'!A:C,3,0)*VLOOKUP($C27&$E27,'Updated SES'!A:J,10,0) -> 0.2016 | O27: =VLOOKUP($B27,'Language Penetration'!$B$1:$BL$14,MATCH('Compile data Working'!$H25,'Language Penetration'!$B$1:$BL$1,0),0) -> 0.105 | P27: =IF(ISBLANK(J27),RANDBETWEEN(1,2)&"%",IF(J27=1,RANDBETWEEN(35,40)&"%",IF(J27=2,RANDBETWEEN(30,35)&"%",IF(J27=3,RANDBETWEEN(25,30)&"%",IF(J27=4,RANDBETWEEN(20,25)&"%",IF(J27=5,RANDBETWEEN(15,20)&"%",IF(J27=6,RANDBETWEEN(10,15)&"%",IF(J27=7,RANDBETWEEN(8,10)&"%",IF(J27=8,RANDBETWEEN(6,8)&"%",IF(J27=9,RANDBETWEEN(4,6)&"%",IF(J27=10,RANDBETWEEN(2,4)&"%",""))))))))))) -> 1% | Q27: =IFERROR(L27*(M27+N27)*O27*P27,RANDBETWEEN(1,2)%*L27*(M27+N27)*O27) -> 0.01928421 | R27: =VLOOKUP(D:D,ranking!W:X,2,0) -> 0.6 | S27: =R27*Q27 -> 0.011570526 | T27: 16.041073
A28: WK-28'2026 | B28: ALL INDIA | C28: Netflix | D28: Theatrical Movies | E28: PAID | F28: Movies | G28: Desire | H28: English,Hindi | I28: 46220 | K28: Drama,Thriller | L28: =VLOOKUP($C28&$E28,'Updated SES'!A:N,14,0) -> 55.4592 | M28: =VLOOKUP($K28,'Genre Penetration'!A:B,2,0)*VLOOKUP($C28&$E28,'Updated SES'!A:I,9,0) -> 0.2695 | N28: =VLOOKUP(K:K,'Genre Penetration'!A:C,3,0)*VLOOKUP($C28&$E28,'Updated SES'!A:J,10,0) -> 0.2295 | O28: =VLOOKUP($B28,'Language Penetration'!$B$1:$BL$14,MATCH('Compile data Working'!$H48,'Language Penetration'!$B$1:$BL$1,0),0) -> 0.2625 | P28: =IF(ISBLANK(J28),RANDBETWEEN(1,2)&"%",IF(J28=1,RANDBETWEEN(35,40)&"%",IF(J28=2,RANDBETWEEN(30,35)&"%",IF(J28=3,RANDBETWEEN(25,30)&"%",IF(J28=4,RANDBETWEEN(20,25)&"%",IF(J28=5,RANDBETWEEN(15,20)&"%",IF(J28=6,RANDBETWEEN(10,15)&"%",IF(J28=7,RANDBETWEEN(8,10)&"%",IF(J28=8,RANDBETWEEN(6,8)&"%",IF(J28=9,RANDBETWEEN(4,6)&"%",IF(J28=10,RANDBETWEEN(2,4)&"%",""))))))))))) -> 1% | Q28: =IFERROR(L28*(M28+N28)*O28*P28,RANDBETWEEN(1,2)%*L28*(M28+N28)*O28) -> 0.07264462 | R28: =VLOOKUP(D:D,ranking!W:X,2,0) -> 0.7 | S28: =R28*Q28 -> 0.050851234 | T28: 15.872473
A29: Trending Top 10 | B29: ALL INDIA | C29: JioHotstar | D29: Theatrical Movies | E29: PAID | F29: Movies | G29: Dhurandhar: The Revenge | H29: Hindi,Kannada,Malayalam,Tamil,Telugu | I29: 46177 | J29: 7 | K29: Action,Crime,Thriller | L29: =VLOOKUP($C29&$E29,'Updated SES'!A:N,14,0) -> 127.11702 | M29: =VLOOKUP($K29,'Genre Penetration'!A:B,2,0)*VLOOKUP($C29&$E29,'Updated SES'!A:I,9,0) -> 0.4824 | N29: =VLOOKUP(K:K,'Genre Penetration'!A:C,3,0)*VLOOKUP($C29&$E29,'Updated SES'!A:J,10,0) -> 0.0924 | O29: =VLOOKUP($B29,'Language Penetration'!$B$1:$BL$14,MATCH('Compile data Working'!$H89,'Language Penetration'!$B$1:$BL$1,0),0) -> 0.6 | P29: =IF(ISBLANK(J29),RANDBETWEEN(1,2)&"%",IF(J29=1,RANDBETWEEN(35,40)&"%",IF(J29=2,RANDBETWEEN(30,35)&"%",IF(J29=3,RANDBETWEEN(25,30)&"%",IF(J29=4,RANDBETWEEN(20,25)&"%",IF(J29=5,RANDBETWEEN(15,20)&"%",IF(J29=6,RANDBETWEEN(10,15)&"%",IF(J29=7,RANDBETWEEN(8,10)&"%",IF(J29=8,RANDBETWEEN(6,8)&"%",IF(J29=9,RANDBETWEEN(4,6)&"%",IF(J29=10,RANDBETWEEN(2,4)&"%",""))))))))))) -> 9% | Q29: =IFERROR(L29*(M29+N29)*O29*P29,RANDBETWEEN(1,2)%*L29*(M29+N29)*O29) -> 3.9456106 | R29: =VLOOKUP(D:D,ranking!W:X,2,0) -> 0.7 | S29: =R29*Q29 -> 2.7619274 | T29: 15.596927
A30: Trending Top 10 | B30: ALL INDIA | C30: Netflix | D30: Theatrical Movies | E30: PAID | F30: Movies | G30: Daadi Ki Shaadi | H30: Hindi | I30: 46206 | J30: 5 | K30: Comedy,Drama,Romance | L30: =VLOOKUP($C30&$E30,'Updated SES'!A:N,14,0) -> 55.4592 | M30: =VLOOKUP($K30,'Genre Penetration'!A:B,2,0)*VLOOKUP($C30&$E30,'Updated SES'!A:I,9,0) -> 0.1813 | N30: =VLOOKUP(K:K,'Genre Penetration'!A:C,3,0)*VLOOKUP($C30&$E30,'Updated SES'!A:J,10,0) -> 0.3213 | O30: =VLOOKUP($B30,'Language Penetration'!$B$1:$BL$14,MATCH('Compile data Working'!$H93,'Language Penetration'!$B$1:$BL$1,0),0) -> 0.20333333 | P30: =IF(ISBLANK(J30),RANDBETWEEN(1,2)&"%",IF(J30=1,RANDBETWEEN(35,40)&"%",IF(J30=2,RANDBETWEEN(30,35)&"%",IF(J30=3,RANDBETWEEN(25,30)&"%",IF(J30=4,RANDBETWEEN(20,25)&"%",IF(J30=5,RANDBETWEEN(15,20)&"%",IF(J30=6,RANDBETWEEN(10,15)&"%",IF(J30=7,RANDBETWEEN(8,10)&"%",IF(J30=8,RANDBETWEEN(6,8)&"%",IF(J30=9,RANDBETWEEN(4,6)&"%",IF(J30=10,RANDBETWEEN(2,4)&"%",""))))))))))) -> 20% | Q30: =IFERROR(L30*(M30+N30)*O30*P30,RANDBETWEEN(1,2)%*L30*(M30+N30)*O30) -> 1.1335343 | R30: =VLOOKUP(D:D,ranking!W:X,2,0) -> 0.7 | S30: =R30*Q30 -> 0.793474 | T30: 15.397473
A31: WK-28'2026 | B31: ALL INDIA | C31: Netflix | D31: SVOD Originals Shows | E31: PAID | F31: Shows | G31: Quarterback Season 3 | H31: English,Hindi | I31: 46217 | K31: Documentary | L31: =VLOOKUP($C31&$E31,'Updated SES'!A:N,14,0) -> 55.4592 | M31: =VLOOKUP($K31,'Genre Penetration'!A:B,2,0)*VLOOKUP($C31&$E31,'Updated SES'!A:I,9,0) -> 0.2205 | N31: =VLOOKUP(K:K,'Genre Penetration'!A:C,3,0)*VLOOKUP($C31&$E31,'Updated SES'!A:J,10,0) -> 0.2805 | O31: =VLOOKUP($B31,'Language Penetration'!$B$1:$BL$14,MATCH('Compile data Working'!$H20,'Language Penetration'!$B$1:$BL$1,0),0) -> 0.6 | P31: =IF(ISBLANK(J31),RANDBETWEEN(1,2)&"%",IF(J31=1,RANDBETWEEN(35,40)&"%",IF(J31=2,RANDBETWEEN(30,35)&"%",IF(J31=3,RANDBETWEEN(25,30)&"%",IF(J31=4,RANDBETWEEN(20,25)&"%",IF(J31=5,RANDBETWEEN(15,20)&"%",IF(J31=6,RANDBETWEEN(10,15)&"%",IF(J31=7,RANDBETWEEN(8,10)&"%",IF(J31=8,RANDBETWEEN(6,8)&"%",IF(J31=9,RANDBETWEEN(4,6)&"%",IF(J31=10,RANDBETWEEN(2,4)&"%",""))))))))))) -> 1% | Q31: =IFERROR(L31*(M31+N31)*O31*P31,RANDBETWEEN(1,2)%*L31*(M31+N31)*O31) -> 0.16671036 | R31: =VLOOKUP(D:D,ranking!W:X,2,0) -> 0.6 | S31: =R31*Q31 -> 0.10002621 | T31: 15.279654
A32: WK-28'2026 | B32: ALL INDIA | C32: Netflix | D32: SVOD Originals Shows | E32: PAID | F32: Shows | G32: The East Palace | H32: English,Hindi,Tamil,Telugu | I32: 46220 | K32: Action,Fantasy | L32: =VLOOKUP($C32&$E32,'Updated SES'!A:N,14,0) -> 55.4592 | M32: =VLOOKUP($K32,'Genre Penetration'!A:B,2,0)*VLOOKUP($C32&$E32,'Updated SES'!A:I,9,0) -> 0.2891 | N32: =VLOOKUP(K:K,'Genre Penetration'!A:C,3,0)*VLOOKUP($C32&$E32,'Updated SES'!A:J,10,0) -> 0.2091 | O32: =VLOOKUP($B32,'Language Penetration'!$B$1:$BL$14,MATCH('Compile data Working'!$H66,'Language Penetration'!$B$1:$BL$1,0),0) -> 0.2 | P32: =IF(ISBLANK(J32),RANDBETWEEN(1,2)&"%",IF(J32=1,RANDBETWEEN(35,40)&"%",IF(J32=2,RANDBETWEEN(30,35)&"%",IF(J32=3,RANDBETWEEN(25,30)&"%",IF(J32=4,RANDBETWEEN(20,25)&"%",IF(J32=5,RANDBETWEEN(15,20)&"%",IF(J32=6,RANDBETWEEN(10,15)&"%",IF(J32=7,RANDBETWEEN(8,10)&"%",IF(J32=8,RANDBETWEEN(6,8)&"%",IF(J32=9,RANDBETWEEN(4,6)&"%",IF(J32=10,RANDBETWEEN(2,4)&"%",""))))))))))) -> 2% | Q32: =IFERROR(L32*(M32+N32)*O32*P32,RANDBETWEEN(1,2)%*L32*(M32+N32)*O32) -> 0.11051909 | R32: =VLOOKUP(D:D,ranking!W:X,2,0) -> 0.6 | S32: =R32*Q32 -> 0.066311456 | T32: 15.211755
A33: Trending Top 10 | B33: ALL INDIA | C33: Amazon Prime Video | D33: Svod Originals Shows | E33: PAID | F33: Shows | G33: Raakh | H33: Hindi,Tamil,Telugu | I33: 46185 | J33: 4 | K33: Crime,Drama,Thriller | L33: =VLOOKUP($C33&$E33,'Updated SES'!A:N,14,0) -> 36.49824 | M33: =VLOOKUP($K33,'Genre Penetration'!A:B,2,0)*VLOOKUP($C33&$E33,'Updated SES'!A:I,9,0) -> 0.3744 | N33: =VLOOKUP(K:K,'Genre Penetration'!A:C,3,0)*VLOOKUP($C33&$E33,'Updated SES'!A:J,10,0) -> 0.1344 | O33: =VLOOKUP($B33,'Language Penetration'!$B$1:$BL$14,MATCH('Compile data Working'!$H78,'Language Penetration'!$B$1:$BL$1,0),0) -> 0.1 | P33: =IF(ISBLANK(J33),RANDBETWEEN(1,2)&"%",IF(J33=1,RANDBETWEEN(35,40)&"%",IF(J33=2,RANDBETWEEN(30,35)&"%",IF(J33=3,RANDBETWEEN(25,30)&"%",IF(J33=4,RANDBETWEEN(20,25)&"%",IF(J33=5,RANDBETWEEN(15,20)&"%",IF(J33=6,RANDBETWEEN(10,15)&"%",IF(J33=7,RANDBETWEEN(8,10)&"%",IF(J33=8,RANDBETWEEN(6,8)&"%",IF(J33=9,RANDBETWEEN(4,6)&"%",IF(J33=10,RANDBETWEEN(2,4)&"%",""))))))))))) -> 22% | Q33: =IFERROR(L33*(M33+N33)*O33*P33,RANDBETWEEN(1,2)%*L33*(M33+N33)*O33) -> 0.4085467 | R33: =VLOOKUP(D:D,ranking!W:X,2,0) -> 0.6 | S33: =R33*Q33 -> 0.24512802 | T33: 15.170755
A34: WK-28'2026 | B34: ALL INDIA | C34: Netflix | D34: SVOD Originals Shows | E34: PAID | F34: Shows | G34: The Map of Longing | H34: English,Hindi,Telugu | I34: 46220 | K34: Drama,Romance | L34: =VLOOKUP($C34&$E34,'Updated SES'!A:N,14,0) -> 55.4592 | M34: =VLOOKUP($K34,'Genre Penetration'!A:B,2,0)*VLOOKUP($C34&$E34,'Updated SES'!A:I,9,0) -> 0.196 | N34: =VLOOKUP(K:K,'Genre Penetration'!A:C,3,0)*VLOOKUP($C34&$E34,'Updated SES'!A:J,10,0) -> 0.306 | O34: =VLOOKUP($B34,'Language Penetration'!$B$1:$BL$14,MATCH('Compile data Working'!$H61,'Language Penetration'!$B$1:$BL$1,0),0) -> 0.2 | P34: =IF(ISBLANK(J34),RANDBETWEEN(1,2)&"%",IF(J34=1,RANDBETWEEN(35,40)&"%",IF(J34=2,RANDBETWEEN(30,35)&"%",IF(J34=3,RANDBETWEEN(25,30)&"%",IF(J34=4,RANDBETWEEN(20,25)&"%",IF(J34=5,RANDBETWEEN(15,20)&"%",IF(J34=6,RANDBETWEEN(10,15)&"%",IF(J34=7,RANDBETWEEN(8,10)&"%",IF(J34=8,RANDBETWEEN(6,8)&"%",IF(J34=9,RANDBETWEEN(4,6)&"%",IF(J34=10,RANDBETWEEN(2,4)&"%",""))))))))))) -> 2% | Q34: =IFERROR(L34*(M34+N34)*O34*P34,RANDBETWEEN(1,2)%*L34*(M34+N34)*O34) -> 0.11136207 | R34: =VLOOKUP(D:D,ranking!W:X,2,0) -> 0.6 | S34: =R34*Q34 -> 0.066817244 | T34: 14.920133
A35: WK-28'2026 | B35: ALL INDIA | C35: Netflix | D35: SVOD Originals Shows | E35: PAID | F35: Shows | G35: Unexplainable | H35: English | I35: 46219 | K35: Drama | L35: =VLOOKUP($C35&$E35,'Updated SES'!A:N,14,0) -> 55.4592 | M35: =VLOOKUP($K35,'Genre Penetration'!A:B,2,0)*VLOOKUP($C35&$E35,'Updated SES'!A:I,9,0) -> 0.245 | N35: =VLOOKUP(K:K,'Genre Penetration'!A:C,3,0)*VLOOKUP($C35&$E35,'Updated SES'!A:J,10,0) -> 0.255 | O35: =VLOOKUP($B35,'Language Penetration'!$B$1:$BL$14,MATCH('Compile data Working'!$H42,'Language Penetration'!$B$1:$BL$1,0),0) -> 0.204 | P35: =IF(ISBLANK(J35),RANDBETWEEN(1,2)&"%",IF(J35=1,RANDBETWEEN(35,40)&"%",IF(J35=2,RANDBETWEEN(30,35)&"%",IF(J35=3,RANDBETWEEN(25,30)&"%",IF(J35=4,RANDBETWEEN(20,25)&"%",IF(J35=5,RANDBETWEEN(15,20)&"%",IF(J35=6,RANDBETWEEN(10,15)&"%",IF(J35=7,RANDBETWEEN(8,10)&"%",IF(J35=8,RANDBETWEEN(6,8)&"%",IF(J35=9,RANDBETWEEN(4,6)&"%",IF(J35=10,RANDBETWEEN(2,4)&"%",""))))))))))) -> 2% | Q35: =IFERROR(L35*(M35+N35)*O35*P35,RANDBETWEEN(1,2)%*L35*(M35+N35)*O35) -> 0.11313677 | R35: =VLOOKUP(D:D,ranking!W:X,2,0) -> 0.6 | S35: =R35*Q35 -> 0.067882061 | T35: 14.740372
A36: WK-28'2026 | B36: ALL INDIA | C36: Netflix | D36: SVOD Originals Shows | E36: PAID | F36: Shows | G36: The Ultimatum: Marry or Move On Season 4 | H36: English,Hindi | I36: 46218 | K36: Reality Tv | L36: =VLOOKUP($C36&$E36,'Updated SES'!A:N,14,0) -> 55.4592 | M36: =VLOOKUP($K36,'Genre Penetration'!A:B,2,0)*VLOOKUP($C36&$E36,'Updated SES'!A:I,9,0) -> 0.196 | N36: =VLOOKUP(K:K,'Genre Penetration'!A:C,3,0)*VLOOKUP($C36&$E36,'Updated SES'!A:J,10,0) -> 0.306 | O36: =VLOOKUP($B36,'Language Penetration'!$B$1:$BL$14,MATCH('Compile data Working'!$H29,'Language Penetration'!$B$1:$BL$1,0),0) -> 0.204 | P36: =IF(ISBLANK(J36),RANDBETWEEN(1,2)&"%",IF(J36=1,RANDBETWEEN(35,40)&"%",IF(J36=2,RANDBETWEEN(30,35)&"%",IF(J36=3,RANDBETWEEN(25,30)&"%",IF(J36=4,RANDBETWEEN(20,25)&"%",IF(J36=5,RANDBETWEEN(15,20)&"%",IF(J36=6,RANDBETWEEN(10,15)&"%",IF(J36=7,RANDBETWEEN(8,10)&"%",IF(J36=8,RANDBETWEEN(6,8)&"%",IF(J36=9,RANDBETWEEN(4,6)&"%",IF(J36=10,RANDBETWEEN(2,4)&"%",""))))))))))) -> 1% | Q36: =IFERROR(L36*(M36+N36)*O36*P36,RANDBETWEEN(1,2)%*L36*(M36+N36)*O36) -> 0.056794658 | R36: =VLOOKUP(D:D,ranking!W:X,2,0) -> 0.6 | S36: =R36*Q36 -> 0.034076795 | T36: 14.476063
A37: WK-28'2026 | B37: ALL INDIA | C37: Netflix | D37: SVOD Originals Shows | E37: PAID | F37: Shows | G37: The Hawk | H37: English,Hindi,Tamil,Telugu | I37: 46219 | K37: Comedy | L37: =VLOOKUP($C37&$E37,'Updated SES'!A:N,14,0) -> 55.4592 | M37: =VLOOKUP($K37,'Genre Penetration'!A:B,2,0)*VLOOKUP($C37&$E37,'Updated SES'!A:I,9,0) -> 0.2205 | N37: =VLOOKUP(K:K,'Genre Penetration'!A:C,3,0)*VLOOKUP($C37&$E37,'Updated SES'!A:J,10,0) -> 0.2805 | O37: =VLOOKUP($B37,'Language Penetration'!$B$1:$BL$14,MATCH('Compile data Working'!$H41,'Language Penetration'!$B$1:$BL$1,0),0) -> 0.20333333 | P37: =IF(ISBLANK(J37),RANDBETWEEN(1,2)&"%",IF(J37=1,RANDBETWEEN(35,40)&"%",IF(J37=2,RANDBETWEEN(30,35)&"%",IF(J37=3,RANDBETWEEN(25,30)&"%",IF(J37=4,RANDBETWEEN(20,25)&"%",IF(J37=5,RANDBETWEEN(15,20)&"%",IF(J37=6,RANDBETWEEN(10,15)&"%",IF(J37=7,RANDBETWEEN(8,10)&"%",IF(J37=8,RANDBETWEEN(6,8)&"%",IF(J37=9,RANDBETWEEN(4,6)&"%",IF(J37=10,RANDBETWEEN(2,4)&"%",""))))))))))) -> 2% | Q37: =IFERROR(L37*(M37+N37)*O37*P37,RANDBETWEEN(1,2)%*L37*(M37+N37)*O37) -> 0.11299257 | R37: =VLOOKUP(D:D,ranking!W:X,2,0) -> 0.6 | S37: =R37*Q37 -> 0.067795544 | T37: 14.135585
A38: WK-28'2026 | B38: ALL INDIA | C38: Netflix | D38: SVOD Originals Shows | E38: PAID | F38: Shows | G38: Stranger Things: VHS Special Edition | H38: English,Hindi,Tamil,Telugu | I38: 46218 | K38: Drama | L38: =VLOOKUP($C38&$E38,'Updated SES'!A:N,14,0) -> 55.4592 | M38: =VLOOKUP($K38,'Genre Penetration'!A:B,2,0)*VLOOKUP($C38&$E38,'Updated SES'!A:I,9,0) -> 0.245 | N38: =VLOOKUP(K:K,'Genre Penetration'!A:C,3,0)*VLOOKUP($C38&$E38,'Updated SES'!A:J,10,0) -> 0.255 | O38: =VLOOKUP($B38,'Language Penetration'!$B$1:$BL$14,MATCH('Compile data Working'!$H27,'Language Penetration'!$B$1:$BL$1,0),0) -> 0.20333333 | P38: =IF(ISBLANK(J38),RANDBETWEEN(1,2)&"%",IF(J38=1,RANDBETWEEN(35,40)&"%",IF(J38=2,RANDBETWEEN(30,35)&"%",IF(J38=3,RANDBETWEEN(25,30)&"%",IF(J38=4,RANDBETWEEN(20,25)&"%",IF(J38=5,RANDBETWEEN(15,20)&"%",IF(J38=6,RANDBETWEEN(10,15)&"%",IF(J38=7,RANDBETWEEN(8,10)&"%",IF(J38=8,RANDBETWEEN(6,8)&"%",IF(J38=9,RANDBETWEEN(4,6)&"%",IF(J38=10,RANDBETWEEN(2,4)&"%",""))))))))))) -> 2% | Q38: =IFERROR(L38*(M38+N38)*O38*P38,RANDBETWEEN(1,2)%*L38*(M38+N38)*O38) -> 0.11276704 | R38: =VLOOKUP(D:D,ranking!W:X,2,0) -> 0.6 | S38: =R38*Q38 -> 0.067660224 | T38: 13.77367
A39: WK-28'2026 | B39: ALL INDIA | C39: JioHotstar | D39: SVOD Originals Shows | E39: PAID | F39: Shows | G39: Spidey and His Amazing Friends Season 5 | H39: English | I39: 46218 | K39: Adventure,Animation,Comedy | L39: =VLOOKUP($C39&$E39,'Updated SES'!A:N,14,0) -> 127.11702 | M39: =VLOOKUP($K39,'Genre Penetration'!A:B,2,0)*VLOOKUP($C39&$E39,'Updated SES'!A:I,9,0) -> 0.335 | N39: =VLOOKUP(K:K,'Genre Penetration'!A:C,3,0)*VLOOKUP($C39&$E39,'Updated SES'!A:J,10,0) -> 0.165 | O39: =VLOOKUP($B39,'Language Penetration'!$B$1:$BL$14,MATCH('Compile data Working'!$H26,'Language Penetration'!$B$1:$BL$1,0),0) -> 0.204 | P39: =IF(ISBLANK(J39),RANDBETWEEN(1,2)&"%",IF(J39=1,RANDBETWEEN(35,40)&"%",IF(J39=2,RANDBETWEEN(30,35)&"%",IF(J39=3,RANDBETWEEN(25,30)&"%",IF(J39=4,RANDBETWEEN(20,25)&"%",IF(J39=5,RANDBETWEEN(15,20)&"%",IF(J39=6,RANDBETWEEN(10,15)&"%",IF(J39=7,RANDBETWEEN(8,10)&"%",IF(J39=8,RANDBETWEEN(6,8)&"%",IF(J39=9,RANDBETWEEN(4,6)&"%",IF(J39=10,RANDBETWEEN(2,4)&"%",""))))))))))) -> 1% | Q39: =IFERROR(L39*(M39+N39)*O39*P39,RANDBETWEEN(1,2)%*L39*(M39+N39)*O39) -> 0.12965936 | R39: =VLOOKUP(D:D,ranking!W:X,2,0) -> 0.6 | S39: =R39*Q39 -> 0.077795616 | T39: 13.682553
A40: WK-28'2026 | B40: ALL INDIA | C40: Netflix | D40: Theatrical Movies | E40: PAID | F40: Movies | G40: Sniper: No Nation | H40: English,Hindi | I40: 46219 | K40: Action | L40: =VLOOKUP($C40&$E40,'Updated SES'!A:N,14,0) -> 55.4592 | M40: =VLOOKUP($K40,'Genre Penetration'!A:B,2,0)*VLOOKUP($C40&$E40,'Updated SES'!A:I,9,0) -> 0.343 | N40: =VLOOKUP(K:K,'Genre Penetration'!A:C,3,0)*VLOOKUP($C40&$E40,'Updated SES'!A:J,10,0) -> 0.153 | O40: =VLOOKUP($B40,'Language Penetration'!$B$1:$BL$14,MATCH('Compile data Working'!$H145,'Language Penetration'!$B$1:$BL$1,0),0) -> 0.1 | P40: =IF(ISBLANK(J40),RANDBETWEEN(1,2)&"%",IF(J40=1,RANDBETWEEN(35,40)&"%",IF(J40=2,RANDBETWEEN(30,35)&"%",IF(J40=3,RANDBETWEEN(25,30)&"%",IF(J40=4,RANDBETWEEN(20,25)&"%",IF(J40=5,RANDBETWEEN(15,20)&"%",IF(J40=6,RANDBETWEEN(10,15)&"%",IF(J40=7,RANDBETWEEN(8,10)&"%",IF(J40=8,RANDBETWEEN(6,8)&"%",IF(J40=9,RANDBETWEEN(4,6)&"%",IF(J40=10,RANDBETWEEN(2,4)&"%",""))))))))))) -> 2% | Q40: =IFERROR(L40*(M40+N40)*O40*P40,RANDBETWEEN(1,2)%*L40*(M40+N40)*O40) -> 0.055015526 | R40: =VLOOKUP(D:D,ranking!W:X,2,0) -> 0.7 | S40: =R40*Q40 -> 0.038510868 | T40: 13.631233
A41: Trending Top 10 | B41: ALL INDIA | C41: Amazon Prime Video | D41: Theatrical Movies | E41: RENT | F41: Movies | G41: Project Hail Mary | H41: English,Hindi,Kannada,Malayalam,Tamil,Telugu | I41: 46206 | J41: 5 | K41: Adventure,Sci-Fi | L41: =VLOOKUP($C41&$E41,'Updated SES'!A:N,14,0) -> 4.689 | M41: =VLOOKUP($K41,'Genre Penetration'!A:B,2,0)*VLOOKUP($C41&$E41,'Updated SES'!A:I,9,0) -> 0.408 | N41: =VLOOKUP(K:K,'Genre Penetration'!A:C,3,0)*VLOOKUP($C41&$E41,'Updated SES'!A:J,10,0) -> 0.128 | O41: =VLOOKUP($B41,'Language Penetration'!$B$1:$BL$14,MATCH('Compile data Working'!$H79,'Language Penetration'!$B$1:$BL$1,0),0) -> 0.6 | P41: =IF(ISBLANK(J41),RANDBETWEEN(1,2)&"%",IF(J41=1,RANDBETWEEN(35,40)&"%",IF(J41=2,RANDBETWEEN(30,35)&"%",IF(J41=3,RANDBETWEEN(25,30)&"%",IF(J41=4,RANDBETWEEN(20,25)&"%",IF(J41=5,RANDBETWEEN(15,20)&"%",IF(J41=6,RANDBETWEEN(10,15)&"%",IF(J41=7,RANDBETWEEN(8,10)&"%",IF(J41=8,RANDBETWEEN(6,8)&"%",IF(J41=9,RANDBETWEEN(4,6)&"%",IF(J41=10,RANDBETWEEN(2,4)&"%",""))))))))))) -> 18% | Q41: =IFERROR(L41*(M41+N41)*O41*P41,RANDBETWEEN(1,2)%*L41*(M41+N41)*O41) -> 0.27143683 | R41: =VLOOKUP(D:D,ranking!W:X,2,0) -> 0.7 | S41: =R41*Q41 -> 0.19000578 | T41: 13.624902
A42: Trending Top 10 | B42: ALL INDIA | C42: Netflix | D42: Svod Originals Shows | E42: PAID | F42: Shows | G42: Super Subbu | H42: Hindi,Kannada,Malayalam,Tamil,Telugu | I42: 46205 | J42: 3 | K42: Comedy,Drama | L42: =VLOOKUP($C42&$E42,'Updated SES'!A:N,14,0) -> 55.4592 | M42: =VLOOKUP($K42,'Genre Penetration'!A:B,2,0)*VLOOKUP($C42&$E42,'Updated SES'!A:I,9,0) -> 0.2303 | N42: =VLOOKUP(K:K,'Genre Penetration'!A:C,3,0)*VLOOKUP($C42&$E42,'Updated SES'!A:J,10,0) -> 0.2703 | O42: =VLOOKUP($B42,'Language Penetration'!$B$1:$BL$14,MATCH('Compile data Working'!$H99,'Language Penetration'!$B$1:$BL$1,0),0) -> 0.6 | P42: =IF(ISBLANK(J42),RANDBETWEEN(1,2)&"%",IF(J42=1,RANDBETWEEN(35,40)&"%",IF(J42=2,RANDBETWEEN(30,35)&"%",IF(J42=3,RANDBETWEEN(25,30)&"%",IF(J42=4,RANDBETWEEN(20,25)&"%",IF(J42=5,RANDBETWEEN(15,20)&"%",IF(J42=6,RANDBETWEEN(10,15)&"%",IF(J42=7,RANDBETWEEN(8,10)&"%",IF(J42=8,RANDBETWEEN(6,8)&"%",IF(J42=9,RANDBETWEEN(4,6)&"%",IF(J42=10,RANDBETWEEN(2,4)&"%",""))))))))))) -> 27% | Q42: =IFERROR(L42*(M42+N42)*O42*P42,RANDBETWEEN(1,2)%*L42*(M42+N42)*O42) -> 4.4975858 | R42: =VLOOKUP(D:D,ranking!W:X,2,0) -> 0.6 | S42: =R42*Q42 -> 2.6985515 | T42: 13.534028
A43: WK-28'2026 | B43: ALL INDIA | C43: JioHotstar | D43: Theatrical Movies | E43: PAID | F43: Movies | G43: Maa Inti Bangaram | H43: Kannada,Malayalam,Tamil,Telugu | I43: 46220 | K43: Action,Drama,Thriller | L43: =VLOOKUP($C43&$E43,'Updated SES'!A:N,14,0) -> 127.11702 | M43: =VLOOKUP($K43,'Genre Penetration'!A:B,2,0)*VLOOKUP($C43&$E43,'Updated SES'!A:I,9,0) -> 0.4556 | N43: =VLOOKUP(K:K,'Genre Penetration'!A:C,3,0)*VLOOKUP($C43&$E43,'Updated SES'!A:J,10,0) -> 0.1056 | O43: =VLOOKUP($B43,'Language Penetration'!$B$1:$BL$14,MATCH('Compile data Working'!$H53,'Language Penetration'!$B$1:$BL$1,0),0) -> 0.2 | P43: =IF(ISBLANK(J43),RANDBETWEEN(1,2)&"%",IF(J43=1,RANDBETWEEN(35,40)&"%",IF(J43=2,RANDBETWEEN(30,35)&"%",IF(J43=3,RANDBETWEEN(25,30)&"%",IF(J43=4,RANDBETWEEN(20,25)&"%",IF(J43=5,RANDBETWEEN(15,20)&"%",IF(J43=6,RANDBETWEEN(10,15)&"%",IF(J43=7,RANDBETWEEN(8,10)&"%",IF(J43=8,RANDBETWEEN(6,8)&"%",IF(J43=9,RANDBETWEEN(4,6)&"%",IF(J43=10,RANDBETWEEN(2,4)&"%",""))))))))))) -> 2% | Q43: =IFERROR(L43*(M43+N43)*O43*P43,RANDBETWEEN(1,2)%*L43*(M43+N43)*O43) -> 0.28535229 | R43: =VLOOKUP(D:D,ranking!W:X,2,0) -> 0.7 | S43: =R43*Q43 -> 0.1997466 | T43: 13.506893
A44: Trending Top 10 | B44: ALL INDIA | C44: Amazon Prime Video | D44: Theatrical Movies | E44: PAID | F44: Movies | G44: The Sheep Detectives | H44: English,Hindi,Kannada,Malayalam,Tamil,Telugu | I44: 46197 | J44: 6 | K44: Comedy,Mystery | L44: =VLOOKUP($C44&$E44,'Updated SES'!A:N,14,0) -> 36.49824 | M44: =VLOOKUP($K44,'Genre Penetration'!A:B,2,0)*VLOOKUP($C44&$E44,'Updated SES'!A:I,9,0) -> 0.26 | N44: =VLOOKUP(K:K,'Genre Penetration'!A:C,3,0)*VLOOKUP($C44&$E44,'Updated SES'!A:J,10,0) -> 0.24 | O44: =VLOOKUP($B44,'Language Penetration'!$B$1:$BL$14,MATCH('Compile data Working'!$H80,'Language Penetration'!$B$1:$BL$1,0),0) -> 0.6 | P44: =IF(ISBLANK(J44),RANDBETWEEN(1,2)&"%",IF(J44=1,RANDBETWEEN(35,40)&"%",IF(J44=2,RANDBETWEEN(30,35)&"%",IF(J44=3,RANDBETWEEN(25,30)&"%",IF(J44=4,RANDBETWEEN(20,25)&"%",IF(J44=5,RANDBETWEEN(15,20)&"%",IF(J44=6,RANDBETWEEN(10,15)&"%",IF(J44=7,RANDBETWEEN(8,10)&"%",IF(J44=8,RANDBETWEEN(6,8)&"%",IF(J44=9,RANDBETWEEN(4,6)&"%",IF(J44=10,RANDBETWEEN(2,4)&"%",""))))))))))) -> 15% | Q44: =IFERROR(L44*(M44+N44)*O44*P44,RANDBETWEEN(1,2)%*L44*(M44+N44)*O44) -> 1.6424208 | R44: =VLOOKUP(D:D,ranking!W:X,2,0) -> 0.7 | S44: =R44*Q44 -> 1.1496946 | T44: 13.247607
A45: WK-28'2026 | B45: ALL INDIA | C45: Amazon Prime Video | D45: Theatrical Movies | E45: RENT | F45: Movies | G45: Speed Demon | H45: English,Hindi | I45: 46219 | K45: Horror | L45: =VLOOKUP($C45&$E45,'Updated SES'!A:N,14,0) -> 4.689 | M45: =VLOOKUP($K45,'Genre Penetration'!A:B,2,0)*VLOOKUP($C45&$E45,'Updated SES'!A:I,9,0) -> 0.4556 | N45: =VLOOKUP(K:K,'Genre Penetration'!A:C,3,0)*VLOOKUP($C45&$E45,'Updated SES'!A:J,10,0) -> 0.1056 | O45: =VLOOKUP($B45,'Language Penetration'!$B$1:$BL$14,MATCH('Compile data Working'!$H39,'Language Penetration'!$B$1:$BL$1,0),0) -> 0.2 | P45: =IF(ISBLANK(J45),RANDBETWEEN(1,2)&"%",IF(J45=1,RANDBETWEEN(35,40)&"%",IF(J45=2,RANDBETWEEN(30,35)&"%",IF(J45=3,RANDBETWEEN(25,30)&"%",IF(J45=4,RANDBETWEEN(20,25)&"%",IF(J45=5,RANDBETWEEN(15,20)&"%",IF(J45=6,RANDBETWEEN(10,15)&"%",IF(J45=7,RANDBETWEEN(8,10)&"%",IF(J45=8,RANDBETWEEN(6,8)&"%",IF(J45=9,RANDBETWEEN(4,6)&"%",IF(J45=10,RANDBETWEEN(2,4)&"%",""))))))))))) -> 1% | Q45: =IFERROR(L45*(M45+N45)*O45*P45,RANDBETWEEN(1,2)%*L45*(M45+N45)*O45) -> 0.0052629336 | R45: =VLOOKUP(D:D,ranking!W:X,2,0) -> 0.7 | S45: =R45*Q45 -> 0.0036840535 | T45: 13.215128
A46: Trending Top 10 | B46: ALL INDIA | C46: Amazon MX Player | D46: Avod Originals Shows | E46: FREE | F46: Shows | G46: Ab Hoga Hisaab | H46: Hindi | I46: 46191 | J46: 1 | K46: Crime,Drama,Thriller | L46: =VLOOKUP($C46&$E46,'Updated SES'!A:N,14,0) -> 78.93987 | M46: =VLOOKUP($K46,'Genre Penetration'!A:B,2,0)*VLOOKUP($C46&$E46,'Updated SES'!A:I,9,0) -> 0.576 | N46: =VLOOKUP(K:K,'Genre Penetration'!A:C,3,0)*VLOOKUP($C46&$E46,'Updated SES'!A:J,10,0) -> 0.056 | O46: =VLOOKUP($B46,'Language Penetration'!$B$1:$BL$14,MATCH('Compile data Working'!$H67,'Language Penetration'!$B$1:$BL$1,0),0) -> 0.07 | P46: =IF(ISBLANK(J46),RANDBETWEEN(1,2)&"%",IF(J46=1,RANDBETWEEN(35,40)&"%",IF(J46=2,RANDBETWEEN(30,35)&"%",IF(J46=3,RANDBETWEEN(25,30)&"%",IF(J46=4,RANDBETWEEN(20,25)&"%",IF(J46=5,RANDBETWEEN(15,20)&"%",IF(J46=6,RANDBETWEEN(10,15)&"%",IF(J46=7,RANDBETWEEN(8,10)&"%",IF(J46=8,RANDBETWEEN(6,8)&"%",IF(J46=9,RANDBETWEEN(4,6)&"%",IF(J46=10,RANDBETWEEN(2,4)&"%",""))))))))))) -> 35% | Q46: =IFERROR(L46*(M46+N46)*O46*P46,RANDBETWEEN(1,2)%*L46*(M46+N46)*O46) -> 1.2223049 | R46: =VLOOKUP(D:D,ranking!W:X,2,0) -> 0.6 | S46: =R46*Q46 -> 0.73338297 | T46: 12.980823
A47: WK-28'2026 | B47: ALL INDIA | C47: Amazon Prime Video | D47: Theatrical Movies | E47: PAID | F47: Movies | G47: Honey Bunch | H47: English,Hindi | I47: 46218 | K47: Drama,Horror,Thriller | L47: =VLOOKUP($C47&$E47,'Updated SES'!A:N,14,0) -> 36.49824 | M47: =VLOOKUP($K47,'Genre Penetration'!A:B,2,0)*VLOOKUP($C47&$E47,'Updated SES'!A:I,9,0) -> 0.338 | N47: =VLOOKUP(K:K,'Genre Penetration'!A:C,3,0)*VLOOKUP($C47&$E47,'Updated SES'!A:J,10,0) -> 0.168 | O47: =VLOOKUP($B47,'Language Penetration'!$B$1:$BL$14,MATCH('Compile data Working'!$H23,'Language Penetration'!$B$1:$BL$1,0),0) -> 0.6 | P47: =IF(ISBLANK(J47),RANDBETWEEN(1,2)&"%",IF(J47=1,RANDBETWEEN(35,40)&"%",IF(J47=2,RANDBETWEEN(30,35)&"%",IF(J47=3,RANDBETWEEN(25,30)&"%",IF(J47=4,RANDBETWEEN(20,25)&"%",IF(J47=5,RANDBETWEEN(15,20)&"%",IF(J47=6,RANDBETWEEN(10,15)&"%",IF(J47=7,RANDBETWEEN(8,10)&"%",IF(J47=8,RANDBETWEEN(6,8)&"%",IF(J47=9,RANDBETWEEN(4,6)&"%",IF(J47=10,RANDBETWEEN(2,4)&"%",""))))))))))) -> 2% | Q47: =IFERROR(L47*(M47+N47)*O47*P47,RANDBETWEEN(1,2)%*L47*(M47+N47)*O47) -> 0.22161731 | R47: =VLOOKUP(D:D,ranking!W:X,2,0) -> 0.7 | S47: =R47*Q47 -> 0.15513212 | T47: 12.88475
A48: WK-28'2026 | B48: ALL INDIA | C48: Netflix | D48: SVOD Originals Movies | E48: PAID | F48: Movies | G48: 23 000 Lives | H48: English,Hindi,Tamil,Telugu | I48: 46220 | K48: Drama | L48: =VLOOKUP($C48&$E48,'Updated SES'!A:N,14,0) -> 55.4592 | M48: =VLOOKUP($K48,'Genre Penetration'!A:B,2,0)*VLOOKUP($C48&$E48,'Updated SES'!A:I,9,0) -> 0.245 | N48: =VLOOKUP(K:K,'Genre Penetration'!A:C,3,0)*VLOOKUP($C48&$E48,'Updated SES'!A:J,10,0) -> 0.255 | O48: =VLOOKUP($B48,'Language Penetration'!$B$1:$BL$14,MATCH('Compile data Working'!$H43,'Language Penetration'!$B$1:$BL$1,0),0) -> 0.105 | P48: =IF(ISBLANK(J48),RANDBETWEEN(1,2)&"%",IF(J48=1,RANDBETWEEN(35,40)&"%",IF(J48=2,RANDBETWEEN(30,35)&"%",IF(J48=3,RANDBETWEEN(25,30)&"%",IF(J48=4,RANDBETWEEN(20,25)&"%",IF(J48=5,RANDBETWEEN(15,20)&"%",IF(J48=6,RANDBETWEEN(10,15)&"%",IF(J48=7,RANDBETWEEN(8,10)&"%",IF(J48=8,RANDBETWEEN(6,8)&"%",IF(J48=9,RANDBETWEEN(4,6)&"%",IF(J48=10,RANDBETWEEN(2,4)&"%",""))))))))))) -> 1% | Q48: =IFERROR(L48*(M48+N48)*O48*P48,RANDBETWEEN(1,2)%*L48*(M48+N48)*O48) -> 0.02911608 | R48: =VLOOKUP(D:D,ranking!W:X,2,0) -> 0.8 | S48: =R48*Q48 -> 0.023292864 | T48: 12.874867
A49: WK-28'2026 | B49: ALL INDIA | C49: JioHotstar | D49: Theatrical Movies | E49: PAID | F49: Movies | G49: Night Patrol | H49: English | I49: 46219 | K49: Horror,Mystery,Thriller | L49: =VLOOKUP($C49&$E49,'Updated SES'!A:N,14,0) -> 127.11702 | M49: =VLOOKUP($K49,'Genre Penetration'!A:B,2,0)*VLOOKUP($C49&$E49,'Updated SES'!A:I,9,0) -> 0.4154 | N49: =VLOOKUP(K:K,'Genre Penetration'!A:C,3,0)*VLOOKUP($C49&$E49,'Updated SES'!A:J,10,0) -> 0.1254 | O49: =VLOOKUP($B49,'Language Penetration'!$B$1:$BL$14,MATCH('Compile data Working'!$H37,'Language Penetration'!$B$1:$BL$1,0),0) -> 0.2625 | P49: =IF(ISBLANK(J49),RANDBETWEEN(1,2)&"%",IF(J49=1,RANDBETWEEN(35,40)&"%",IF(J49=2,RANDBETWEEN(30,35)&"%",IF(J49=3,RANDBETWEEN(25,30)&"%",IF(J49=4,RANDBETWEEN(20,25)&"%",IF(J49=5,RANDBETWEEN(15,20)&"%",IF(J49=6,RANDBETWEEN(10,15)&"%",IF(J49=7,RANDBETWEEN(8,10)&"%",IF(J49=8,RANDBETWEEN(6,8)&"%",IF(J49=9,RANDBETWEEN(4,6)&"%",IF(J49=10,RANDBETWEEN(2,4)&"%",""))))))))))) -> 1% | Q49: =IFERROR(L49*(M49+N49)*O49*P49,RANDBETWEEN(1,2)%*L49*(M49+N49)*O49) -> 0.18045532 | R49: =VLOOKUP(D:D,ranking!W:X,2,0) -> 0.7 | S49: =R49*Q49 -> 0.12631873 | T49: 12.770382
A50: Trending Top 10 | B50: ALL INDIA | C50: Netflix | D50: Svod Originals Shows | E50: PAID | F50: Shows | G50: Avatar the Last Airbender Season 2 | H50: English,Hindi | I50: 46198 | J50: 10 | K50: Action,Adventure,Comedy | L50: =VLOOKUP($C50&$E50,'Updated SES'!A:N,14,0) -> 55.4592 | M50: =VLOOKUP($K50,'Genre Penetration'!A:B,2,0)*VLOOKUP($C50&$E50,'Updated SES'!A:I,9,0) -> 0.294 | N50: =VLOOKUP(K:K,'Genre Penetration'!A:C,3,0)*VLOOKUP($C50&$E50,'Updated SES'!A:J,10,0) -> 0.204 | O50: =VLOOKUP($B50,'Language Penetration'!$B$1:$BL$14,MATCH('Compile data Working'!$H103,'Language Penetration'!$B$1:$BL$1,0),0) -> 0.6 | P50: =IF(ISBLANK(J50),RANDBETWEEN(1,2)&"%",IF(J50=1,RANDBETWEEN(35,40)&"%",IF(J50=2,RANDBETWEEN(30,35)&"%",IF(J50=3,RANDBETWEEN(25,30)&"%",IF(J50=4,RANDBETWEEN(20,25)&"%",IF(J50=5,RANDBETWEEN(15,20)&"%",IF(J50=6,RANDBETWEEN(10,15)&"%",IF(J50=7,RANDBETWEEN(8,10)&"%",IF(J50=8,RANDBETWEEN(6,8)&"%",IF(J50=9,RANDBETWEEN(4,6)&"%",IF(J50=10,RANDBETWEEN(2,4)&"%",""))))))))))) -> 3% | Q50: =IFERROR(L50*(M50+N50)*O50*P50,RANDBETWEEN(1,2)%*L50*(M50+N50)*O50) -> 0.49713627 | R50: =VLOOKUP(D:D,ranking!W:X,2,0) -> 0.6 | S50: =R50*Q50 -> 0.29828176 | T50: 12.610177
A51: WK-28'2026 | B51: ALL INDIA | C51: JioHotstar | D51: SVOD Originals Movies | E51: PAID | F51: Movies | G51: The Odyssey: The Making of an Epic | H51: English | I51: 46217 | K51: Documentary | L51: =VLOOKUP($C51&$E51,'Updated SES'!A:N,14,0) -> 127.11702 | M51: =VLOOKUP($K51,'Genre Penetration'!A:B,2,0)*VLOOKUP($C51&$E51,'Updated SES'!A:I,9,0) -> 0.3015 | N51: =VLOOKUP(K:K,'Genre Penetration'!A:C,3,0)*VLOOKUP($C51&$E51,'Updated SES'!A:J,10,0) -> 0.1815 | O51: =VLOOKUP($B51,'Language Penetration'!$B$1:$BL$14,MATCH('Compile data Working'!$H22,'Language Penetration'!$B$1:$BL$1,0),0) -> 0.2 | P51: =IF(ISBLANK(J51),RANDBETWEEN(1,2)&"%",IF(J51=1,RANDBETWEEN(35,40)&"%",IF(J51=2,RANDBETWEEN(30,35)&"%",IF(J51=3,RANDBETWEEN(25,30)&"%",IF(J51=4,RANDBETWEEN(20,25)&"%",IF(J51=5,RANDBETWEEN(15,20)&"%",IF(J51=6,RANDBETWEEN(10,15)&"%",IF(J51=7,RANDBETWEEN(8,10)&"%",IF(J51=8,RANDBETWEEN(6,8)&"%",IF(J51=9,RANDBETWEEN(4,6)&"%",IF(J51=10,RANDBETWEEN(2,4)&"%",""))))))))))) -> 1% | Q51: =IFERROR(L51*(M51+N51)*O51*P51,RANDBETWEEN(1,2)%*L51*(M51+N51)*O51) -> 0.12279504 | R51: =VLOOKUP(D:D,ranking!W:X,2,0) -> 0.8 | S51: =R51*Q51 -> 0.098236033 | T51: 12.594723
A52: WK-28'2026 | B52: ALL INDIA | C52: Amazon Prime Video | D52: SVOD Originals Shows | E52: PAID | F52: Shows | G52: Young Farts Trailer Parts | H52: English | I52: 46220 | K52: Documentary | L52: =VLOOKUP($C52&$E52,'Updated SES'!A:N,14,0) -> 36.49824 | M52: =VLOOKUP($K52,'Genre Penetration'!A:B,2,0)*VLOOKUP($C52&$E52,'Updated SES'!A:I,9,0) -> 0.234 | N52: =VLOOKUP(K:K,'Genre Penetration'!A:C,3,0)*VLOOKUP($C52&$E52,'Updated SES'!A:J,10,0) -> 0.264 | O52: =VLOOKUP($B52,'Language Penetration'!$B$1:$BL$14,MATCH('Compile data Working'!$H64,'Language Penetration'!$B$1:$BL$1,0),0) -> 0.4 | P52: =IF(ISBLANK(J52),RANDBETWEEN(1,2)&"%",IF(J52=1,RANDBETWEEN(35,40)&"%",IF(J52=2,RANDBETWEEN(30,35)&"%",IF(J52=3,RANDBETWEEN(25,30)&"%",IF(J52=4,RANDBETWEEN(20,25)&"%",IF(J52=5,RANDBETWEEN(15,20)&"%",IF(J52=6,RANDBETWEEN(10,15)&"%",IF(J52=7,RANDBETWEEN(8,10)&"%",IF(J52=8,RANDBETWEEN(6,8)&"%",IF(J52=9,RANDBETWEEN(4,6)&"%",IF(J52=10,RANDBETWEEN(2,4)&"%",""))))))))))) -> 2% | Q52: =IFERROR(L52*(M52+N52)*O52*P52,RANDBETWEEN(1,2)%*L52*(M52+N52)*O52) -> 0.14540899 | R52: =VLOOKUP(D:D,ranking!W:X,2,0) -> 0.6 | S52: =R52*Q52 -> 0.087245393 | T52: 12.389182
A53: WK-28'2026 | B53: ALL INDIA | C53: Amazon Prime Video | D53: Theatrical Movies | E53: RENT | F53: Movies | G53: City of Dreams | H53: English | I53: 46217 | K53: Crime,Mystery,Thriller | L53: =VLOOKUP($C53&$E53,'Updated SES'!A:N,14,0) -> 4.689 | M53: =VLOOKUP($K53,'Genre Penetration'!A:B,2,0)*VLOOKUP($C53&$E53,'Updated SES'!A:I,9,0) -> 0.3944 | N53: =VLOOKUP(K:K,'Genre Penetration'!A:C,3,0)*VLOOKUP($C53&$E53,'Updated SES'!A:J,10,0) -> 0.1344 | O53: =VLOOKUP($B53,'Language Penetration'!$B$1:$BL$14,MATCH('Compile data Working'!$H18,'Language Penetration'!$B$1:$BL$1,0),0) -> 0.6 | P53: =IF(ISBLANK(J53),RANDBETWEEN(1,2)&"%",IF(J53=1,RANDBETWEEN(35,40)&"%",IF(J53=2,RANDBETWEEN(30,35)&"%",IF(J53=3,RANDBETWEEN(25,30)&"%",IF(J53=4,RANDBETWEEN(20,25)&"%",IF(J53=5,RANDBETWEEN(15,20)&"%",IF(J53=6,RANDBETWEEN(10,15)&"%",IF(J53=7,RANDBETWEEN(8,10)&"%",IF(J53=8,RANDBETWEEN(6,8)&"%",IF(J53=9,RANDBETWEEN(4,6)&"%",IF(J53=10,RANDBETWEEN(2,4)&"%",""))))))))))) -> 1% | Q53: =IFERROR(L53*(M53+N53)*O53*P53,RANDBETWEEN(1,2)%*L53*(M53+N53)*O53) -> 0.014877259 | R53: =VLOOKUP(D:D,ranking!W:X,2,0) -> 0.7 | S53: =R53*Q53 -> 0.010414081 | T53: 12.223993
A54: WK-28'2026 | B54: ALL INDIA | C54: Netflix | D54: SVOD Originals Shows | E54: PAID | F54: Shows | G54: Young Sheldon Season 6 | H54: English | I54: 46218 | K54: Comedy | L54: =VLOOKUP($C54&$E54,'Updated SES'!A:N,14,0) -> 55.4592 | M54: =VLOOKUP($K54,'Genre Penetration'!A:B,2,0)*VLOOKUP($C54&$E54,'Updated SES'!A:I,9,0) -> 0.2205 | N54: =VLOOKUP(K:K,'Genre Penetration'!A:C,3,0)*VLOOKUP($C54&$E54,'Updated SES'!A:J,10,0) -> 0.2805 | O54: =VLOOKUP($B54,'Language Penetration'!$B$1:$BL$14,MATCH('Compile data Working'!$H30,'Language Penetration'!$B$1:$BL$1,0),0) -> 0.6 | P54: =IF(ISBLANK(J54),RANDBETWEEN(1,2)&"%",IF(J54=1,RANDBETWEEN(35,40)&"%",IF(J54=2,RANDBETWEEN(30,35)&"%",IF(J54=3,RANDBETWEEN(25,30)&"%",IF(J54=4,RANDBETWEEN(20,25)&"%",IF(J54=5,RANDBETWEEN(15,20)&"%",IF(J54=6,RANDBETWEEN(10,15)&"%",IF(J54=7,RANDBETWEEN(8,10)&"%",IF(J54=8,RANDBETWEEN(6,8)&"%",IF(J54=9,RANDBETWEEN(4,6)&"%",IF(J54=10,RANDBETWEEN(2,4)&"%",""))))))))))) -> 2% | Q54: =IFERROR(L54*(M54+N54)*O54*P54,RANDBETWEEN(1,2)%*L54*(M54+N54)*O54) -> 0.33342071 | R54: =VLOOKUP(D:D,ranking!W:X,2,0) -> 0.6 | S54: =R54*Q54 -> 0.20005243 | T54: 12.07726
A55: WK-28'2026 | B55: ALL INDIA | C55: Netflix | D55: SVOD Originals Shows | E55: PAID | F55: Shows | G55: Switched on Pop | H55: English | I55: 46217 | K55: Music | L55: =VLOOKUP($C55&$E55,'Updated SES'!A:N,14,0) -> 55.4592 | M55: =VLOOKUP($K55,'Genre Penetration'!A:B,2,0)*VLOOKUP($C55&$E55,'Updated SES'!A:I,9,0) -> 0.2695 | N55: =VLOOKUP(K:K,'Genre Penetration'!A:C,3,0)*VLOOKUP($C55&$E55,'Updated SES'!A:J,10,0) -> 0.2295 | O55: =VLOOKUP($B55,'Language Penetration'!$B$1:$BL$14,MATCH('Compile data Working'!$H21,'Language Penetration'!$B$1:$BL$1,0),0) -> 0.204 | P55: =IF(ISBLANK(J55),RANDBETWEEN(1,2)&"%",IF(J55=1,RANDBETWEEN(35,40)&"%",IF(J55=2,RANDBETWEEN(30,35)&"%",IF(J55=3,RANDBETWEEN(25,30)&"%",IF(J55=4,RANDBETWEEN(20,25)&"%",IF(J55=5,RANDBETWEEN(15,20)&"%",IF(J55=6,RANDBETWEEN(10,15)&"%",IF(J55=7,RANDBETWEEN(8,10)&"%",IF(J55=8,RANDBETWEEN(6,8)&"%",IF(J55=9,RANDBETWEEN(4,6)&"%",IF(J55=10,RANDBETWEEN(2,4)&"%",""))))))))))) -> 2% | Q55: =IFERROR(L55*(M55+N55)*O55*P55,RANDBETWEEN(1,2)%*L55*(M55+N55)*O55) -> 0.11291049 | R55: =VLOOKUP(D:D,ranking!W:X,2,0) -> 0.6 | S55: =R55*Q55 -> 0.067746297 | T55: 11.684441
A56: WK-28'2026 | B56: ALL INDIA | C56: Amazon Prime Video | D56: SVOD Originals Shows | E56: PAID | F56: Shows | G56: Murder 101 | H56: English | I56: 46216 | K56: Crime,Drama | L56: =VLOOKUP($C56&$E56,'Updated SES'!A:N,14,0) -> 36.49824 | M56: =VLOOKUP($K56,'Genre Penetration'!A:B,2,0)*VLOOKUP($C56&$E56,'Updated SES'!A:I,9,0) -> 0.3016 | N56: =VLOOKUP(K:K,'Genre Penetration'!A:C,3,0)*VLOOKUP($C56&$E56,'Updated SES'!A:J,10,0) -> 0.2016 | O56: =VLOOKUP($B56,'Language Penetration'!$B$1:$BL$14,MATCH('Compile data Working'!$H12,'Language Penetration'!$B$1:$BL$1,0),0) -> 0.6 | P56: =IF(ISBLANK(J56),RANDBETWEEN(1,2)&"%",IF(J56=1,RANDBETWEEN(35,40)&"%",IF(J56=2,RANDBETWEEN(30,35)&"%",IF(J56=3,RANDBETWEEN(25,30)&"%",IF(J56=4,RANDBETWEEN(20,25)&"%",IF(J56=5,RANDBETWEEN(15,20)&"%",IF(J56=6,RANDBETWEEN(10,15)&"%",IF(J56=7,RANDBETWEEN(8,10)&"%",IF(J56=8,RANDBETWEEN(6,8)&"%",IF(J56=9,RANDBETWEEN(4,6)&"%",IF(J56=10,RANDBETWEEN(2,4)&"%",""))))))))))) -> 2% | Q56: =IFERROR(L56*(M56+N56)*O56*P56,RANDBETWEEN(1,2)%*L56*(M56+N56)*O56) -> 0.22039097 | R56: =VLOOKUP(D:D,ranking!W:X,2,0) -> 0.6 | S56: =R56*Q56 -> 0.13223458 | T56: 11.563237
A57: WK-28'2026 | B57: ALL INDIA | C57: Netflix | D57: SVOD Originals Movies | E57: PAID | F57: Movies | G57: Me Before Me | H57: English,Hindi | I57: 46219 | K57: Comedy,Drama | L57: =VLOOKUP($C57&$E57,'Updated SES'!A:N,14,0) -> 55.4592 | M57: =VLOOKUP($K57,'Genre Penetration'!A:B,2,0)*VLOOKUP($C57&$E57,'Updated SES'!A:I,9,0) -> 0.2303 | N57: =VLOOKUP(K:K,'Genre Penetration'!A:C,3,0)*VLOOKUP($C57&$E57,'Updated SES'!A:J,10,0) -> 0.2703 | O57: =VLOOKUP($B57,'Language Penetration'!$B$1:$BL$14,MATCH('Compile data Working'!$H36,'Language Penetration'!$B$1:$BL$1,0),0) -> 0.4 | P57: =IF(ISBLANK(J57),RANDBETWEEN(1,2)&"%",IF(J57=1,RANDBETWEEN(35,40)&"%",IF(J57=2,RANDBETWEEN(30,35)&"%",IF(J57=3,RANDBETWEEN(25,30)&"%",IF(J57=4,RANDBETWEEN(20,25)&"%",IF(J57=5,RANDBETWEEN(15,20)&"%",IF(J57=6,RANDBETWEEN(10,15)&"%",IF(J57=7,RANDBETWEEN(8,10)&"%",IF(J57=8,RANDBETWEEN(6,8)&"%",IF(J57=9,RANDBETWEEN(4,6)&"%",IF(J57=10,RANDBETWEEN(2,4)&"%",""))))))))))) -> 2% | Q57: =IFERROR(L57*(M57+N57)*O57*P57,RANDBETWEEN(1,2)%*L57*(M57+N57)*O57) -> 0.222103 | R57: =VLOOKUP(D:D,ranking!W:X,2,0) -> 0.8 | S57: =R57*Q57 -> 0.1776824 | T57: 11.537978
A58: WK-28'2026 | B58: ALL INDIA | C58: Netflix | D58: SVOD Originals Shows | E58: PAID | F58: Shows | G58: The Tick Season 2 | H58: English | I58: 46218 | K58: Action,Adventure,Comedy | L58: =VLOOKUP($C58&$E58,'Updated SES'!A:N,14,0) -> 55.4592 | M58: =VLOOKUP($K58,'Genre Penetration'!A:B,2,0)*VLOOKUP($C58&$E58,'Updated SES'!A:I,9,0) -> 0.294 | N58: =VLOOKUP(K:K,'Genre Penetration'!A:C,3,0)*VLOOKUP($C58&$E58,'Updated SES'!A:J,10,0) -> 0.204 | O58: =VLOOKUP($B58,'Language Penetration'!$B$1:$BL$14,MATCH('Compile data Working'!$H28,'Language Penetration'!$B$1:$BL$1,0),0) -> 0.4 | P58: =IF(ISBLANK(J58),RANDBETWEEN(1,2)&"%",IF(J58=1,RANDBETWEEN(35,40)&"%",IF(J58=2,RANDBETWEEN(30,35)&"%",IF(J58=3,RANDBETWEEN(25,30)&"%",IF(J58=4,RANDBETWEEN(20,25)&"%",IF(J58=5,RANDBETWEEN(15,20)&"%",IF(J58=6,RANDBETWEEN(10,15)&"%",IF(J58=7,RANDBETWEEN(8,10)&"%",IF(J58=8,RANDBETWEEN(6,8)&"%",IF(J58=9,RANDBETWEEN(4,6)&"%",IF(J58=10,RANDBETWEEN(2,4)&"%",""))))))))))) -> 2% | Q58: =IFERROR(L58*(M58+N58)*O58*P58,RANDBETWEEN(1,2)%*L58*(M58+N58)*O58) -> 0.22094945 | R58: =VLOOKUP(D:D,ranking!W:X,2,0) -> 0.6 | S58: =R58*Q58 -> 0.13256967 | T58: 11.178457
A59: WK-28'2026 | B59: ALL INDIA | C59: JioHotstar | D59: Theatrical Movies | E59: PAID | F59: Movies | G59: Ready or Not: Here I Come | H59: English | I59: 46220 | K59: Comedy,Horror,Thriller | L59: =VLOOKUP($C59&$E59,'Updated SES'!A:N,14,0) -> 127.11702 | M59: =VLOOKUP($K59,'Genre Penetration'!A:B,2,0)*VLOOKUP($C59&$E59,'Updated SES'!A:I,9,0) -> 0.43885 | N59: =VLOOKUP(K:K,'Genre Penetration'!A:C,3,0)*VLOOKUP($C59&$E59,'Updated SES'!A:J,10,0) -> 0.11385 | O59: =VLOOKUP($B59,'Language Penetration'!$B$1:$BL$14,MATCH('Compile data Working'!$H56,'Language Penetration'!$B$1:$BL$1,0),0) -> 0.2 | P59: =IF(ISBLANK(J59),RANDBETWEEN(1,2)&"%",IF(J59=1,RANDBETWEEN(35,40)&"%",IF(J59=2,RANDBETWEEN(30,35)&"%",IF(J59=3,RANDBETWEEN(25,30)&"%",IF(J59=4,RANDBETWEEN(20,25)&"%",IF(J59=5,RANDBETWEEN(15,20)&"%",IF(J59=6,RANDBETWEEN(10,15)&"%",IF(J59=7,RANDBETWEEN(8,10)&"%",IF(J59=8,RANDBETWEEN(6,8)&"%",IF(J59=9,RANDBETWEEN(4,6)&"%",IF(J59=10,RANDBETWEEN(2,4)&"%",""))))))))))) -> 2% | Q59: =IFERROR(L59*(M59+N59)*O59*P59,RANDBETWEEN(1,2)%*L59*(M59+N59)*O59) -> 0.28103031 | R59: =VLOOKUP(D:D,ranking!W:X,2,0) -> 0.7 | S59: =R59*Q59 -> 0.19672122 | T59: 10.946042
A60: WK-28'2026 | B60: ALL INDIA | C60: Netflix | D60: SVOD Originals Shows | E60: PAID | F60: Shows | G60: On Purpose with Jay Shetty Season 2 | H60: English | I60: 46216 | K60: Talk Show | L60: =VLOOKUP($C60&$E60,'Updated SES'!A:N,14,0) -> 55.4592 | M60: =VLOOKUP($K60,'Genre Penetration'!A:B,2,0)*VLOOKUP($C60&$E60,'Updated SES'!A:I,9,0) -> 0.245 | N60: =VLOOKUP(K:K,'Genre Penetration'!A:C,3,0)*VLOOKUP($C60&$E60,'Updated SES'!A:J,10,0) -> 0.255 | O60: =VLOOKUP($B60,'Language Penetration'!$B$1:$BL$14,MATCH('Compile data Working'!$H13,'Language Penetration'!$B$1:$BL$1,0),0) -> 0.6 | P60: =IF(ISBLANK(J60),RANDBETWEEN(1,2)&"%",IF(J60=1,RANDBETWEEN(35,40)&"%",IF(J60=2,RANDBETWEEN(30,35)&"%",IF(J60=3,RANDBETWEEN(25,30)&"%",IF(J60=4,RANDBETWEEN(20,25)&"%",IF(J60=5,RANDBETWEEN(15,20)&"%",IF(J60=6,RANDBETWEEN(10,15)&"%",IF(J60=7,RANDBETWEEN(8,10)&"%",IF(J60=8,RANDBETWEEN(6,8)&"%",IF(J60=9,RANDBETWEEN(4,6)&"%",IF(J60=10,RANDBETWEEN(2,4)&"%",""))))))))))) -> 2% | Q60: =IFERROR(L60*(M60+N60)*O60*P60,RANDBETWEEN(1,2)%*L60*(M60+N60)*O60) -> 0.3327552 | R60: =VLOOKUP(D:D,ranking!W:X,2,0) -> 0.6 | S60: =R60*Q60 -> 0.19965312 | T60: 10.785638
A61: WK-28'2026 | B61: ALL INDIA | C61: Amazon Prime Video | D61: SVOD Originals Shows | E61: PAID | F61: Shows | G61: A Brief History of Cricket Down Under: Changing of the Guard | H61: English | I61: 46219 | K61: Documentary | L61: =VLOOKUP($C61&$E61,'Updated SES'!A:N,14,0) -> 36.49824 | M61: =VLOOKUP($K61,'Genre Penetration'!A:B,2,0)*VLOOKUP($C61&$E61,'Updated SES'!A:I,9,0) -> 0.234 | N61: =VLOOKUP(K:K,'Genre Penetration'!A:C,3,0)*VLOOKUP($C61&$E61,'Updated SES'!A:J,10,0) -> 0.264 | O61: =VLOOKUP($B61,'Language Penetration'!$B$1:$BL$14,MATCH('Compile data Working'!$H31,'Language Penetration'!$B$1:$BL$1,0),0) -> 0.4 | P61: =IF(ISBLANK(J61),RANDBETWEEN(1,2)&"%",IF(J61=1,RANDBETWEEN(35,40)&"%",IF(J61=2,RANDBETWEEN(30,35)&"%",IF(J61=3,RANDBETWEEN(25,30)&"%",IF(J61=4,RANDBETWEEN(20,25)&"%",IF(J61=5,RANDBETWEEN(15,20)&"%",IF(J61=6,RANDBETWEEN(10,15)&"%",IF(J61=7,RANDBETWEEN(8,10)&"%",IF(J61=8,RANDBETWEEN(6,8)&"%",IF(J61=9,RANDBETWEEN(4,6)&"%",IF(J61=10,RANDBETWEEN(2,4)&"%",""))))))))))) -> 2% | Q61: =IFERROR(L61*(M61+N61)*O61*P61,RANDBETWEEN(1,2)%*L61*(M61+N61)*O61) -> 0.14540899 | R61: =VLOOKUP(D:D,ranking!W:X,2,0) -> 0.6 | S61: =R61*Q61 -> 0.087245393 | T61: 10.737291
A62: WK-28'2026 | B62: ALL INDIA | C62: Netflix | D62: SVOD Originals Movies | E62: PAID | F62: Movies | G62: Heartstopper Forever | H62: English,Hindi | I62: 46220 | K62: Drama,Romance | L62: =VLOOKUP($C62&$E62,'Updated SES'!A:N,14,0) -> 55.4592 | M62: =VLOOKUP($K62,'Genre Penetration'!A:B,2,0)*VLOOKUP($C62&$E62,'Updated SES'!A:I,9,0) -> 0.196 | N62: =VLOOKUP(K:K,'Genre Penetration'!A:C,3,0)*VLOOKUP($C62&$E62,'Updated SES'!A:J,10,0) -> 0.306 | O62: =VLOOKUP($B62,'Language Penetration'!$B$1:$BL$14,MATCH('Compile data Working'!$H51,'Language Penetration'!$B$1:$BL$1,0),0) -> 0.2 | P62: =IF(ISBLANK(J62),RANDBETWEEN(1,2)&"%",IF(J62=1,RANDBETWEEN(35,40)&"%",IF(J62=2,RANDBETWEEN(30,35)&"%",IF(J62=3,RANDBETWEEN(25,30)&"%",IF(J62=4,RANDBETWEEN(20,25)&"%",IF(J62=5,RANDBETWEEN(15,20)&"%",IF(J62=6,RANDBETWEEN(10,15)&"%",IF(J62=7,RANDBETWEEN(8,10)&"%",IF(J62=8,RANDBETWEEN(6,8)&"%",IF(J62=9,RANDBETWEEN(4,6)&"%",IF(J62=10,RANDBETWEEN(2,4)&"%",""))))))))))) -> 1% | Q62: =IFERROR(L62*(M62+N62)*O62*P62,RANDBETWEEN(1,2)%*L62*(M62+N62)*O62) -> 0.055681037 | R62: =VLOOKUP(D:D,ranking!W:X,2,0) -> 0.8 | S62: =R62*Q62 -> 0.044544829 | T62: 10.661808
A63: Trending Top 10 | B63: ALL INDIA | C63: Netflix | D63: Svod Originals Shows | E63: PAID | F63: Shows | G63: Agent Kim Reactivated | H63: English | I63: 46200 | J63: 4 | K63: Action,Crime,Thriller | L63: =VLOOKUP($C63&$E63,'Updated SES'!A:N,14,0) -> 55.4592 | M63: =VLOOKUP($K63,'Genre Penetration'!A:B,2,0)*VLOOKUP($C63&$E63,'Updated SES'!A:I,9,0) -> 0.3528 | N63: =VLOOKUP(K:K,'Genre Penetration'!A:C,3,0)*VLOOKUP($C63&$E63,'Updated SES'!A:J,10,0) -> 0.1428 | O63: =VLOOKUP($B63,'Language Penetration'!$B$1:$BL$14,MATCH('Compile data Working'!$H100,'Language Penetration'!$B$1:$BL$1,0),0) -> 0.204 | P63: =IF(ISBLANK(J63),RANDBETWEEN(1,2)&"%",IF(J63=1,RANDBETWEEN(35,40)&"%",IF(J63=2,RANDBETWEEN(30,35)&"%",IF(J63=3,RANDBETWEEN(25,30)&"%",IF(J63=4,RANDBETWEEN(20,25)&"%",IF(J63=5,RANDBETWEEN(15,20)&"%",IF(J63=6,RANDBETWEEN(10,15)&"%",IF(J63=7,RANDBETWEEN(8,10)&"%",IF(J63=8,RANDBETWEEN(6,8)&"%",IF(J63=9,RANDBETWEEN(4,6)&"%",IF(J63=10,RANDBETWEEN(2,4)&"%",""))))))))))) -> 21% | Q63: =IFERROR(L63*(M63+N63)*O63*P63,RANDBETWEEN(1,2)%*L63*(M63+N63)*O63) -> 1.1774822 | R63: =VLOOKUP(D:D,ranking!W:X,2,0) -> 0.6 | S63: =R63*Q63 -> 0.70648934 | T63: 10.603356
A64: WK-28'2026 | B64: ALL INDIA | C64: Netflix | D64: Theatrical Movies | E64: PAID | F64: Movies | G64: Golden Kamuy -The Abashiri Prison Raid- | H64: English,Hindi | I64: 46216 | K64: Action,Adventure,Drama | L64: =VLOOKUP($C64&$E64,'Updated SES'!A:N,14,0) -> 55.4592 | M64: =VLOOKUP($K64,'Genre Penetration'!A:B,2,0)*VLOOKUP($C64&$E64,'Updated SES'!A:I,9,0) -> 0.2842 | N64: =VLOOKUP(K:K,'Genre Penetration'!A:C,3,0)*VLOOKUP($C64&$E64,'Updated SES'!A:J,10,0) -> 0.2142 | O64: =VLOOKUP($B64,'Language Penetration'!$B$1:$BL$14,MATCH('Compile data Working'!$H10,'Language Penetration'!$B$1:$BL$1,0),0) -> 0.19 | P64: =IF(ISBLANK(J64),RANDBETWEEN(1,2)&"%",IF(J64=1,RANDBETWEEN(35,40)&"%",IF(J64=2,RANDBETWEEN(30,35)&"%",IF(J64=3,RANDBETWEEN(25,30)&"%",IF(J64=4,RANDBETWEEN(20,25)&"%",IF(J64=5,RANDBETWEEN(15,20)&"%",IF(J64=6,RANDBETWEEN(10,15)&"%",IF(J64=7,RANDBETWEEN(8,10)&"%",IF(J64=8,RANDBETWEEN(6,8)&"%",IF(J64=9,RANDBETWEEN(4,6)&"%",IF(J64=10,RANDBETWEEN(2,4)&"%",""))))))))))) -> 2% | Q64: =IFERROR(L64*(M64+N64)*O64*P64,RANDBETWEEN(1,2)%*L64*(M64+N64)*O64) -> 0.10503529 | R64: =VLOOKUP(D:D,ranking!W:X,2,0) -> 0.7 | S64: =R64*Q64 -> 0.073524702 | T64: 10.380851
A65: Trending Top 10 | B65: ALL INDIA | C65: Netflix | D65: Svod Originals Shows | E65: PAID | F65: Shows | G65: Teach You a Lesson | H65: English,Hindi,Tamil,Telugu | I65: 46178 | J65: 8 | K65: Action,Drama | L65: =VLOOKUP($C65&$E65,'Updated SES'!A:N,14,0) -> 55.4592 | M65: =VLOOKUP($K65,'Genre Penetration'!A:B,2,0)*VLOOKUP($C65&$E65,'Updated SES'!A:I,9,0) -> 0.2597 | N65: =VLOOKUP(K:K,'Genre Penetration'!A:C,3,0)*VLOOKUP($C65&$E65,'Updated SES'!A:J,10,0) -> 0.2397 | O65: =VLOOKUP($B65,'Language Penetration'!$B$1:$BL$14,MATCH('Compile data Working'!$H102,'Language Penetration'!$B$1:$BL$1,0),0) -> 0.1 | P65: =IF(ISBLANK(J65),RANDBETWEEN(1,2)&"%",IF(J65=1,RANDBETWEEN(35,40)&"%",IF(J65=2,RANDBETWEEN(30,35)&"%",IF(J65=3,RANDBETWEEN(25,30)&"%",IF(J65=4,RANDBETWEEN(20,25)&"%",IF(J65=5,RANDBETWEEN(15,20)&"%",IF(J65=6,RANDBETWEEN(10,15)&"%",IF(J65=7,RANDBETWEEN(8,10)&"%",IF(J65=8,RANDBETWEEN(6,8)&"%",IF(J65=9,RANDBETWEEN(4,6)&"%",IF(J65=10,RANDBETWEEN(2,4)&"%",""))))))))))) -> 8% | Q65: =IFERROR(L65*(M65+N65)*O65*P65,RANDBETWEEN(1,2)%*L65*(M65+N65)*O65) -> 0.2215706 | R65: =VLOOKUP(D:D,ranking!W:X,2,0) -> 0.6 | S65: =R65*Q65 -> 0.13294236 | T65: 10.014281
A66: WK-28'2026 | B66: ALL INDIA | C66: Amazon Prime Video | D66: Theatrical Movies | E66: PAID | F66: Movies | G66: The Breadwinner | H66: English | I66: 46219 | K66: Comedy | L66: =VLOOKUP($C66&$E66,'Updated SES'!A:N,14,0) -> 36.49824 | M66: =VLOOKUP($K66,'Genre Penetration'!A:B,2,0)*VLOOKUP($C66&$E66,'Updated SES'!A:I,9,0) -> 0.234 | N66: =VLOOKUP(K:K,'Genre Penetration'!A:C,3,0)*VLOOKUP($C66&$E66,'Updated SES'!A:J,10,0) -> 0.264 | O66: =VLOOKUP($B66,'Language Penetration'!$B$1:$BL$14,MATCH('Compile data Working'!$H40,'Language Penetration'!$B$1:$BL$1,0),0) -> 0.4 | P66: =IF(ISBLANK(J66),RANDBETWEEN(1,2)&"%",IF(J66=1,RANDBETWEEN(35,40)&"%",IF(J66=2,RANDBETWEEN(30,35)&"%",IF(J66=3,RANDBETWEEN(25,30)&"%",IF(J66=4,RANDBETWEEN(20,25)&"%",IF(J66=5,RANDBETWEEN(15,20)&"%",IF(J66=6,RANDBETWEEN(10,15)&"%",IF(J66=7,RANDBETWEEN(8,10)&"%",IF(J66=8,RANDBETWEEN(6,8)&"%",IF(J66=9,RANDBETWEEN(4,6)&"%",IF(J66=10,RANDBETWEEN(2,4)&"%",""))))))))))) -> 1% | Q66: =IFERROR(L66*(M66+N66)*O66*P66,RANDBETWEEN(1,2)%*L66*(M66+N66)*O66) -> 0.072704494 | R66: =VLOOKUP(D:D,ranking!W:X,2,0) -> 0.7 | S66: =R66*Q66 -> 0.050893146 | T66: 9.911346
A67: WK-28'2026 | B67: ALL INDIA | C67: Manorama Max | D67: Theatrical Movies | E67: PAID | F67: Movies | G67: Oru Vadakkan Velicham | H67: Malayalam | I67: 46217 | K67: Crime | L67: =VLOOKUP($C67&$E67,'Updated SES'!A:N,14,0) -> 0.1509 | M67: =VLOOKUP($K67,'Genre Penetration'!A:B,2,0)*VLOOKUP($C67&$E67,'Updated SES'!A:I,9,0) -> 0.4514 | N67: =VLOOKUP(K:K,'Genre Penetration'!A:C,3,0)*VLOOKUP($C67&$E67,'Updated SES'!A:J,10,0) -> 0.1014 | O67: =VLOOKUP($B67,'Language Penetration'!$B$1:$BL$14,MATCH('Compile data Working'!$H19,'Language Penetration'!$B$1:$BL$1,0),0) -> 0.4 | P67: =IF(ISBLANK(J67),RANDBETWEEN(1,2)&"%",IF(J67=1,RANDBETWEEN(35,40)&"%",IF(J67=2,RANDBETWEEN(30,35)&"%",IF(J67=3,RANDBETWEEN(25,30)&"%",IF(J67=4,RANDBETWEEN(20,25)&"%",IF(J67=5,RANDBETWEEN(15,20)&"%",IF(J67=6,RANDBETWEEN(10,15)&"%",IF(J67=7,RANDBETWEEN(8,10)&"%",IF(J67=8,RANDBETWEEN(6,8)&"%",IF(J67=9,RANDBETWEEN(4,6)&"%",IF(J67=10,RANDBETWEEN(2,4)&"%",""))))))))))) -> 1% | Q67: =IFERROR(L67*(M67+N67)*O67*P67,RANDBETWEEN(1,2)%*L67*(M67+N67)*O67) -> 0.00033367008 | R67: =VLOOKUP(D:D,ranking!W:X,2,0) -> 0.7 | S67: =R67*Q67 -> 0.00023356906 | T67: 9.7791947
A68: WK-28'2026 | B68: ALL INDIA | C68: Amazon Prime Video | D68: Theatrical Movies | E68: PAID | F68: Movies | G68: Sannidhanam P.O. | H68: Tamil | I68: 46220 | K68: Drama,Mystery | L68: =VLOOKUP($C68&$E68,'Updated SES'!A:N,14,0) -> 36.49824 | M68: =VLOOKUP($K68,'Genre Penetration'!A:B,2,0)*VLOOKUP($C68&$E68,'Updated SES'!A:I,9,0) -> 0.3016 | N68: =VLOOKUP(K:K,'Genre Penetration'!A:C,3,0)*VLOOKUP($C68&$E68,'Updated SES'!A:J,10,0) -> 0.2016 | O68: =VLOOKUP($B68,'Language Penetration'!$B$1:$BL$14,MATCH('Compile data Working'!$H57,'Language Penetration'!$B$1:$BL$1,0),0) -> 0.4 | P68: =IF(ISBLANK(J68),RANDBETWEEN(1,2)&"%",IF(J68=1,RANDBETWEEN(35,40)&"%",IF(J68=2,RANDBETWEEN(30,35)&"%",IF(J68=3,RANDBETWEEN(25,30)&"%",IF(J68=4,RANDBETWEEN(20,25)&"%",IF(J68=5,RANDBETWEEN(15,20)&"%",IF(J68=6,RANDBETWEEN(10,15)&"%",IF(J68=7,RANDBETWEEN(8,10)&"%",IF(J68=8,RANDBETWEEN(6,8)&"%",IF(J68=9,RANDBETWEEN(4,6)&"%",IF(J68=10,RANDBETWEEN(2,4)&"%",""))))))))))) -> 2% | Q68: =IFERROR(L68*(M68+N68)*O68*P68,RANDBETWEEN(1,2)%*L68*(M68+N68)*O68) -> 0.14692731 | R68: =VLOOKUP(D:D,ranking!W:X,2,0) -> 0.7 | S68: =R68*Q68 -> 0.10284912 | T68: 9.5809678
A69: Trending Top 10 | B69: ALL INDIA | C69: Amazon Prime Video | D69: Theatrical Movies | E69: PAID | F69: Movies | G69: Dose | H69: Hindi,Malayalam,Tamil,Telugu | I69: 46213 | J69: 9 | K69: Drama | L69: =VLOOKUP($C69&$E69,'Updated SES'!A:N,14,0) -> 36.49824 | M69: =VLOOKUP($K69,'Genre Penetration'!A:B,2,0)*VLOOKUP($C69&$E69,'Updated SES'!A:I,9,0) -> 0.26 | N69: =VLOOKUP(K:K,'Genre Penetration'!A:C,3,0)*VLOOKUP($C69&$E69,'Updated SES'!A:J,10,0) -> 0.24 | O69: =VLOOKUP($B69,'Language Penetration'!$B$1:$BL$14,MATCH('Compile data Working'!$H83,'Language Penetration'!$B$1:$BL$1,0),0) -> 0.2 | P69: =IF(ISBLANK(J69),RANDBETWEEN(1,2)&"%",IF(J69=1,RANDBETWEEN(35,40)&"%",IF(J69=2,RANDBETWEEN(30,35)&"%",IF(J69=3,RANDBETWEEN(25,30)&"%",IF(J69=4,RANDBETWEEN(20,25)&"%",IF(J69=5,RANDBETWEEN(15,20)&"%",IF(J69=6,RANDBETWEEN(10,15)&"%",IF(J69=7,RANDBETWEEN(8,10)&"%",IF(J69=8,RANDBETWEEN(6,8)&"%",IF(J69=9,RANDBETWEEN(4,6)&"%",IF(J69=10,RANDBETWEEN(2,4)&"%",""))))))))))) -> 6% | Q69: =IFERROR(L69*(M69+N69)*O69*P69,RANDBETWEEN(1,2)%*L69*(M69+N69)*O69) -> 0.21898944 | R69: =VLOOKUP(D:D,ranking!W:X,2,0) -> 0.7 | S69: =R69*Q69 -> 0.15329261 | T69: 9.247189
A70: WK-28'2026 | B70: ALL INDIA | C70: Netflix | D70: Theatrical Movies | E70: PAID | F70: Movies | G70: Quarantine 2: Terminal | H70: English,Hindi | I70: 46220 | K70: Horror,Thriller | L70: =VLOOKUP($C70&$E70,'Updated SES'!A:N,14,0) -> 55.4592 | M70: =VLOOKUP($K70,'Genre Penetration'!A:B,2,0)*VLOOKUP($C70&$E70,'Updated SES'!A:I,9,0) -> 0.343 | N70: =VLOOKUP(K:K,'Genre Penetration'!A:C,3,0)*VLOOKUP($C70&$E70,'Updated SES'!A:J,10,0) -> 0.153 | O70: =VLOOKUP($B70,'Language Penetration'!$B$1:$BL$14,MATCH('Compile data Working'!$H54,'Language Penetration'!$B$1:$BL$1,0),0) -> 0.2 | P70: =IF(ISBLANK(J70),RANDBETWEEN(1,2)&"%",IF(J70=1,RANDBETWEEN(35,40)&"%",IF(J70=2,RANDBETWEEN(30,35)&"%",IF(J70=3,RANDBETWEEN(25,30)&"%",IF(J70=4,RANDBETWEEN(20,25)&"%",IF(J70=5,RANDBETWEEN(15,20)&"%",IF(J70=6,RANDBETWEEN(10,15)&"%",IF(J70=7,RANDBETWEEN(8,10)&"%",IF(J70=8,RANDBETWEEN(6,8)&"%",IF(J70=9,RANDBETWEEN(4,6)&"%",IF(J70=10,RANDBETWEEN(2,4)&"%",""))))))))))) -> 2% | Q70: =IFERROR(L70*(M70+N70)*O70*P70,RANDBETWEEN(1,2)%*L70*(M70+N70)*O70) -> 0.11003105 | R70: =VLOOKUP(D:D,ranking!W:X,2,0) -> 0.7 | S70: =R70*Q70 -> 0.077021737 | T70: 9.2010902
A71: WK-28'2026 | B71: ALL INDIA | C71: Amazon Prime Video | D71: Theatrical Movies | E71: PAID | F71: Movies | G71: Gedelaraju Kakinada Taluka | H71: Telugu | I71: 46220 | K71: Drama | L71: =VLOOKUP($C71&$E71,'Updated SES'!A:N,14,0) -> 36.49824 | M71: =VLOOKUP($K71,'Genre Penetration'!A:B,2,0)*VLOOKUP($C71&$E71,'Updated SES'!A:I,9,0) -> 0.26 | N71: =VLOOKUP(K:K,'Genre Penetration'!A:C,3,0)*VLOOKUP($C71&$E71,'Updated SES'!A:J,10,0) -> 0.24 | O71: =VLOOKUP($B71,'Language Penetration'!$B$1:$BL$14,MATCH('Compile data Working'!$H50,'Language Penetration'!$B$1:$BL$1,0),0) -> 0.4 | P71: =IF(ISBLANK(J71),RANDBETWEEN(1,2)&"%",IF(J71=1,RANDBETWEEN(35,40)&"%",IF(J71=2,RANDBETWEEN(30,35)&"%",IF(J71=3,RANDBETWEEN(25,30)&"%",IF(J71=4,RANDBETWEEN(20,25)&"%",IF(J71=5,RANDBETWEEN(15,20)&"%",IF(J71=6,RANDBETWEEN(10,15)&"%",IF(J71=7,RANDBETWEEN(8,10)&"%",IF(J71=8,RANDBETWEEN(6,8)&"%",IF(J71=9,RANDBETWEEN(4,6)&"%",IF(J71=10,RANDBETWEEN(2,4)&"%",""))))))))))) -> 1% | Q71: =IFERROR(L71*(M71+N71)*O71*P71,RANDBETWEEN(1,2)%*L71*(M71+N71)*O71) -> 0.07299648 | R71: =VLOOKUP(D:D,ranking!W:X,2,0) -> 0.7 | S71: =R71*Q71 -> 0.051097536 | T71: 9.0854005
A72: Trending Top 10 | B72: ALL INDIA | C72: Netflix | D72: Theatrical Movies | E72: PAID | F72: Movies | G72: Bhooth Bangla | H72: Hindi | I72: 46185 | J72: 7 | K72: Comedy,Horror | L72: =VLOOKUP($C72&$E72,'Updated SES'!A:N,14,0) -> 55.4592 | M72: =VLOOKUP($K72,'Genre Penetration'!A:B,2,0)*VLOOKUP($C72&$E72,'Updated SES'!A:I,9,0) -> 0.2989 | N72: =VLOOKUP(K:K,'Genre Penetration'!A:C,3,0)*VLOOKUP($C72&$E72,'Updated SES'!A:J,10,0) -> 0.1989 | O72: =VLOOKUP($B72,'Language Penetration'!$B$1:$BL$14,MATCH('Compile data Working'!$H95,'Language Penetration'!$B$1:$BL$1,0),0) -> 0.1 | P72: =IF(ISBLANK(J72),RANDBETWEEN(1,2)&"%",IF(J72=1,RANDBETWEEN(35,40)&"%",IF(J72=2,RANDBETWEEN(30,35)&"%",IF(J72=3,RANDBETWEEN(25,30)&"%",IF(J72=4,RANDBETWEEN(20,25)&"%",IF(J72=5,RANDBETWEEN(15,20)&"%",IF(J72=6,RANDBETWEEN(10,15)&"%",IF(J72=7,RANDBETWEEN(8,10)&"%",IF(J72=8,RANDBETWEEN(6,8)&"%",IF(J72=9,RANDBETWEEN(4,6)&"%",IF(J72=10,RANDBETWEEN(2,4)&"%",""))))))))))) -> 9% | Q72: =IFERROR(L72*(M72+N72)*O72*P72,RANDBETWEEN(1,2)%*L72*(M72+N72)*O72) -> 0.24846831 | R72: =VLOOKUP(D:D,ranking!W:X,2,0) -> 0.7 | S72: =R72*Q72 -> 0.17392782 | T72: 9.0708935
A73: WK-28'2026 | B73: ALL INDIA | C73: Netflix | D73: SVOD Originals Shows | E73: PAID | F73: Shows | G73: Hot Ones: Extra Heat | H73: English | I73: 46216 | K73: Reality Tv | L73: =VLOOKUP($C73&$E73,'Updated SES'!A:N,14,0) -> 55.4592 | M73: =VLOOKUP($K73,'Genre Penetration'!A:B,2,0)*VLOOKUP($C73&$E73,'Updated SES'!A:I,9,0) -> 0.196 | N73: =VLOOKUP(K:K,'Genre Penetration'!A:C,3,0)*VLOOKUP($C73&$E73,'Updated SES'!A:J,10,0) -> 0.306 | O73: =VLOOKUP($B73,'Language Penetration'!$B$1:$BL$14,MATCH('Compile data Working'!$H11,'Language Penetration'!$B$1:$BL$1,0),0) -> 0.6 | P73: =IF(ISBLANK(J73),RANDBETWEEN(1,2)&"%",IF(J73=1,RANDBETWEEN(35,40)&"%",IF(J73=2,RANDBETWEEN(30,35)&"%",IF(J73=3,RANDBETWEEN(25,30)&"%",IF(J73=4,RANDBETWEEN(20,25)&"%",IF(J73=5,RANDBETWEEN(15,20)&"%",IF(J73=6,RANDBETWEEN(10,15)&"%",IF(J73=7,RANDBETWEEN(8,10)&"%",IF(J73=8,RANDBETWEEN(6,8)&"%",IF(J73=9,RANDBETWEEN(4,6)&"%",IF(J73=10,RANDBETWEEN(2,4)&"%",""))))))))))) -> 1% | Q73: =IFERROR(L73*(M73+N73)*O73*P73,RANDBETWEEN(1,2)%*L73*(M73+N73)*O73) -> 0.16704311 | R73: =VLOOKUP(D:D,ranking!W:X,2,0) -> 0.6 | S73: =R73*Q73 -> 0.10022587 | T73: 8.9880317
A74: Trending Top 10 | B74: ALL INDIA | C74: Netflix | D74: Theatrical Movies | E74: PAID | F74: Movies | G74: Sing Geetham | H74: Hindi,Kannada,Malayalam,Tamil,Telugu | I74: 46211 | J74: 8 | K74: Comedy,Drama,Romance | L74: =VLOOKUP($C74&$E74,'Updated SES'!A:N,14,0) -> 55.4592 | M74: =VLOOKUP($K74,'Genre Penetration'!A:B,2,0)*VLOOKUP($C74&$E74,'Updated SES'!A:I,9,0) -> 0.1813 | N74: =VLOOKUP(K:K,'Genre Penetration'!A:C,3,0)*VLOOKUP($C74&$E74,'Updated SES'!A:J,10,0) -> 0.3213 | O74: =VLOOKUP($B74,'Language Penetration'!$B$1:$BL$14,MATCH('Compile data Working'!$H96,'Language Penetration'!$B$1:$BL$1,0),0) -> 0.1 | P74: =IF(ISBLANK(J74),RANDBETWEEN(1,2)&"%",IF(J74=1,RANDBETWEEN(35,40)&"%",IF(J74=2,RANDBETWEEN(30,35)&"%",IF(J74=3,RANDBETWEEN(25,30)&"%",IF(J74=4,RANDBETWEEN(20,25)&"%",IF(J74=5,RANDBETWEEN(15,20)&"%",IF(J74=6,RANDBETWEEN(10,15)&"%",IF(J74=7,RANDBETWEEN(8,10)&"%",IF(J74=8,RANDBETWEEN(6,8)&"%",IF(J74=9,RANDBETWEEN(4,6)&"%",IF(J74=10,RANDBETWEEN(2,4)&"%",""))))))))))) -> 8% | Q74: =IFERROR(L74*(M74+N74)*O74*P74,RANDBETWEEN(1,2)%*L74*(M74+N74)*O74) -> 0.22299035 | R74: =VLOOKUP(D:D,ranking!W:X,2,0) -> 0.7 | S74: =R74*Q74 -> 0.15609325 | T74: 8.7235515
A75: Trending Top 10 | B75: ALL INDIA | C75: Sony Liv | D75: Tv Catch-Up | E75: FREE | F75: Tv catchup | G75: Taarak Mehta Ka Ooltah Chashmah | H75: Hindi | I75: - | J75: 7 | K75: Comedy | L75: =VLOOKUP($C75&$E75,'Updated SES'!A:N,14,0) -> 5.268 | M75: =VLOOKUP($K75,'Genre Penetration'!A:B,2,0)*VLOOKUP($C75&$E75,'Updated SES'!A:I,9,0) -> 0.297 | N75: =VLOOKUP(K:K,'Genre Penetration'!A:C,3,0)*VLOOKUP($C75&$E75,'Updated SES'!A:J,10,0) -> 0.187 | O75: =VLOOKUP($B75,'Language Penetration'!$B$1:$BL$14,MATCH('Compile data Working'!$H110,'Language Penetration'!$B$1:$BL$1,0),0) -> 0.6 | P75: =IF(ISBLANK(J75),RANDBETWEEN(1,2)&"%",IF(J75=1,RANDBETWEEN(35,40)&"%",IF(J75=2,RANDBETWEEN(30,35)&"%",IF(J75=3,RANDBETWEEN(25,30)&"%",IF(J75=4,RANDBETWEEN(20,25)&"%",IF(J75=5,RANDBETWEEN(15,20)&"%",IF(J75=6,RANDBETWEEN(10,15)&"%",IF(J75=7,RANDBETWEEN(8,10)&"%",IF(J75=8,RANDBETWEEN(6,8)&"%",IF(J75=9,RANDBETWEEN(4,6)&"%",IF(J75=10,RANDBETWEEN(2,4)&"%",""))))))))))) -> 9% | Q75: =IFERROR(L75*(M75+N75)*O75*P75,RANDBETWEEN(1,2)%*L75*(M75+N75)*O75) -> 0.13768445 | R75: =VLOOKUP(D:D,ranking!W:X,2,0) -> 0.3 | S75: =R75*Q75 -> 0.041305334 | T75: 8.6691136
A76: Trending Top 10 | B76: ALL INDIA | C76: Sony Liv | D76: Svod Originals Shows | E76: PAID | F76: Shows | G76: Gullak Season 5 | H76: Hindi | I76: 46178 | J76: 5 | K76: Comedy,Drama | L76: =VLOOKUP($C76&$E76,'Updated SES'!A:N,14,0) -> 21.68204 | M76: =VLOOKUP($K76,'Genre Penetration'!A:B,2,0)*VLOOKUP($C76&$E76,'Updated SES'!A:I,9,0) -> 0.3055 | N76: =VLOOKUP(K:K,'Genre Penetration'!A:C,3,0)*VLOOKUP($C76&$E76,'Updated SES'!A:J,10,0) -> 0.1855 | O76: =VLOOKUP($B76,'Language Penetration'!$B$1:$BL$14,MATCH('Compile data Working'!$H108,'Language Penetration'!$B$1:$BL$1,0),0) -> 0.6 | P76: =IF(ISBLANK(J76),RANDBETWEEN(1,2)&"%",IF(J76=1,RANDBETWEEN(35,40)&"%",IF(J76=2,RANDBETWEEN(30,35)&"%",IF(J76=3,RANDBETWEEN(25,30)&"%",IF(J76=4,RANDBETWEEN(20,25)&"%",IF(J76=5,RANDBETWEEN(15,20)&"%",IF(J76=6,RANDBETWEEN(10,15)&"%",IF(J76=7,RANDBETWEEN(8,10)&"%",IF(J76=8,RANDBETWEEN(6,8)&"%",IF(J76=9,RANDBETWEEN(4,6)&"%",IF(J76=10,RANDBETWEEN(2,4)&"%",""))))))))))) -> 19% | Q76: =IFERROR(L76*(M76+N76)*O76*P76,RANDBETWEEN(1,2)%*L76*(M76+N76)*O76) -> 1.2136305 | R76: =VLOOKUP(D:D,ranking!W:X,2,0) -> 0.6 | S76: =R76*Q76 -> 0.7281783 | T76: 8.6286614
A77: WK-28'2026 | B77: ALL INDIA | C77: Netflix | D77: Theatrical Movies | E77: PAID | F77: Movies | G77: A Mighty Wind | H77: English | I77: 46219 | K77: Comedy | L77: =VLOOKUP($C77&$E77,'Updated SES'!A:N,14,0) -> 55.4592 | M77: =VLOOKUP($K77,'Genre Penetration'!A:B,2,0)*VLOOKUP($C77&$E77,'Updated SES'!A:I,9,0) -> 0.2205 | N77: =VLOOKUP(K:K,'Genre Penetration'!A:C,3,0)*VLOOKUP($C77&$E77,'Updated SES'!A:J,10,0) -> 0.2805 | O77: =VLOOKUP($B77,'Language Penetration'!$B$1:$BL$14,MATCH('Compile data Working'!$H32,'Language Penetration'!$B$1:$BL$1,0),0) -> 0.2625 | P77: =IF(ISBLANK(J77),RANDBETWEEN(1,2)&"%",IF(J77=1,RANDBETWEEN(35,40)&"%",IF(J77=2,RANDBETWEEN(30,35)&"%",IF(J77=3,RANDBETWEEN(25,30)&"%",IF(J77=4,RANDBETWEEN(20,25)&"%",IF(J77=5,RANDBETWEEN(15,20)&"%",IF(J77=6,RANDBETWEEN(10,15)&"%",IF(J77=7,RANDBETWEEN(8,10)&"%",IF(J77=8,RANDBETWEEN(6,8)&"%",IF(J77=9,RANDBETWEEN(4,6)&"%",IF(J77=10,RANDBETWEEN(2,4)&"%",""))))))))))) -> 2% | Q77: =IFERROR(L77*(M77+N77)*O77*P77,RANDBETWEEN(1,2)%*L77*(M77+N77)*O77) -> 0.14587156 | R77: =VLOOKUP(D:D,ranking!W:X,2,0) -> 0.7 | S77: =R77*Q77 -> 0.10211009 | T77: 8.4820476
A78: WK-28'2026 | B78: ALL INDIA | C78: Amazon Prime Video | D78: Theatrical Movies | E78: RENT | F78: Movies | G78: Dark Face | H78: Tamil | I78: 46214 | K78: Thriller | L78: =VLOOKUP($C78&$E78,'Updated SES'!A:N,14,0) -> 4.689 | M78: =VLOOKUP($K78,'Genre Penetration'!A:B,2,0)*VLOOKUP($C78&$E78,'Updated SES'!A:I,9,0) -> 0.4352 | N78: =VLOOKUP(K:K,'Genre Penetration'!A:C,3,0)*VLOOKUP($C78&$E78,'Updated SES'!A:J,10,0) -> 0.1152 | O78: =VLOOKUP($B78,'Language Penetration'!$B$1:$BL$14,MATCH('Compile data Working'!$H6,'Language Penetration'!$B$1:$BL$1,0),0) -> 0.2425 | P78: =IF(ISBLANK(J78),RANDBETWEEN(1,2)&"%",IF(J78=1,RANDBETWEEN(35,40)&"%",IF(J78=2,RANDBETWEEN(30,35)&"%",IF(J78=3,RANDBETWEEN(25,30)&"%",IF(J78=4,RANDBETWEEN(20,25)&"%",IF(J78=5,RANDBETWEEN(15,20)&"%",IF(J78=6,RANDBETWEEN(10,15)&"%",IF(J78=7,RANDBETWEEN(8,10)&"%",IF(J78=8,RANDBETWEEN(6,8)&"%",IF(J78=9,RANDBETWEEN(4,6)&"%",IF(J78=10,RANDBETWEEN(2,4)&"%",""))))))))))) -> 1% | Q78: =IFERROR(L78*(M78+N78)*O78*P78,RANDBETWEEN(1,2)%*L78*(M78+N78)*O78) -> 0.0062585021 | R78: =VLOOKUP(D:D,ranking!W:X,2,0) -> 0.7 | S78: =R78*Q78 -> 0.0043809515 | T78: 8.259455
A79: Trending Top 10 | B79: ALL INDIA | C79: Sony Liv | D79: Tv Catch-Up | E79: FREE | F79: Tv catchup | G79: Hastinapur Ke Veer | H79: Hindi | I79: 46175 | J79: 1 | K79: Mythology | L79: =VLOOKUP($C79&$E79,'Updated SES'!A:N,14,0) -> 5.268 | M79: =VLOOKUP($K79,'Genre Penetration'!A:B,2,0)*VLOOKUP($C79&$E79,'Updated SES'!A:I,9,0) -> 0.3828 | N79: =VLOOKUP(K:K,'Genre Penetration'!A:C,3,0)*VLOOKUP($C79&$E79,'Updated SES'!A:J,10,0) -> 0.1428 | O79: =VLOOKUP($B79,'Language Penetration'!$B$1:$BL$14,MATCH('Compile data Working'!$H104,'Language Penetration'!$B$1:$BL$1,0),0) -> 0.6 | P79: =IF(ISBLANK(J79),RANDBETWEEN(1,2)&"%",IF(J79=1,RANDBETWEEN(35,40)&"%",IF(J79=2,RANDBETWEEN(30,35)&"%",IF(J79=3,RANDBETWEEN(25,30)&"%",IF(J79=4,RANDBETWEEN(20,25)&"%",IF(J79=5,RANDBETWEEN(15,20)&"%",IF(J79=6,RANDBETWEEN(10,15)&"%",IF(J79=7,RANDBETWEEN(8,10)&"%",IF(J79=8,RANDBETWEEN(6,8)&"%",IF(J79=9,RANDBETWEEN(4,6)&"%",IF(J79=10,RANDBETWEEN(2,4)&"%",""))))))))))) -> 38% | Q79: =IFERROR(L79*(M79+N79)*O79*P79,RANDBETWEEN(1,2)%*L79*(M79+N79)*O79) -> 0.63130026 | R79: =VLOOKUP(D:D,ranking!W:X,2,0) -> 0.3 | S79: =R79*Q79 -> 0.18939008 | T79: 8.2359502
A80: Trending Top 10 | B80: ALL INDIA | C80: Sony Liv | D80: Tv Catch-Up | E80: FREE | F80: Tv catchup | G80: India's Best Dancer | H80: Hindi | I80: 46179 | J80: 3 | K80: RealityTv | L80: =VLOOKUP($C80&$E80,'Updated SES'!A:N,14,0) -> 5.268 | M80: =VLOOKUP($K80,'Genre Penetration'!A:B,2,0)*VLOOKUP($C80&$E80,'Updated SES'!A:I,9,0) -> 0.264 | N80: =VLOOKUP(K:K,'Genre Penetration'!A:C,3,0)*VLOOKUP($C80&$E80,'Updated SES'!A:J,10,0) -> 0.204 | O80: =VLOOKUP($B80,'Language Penetration'!$B$1:$BL$14,MATCH('Compile data Working'!$H106,'Language Penetration'!$B$1:$BL$1,0),0) -> 0.6 | P80: =IF(ISBLANK(J80),RANDBETWEEN(1,2)&"%",IF(J80=1,RANDBETWEEN(35,40)&"%",IF(J80=2,RANDBETWEEN(30,35)&"%",IF(J80=3,RANDBETWEEN(25,30)&"%",IF(J80=4,RANDBETWEEN(20,25)&"%",IF(J80=5,RANDBETWEEN(15,20)&"%",IF(J80=6,RANDBETWEEN(10,15)&"%",IF(J80=7,RANDBETWEEN(8,10)&"%",IF(J80=8,RANDBETWEEN(6,8)&"%",IF(J80=9,RANDBETWEEN(4,6)&"%",IF(J80=10,RANDBETWEEN(2,4)&"%",""))))))))))) -> 27% | Q80: =IFERROR(L80*(M80+N80)*O80*P80,RANDBETWEEN(1,2)%*L80*(M80+N80)*O80) -> 0.39939869 | R80: =VLOOKUP(D:D,ranking!W:X,2,0) -> 0.3 | S80: =R80*Q80 -> 0.11981961 | T80: 8.136718
A81: Trending Top 10 | B81: ALL INDIA | C81: Netflix | D81: Svod Originals Shows | E81: PAID | F81: Shows | G81: I Will Find You | H81: English,Hindi,Tamil,Telugu | I81: 46191 | J81: 6 | K81: Crime,Drama,Thriller | L81: =VLOOKUP($C81&$E81,'Updated SES'!A:N,14,0) -> 55.4592 | M81: =VLOOKUP($K81,'Genre Penetration'!A:B,2,0)*VLOOKUP($C81&$E81,'Updated SES'!A:I,9,0) -> 0.3528 | N81: =VLOOKUP(K:K,'Genre Penetration'!A:C,3,0)*VLOOKUP($C81&$E81,'Updated SES'!A:J,10,0) -> 0.1428 | O81: =VLOOKUP($B81,'Language Penetration'!$B$1:$BL$14,MATCH('Compile data Working'!$H101,'Language Penetration'!$B$1:$BL$1,0),0) -> 0.23 | P81: =IF(ISBLANK(J81),RANDBETWEEN(1,2)&"%",IF(J81=1,RANDBETWEEN(35,40)&"%",IF(J81=2,RANDBETWEEN(30,35)&"%",IF(J81=3,RANDBETWEEN(25,30)&"%",IF(J81=4,RANDBETWEEN(20,25)&"%",IF(J81=5,RANDBETWEEN(15,20)&"%",IF(J81=6,RANDBETWEEN(10,15)&"%",IF(J81=7,RANDBETWEEN(8,10)&"%",IF(J81=8,RANDBETWEEN(6,8)&"%",IF(J81=9,RANDBETWEEN(4,6)&"%",IF(J81=10,RANDBETWEEN(2,4)&"%",""))))))))))) -> 15% | Q81: =IFERROR(L81*(M81+N81)*O81*P81,RANDBETWEEN(1,2)%*L81*(M81+N81)*O81) -> 0.94825249 | R81: =VLOOKUP(D:D,ranking!W:X,2,0) -> 0.6 | S81: =R81*Q81 -> 0.5689515 | T81: 8.1304043
A82: Trending Top 10 | B82: ALL INDIA | C82: Sony Liv | D82: Theatrical Movies | E82: PAID | F82: Movies | G82: Athiradi | H82: Hindi,Kannada,Malayalam,Tamil,Telugu | I82: 46192 | J82: 9 | K82: Action,Comedy,Drama | L82: =VLOOKUP($C82&$E82,'Updated SES'!A:N,14,0) -> 21.68204 | M82: =VLOOKUP($K82,'Genre Penetration'!A:B,2,0)*VLOOKUP($C82&$E82,'Updated SES'!A:I,9,0) -> 0.312 | N82: =VLOOKUP(K:K,'Genre Penetration'!A:C,3,0)*VLOOKUP($C82&$E82,'Updated SES'!A:J,10,0) -> 0.182 | O82: =VLOOKUP($B82,'Language Penetration'!$B$1:$BL$14,MATCH('Compile data Working'!$H112,'Language Penetration'!$B$1:$BL$1,0),0) -> 0.07 | P82: =IF(ISBLANK(J82),RANDBETWEEN(1,2)&"%",IF(J82=1,RANDBETWEEN(35,40)&"%",IF(J82=2,RANDBETWEEN(30,35)&"%",IF(J82=3,RANDBETWEEN(25,30)&"%",IF(J82=4,RANDBETWEEN(20,25)&"%",IF(J82=5,RANDBETWEEN(15,20)&"%",IF(J82=6,RANDBETWEEN(10,15)&"%",IF(J82=7,RANDBETWEEN(8,10)&"%",IF(J82=8,RANDBETWEEN(6,8)&"%",IF(J82=9,RANDBETWEEN(4,6)&"%",IF(J82=10,RANDBETWEEN(2,4)&"%",""))))))))))) -> 4% | Q82: =IFERROR(L82*(M82+N82)*O82*P82,RANDBETWEEN(1,2)%*L82*(M82+N82)*O82) -> 0.029990598 | R82: =VLOOKUP(D:D,ranking!W:X,2,0) -> 0.7 | S82: =R82*Q82 -> 0.020993418 | T82: 8.0223472
A83: WK-28'2026 | B83: ALL INDIA | C83: Netflix | D83: Theatrical Movies | E83: PAID | F83: Movies | G83: Father Figures | H83: English | I83: 46219 | K83: Comedy | L83: =VLOOKUP($C83&$E83,'Updated SES'!A:N,14,0) -> 55.4592 | M83: =VLOOKUP($K83,'Genre Penetration'!A:B,2,0)*VLOOKUP($C83&$E83,'Updated SES'!A:I,9,0) -> 0.2205 | N83: =VLOOKUP(K:K,'Genre Penetration'!A:C,3,0)*VLOOKUP($C83&$E83,'Updated SES'!A:J,10,0) -> 0.2805 | O83: =VLOOKUP($B83,'Language Penetration'!$B$1:$BL$14,MATCH('Compile data Working'!$H33,'Language Penetration'!$B$1:$BL$1,0),0) -> 0.28333333 | P83: =IF(ISBLANK(J83),RANDBETWEEN(1,2)&"%",IF(J83=1,RANDBETWEEN(35,40)&"%",IF(J83=2,RANDBETWEEN(30,35)&"%",IF(J83=3,RANDBETWEEN(25,30)&"%",IF(J83=4,RANDBETWEEN(20,25)&"%",IF(J83=5,RANDBETWEEN(15,20)&"%",IF(J83=6,RANDBETWEEN(10,15)&"%",IF(J83=7,RANDBETWEEN(8,10)&"%",IF(J83=8,RANDBETWEEN(6,8)&"%",IF(J83=9,RANDBETWEEN(4,6)&"%",IF(J83=10,RANDBETWEEN(2,4)&"%",""))))))))))) -> 1% | Q83: =IFERROR(L83*(M83+N83)*O83*P83,RANDBETWEEN(1,2)%*L83*(M83+N83)*O83) -> 0.078724334 | R83: =VLOOKUP(D:D,ranking!W:X,2,0) -> 0.7 | S83: =R83*Q83 -> 0.055107034 | T83: 8.0213295
A84: Cott Data Servey | B84: ALL INDIA | C84: JioHotstar | D84: Tv Catch-Up | E84: PAID | F84: Tv catchup | G84: Anupama | H84: Hindi | I84: 44025 | K84: Drama | L84: =VLOOKUP($C84&$E84,'Updated SES'!A:N,14,0) -> 127.11702 | M84: =VLOOKUP($K84,'Genre Penetration'!A:B,2,0)*VLOOKUP($C84&$E84,'Updated SES'!A:I,9,0) -> 0.335 | N84: =VLOOKUP(K:K,'Genre Penetration'!A:C,3,0)*VLOOKUP($C84&$E84,'Updated SES'!A:J,10,0) -> 0.165 | O84: =VLOOKUP($B84,'Language Penetration'!$B$1:$BL$14,MATCH('Compile data Working'!$H133,'Language Penetration'!$B$1:$BL$1,0),0) -> 0.204 | P84: =IF(ISBLANK(J84),RANDBETWEEN(1,2)&"%",IF(J84=1,RANDBETWEEN(35,40)&"%",IF(J84=2,RANDBETWEEN(30,35)&"%",IF(J84=3,RANDBETWEEN(25,30)&"%",IF(J84=4,RANDBETWEEN(20,25)&"%",IF(J84=5,RANDBETWEEN(15,20)&"%",IF(J84=6,RANDBETWEEN(10,15)&"%",IF(J84=7,RANDBETWEEN(8,10)&"%",IF(J84=8,RANDBETWEEN(6,8)&"%",IF(J84=9,RANDBETWEEN(4,6)&"%",IF(J84=10,RANDBETWEEN(2,4)&"%",""))))))))))) -> 2% | Q84: =IFERROR(L84*(M84+N84)*O84*P84,RANDBETWEEN(1,2)%*L84*(M84+N84)*O84) -> 0.25931872 | R84: =VLOOKUP(D:D,ranking!W:X,2,0) -> 0.3 | S84: =R84*Q84 -> 0.077795616 | T84: 7.3358628
A85: Trending Top 10 | B85: ALL INDIA | C85: JioHotstar | D85: Svod Originals Shows | E85: PAID | F85: Shows | G85: Resort | H85: Hindi,Kannada,Malayalam,Tamil,Telugu | I85: 46094 | J85: 6 | K85: Comedy,Drama,Romance | L85: =VLOOKUP($C85&$E85,'Updated SES'!A:N,14,0) -> 127.11702 | M85: =VLOOKUP($K85,'Genre Penetration'!A:B,2,0)*VLOOKUP($C85&$E85,'Updated SES'!A:I,9,0) -> 0.2479 | N85: =VLOOKUP(K:K,'Genre Penetration'!A:C,3,0)*VLOOKUP($C85&$E85,'Updated SES'!A:J,10,0) -> 0.2079 | O85: =VLOOKUP($B85,'Language Penetration'!$B$1:$BL$14,MATCH('Compile data Working'!$H88,'Language Penetration'!$B$1:$BL$1,0),0) -> 0.6 | P85: =IF(ISBLANK(J85),RANDBETWEEN(1,2)&"%",IF(J85=1,RANDBETWEEN(35,40)&"%",IF(J85=2,RANDBETWEEN(30,35)&"%",IF(J85=3,RANDBETWEEN(25,30)&"%",IF(J85=4,RANDBETWEEN(20,25)&"%",IF(J85=5,RANDBETWEEN(15,20)&"%",IF(J85=6,RANDBETWEEN(10,15)&"%",IF(J85=7,RANDBETWEEN(8,10)&"%",IF(J85=8,RANDBETWEEN(6,8)&"%",IF(J85=9,RANDBETWEEN(4,6)&"%",IF(J85=10,RANDBETWEEN(2,4)&"%",""))))))))))) -> 14% | Q85: =IFERROR(L85*(M85+N85)*O85*P85,RANDBETWEEN(1,2)%*L85*(M85+N85)*O85) -> 4.8669548 | R85: =VLOOKUP(D:D,ranking!W:X,2,0) -> 0.6 | S85: =R85*Q85 -> 2.9201729 | T85: 6.8033219
A86: WK-28'2026 | B86: ALL INDIA | C86: Amazon Prime Video | D86: Theatrical Movies | E86: RENT | F86: Movies | G86: Abar Hawa Bodol | H86: Bengali | I86: 46220 | K86: Comedy,Drama | L86: =VLOOKUP($C86&$E86,'Updated SES'!A:N,14,0) -> 4.689 | M86: =VLOOKUP($K86,'Genre Penetration'!A:B,2,0)*VLOOKUP($C86&$E86,'Updated SES'!A:I,9,0) -> 0.3196 | N86: =VLOOKUP(K:K,'Genre Penetration'!A:C,3,0)*VLOOKUP($C86&$E86,'Updated SES'!A:J,10,0) -> 0.1696 | O86: =VLOOKUP($B86,'Language Penetration'!$B$1:$BL$14,MATCH('Compile data Working'!$H44,'Language Penetration'!$B$1:$BL$1,0),0) -> 0.20333333 | P86: =IF(ISBLANK(J86),RANDBETWEEN(1,2)&"%",IF(J86=1,RANDBETWEEN(35,40)&"%",IF(J86=2,RANDBETWEEN(30,35)&"%",IF(J86=3,RANDBETWEEN(25,30)&"%",IF(J86=4,RANDBETWEEN(20,25)&"%",IF(J86=5,RANDBETWEEN(15,20)&"%",IF(J86=6,RANDBETWEEN(10,15)&"%",IF(J86=7,RANDBETWEEN(8,10)&"%",IF(J86=8,RANDBETWEEN(6,8)&"%",IF(J86=9,RANDBETWEEN(4,6)&"%",IF(J86=10,RANDBETWEEN(2,4)&"%",""))))))))))) -> 1% | Q86: =IFERROR(L86*(M86+N86)*O86*P86,RANDBETWEEN(1,2)%*L86*(M86+N86)*O86) -> 0.0046641796 | R86: =VLOOKUP(D:D,ranking!W:X,2,0) -> 0.7 | S86: =R86*Q86 -> 0.0032649257 | T86: 6.607564
A87: Trending Top 10 | B87: ALL INDIA | C87: Amazon MX Player | D87: Avod Originals Shows | E87: FREE | F87: Shows | G87: Made in India – A Titan Story | H87: Hindi | I87: 46176 | J87: 2 | K87: Drama | L87: =VLOOKUP($C87&$E87,'Updated SES'!A:N,14,0) -> 78.93987 | M87: =VLOOKUP($K87,'Genre Penetration'!A:B,2,0)*VLOOKUP($C87&$E87,'Updated SES'!A:I,9,0) -> 0.4 | N87: =VLOOKUP(K:K,'Genre Penetration'!A:C,3,0)*VLOOKUP($C87&$E87,'Updated SES'!A:J,10,0) -> 0.1 | O87: =VLOOKUP($B87,'Language Penetration'!$B$1:$BL$14,MATCH('Compile data Working'!$H68,'Language Penetration'!$B$1:$BL$1,0),0) -> 0.1 | P87: =IF(ISBLANK(J87),RANDBETWEEN(1,2)&"%",IF(J87=1,RANDBETWEEN(35,40)&"%",IF(J87=2,RANDBETWEEN(30,35)&"%",IF(J87=3,RANDBETWEEN(25,30)&"%",IF(J87=4,RANDBETWEEN(20,25)&"%",IF(J87=5,RANDBETWEEN(15,20)&"%",IF(J87=6,RANDBETWEEN(10,15)&"%",IF(J87=7,RANDBETWEEN(8,10)&"%",IF(J87=8,RANDBETWEEN(6,8)&"%",IF(J87=9,RANDBETWEEN(4,6)&"%",IF(J87=10,RANDBETWEEN(2,4)&"%",""))))))))))) -> 35% | Q87: =IFERROR(L87*(M87+N87)*O87*P87,RANDBETWEEN(1,2)%*L87*(M87+N87)*O87) -> 1.3814477 | R87: =VLOOKUP(D:D,ranking!W:X,2,0) -> 0.6 | S87: =R87*Q87 -> 0.82886864 | T87: 6.4963204
A88: Trending Top 10 | B88: ALL INDIA | C88: Sony Liv | D88: Tv Catch-Up | E88: FREE | F88: Tv catchup | G88: Indian Idol S16 | H88: Hindi | I88: 45948 | J88: 2 | K88: RealityTv | L88: =VLOOKUP($C88&$E88,'Updated SES'!A:N,14,0) -> 5.268 | M88: =VLOOKUP($K88,'Genre Penetration'!A:B,2,0)*VLOOKUP($C88&$E88,'Updated SES'!A:I,9,0) -> 0.264 | N88: =VLOOKUP(K:K,'Genre Penetration'!A:C,3,0)*VLOOKUP($C88&$E88,'Updated SES'!A:J,10,0) -> 0.204 | O88: =VLOOKUP($B88,'Language Penetration'!$B$1:$BL$14,MATCH('Compile data Working'!$H105,'Language Penetration'!$B$1:$BL$1,0),0) -> 0.12 | P88: =IF(ISBLANK(J88),RANDBETWEEN(1,2)&"%",IF(J88=1,RANDBETWEEN(35,40)&"%",IF(J88=2,RANDBETWEEN(30,35)&"%",IF(J88=3,RANDBETWEEN(25,30)&"%",IF(J88=4,RANDBETWEEN(20,25)&"%",IF(J88=5,RANDBETWEEN(15,20)&"%",IF(J88=6,RANDBETWEEN(10,15)&"%",IF(J88=7,RANDBETWEEN(8,10)&"%",IF(J88=8,RANDBETWEEN(6,8)&"%",IF(J88=9,RANDBETWEEN(4,6)&"%",IF(J88=10,RANDBETWEEN(2,4)&"%",""))))))))))) -> 34% | Q88: =IFERROR(L88*(M88+N88)*O88*P88,RANDBETWEEN(1,2)%*L88*(M88+N88)*O88) -> 0.1005893 | R88: =VLOOKUP(D:D,ranking!W:X,2,0) -> 0.3 | S88: =R88*Q88 -> 0.03017679 | T88: 6.0072024
A89: Cott Data Servey | B89: ALL INDIA | C89: JioHotstar | D89: Tv Catch-Up | E89: PAID | F89: Tv catchup | G89: Yeh Rishta Kya Kehlata Hai | H89: Hindi | I89: 39825 | K89: Drama | L89: =VLOOKUP($C89&$E89,'Updated SES'!A:N,14,0) -> 127.11702 | M89: =VLOOKUP($K89,'Genre Penetration'!A:B,2,0)*VLOOKUP($C89&$E89,'Updated SES'!A:I,9,0) -> 0.335 | N89: =VLOOKUP(K:K,'Genre Penetration'!A:C,3,0)*VLOOKUP($C89&$E89,'Updated SES'!A:J,10,0) -> 0.165 | O89: =VLOOKUP($B89,'Language Penetration'!$B$1:$BL$14,MATCH('Compile data Working'!$H135,'Language Penetration'!$B$1:$BL$1,0),0) -> 0.09 | P89: =IF(ISBLANK(J89),RANDBETWEEN(1,2)&"%",IF(J89=1,RANDBETWEEN(35,40)&"%",IF(J89=2,RANDBETWEEN(30,35)&"%",IF(J89=3,RANDBETWEEN(25,30)&"%",IF(J89=4,RANDBETWEEN(20,25)&"%",IF(J89=5,RANDBETWEEN(15,20)&"%",IF(J89=6,RANDBETWEEN(10,15)&"%",IF(J89=7,RANDBETWEEN(8,10)&"%",IF(J89=8,RANDBETWEEN(6,8)&"%",IF(J89=9,RANDBETWEEN(4,6)&"%",IF(J89=10,RANDBETWEEN(2,4)&"%",""))))))))))) -> 2% | Q89: =IFERROR(L89*(M89+N89)*O89*P89,RANDBETWEEN(1,2)%*L89*(M89+N89)*O89) -> 0.11440532 | R89: =VLOOKUP(D:D,ranking!W:X,2,0) -> 0.3 | S89: =R89*Q89 -> 0.034321595 | T89: 5.8988082
A90: Trending Top 10 | B90: ALL INDIA | C90: Zee5 | D90: Theatrical Movies | E90: PAID | F90: Movies | G90: Parimala & Co | H90: Hindi,Kannada,Malayalam,Tamil,Telugu | I90: 46213 | J90: 1 | K90: Comedy,Crime,Thriller | L90: =VLOOKUP($C90&$E90,'Updated SES'!A:N,14,0) -> 60.152 | M90: =VLOOKUP($K90,'Genre Penetration'!A:B,2,0)*VLOOKUP($C90&$E90,'Updated SES'!A:I,9,0) -> 0.403 | N90: =VLOOKUP(K:K,'Genre Penetration'!A:C,3,0)*VLOOKUP($C90&$E90,'Updated SES'!A:J,10,0) -> 0.133 | O90: =VLOOKUP($B90,'Language Penetration'!$B$1:$BL$14,MATCH('Compile data Working'!$H114,'Language Penetration'!$B$1:$BL$1,0),0) -> 0.6 | P90: =IF(ISBLANK(J90),RANDBETWEEN(1,2)&"%",IF(J90=1,RANDBETWEEN(35,40)&"%",IF(J90=2,RANDBETWEEN(30,35)&"%",IF(J90=3,RANDBETWEEN(25,30)&"%",IF(J90=4,RANDBETWEEN(20,25)&"%",IF(J90=5,RANDBETWEEN(15,20)&"%",IF(J90=6,RANDBETWEEN(10,15)&"%",IF(J90=7,RANDBETWEEN(8,10)&"%",IF(J90=8,RANDBETWEEN(6,8)&"%",IF(J90=9,RANDBETWEEN(4,6)&"%",IF(J90=10,RANDBETWEEN(2,4)&"%",""))))))))))) -> 40% | Q90: =IFERROR(L90*(M90+N90)*O90*P90,RANDBETWEEN(1,2)%*L90*(M90+N90)*O90) -> 7.7379533 | R90: =VLOOKUP(D:D,ranking!W:X,2,0) -> 0.7 | S90: =R90*Q90 -> 5.4165673 | T90: 5.863313
A91: Cott Data Servey | B91: ALL INDIA | C91: JioHotstar | D91: Tv Catch-Up | E91: PAID | F91: Tv catchup | G91: Kyunki Saas Bhi Kabhi Bahu Thi | H91: Hindi | I91: 36710 | K91: Drama | L91: =VLOOKUP($C91&$E91,'Updated SES'!A:N,14,0) -> 127.11702 | M91: =VLOOKUP($K91,'Genre Penetration'!A:B,2,0)*VLOOKUP($C91&$E91,'Updated SES'!A:I,9,0) -> 0.335 | N91: =VLOOKUP(K:K,'Genre Penetration'!A:C,3,0)*VLOOKUP($C91&$E91,'Updated SES'!A:J,10,0) -> 0.165 | O91: =VLOOKUP($B91,'Language Penetration'!$B$1:$BL$14,MATCH('Compile data Working'!$H134,'Language Penetration'!$B$1:$BL$1,0),0) -> 0.6 | P91: =IF(ISBLANK(J91),RANDBETWEEN(1,2)&"%",IF(J91=1,RANDBETWEEN(35,40)&"%",IF(J91=2,RANDBETWEEN(30,35)&"%",IF(J91=3,RANDBETWEEN(25,30)&"%",IF(J91=4,RANDBETWEEN(20,25)&"%",IF(J91=5,RANDBETWEEN(15,20)&"%",IF(J91=6,RANDBETWEEN(10,15)&"%",IF(J91=7,RANDBETWEEN(8,10)&"%",IF(J91=8,RANDBETWEEN(6,8)&"%",IF(J91=9,RANDBETWEEN(4,6)&"%",IF(J91=10,RANDBETWEEN(2,4)&"%",""))))))))))) -> 2% | Q91: =IFERROR(L91*(M91+N91)*O91*P91,RANDBETWEEN(1,2)%*L91*(M91+N91)*O91) -> 0.76270212 | R91: =VLOOKUP(D:D,ranking!W:X,2,0) -> 0.3 | S91: =R91*Q91 -> 0.22881064 | T91: 5.8025256
A92: Trending Top 10 | B92: ALL INDIA | C92: Zee5 | D92: SVOD Originals Shows | E92: PAID | F92: Shows | G92: Mukhbir: The Story of a Spy – The Movie | H92: Hindi,Punjabi,Tamil,Telugu | I92: 46213 | J92: 2 | K92: Drama,Mystery,Thriller | L92: =VLOOKUP($C92&$E92,'Updated SES'!A:N,14,0) -> 60.152 | M92: =VLOOKUP($K92,'Genre Penetration'!A:B,2,0)*VLOOKUP($C92&$E92,'Updated SES'!A:I,9,0) -> 0.35425 | N92: =VLOOKUP(K:K,'Genre Penetration'!A:C,3,0)*VLOOKUP($C92&$E92,'Updated SES'!A:J,10,0) -> 0.15925 | O92: =VLOOKUP($B92,'Language Penetration'!$B$1:$BL$14,MATCH('Compile data Working'!$H115,'Language Penetration'!$B$1:$BL$1,0),0) -> 0.204 | P92: =IF(ISBLANK(J92),RANDBETWEEN(1,2)&"%",IF(J92=1,RANDBETWEEN(35,40)&"%",IF(J92=2,RANDBETWEEN(30,35)&"%",IF(J92=3,RANDBETWEEN(25,30)&"%",IF(J92=4,RANDBETWEEN(20,25)&"%",IF(J92=5,RANDBETWEEN(15,20)&"%",IF(J92=6,RANDBETWEEN(10,15)&"%",IF(J92=7,RANDBETWEEN(8,10)&"%",IF(J92=8,RANDBETWEEN(6,8)&"%",IF(J92=9,RANDBETWEEN(4,6)&"%",IF(J92=10,RANDBETWEEN(2,4)&"%",""))))))))))) -> 31% | Q92: =IFERROR(L92*(M92+N92)*O92*P92,RANDBETWEEN(1,2)%*L92*(M92+N92)*O92) -> 1.9533604 | R92: =VLOOKUP(D:D,ranking!W:X,2,0) -> 0.6 | S92: =R92*Q92 -> 1.1720162 | T92: 5.4724255
A93: Trending Top 10 | B93: ALL INDIA | C93: Amazon Prime Video | D93: Svod Originals Shows | E93: PAID | F93: Shows | G93: Off Campus | H93: English,Hindi,Kannada,Malayalam,Tamil,Telugu | I93: 46155 | J93: 8 | K93: Drama,Romance | L93: =VLOOKUP($C93&$E93,'Updated SES'!A:N,14,0) -> 36.49824 | M93: =VLOOKUP($K93,'Genre Penetration'!A:B,2,0)*VLOOKUP($C93&$E93,'Updated SES'!A:I,9,0) -> 0.208 | N93: =VLOOKUP(K:K,'Genre Penetration'!A:C,3,0)*VLOOKUP($C93&$E93,'Updated SES'!A:J,10,0) -> 0.288 | O93: =VLOOKUP($B93,'Language Penetration'!$B$1:$BL$14,MATCH('Compile data Working'!$H82,'Language Penetration'!$B$1:$BL$1,0),0) -> 0.204 | P93: =IF(ISBLANK(J93),RANDBETWEEN(1,2)&"%",IF(J93=1,RANDBETWEEN(35,40)&"%",IF(J93=2,RANDBETWEEN(30,35)&"%",IF(J93=3,RANDBETWEEN(25,30)&"%",IF(J93=4,RANDBETWEEN(20,25)&"%",IF(J93=5,RANDBETWEEN(15,20)&"%",IF(J93=6,RANDBETWEEN(10,15)&"%",IF(J93=7,RANDBETWEEN(8,10)&"%",IF(J93=8,RANDBETWEEN(6,8)&"%",IF(J93=9,RANDBETWEEN(4,6)&"%",IF(J93=10,RANDBETWEEN(2,4)&"%",""))))))))))) -> 7% | Q93: =IFERROR(L93*(M93+N93)*O93*P93,RANDBETWEEN(1,2)%*L93*(M93+N93)*O93) -> 0.25851265 | R93: =VLOOKUP(D:D,ranking!W:X,2,0) -> 0.6 | S93: =R93*Q93 -> 0.15510759 | T93: 5.3401607
A94: Trending Top 10 | B94: ALL INDIA | C94: Amazon MX Player | D94: Avod Originals Shows | E94: FREE | F94: Shows | G94: Vimal Khanna | H94: Hindi | I94: 46157 | J94: 3 | K94: Crime,Thriller | L94: =VLOOKUP($C94&$E94,'Updated SES'!A:N,14,0) -> 78.93987 | M94: =VLOOKUP($K94,'Genre Penetration'!A:B,2,0)*VLOOKUP($C94&$E94,'Updated SES'!A:I,9,0) -> 0.496 | N94: =VLOOKUP(K:K,'Genre Penetration'!A:C,3,0)*VLOOKUP($C94&$E94,'Updated SES'!A:J,10,0) -> 0.076 | O94: =VLOOKUP($B94,'Language Penetration'!$B$1:$BL$14,MATCH('Compile data Working'!$H69,'Language Penetration'!$B$1:$BL$1,0),0) -> 0.23 | P94: =IF(ISBLANK(J94),RANDBETWEEN(1,2)&"%",IF(J94=1,RANDBETWEEN(35,40)&"%",IF(J94=2,RANDBETWEEN(30,35)&"%",IF(J94=3,RANDBETWEEN(25,30)&"%",IF(J94=4,RANDBETWEEN(20,25)&"%",IF(J94=5,RANDBETWEEN(15,20)&"%",IF(J94=6,RANDBETWEEN(10,15)&"%",IF(J94=7,RANDBETWEEN(8,10)&"%",IF(J94=8,RANDBETWEEN(6,8)&"%",IF(J94=9,RANDBETWEEN(4,6)&"%",IF(J94=10,RANDBETWEEN(2,4)&"%",""))))))))))) -> 30% | Q94: =IFERROR(L94*(M94+N94)*O94*P94,RANDBETWEEN(1,2)%*L94*(M94+N94)*O94) -> 3.1155988 | R94: =VLOOKUP(D:D,ranking!W:X,2,0) -> 0.6 | S94: =R94*Q94 -> 1.8693593 | T94: 4.9174488
A95: Cott Data Servey | B95: ALL INDIA | C95: JioHotstar | D95: Tv Catch-Up | E95: PAID | F95: Tv catchup | G95: Thai Maaman | H95: Tamil | I95: - | K95: Drama | L95: =VLOOKUP($C95&$E95,'Updated SES'!A:N,14,0) -> 127.11702 | M95: =VLOOKUP($K95,'Genre Penetration'!A:B,2,0)*VLOOKUP($C95&$E95,'Updated SES'!A:I,9,0) -> 0.335 | N95: =VLOOKUP(K:K,'Genre Penetration'!A:C,3,0)*VLOOKUP($C95&$E95,'Updated SES'!A:J,10,0) -> 0.165 | O95: =VLOOKUP($B95,'Language Penetration'!$B$1:$BL$14,MATCH('Compile data Working'!$H136,'Language Penetration'!$B$1:$BL$1,0),0) -> 0.1 | P95: =IF(ISBLANK(J95),RANDBETWEEN(1,2)&"%",IF(J95=1,RANDBETWEEN(35,40)&"%",IF(J95=2,RANDBETWEEN(30,35)&"%",IF(J95=3,RANDBETWEEN(25,30)&"%",IF(J95=4,RANDBETWEEN(20,25)&"%",IF(J95=5,RANDBETWEEN(15,20)&"%",IF(J95=6,RANDBETWEEN(10,15)&"%",IF(J95=7,RANDBETWEEN(8,10)&"%",IF(J95=8,RANDBETWEEN(6,8)&"%",IF(J95=9,RANDBETWEEN(4,6)&"%",IF(J95=10,RANDBETWEEN(2,4)&"%",""))))))))))) -> 2% | Q95: =IFERROR(L95*(M95+N95)*O95*P95,RANDBETWEEN(1,2)%*L95*(M95+N95)*O95) -> 0.12711702 | R95: =VLOOKUP(D:D,ranking!W:X,2,0) -> 0.3 | S95: =R95*Q95 -> 0.038135106 | T95: 4.911147
A96: Cott Data Servey | B96: ALL INDIA | C96: JioHotstar | D96: Tv Catch-Up | E96: PAID | F96: Tv catchup | G96: Siragadikka Aasai | H96: Tamil | I96: 44949 | K96: Drama | L96: =VLOOKUP($C96&$E96,'Updated SES'!A:N,14,0) -> 127.11702 | M96: =VLOOKUP($K96,'Genre Penetration'!A:B,2,0)*VLOOKUP($C96&$E96,'Updated SES'!A:I,9,0) -> 0.335 | N96: =VLOOKUP(K:K,'Genre Penetration'!A:C,3,0)*VLOOKUP($C96&$E96,'Updated SES'!A:J,10,0) -> 0.165 | O96: =VLOOKUP($B96,'Language Penetration'!$B$1:$BL$14,MATCH('Compile data Working'!$H137,'Language Penetration'!$B$1:$BL$1,0),0) -> 0.1 | P96: =IF(ISBLANK(J96),RANDBETWEEN(1,2)&"%",IF(J96=1,RANDBETWEEN(35,40)&"%",IF(J96=2,RANDBETWEEN(30,35)&"%",IF(J96=3,RANDBETWEEN(25,30)&"%",IF(J96=4,RANDBETWEEN(20,25)&"%",IF(J96=5,RANDBETWEEN(15,20)&"%",IF(J96=6,RANDBETWEEN(10,15)&"%",IF(J96=7,RANDBETWEEN(8,10)&"%",IF(J96=8,RANDBETWEEN(6,8)&"%",IF(J96=9,RANDBETWEEN(4,6)&"%",IF(J96=10,RANDBETWEEN(2,4)&"%",""))))))))))) -> 1% | Q96: =IFERROR(L96*(M96+N96)*O96*P96,RANDBETWEEN(1,2)%*L96*(M96+N96)*O96) -> 0.06355851 | R96: =VLOOKUP(D:D,ranking!W:X,2,0) -> 0.3 | S96: =R96*Q96 -> 0.019067553 | T96: 4.7615128
A97: Trending Top 10 | B97: ALL INDIA | C97: Zee5 | D97: SVOD Originals Movies | E97: PAID | F97: Movies | G97: Frame | H97: Marathi | I97: 46213 | J97: 4 | K97: Drama | L97: =VLOOKUP($C97&$E97,'Updated SES'!A:N,14,0) -> 60.152 | M97: =VLOOKUP($K97,'Genre Penetration'!A:B,2,0)*VLOOKUP($C97&$E97,'Updated SES'!A:I,9,0) -> 0.325 | N97: =VLOOKUP(K:K,'Genre Penetration'!A:C,3,0)*VLOOKUP($C97&$E97,'Updated SES'!A:J,10,0) -> 0.175 | O97: =VLOOKUP($B97,'Language Penetration'!$B$1:$BL$14,MATCH('Compile data Working'!$H117,'Language Penetration'!$B$1:$BL$1,0),0) -> 0.6 | P97: =IF(ISBLANK(J97),RANDBETWEEN(1,2)&"%",IF(J97=1,RANDBETWEEN(35,40)&"%",IF(J97=2,RANDBETWEEN(30,35)&"%",IF(J97=3,RANDBETWEEN(25,30)&"%",IF(J97=4,RANDBETWEEN(20,25)&"%",IF(J97=5,RANDBETWEEN(15,20)&"%",IF(J97=6,RANDBETWEEN(10,15)&"%",IF(J97=7,RANDBETWEEN(8,10)&"%",IF(J97=8,RANDBETWEEN(6,8)&"%",IF(J97=9,RANDBETWEEN(4,6)&"%",IF(J97=10,RANDBETWEEN(2,4)&"%",""))))))))))) -> 21% | Q97: =IFERROR(L97*(M97+N97)*O97*P97,RANDBETWEEN(1,2)%*L97*(M97+N97)*O97) -> 3.789576 | R97: =VLOOKUP(D:D,ranking!W:X,2,0) -> 0.8 | S97: =R97*Q97 -> 3.0316608 | T97: 4.6906504
A98: Trending Top 10 | B98: ALL INDIA | C98: Sony Liv | D98: Theatrical Movies | E98: PAID | F98: Movies | G98: Balti | H98: Hindi,Kannada,Malayalam,Tamil,Telugu | I98: 46212 | J98: 4 | K98: Action,Crime,Drama | L98: =VLOOKUP($C98&$E98,'Updated SES'!A:N,14,0) -> 21.68204 | M98: =VLOOKUP($K98,'Genre Penetration'!A:B,2,0)*VLOOKUP($C98&$E98,'Updated SES'!A:I,9,0) -> 0.3965 | N98: =VLOOKUP(K:K,'Genre Penetration'!A:C,3,0)*VLOOKUP($C98&$E98,'Updated SES'!A:J,10,0) -> 0.1365 | O98: =VLOOKUP($B98,'Language Penetration'!$B$1:$BL$14,MATCH('Compile data Working'!$H107,'Language Penetration'!$B$1:$BL$1,0),0) -> 0.07 | P98: =IF(ISBLANK(J98),RANDBETWEEN(1,2)&"%",IF(J98=1,RANDBETWEEN(35,40)&"%",IF(J98=2,RANDBETWEEN(30,35)&"%",IF(J98=3,RANDBETWEEN(25,30)&"%",IF(J98=4,RANDBETWEEN(20,25)&"%",IF(J98=5,RANDBETWEEN(15,20)&"%",IF(J98=6,RANDBETWEEN(10,15)&"%",IF(J98=7,RANDBETWEEN(8,10)&"%",IF(J98=8,RANDBETWEEN(6,8)&"%",IF(J98=9,RANDBETWEEN(4,6)&"%",IF(J98=10,RANDBETWEEN(2,4)&"%",""))))))))))) -> 25% | Q98: =IFERROR(L98*(M98+N98)*O98*P98,RANDBETWEEN(1,2)%*L98*(M98+N98)*O98) -> 0.20223923 | R98: =VLOOKUP(D:D,ranking!W:X,2,0) -> 0.7 | S98: =R98*Q98 -> 0.14156746 | T98: 3.9088753
A99: Cott Data Servey | B99: ALL INDIA | C99: JioHotstar | D99: Tv Catch-Up | E99: PAID | F99: Tv catchup | G99: Dr. Aarambhi | H99: Hindi | I99: - | K99: Drama | L99: =VLOOKUP($C99&$E99,'Updated SES'!A:N,14,0) -> 127.11702 | M99: =VLOOKUP($K99,'Genre Penetration'!A:B,2,0)*VLOOKUP($C99&$E99,'Updated SES'!A:I,9,0) -> 0.335 | N99: =VLOOKUP(K:K,'Genre Penetration'!A:C,3,0)*VLOOKUP($C99&$E99,'Updated SES'!A:J,10,0) -> 0.165 | O99: =VLOOKUP($B99,'Language Penetration'!$B$1:$BL$14,MATCH('Compile data Working'!$H138,'Language Penetration'!$B$1:$BL$1,0),0) -> 0.1 | P99: =IF(ISBLANK(J99),RANDBETWEEN(1,2)&"%",IF(J99=1,RANDBETWEEN(35,40)&"%",IF(J99=2,RANDBETWEEN(30,35)&"%",IF(J99=3,RANDBETWEEN(25,30)&"%",IF(J99=4,RANDBETWEEN(20,25)&"%",IF(J99=5,RANDBETWEEN(15,20)&"%",IF(J99=6,RANDBETWEEN(10,15)&"%",IF(J99=7,RANDBETWEEN(8,10)&"%",IF(J99=8,RANDBETWEEN(6,8)&"%",IF(J99=9,RANDBETWEEN(4,6)&"%",IF(J99=10,RANDBETWEEN(2,4)&"%",""))))))))))) -> 2% | Q99: =IFERROR(L99*(M99+N99)*O99*P99,RANDBETWEEN(1,2)%*L99*(M99+N99)*O99) -> 0.12711702 | R99: =VLOOKUP(D:D,ranking!W:X,2,0) -> 0.3 | S99: =R99*Q99 -> 0.038135106 | T99: 3.5305554
A100: Trending Top 10 | B100: ALL INDIA | C100: Sony Liv | D100: Theatrical Movies | E100: PAID | F100: Movies | G100: Karakkam | H100: Hindi,Kannada,Malayalam,Tamil,Telugu | I100: 46206 | J100: 8 | K100: Comedy,Horror,Thriller | L100: =VLOOKUP($C100&$E100,'Updated SES'!A:N,14,0) -> 21.68204 | M100: =VLOOKUP($K100,'Genre Penetration'!A:B,2,0)*VLOOKUP($C100&$E100,'Updated SES'!A:I,9,0) -> 0.42575 | N100: =VLOOKUP(K:K,'Genre Penetration'!A:C,3,0)*VLOOKUP($C100&$E100,'Updated SES'!A:J,10,0) -> 0.12075 | O100: =VLOOKUP($B100,'Language Penetration'!$B$1:$BL$14,MATCH('Compile data Working'!$H111,'Language Penetration'!$B$1:$BL$1,0),0) -> 0.204 | P100: =IF(ISBLANK(J100),RANDBETWEEN(1,2)&"%",IF(J100=1,RANDBETWEEN(35,40)&"%",IF(J100=2,RANDBETWEEN(30,35)&"%",IF(J100=3,RANDBETWEEN(25,30)&"%",IF(J100=4,RANDBETWEEN(20,25)&"%",IF(J100=5,RANDBETWEEN(15,20)&"%",IF(J100=6,RANDBETWEEN(10,15)&"%",IF(J100=7,RANDBETWEEN(8,10)&"%",IF(J100=8,RANDBETWEEN(6,8)&"%",IF(J100=9,RANDBETWEEN(4,6)&"%",IF(J100=10,RANDBETWEEN(2,4)&"%",""))))))))))) -> 6% | Q100: =IFERROR(L100*(M100+N100)*O100*P100,RANDBETWEEN(1,2)%*L100*(M100+N100)*O100) -> 0.14503463 | R100: =VLOOKUP(D:D,ranking!W:X,2,0) -> 0.7 | S100: =R100*Q100 -> 0.10152424 | T100: 3.4693551
A101: Trending Top 10 | B101: ALL INDIA | C101: Sony Liv | D101: Svod Originals Shows | E101: PAID | F101: Shows | G101: Perfect Family Season 2 | H101: Hindi,Malayalam,Tamil,Telugu | I101: 46199 | J101: 10 | K101: Drama | L101: =VLOOKUP($C101&$E101,'Updated SES'!A:N,14,0) -> 21.68204 | M101: =VLOOKUP($K101,'Genre Penetration'!A:B,2,0)*VLOOKUP($C101&$E101,'Updated SES'!A:I,9,0) -> 0.325 | N101: =VLOOKUP(K:K,'Genre Penetration'!A:C,3,0)*VLOOKUP($C101&$E101,'Updated SES'!A:J,10,0) -> 0.175 | O101: =VLOOKUP($B101,'Language Penetration'!$B$1:$BL$14,MATCH('Compile data Working'!$H113,'Language Penetration'!$B$1:$BL$1,0),0) -> 0.6 | P101: =IF(ISBLANK(J101),RANDBETWEEN(1,2)&"%",IF(J101=1,RANDBETWEEN(35,40)&"%",IF(J101=2,RANDBETWEEN(30,35)&"%",IF(J101=3,RANDBETWEEN(25,30)&"%",IF(J101=4,RANDBETWEEN(20,25)&"%",IF(J101=5,RANDBETWEEN(15,20)&"%",IF(J101=6,RANDBETWEEN(10,15)&"%",IF(J101=7,RANDBETWEEN(8,10)&"%",IF(J101=8,RANDBETWEEN(6,8)&"%",IF(J101=9,RANDBETWEEN(4,6)&"%",IF(J101=10,RANDBETWEEN(2,4)&"%",""))))))))))) -> 2% | Q101: =IFERROR(L101*(M101+N101)*O101*P101,RANDBETWEEN(1,2)%*L101*(M101+N101)*O101) -> 0.13009224 | R101: =VLOOKUP(D:D,ranking!W:X,2,0) -> 0.6 | S101: =R101*Q101 -> 0.078055344 | T101: 3.343819
...

Sheet ranking
A1: =B1&D1 -> OTT PLATFORMTop 10 | B1: OTT PLATFORM | C1: Content format | D1: Top 10 | E1: PAID/FREE | F1: Show/Movies | G1: Genre | H1: Language | I1: Average of Rank | J1: Round | L1: Rank | M1: Watching Percentage | O1: Rank | P1: Watching Percentage | S1: Rank | T1: Watching Percentage | AB1: 1) Original Shows - 80%
A2: =B2&D2 -> Adda TimesAbhishapto | B2: Adda Times | C2: Svod Originals Shows | D2: Abhishapto | E2: PAID | F2: Show | G2: Drama | H2: Bengali | I2: 9 | J2: 9 | L2: 7 | M2: 40-35% | O2: 7 | P2: 40-35% | S2: 1 | T2: 0.9 | W2: Content format | X2: Watching % | AB2: 2) Original Movies - 100%
A3: =B3&D3 -> Adda TimesBasanta Ese Geche | B3: Adda Times | C3: Svod Originals Shows | D3: Basanta Ese Geche | E3: PAID | F3: Show | G3: Drama | H3: Bengali | I3: 2 | J3: 2 | L3: 6 | M3: 35-30% | O3: 6 | P3: 35-30% | S3: 2 | T3: 0.85 | W3: Avod Originals Movies | X3: 0.8 | AB3: 3) Theatrical releases - 75% (conditions pl discuss)
A4: =B4&D4 -> Adda TimesCabaret | B4: Adda Times | C4: Svod Originals Shows | D4: Cabaret | E4: PAID | F4: Show | G4: Drama | H4: Bengali | I4: 4 | J4: 4 | L4: 5 | M4: 30-25% | O4: 5 | P4: 30-25% | S4: 3 | T4: 0.8 | W4: Avod Originals Shows | X4: 0.6 | AB4: 4) Catch up TV Shows - 30% (For bigg boss its also live and have highlights so higher)
A5: =B5&D5 -> Adda TimesGhoshbabur-retirement-plan | B5: Adda Times | C5: Svod Originals Shows | D5: Ghoshbabur-retirement-plan | E5: PAID | F5: Show | G5: Drama | H5: Bengali | I5: 7 | J5: 7 | L5: 4 | M5: 25-20% | O5: 4 | P5: 25-20% | S5: 4 | T5: 0.7 | W5: Live Event | X5: 0.1 | AB5: 5) Live sports - depending upon sports 100% for Cricket, Kabbadi 40%, rest sport 10-15%
A6: =B6&D6 -> Adda TimesKothamrita | B6: Adda Times | C6: Svod Originals Shows | D6: Kothamrita | E6: PAID | F6: Show | G6: Drama,Family | H6: Bengali | I6: 10 | J6: 10 | L6: 3 | M6: 20-15% | O6: 3 | P6: 20-15% | S6: 5 | T6: 0.65 | W6: Svod Originals Movies | X6: 0.8 | AB6: 4) Highlights - 10% of Live sports
A7: =B7&D7 -> Adda TimesNandini | B7: Adda Times | C7: Svod Originals Shows | D7: Nandini | E7: PAID | F7: Show | G7: Drama | H7: Bengali | I7: 8 | J7: 8 | L7: 2 | M7: 15-10% | O7: 2 | P7: 15-10% | S7: 6 | T7: 0.6 | W7: Svod Originals Shows | X7: 0.6
A8: =B8&D8 -> Adda TimesPetni | B8: Adda Times | C8: Svod Originals Shows | D8: Petni | E8: PAID | F8: Show | G8: Drama | H8: Bengali | I8: 5 | J8: 5 | L8: 1 | M8: 10-8% | O8: 1 | P8: 10-8% | S8: 7 | T8: 0.55 | W8: Theatrical releases | X8: 0.7
A9: =B9&D9 -> Adda TimesPreme Pora Baron | B9: Adda Times | C9: Svod Originals Shows | D9: Preme Pora Baron | E9: PAID | F9: Show | G9: Drama | H9: Bengali | I9: 3 | J9: 3 | L9: 8 | M9: 8-6% | S9: 8 | T9: 0.5 | W9: Tv Catch-Up | X9: 0.3
A10: =B10&D10 -> Adda TimesSIN - Whispers Of Guilt | B10: Adda Times | C10: Svod Originals Shows | D10: SIN - Whispers Of Guilt | E10: PAID | F10: Show | G10: Comedy | H10: Bengali | I10: 6 | J10: 6 | L10: 9 | M10: 6-4% | S10: 9 | T10: 0.45 | W10: Theatrical Movies | X10: 0.7
A11: =B11&D11 -> Adda TimesThe First Rain | B11: Adda Times | C11: Svod Originals Shows | D11: The First Rain | E11: PAID | F11: Show | G11: Drama,Romance | H11: Bengali | I11: 1 | J11: 1 | L11: 10 | M11: 4-2% | S11: 10 | T11: 0.4
A12: =B12&D12 -> Aha Video11th Hour | B12: Aha Video | C12: Svod Originals Shows | D12: 11th Hour | E12: PAID | F12: Show | G12: Drama,Thriller | H12: Telugu | I12: 8 | J12: 8 | S12: 11 | T12: =T11*90% -> 0.36
A13: =B13&D13 -> Aha VideoAkash Vaani | B13: Aha Video | C13: Svod Originals Shows | D13: Akash Vaani | E13: PAID | F13: Show | G13: Comedy,Romane | H13: Tamil,Telugu | I13: 5 | J13: 5 | S13: 12 | T13: =T12*90% -> 0.324
A14: =B14&D14 -> Aha VideoAmmuchi 2 | B14: Aha Video | C14: Svod Originals Shows | D14: Ammuchi 2 | E14: PAID | F14: Show | G14: Comedy | H14: Tamil | I14: 6 | J14: 6 | S14: 13 | T14: =T13*90% -> 0.2916
A15: =B15&D15 -> Aha VideoAnya's Tutorial | B15: Aha Video | C15: Svod Originals Shows | D15: Anya's Tutorial | E15: PAID | F15: Show | G15: Drama | H15: Tamil | I15: 10 | J15: 10 | S15: 14 | T15: =T14*90% -> 0.26244
A16: =B16&D16 -> Aha VideoEmoji | B16: Aha Video | C16: Svod Originals Shows | D16: Emoji | E16: PAID | F16: Show | G16: Romance | H16: Tamil | I16: 3 | J16: 3 | S16: 15 | T16: =T15*90% -> 0.236196
A17: =B17&D17 -> Aha VideoEP7 Youtubers | B17: Aha Video | C17: Svod Originals Shows | D17: EP7 Youtubers | E17: PAID | F17: Show | G17: Game Show | H17: Telugu | I17: 4 | J17: 4 | S17: 16 | T17: =T16*90% -> 0.2125764
A18: =B18&D18 -> Aha VideoIrai | B18: Aha Video | C18: Svod Originals Shows | D18: Irai | E18: PAID | F18: Show | G18: Action,Crime,Drama | H18: Tamil | I18: 2 | J18: 2 | S18: 17 | T18: =T17*90% -> 0.19131876
A19: =B19&D19 -> Aha VideoKuthukku Pathu | B19: Aha Video | C19: Svod Originals Shows | D19: Kuthukku Pathu | E19: PAID | F19: Show | G19: Comedy | H19: Tamil | I19: 7 | J19: 7 | S19: 18 | T19: =T18*90% -> 0.17218688
A20: =B20&D20 -> Aha VideoMad Company | B20: Aha Video | C20: Svod Originals Shows | D20: Mad Company | E20: PAID | F20: Show | G20: Comedy,Drama | H20: Tamil | I20: 9 | J20: 9 | S20: 19 | T20: =T19*90% -> 0.1549682
A21: =B21&D21 -> Aha VideoPettaikaali | B21: Aha Video | C21: Svod Originals Shows | D21: Pettaikaali | E21: PAID | F21: Show | G21: Action | H21: Tamil | I21: 1 | J21: 1 | S21: 20 | T21: =T20*90% -> 0.13947138
A22: =B22&D22 -> Aha VideoAyngaran | B22: Aha Video | C22: Theatrical releases | D22: Ayngaran | E22: PAID | F22: Movie | G22: Action,Drama | H22: Tamil | I22: 4 | J22: 4 | S22: 21 | T22: =T21*90% -> 0.12552424
A23: =B23&D23 -> Aha VideoDiary | B23: Aha Video | C23: Theatrical releases | D23: Diary | E23: PAID | F23: Movie | G23: Horror,Thriller | H23: Tamil | I23: 3 | J23: 3 | S23: 22 | T23: =T22*90% -> 0.11297181
... A92: =B92&D92 -> Apple TvBefore | B92: Apple Tv | C92: Svod Originals Shows | D92: Before | E92: PAID | F92: Show | G92: Drama,Thriller | H92: English | I92: 9 | J92: 9 | S92: 100 | T92: =T91*90% -> 7.865082e-05
A93: =B93&D93 -> Apple TvDisclaimer | B93: Apple Tv | C93: Svod Originals Shows | D93: Disclaimer | E93: PAID | F93: Show | G93: Drama,Mystery,Thriller | H93: English | I93: 5 | J93: 5
A94: =B94&D94 -> Apple TvPresumed Innocent | B94: Apple Tv | C94: Svod Originals Shows | D94: Presumed Innocent | E94: PAID | F94: Show | G94: Crime,Drama,Mystery | H94: English | I94: 7 | J94: 7
A95: =B95&D95 -> Apple TvSee | B95: Apple Tv | C95: Svod Originals Shows | D95: See | E95: PAID | F95: Show | G95: Action,Drama,Sci-Fi | H95: English | I95: 8 | J95: 8
A96: =B96&D96 -> Apple TvSeverance | B96: Apple Tv | C96: Svod Originals Shows | D96: Severance | E96: PAID | F96: Show | G96: Drama,Mystery,Thriller | H96: English | I96: 10 | J96: 10
A97: =B97&D97 -> Apple TvShrinking | B97: Apple Tv | C97: Svod Originals Shows | D97: Shrinking | E97: PAID | F97: Show | G97: Comedy,Drama | H97: English | I97: 3 | J97: 3
A98: =B98&D98 -> Apple TvSilo | B98: Apple Tv | C98: Svod Originals Shows | D98: Silo | E98: PAID | F98: Show | G98: Drama,Mystery,Sci-Fi | H98: English | I98: 1 | J98: 1
A99: =B99&D99 -> Apple TvSlow Horses | B99: Apple Tv | C99: Svod Originals Shows | D99: Slow Horses | E99: PAID | F99: Show | G99: Drama,Thriller | H99: English | I99: 6 | J99: 6
A100: =B100&D100 -> Apple TvTed Lasso | B100: Apple Tv | C100: Svod Originals Shows | D100: Ted Lasso | E100: PAID | F100: Show | G100: Comedy,Drama,Sport | H100: English | I100: 4 | J100: 4
A101: =B101&D101 -> Apple TvKillers of the Flower Moon | B101: Apple Tv | C101: Theatrical releases | D101: Killers of the Flower Moon | E101: PAID | F101: Movie | G101: Crime,Drama,Mystery | H101: English | I101: 8 | J101: 8
A102: =B102&D102 -> Apple TvLuck | B102: Apple Tv | C102: Theatrical releases | D102: Luck | E102: PAID | F102: Movie | G102: Animation,Adventure,Comedy | H102: English | I102: 4 | J102: 4
A103: =B103&D103 -> Apple TvWolfs | B103: Apple Tv | C103: Theatrical releases | D103: Wolfs | E103: PAID | F103: Movie | G103: Crime,Thriller | H103: English | I103: 1 | J103: 1
A104: =B104&D104 -> Chaupal TvJatt & Jullit 3 | B104: Chaupal Tv | C104: Svod Originals Movies | D104: Jatt & Jullit 3 | E104: PAID | F104: Movie | G104: Comedy,Romance | H104: Punjabi | I104: 3 | J104: 3
... A393: =B393&D393 -> Zee5Yek Number | B393: Zee5 | C393: Svod Originals Movies | D393: Yek Number | E393: PAID | F393: Movie | G393: Drama | H393: Marathi | I393: 4.6666667 | J393: 5
A394: =B394&D394 -> Zee52012 | B394: Zee5 | C394: Theatrical releases | D394: 2012 | E394: RENT | F394: Movie | G394: Action,Sci-Fi | H394: Hindi,English,Tamil, | I394: 9 | J394: 9
A395: =B395&D395 -> Zee5Bhaiyya Ji | B395: Zee5 | C395: Theatrical releases | D395: Bhaiyya Ji | E395: PAID | F395: Movie | G395: Action,Drama | H395: Hindi | I395: 7.3333333 | J395: 7
A396: =B396&D396 -> Zee5Fifty Shades Freed | B396: Zee5 | C396: Theatrical releases | D396: Fifty Shades Freed | E396: RENT | F396: Movie | G396: Romance,Drama,Thriller | H396: Hindi,English | I396: 6 | J396: 6
A397: =B397&D397 -> Zee5Fifty Shades of Grey | B397: Zee5 | C397: Theatrical releases | D397: Fifty Shades of Grey | E397: RENT | F397: Movie | G397: Romance,Drama,Thriller | H397: Hindi,English | I397: 4 | J397: 4
A398: =B398&D398 -> Zee5Gladiator | B398: Zee5 | C398: Theatrical releases | D398: Gladiator | E398: RENT | F398: Movie | G398: Action,Drama | H398: Hindi,English,Tamil,Telugu | I398: 8 | J398: 8
A399: =B399&D399 -> Zee5It Ends with Us | B399: Zee5 | C399: Theatrical releases | D399: It Ends with Us | E399: RENT | F399: Movie | G399: Drama,Romance | H399: Hindi,English | I399: 2 | J399: 2
A400: =B400&D400 -> Zee5Maa Nanna Superhero | B400: Zee5 | C400: Theatrical releases | D400: Maa Nanna Superhero | E400: PAID | F400: Movie | G400: Family,Drama,Romance | H400: Telegu | I400: 1.3333333 | J400: 1
A401: =B401&D401 -> Zee5Nunakkuzhi | B401: Zee5 | C401: Theatrical releases | D401: Nunakkuzhi | E401: PAID | F401: Movie | G401: Crime,Drama | H401: Malayalam,Telugu,Kannada | I401: 9 | J401: 9
A402: =B402&D402 -> Zee5Raghu Thatha | B402: Zee5 | C402: Theatrical releases | D402: Raghu Thatha | E402: PAID | F402: Movie | G402: Comedy | H402: Hindi,Tamil | I402: 7.3333333 | J402: 7
A403: =B403&D403 -> Zee5Simmba | B403: Zee5 | C403: Theatrical releases | D403: Simmba | E403: PAID | F403: Movie | G403: Action,Drama | H403: Hindi | I403: 9 | J403: 9
A404: =B404&D404 -> Zee5Spider-Man No Way Home | B404: Zee5 | C404: Theatrical releases | D404: Spider-Man No Way Home | E404: RENT | F404: Movie | G404: Adventure,Fantasy,Sci-Fi | H404: Hindi,English,Tamil,Telugu | I404: 10 | J404: 10
A405: =B405&D405 -> Zee5The Girl With The Dragon Tattoo | B405: Zee5 | C405: Theatrical releases | D405: The Girl With The Dragon Tattoo | E405: RENT | F405: Movie | G405: Crime,Drama,Mystery | H405: English | I405: 1 | J405: 1
A406: =B406&D406 -> Zee5The Pursuit of Happyness | B406: Zee5 | C406: Theatrical releases | D406: The Pursuit of Happyness | E406: RENT | F406: Movie | G406: Drama | H406: English,Telugu | I406: 3 | J406: 3
... A419: =B419&D419 -> Zee5Vasudha | B419: Zee5 | C419: Tv Catch-Up | D419: Vasudha | E419: FREE | F419: Tv-Shows | G419: Drama | H419: Hindi | I419: 5 | J419: 5

Sheet Updated SES
A2: OTT PlatformsTYPE | B2: OTT Platforms | C2: Language | D2: Region | E2: TYPE | F2: Show Type | G2: Top 10 | H2: Actual Subscribers | I2: Male % | J2: Female % | K2: CTV | L2: Mobile | M2: CTV+Mobile | N2: Total Viewers | V2: Category | W2: 2-24 | X2: 25-34 | Y2: 35-44 | Z2: 45+
A3: =B3&E3 -> Adda TimesPAID | B3: Adda Times | C3: Bengali | D3: West Bengali | E3: PAID | F3: SVOD | G3: NA | H3: 1.6 | I3: 0.8 | J3: 0.2 | K3: 0.13 | L3: 0.87 | M3: 0.06 | N3: =H3*K3*3+H3*L3*1.1-H3*M3*3 -> 1.8672 | O3: =VLOOKUP(B:B,'[1]Revenue share'!$C$6:$J$16,8,0) -> #N/A | V3: ALL INDIA | W3: 0.3 | X3: 0.33 | Y3: 0.2 | Z3: 0.17
A4: =B4&E4 -> Aha VideoPAID | B4: Aha Video | C4: Telugu & Tamil | D4: Andhra Pradesh,Telangana,Tamilnadu | E4: PAID | F4: SVOD | G4: Yes | H4: 9.23 | I4: 0.76 | J4: 0.24 | K4: 0.22 | L4: 0.78 | M4: 0.05 | N4: =H4*K4*3+H4*L4*1.1-H4*M4*3 -> 12.62664 | O4: =VLOOKUP(B:B,'[1]Revenue share'!$C$6:$J$16,8,0) -> #N/A
A5: =B5&E5 -> Aha VideoFREE | B5: Aha Video | C5: Telugu & Tamil | D5: Andhra Pradesh,Telangana,Tamilnadu | E5: FREE | F5: AVOD | G5: Yes | H5: 3.75 | I5: 0.76 | J5: 0.24 | K5: 0.22 | L5: 0.78 | M5: 0.05 | N5: =H5*K5*3+H5*L5*1.1-H5*M5*3 -> 5.13 | O5: =VLOOKUP(B:B,'[1]Revenue share'!$C$6:$J$16,8,0) -> #N/A
A6: =B6&E6 -> AlttPAID | B6: Altt | C6: Hindi | D6: All India | E6: PAID | F6: SVOD | G6: Yes | H6: 12.16 | I6: 0.65 | J6: 0.35 | K6: 0.26 | L6: 0.74 | M6: 0.07 | N6: =H6*K6*3+H6*L6*1.1-H6*M6*3 -> 16.82944 | O6: =VLOOKUP(B:B,'[1]Revenue share'!$C$6:$J$16,8,0) -> #N/A
A7: =B7&E7 -> Amazon Prime VideoPAID | B7: Amazon Prime Video | C7: Hindi,English,Tamil,Telugu,Malayalam,Kannada,Bengali | D7: All India | E7: PAID | F7: SVOD | G7: Yes | H7: 22.08 | I7: 0.52 | J7: 0.48 | K7: 0.37 | L7: 0.63 | M7: 0.05 | N7: =H7*K7*3+H7*L7*1.1-H7*M7*3 -> 36.49824 | O7: =VLOOKUP(B:B,'[1]Revenue share'!$C$6:$J$16,8,0) -> 78
A8: =B8&E8 -> Amazon Prime VideoFREE | B8: Amazon Prime Video | C8: Hindi,English,Tamil,Telugu,Malayalam,Kannada,Bengali | D8: All India | E8: FREE | F8: SVOD | G8: Yes | H8: 5.09 | I8: 0.52 | J8: 0.48 | K8: 0.37 | L8: 0.63 | M8: 0.05 | N8: =H8*K8*3+H8*L8*1.1-H8*M8*3 -> 8.41377 | O8: =VLOOKUP(B:B,'[1]Revenue share'!$C$6:$J$16,8,0) -> 78 | T8: Demographic Profile | U8: Jio Hotstar | V8: Amazon Prime Video | W8: Netflix | X8: Amazon MX Player | Y8: Zee5 | Z8: Sony Liv | AA8: Alt Balaji | AB8: Sun NXT | AC8: Hoichoi | AD8: Aha Video | AE8: Stage | AF8: Other OTT (Non Regional) | AG8: Other OTT (Regional) | AK8: Location | AL8: Jio Hotstar | AM8: Amazon Prime Video | AN8: Netflix | AO8: Amazon MX Player | AP8: Zee5 | AQ8: Sony Liv | AR8: Alt Balaji | AS8: Sun NXT | AT8: Hoichoi | AU8: Aha Video | AV8: Stage | AW8: Other OTT (Non Regional) | AX8: Other OTT (Regional)
A9: =B9&E9 -> Amazon Prime VideoRENT | B9: Amazon Prime Video | C9: Hindi,English,Tamil,Telugu,Malayalam,Kannada,Bengali | D9: All India | E9: RENT | F9: Rent | G9: NA | H9: 3 | I9: 0.68 | J9: 0.32 | K9: 0.37 | L9: 0.63 | M9: 0.08 | N9: =H9*K9*3+H9*L9*1.1-H9*M9*3 -> 4.689 | O9: =VLOOKUP(B:B,'[1]Revenue share'!$C$6:$J$16,8,0) -> 78 | T9: M <18 | U9: 0.10790021 | V9: 0.034482029 | W9: 0.035616735 | X9: 0.081691769 | Y9: 0.014519981 | Z9: 0.04214677 | AA9: 0.033684735 | AB9: 0.03331181 | AC9: 0.1309339 | AD9: 0.023882568 | AE9: 0.031394817 | AF9: 0.10547326 | AG9: 0.048860553 | AK9: North - Metro & T1 | AL9: 0.16111013 | AM9: 0.22260068 | AN9: 0.23109857 | AO9: 0.3575414 | AP9: 0.19018048 | AQ9: 0.2027027 | AR9: 0.1888668 | AS9: 0.0010650257 | AT9: 0.0044869546 | AU9: 0.0020714194 | AV9: 0.51032078 | AW9: 0.19978664 | AX9: 0.096550337
A10: =B10&E10 -> Chaupal TvPAID | B10: Chaupal Tv | C10: Punjabi,Haryanvi & Bhojpuri | D10: Punjab,Haryana | E10: PAID | F10: SVOD | G10: Yes | H10: 3 | I10: 0.75 | J10: 0.25 | K10: 0.21 | L10: 0.79 | M10: 0.04 | N10: =H10*K10*3+H10*L10*1.1-H10*M10*3 -> 4.137 | O10: =VLOOKUP(B:B,'[1]Revenue share'!$C$6:$J$16,8,0) -> #N/A | T10: M 18 - 24 | U10: 0.14054356 | V10: 0.18038936 | W10: 0.24206269 | X10: 0.295904 | Y10: 0.11419832 | Z10: 0.11639679 | AA10: 0.20357729 | AB10: 0.16104755 | AC10: 0.14952818 | AD10: 0.048690028 | AE10: 0.14162628 | AF10: 0.23500334 | AG10: 0.23623517 | AK10: North - T2 & beyond | AL10: 0.15261917 | AM10: 0.10118213 | AN10: 0.082514352 | AO10: 0.32232161 | AP10: 0.15864545 | AQ10: 0.11583012 | AR10: 0.14761431 | AS10: 0.00098613494 | AT10: 0.0035895637 | AU10: 0.0040654026 | AV10: 0.36247084 | AW10: 0.11870818 | AX10: 0.14331691
A11: =B11&E11 -> CrunchyrollPAID | B11: Crunchyroll | C11: English,Hindi,Tamil,Telugu | D11: All India | E11: PAID | F11: SVOD | H11: 0.5 | I11: 0.6 | J11: 0.4 | K11: 0.32 | L11: 0.68 | M11: 0.06 | N11: =H11*K11*3+H11*L11*1.1-H11*M11*3 -> 0.764 | O11: =VLOOKUP(B:B,'[1]Revenue share'!$C$6:$J$16,8,0) -> #N/A | T11: M 25 - 35 | U11: 0.17724335 | V11: 0.18505263 | W11: 0.17971993 | X11: 0.20620893 | Y11: 0.31960948 | Z11: 0.21284907 | AA11: 0.37756983 | AB11: 0.18975553 | AC11: 0.22169791 | AD11: 0.25680117 | AE11: 0.33298188 | AF11: 0.10881286 | AG11: 0.2451778 | AK11: South - Metro & T1 | AL11: 0.15557208 | AM11: 0.1731116 | AN11: 0.21835166 | AO11: 0.0051014082 | AP11: 0.14535222 | AQ11: 0.16679537 | AR11: 0.14890656 | AS11: 0.50588723 | AT11: 0.0023311853 | AU11: 0.53280006 | AV11: 0.0026036775 | AW11: 0.14693046 | AX11: 0.1971236
A12: =B12&E12 -> Dangal PlayPAID | B12: Dangal Play | C12: Hindi,Bhojpuri,Bengali | D12: All India | E12: PAID | F12: SVOD | H12: 21.05 | I12: 0.7 | J12: 0.3 | K12: 0.43 | L12: 0.57 | M12: 0.06 | N12: =H12*K12*3+H12*L12*1.1-H12*M12*3 -> 36.56385 | O12: =VLOOKUP(B:B,'[1]Revenue share'!$C$6:$J$16,8,0) -> #N/A | T12: M 35 + | U12: 0.10887583 | V12: 0.11939442 | W12: 0.08478955 | X12: 0.068160999 | Y12: 0.087892933 | Z12: 0.031209633 | AA12: 0.082822869 | AB12: 0.083103184 | AC12: 0.076042083 | AD12: 0.088082457 | AE12: 0.17890103 | AF12: 0.12446243 | AG12: 0.10011387 | AK12: South - T2 & beyond | AL12: 0.11018318 | AM12: 0.092867161 | AN12: 0.073562324 | AO12: 0.0034009388 | AP12: 0.12691636 | AQ12: 0.093822394 | AR12: 0.13439364 | AS12: 0.48369919 | AT12: 0.0039468582 | AU12: 0.45135843 | AV12: 0.0043430313 | AW12: 0.093104452 | AX12: 0.18103188
A13: =B13&E13 -> Dangal PlayFREE | B13: Dangal Play | C13: Hindi,Bhojpuri,Bengali | D13: All India | E13: FREE | F13: AVOD | H13: 10 | I13: 0.65 | J13: 0.35 | K13: 0.43 | L13: 0.57 | M13: 0.07 | N13: =H13*K13*3+H13*L13*1.1-H13*M13*3 -> 17.07 | O13: =VLOOKUP(B:B,'[1]Revenue share'!$C$6:$J$16,8,0) -> #N/A | T13: F <18 | U13: 0.067544954 | V13: 0.059431785 | W13: 0.05070119 | X13: 0.0429434 | Y13: 0.030664808 | Z13: 0.092259348 | AA13: 0.041851112 | AB13: 0.17740788 | AC13: 0.14823772 | AD13: 0.17170942 | AE13: 0.048995614 | AF13: 0.05055501 | AG13: 0.066595817 | AK13: West - Metro & T1 | AL13: 0.13111884 | AM13: 0.19635344 | AN13: 0.24394278 | AO13: 0.10746022 | AP13: 0.16766932 | AQ13: 0.1969112 | AR13: 0.17534791 | AS13: 0.0053744354 | AT13: 0.0037188175 | AU13: 0.0012544671 | AV13: 0.0030484926 | AW13: 0.22829987 | AX13: 0.1568943
A14: =B14&E14 -> Discovery+PAID | B14: Discovery+ | C14: Hindi,English,Tamil,Telugu,Malayalam,Kannada,Bengali | D14: All India | E14: PAID | F14: SVOD | H14: 0.5 | I14: 0.7 | J14: 0.3 | K14: 0.35 | L14: 0.65 | M14: 0.05 | N14: =H14*K14*3+H14*L14*1.1-H14*M14*3 -> 0.8075 | O14: =VLOOKUP(B:B,'[1]Revenue share'!$C$6:$J$16,8,0) -> #N/A | T14: F 18 - 24 | U14: 0.14650665 | V14: 0.15728122 | W14: 0.18709991 | X14: 0.17122328 | Y14: 0.14899226 | Z14: 0.217117 | AA14: 0.11122219 | AB14: 0.11223041 | AC14: 0.094567299 | AD14: 0.16786815 | AE14: 0.10609277 | AF14: 0.22034606 | AG14: 0.10207545 | AK14: West - T2 & beyond | AL14: 0.12195848 | AM14: 0.081747145 | AN14: 0.062469592 | AO14: 0.079296195 | AP14: 0.099941781 | AQ14: 0.1003861 | AR14: 0.097415507 | AS14: 0.00096641224 | AT14: 0.0046291338 | AU14: 0.0064368875 | AV14: 0.0039206029 | AW14: 0.099893318 | AX14: 0.10057327
A15: =B15&E15 -> Epic OnPAID | B15: Epic On | C15: Hindi,Bhojpuri,Punjabi | D15: Punjab,Haryana | E15: PAID | F15: SVOD | H15: 0.5 | I15: 0.76 | J15: 0.24 | K15: 0.34 | L15: 0.66 | M15: 0.06 | N15: =H15*K15*3+H15*L15*1.1-H15*M15*3 -> 0.783 | O15: =VLOOKUP(B:B,'[1]Revenue share'!$C$6:$J$16,8,0) -> #N/A | T15: F 25 - 35 | U15: 0.1159889 | V15: 0.16656059 | W15: 0.16007978 | X15: 0.10360112 | Y15: 0.20704508 | Z15: 0.18481873 | AA15: 0.066525979 | AB15: 0.12567328 | AC15: 0.098019334 | AD15: 0.090482351 | AE15: 0.080154068 | AF15: 0.083112123 | AG15: 0.12208812 | AK15: East - Metro & T1 | AL15: 0.0971278 | AM15: 0.092867161 | AN15: 0.06743213 | AO15: 0.064298999 | AP15: 0.068600815 | AQ15: 0.083397683 | AR15: 0.06888668 | AS15: 0.0010847484 | AT15: 0.62764313 | AU15: 0.0010163507 | AV15: 0.064726935 | AW15: 0.083018136 | AX15: 0.076737403
A16: =B16&E16 -> Epic OnFREE | B16: Epic On | C16: Hindi,Bhojpuri,Punjabi | D16: Punjab,Haryana | E16: FREE | F16: AVOD | H16: 0.8 | I16: 0.75 | J16: 0.25 | K16: 0.34 | L16: 0.66 | M16: 0.07 | N16: =H16*K16*3+H16*L16*1.1-H16*M16*3 -> 1.2288 | O16: =VLOOKUP(B:B,'[1]Revenue share'!$C$6:$J$16,8,0) -> #N/A | T16: F 35 + | U16: 0.13539655 | V16: 0.097407966 | W16: 0.059930221 | X16: 0.030266502 | Y16: 0.077077141 | Z16: 0.10320266 | AA16: 0.082745996 | AB16: 0.11747036 | AC16: 0.080973581 | AD16: 0.15248385 | AE16: 0.079853542 | AF16: 0.072234915 | AG16: 0.078853215 | AK16: East - T2 & beyond | AL16: 0.070310318 | AM16: 0.039270687 | AN16: 0.020628588 | AO16: 0.060579222 | AP16: 0.042693577 | AQ16: 0.04015444 | AR16: 0.038568588 | AS16: 0.0009368282 | AT16: 0.34965436 | AU16: 0.0009969916 | AV16: 0.048565641 | AW16: 0.030258947 | AX16: 0.047772302
A17: =B17&E17 -> Eros NowPAID | B17: Eros Now | C17: Hindi | D17: All India | E17: PAID | F17: SVOD | H17: 36.2 | I17: 0.75 | J17: 0.25 | K17: 0.24 | L17: 0.76 | M17: 0.06 | N17: =H17*K17*3+H17*L17*1.1-H17*M17*3 -> 49.8112 | O17: =VLOOKUP(B:B,'[1]Revenue share'!$C$6:$J$16,8,0) -> #N/A
A18: =B18&E18 -> Etv WinPAID | B18: Etv Win | C18: Malayalam,Kannada,Telugu,Hindi,Tamil | D18: Kerala | E18: PAID | F18: SVOD | H18: 1.5 | I18: 0.78 | J18: 0.22 | K18: 0.18 | L18: 0.82 | M18: 0.07 | N18: =H18*K18*3+H18*L18*1.1-H18*M18*3 -> 1.848 | O18: =VLOOKUP(B:B,'[1]Revenue share'!$C$6:$J$16,8,0) -> #N/A
A19: =B19&E19 -> HoichoiPAID | B19: Hoichoi | C19: Hindi,Bengali | D19: West Bengali | E19: PAID | F19: SVOD | H19: 10.13 | I19: 0.6 | J19: 0.4 | K19: 0.41 | L19: 0.59 | M19: 0.07 | N19: =H19*K19*3+H19*L19*1.1-H19*M19*3 -> 16.90697 | O19: =VLOOKUP(B:B,'[1]Revenue share'!$C$6:$J$16,8,0) -> 22.1 | T19: Randbetween to change % Every time
A20: =B20&E20 -> Hr OttPAID | B20: Hr Ott | C20: Malayalam | D20: Kerala | E20: PAID | F20: SVOD | H20: 0 | I20: 0.8 | J20: 0.2 | K20: 0.36 | L20: 0.64 | M20: 0.07 | N20: =H20*K20*3+H20*L20*1.1-H20*M20*3 -> 0 | O20: =VLOOKUP(B:B,'[1]Revenue share'!$C$6:$J$16,8,0) -> #N/A | T20: Demographic Profile | U20: Jio Hotstar | V20: Amazon Prime Video | W20: Netflix | X20: Amazon MX Player | Y20: Zee5 | Z20: Sony Liv | AA20: Alt Balaji | AB20: Sun NXT | AC20: Hoichoi | AD20: Aha Video | AE20: Stage | AF20: Other OTT (Non Regional) | AG20: Other OTT (Regional) | AK20: Demographic Profile | AL20: Jio Hotstar | AM20: Amazon Prime Video | AN20: Netflix | AO20: Amazon MX Player | AP20: Zee5 | AQ20: Sony Liv | AR20: Alt Balaji | AS20: Sun NXT | AT20: Hoichoi | AU20: Aha Video | AV20: Stage | AW20: Other OTT (Non Regional) | AX20: Other OTT (Regional)
A21: =B21&E21 -> JioHotstarFREE | B21: JioHotstar | C21: Hindi,English,Tamil,Telugu,Malayalam,Kannada,Bengali | D21: All India | E21: FREE | F21: AVOD | H21: 39.06 | I21: 0.625 | J21: 0.375 | K21: 0.28 | L21: 0.72 | M21: 0.065 | N21: =H21*K21*3+H21*L21*1.1-H21*M21*3 -> 56.12922 | O21: =VLOOKUP(B:B,'[1]Revenue share'!$C$6:$J$16,8,0) -> 414 | T21: M <18 | U21: =U9*RANDBETWEEN(90,105)/100 -> 0.10897922 | V21: =V9*RANDBETWEEN(80,110)/100 -> 0.032413107 | W21: =W9*RANDBETWEEN(95,115)/100 -> 0.037753739 | X21: =X9*RANDBETWEEN(98,118)/100 -> 0.089044028 | Y21: =Y9*RANDBETWEEN(90,105)/100 -> 0.014519981 | Z21: =Z9*RANDBETWEEN(90,105)/100 -> 0.040039432 | AA21: =AA9*RANDBETWEEN(90,105)/100 -> 0.032674193 | AB21: =AB9*RANDBETWEEN(90,105)/100 -> 0.032312456 | AC21: =AC9*RANDBETWEEN(90,105)/100 -> 0.12438721 | AD21: =AD9*RANDBETWEEN(90,105)/100 -> 0.021971963 | AE21: =AE9*RANDBETWEEN(90,105)/100 -> 0.029825076 | AF21: =AF9*RANDBETWEEN(90,105)/100 -> 0.097035396 | AG21: =AG9*RANDBETWEEN(90,105)/100 -> 0.047883342 | AK21: North - Metro & T1 | AL21: =AL9*RANDBETWEEN(90,105)/100 -> 0.15305462 | AM21: =AM9*RANDBETWEEN(90,105)/100 -> 0.21147065 | AN21: =AN9*RANDBETWEEN(90,105)/100 -> 0.2264766 | AO21: =AO9*RANDBETWEEN(90,105)/100 -> 0.3575414 | AP21: =AP9*RANDBETWEEN(90,105)/100 -> 0.18827867 | AQ21: =AQ9*RANDBETWEEN(90,105)/100 -> 0.20675676 | AR21: =AR9*RANDBETWEEN(90,105)/100 -> 0.17375746 | AS21: =AS9*RANDBETWEEN(90,105)/100 -> 0.0010437252 | ... AX21: =AX9*RANDBETWEEN(90,105)/100 -> 0.09172282
A22: =B22&E22 -> KlikkPAID | B22: Klikk | C22: Bengali | D22: West Bengali | E22: PAID | F22: SVOD | H22: 0.1 | I22: 0.85 | J22: 0.15 | K22: 0.31 | L22: 0.69 | M22: 0.06 | N22: =H22*K22*3+H22*L22*1.1-H22*M22*3 -> 0.1509 | O22: =VLOOKUP(B:B,'[1]Revenue share'!$C$6:$J$16,8,0) -> #N/A | T22: M 18 - 24 | U22: =U10*RANDBETWEEN(90,105)/100 -> 0.14194899 | V22: =V10*RANDBETWEEN(80,110)/100 -> 0.19121272 | W22: =W10*RANDBETWEEN(95,115)/100 -> 0.24690394 | X22: =X10*RANDBETWEEN(98,118)/100 -> 0.32845344 | Y22: =Y10*RANDBETWEEN(90,105)/100 -> 0.10392047 | Z22: =Z10*RANDBETWEEN(90,105)/100 -> 0.12105267 | AA22: =AA10*RANDBETWEEN(90,105)/100 -> 0.2096846 | AB22: =AB10*RANDBETWEEN(90,105)/100 -> 0.1642685 | AC22: =AC10*RANDBETWEEN(90,105)/100 -> 0.14952818 | AD22: =AD10*RANDBETWEEN(90,105)/100 -> 0.050637629 | AE22: =AE10*RANDBETWEEN(90,105)/100 -> 0.1444588 | AF22: =AF10*RANDBETWEEN(90,105)/100 -> 0.22090314 | AG22: =AG10*RANDBETWEEN(90,105)/100 -> 0.21733635 | AK22: North - T2 & beyond | AL22: =AL10*RANDBETWEEN(90,105)/100 -> 0.14193583 | AM22: =AM10*RANDBETWEEN(90,105)/100 -> 0.092075736 | AN22: =AN10*RANDBETWEEN(90,105)/100 -> 0.080864065 | AO22: =AO10*RANDBETWEEN(90,105)/100 -> 0.3190984 | AP22: =AP10*RANDBETWEEN(90,105)/100 -> 0.1602319 | AQ22: =AQ10*RANDBETWEEN(90,105)/100 -> 0.10772201 | AR22: =AR10*RANDBETWEEN(90,105)/100 -> 0.15499503 | AS22: =AS10*RANDBETWEEN(90,105)/100 -> 0.0010354417 | ... AX22: =AX10*RANDBETWEEN(90,105)/100 -> 0.15048275
A23: =B23&E23 -> Lionsgate PlayPAID | B23: Lionsgate Play | C23: English,Hindi,Tamil,Telugu,Kannada | D23: All India | E23: PAID | F23: SVOD | H23: 20 | I23: 0.82 | J23: 0.18 | K23: 0.23 | L23: 0.77 | M23: 0.09 | N23: =H23*K23*3+H23*L23*1.1-H23*M23*3 -> 25.34 | O23: =VLOOKUP(B:B,'[1]Revenue share'!$C$6:$J$16,8,0) -> #N/A | T23: M 25 - 35 | U23: =U11*RANDBETWEEN(90,105)/100 -> 0.18256065 | V23: =V11*RANDBETWEEN(80,110)/100 -> 0.1758 | W23: =W11*RANDBETWEEN(95,115)/100 -> 0.17073393 | X23: =X11*RANDBETWEEN(98,118)/100 -> 0.23507818 | Y23: =Y11*RANDBETWEEN(90,105)/100 -> 0.29723682 | Z23: =Z11*RANDBETWEEN(90,105)/100 -> 0.21072058 | AA23: =AA11*RANDBETWEEN(90,105)/100 -> 0.37001844 | AB23: =AB11*RANDBETWEEN(90,105)/100 -> 0.19355064 | AC23: =AC11*RANDBETWEEN(90,105)/100 -> 0.20396207 | AD23: =AD11*RANDBETWEEN(90,105)/100 -> 0.25423316 | AE23: =AE11*RANDBETWEEN(90,105)/100 -> 0.31633279 | AF23: =AF11*RANDBETWEEN(90,105)/100 -> 0.10881286 | AG23: =AG11*RANDBETWEEN(90,105)/100 -> 0.22066002 | AK23: South - Metro & T1 | AL23: =AL11*RANDBETWEEN(90,105)/100 -> 0.1493492 | AM23: =AM11*RANDBETWEEN(90,105)/100 -> 0.17138048 | AN23: =AN11*RANDBETWEEN(90,105)/100 -> 0.22490221 | AO23: =AO11*RANDBETWEEN(90,105)/100 -> 0.0052544504 | AP23: =AP11*RANDBETWEEN(90,105)/100 -> 0.15116631 | AQ23: =AQ11*RANDBETWEEN(90,105)/100 -> 0.16012355 | AR23: =AR11*RANDBETWEEN(90,105)/100 -> 0.15337376 | AS23: =AS11*RANDBETWEEN(90,105)/100 -> 0.52612271 | ... AX23: =AX11*RANDBETWEEN(90,105)/100 -> 0.18923866
A24: =B24&E24 -> Manorama MaxPAID | B24: Manorama Max | C24: Malayalam,Tamil,Telugu | D24: Kerala,Tamil,Andra Pradesh | E24: PAID | F24: SVOD | H24: 0.1 | I24: 0.74 | J24: 0.26 | K24: 0.31 | L24: 0.69 | M24: 0.06 | N24: =H24*K24*3+H24*L24*1.1-H24*M24*3 -> 0.1509 | O24: =VLOOKUP(B:B,'[1]Revenue share'!$C$6:$J$16,8,0) -> #N/A | T24: M 35 + | U24: =U12*RANDBETWEEN(90,105)/100 -> 0.11431962 | V24: =V12*RANDBETWEEN(80,110)/100 -> 0.11581258 | W24: =W12*RANDBETWEEN(95,115)/100 -> 0.094116401 | X24: =X12*RANDBETWEEN(98,118)/100 -> 0.072250659 | Y24: =Y12*RANDBETWEEN(90,105)/100 -> 0.090529721 | Z24: =Z12*RANDBETWEEN(90,105)/100 -> 0.032145922 | AA24: =AA12*RANDBETWEEN(90,105)/100 -> 0.077853497 | AB24: =AB12*RANDBETWEEN(90,105)/100 -> 0.077285961 | AC24: =AC12*RANDBETWEEN(90,105)/100 -> 0.072239979 | AD24: =AD12*RANDBETWEEN(90,105)/100 -> 0.09248658 | AE24: =AE12*RANDBETWEEN(90,105)/100 -> 0.16816697 | AF24: =AF12*RANDBETWEEN(90,105)/100 -> 0.12944093 | AG24: =AG12*RANDBETWEEN(90,105)/100 -> 0.094107042 | AK24: South - T2 & beyond | AL24: =AL12*RANDBETWEEN(90,105)/100 -> 0.11569234 | AM24: =AM12*RANDBETWEEN(90,105)/100 -> 0.093795832 | AN24: =AN12*RANDBETWEEN(90,105)/100 -> 0.066206091 | AO24: =AO12*RANDBETWEEN(90,105)/100 -> 0.0031288637 | AP24: =AP12*RANDBETWEEN(90,105)/100 -> 0.11422472 | AQ24: =AQ12*RANDBETWEEN(90,105)/100 -> 0.087254826 | AR24: =AR12*RANDBETWEEN(90,105)/100 -> 0.12364215 | AS24: =AS12*RANDBETWEEN(90,105)/100 -> 0.50304716 | ... AX24: =AX12*RANDBETWEEN(90,105)/100 -> 0.17016997
A25: =B25&E25 -> Amazon Mx PlayerFREE | B25: Amazon Mx Player | C25: Hindi,English,Tamil,Telugu,Malayalam,Kannada,Bengali | D25: All India | E25: FREE | F25: AVOD | H25: 72.89 | I25: 0.8 | J25: 0.2 | K25: 0.07 | L25: 0.93 | M25: 0.05 | N25: =H25*K25*3+H25*L25*1.1-H25*M25*3 -> 78.93987 | O25: =VLOOKUP(B:B,'[1]Revenue share'!$C$6:$J$16,8,0) -> 168 | T25: F <18 | U25: =U13*RANDBETWEEN(90,105)/100 -> 0.070922202 | V25: =V13*RANDBETWEEN(80,110)/100 -> 0.057648831 | W25: =W13*RANDBETWEEN(95,115)/100 -> 0.058306368 | X25: =X13*RANDBETWEEN(98,118)/100 -> 0.050243778 | Y25: =Y13*RANDBETWEEN(90,105)/100 -> 0.029438215 | Z25: =Z13*RANDBETWEEN(90,105)/100 -> 0.0848786 | AA25: =AA13*RANDBETWEEN(90,105)/100 -> 0.041014089 | AB25: =AB13*RANDBETWEEN(90,105)/100 -> 0.17031157 | AC25: =AC13*RANDBETWEEN(90,105)/100 -> 0.14379058 | AD25: =AD13*RANDBETWEEN(90,105)/100 -> 0.16999233 | AE25: =AE13*RANDBETWEEN(90,105)/100 -> 0.045075965 | AF25: =AF13*RANDBETWEEN(90,105)/100 -> 0.05308276 | AG25: =AG13*RANDBETWEEN(90,105)/100 -> 0.064597942 | AK25: West - Metro & T1 | AL25: =AL13*RANDBETWEEN(90,105)/100 -> 0.12062934 | AM25: =AM13*RANDBETWEEN(90,105)/100 -> 0.20617111 | AN25: =AN13*RANDBETWEEN(90,105)/100 -> 0.2366245 | AO25: =AO13*RANDBETWEEN(90,105)/100 -> 0.10853482 | AP25: =AP13*RANDBETWEEN(90,105)/100 -> 0.16599263 | AQ25: =AQ13*RANDBETWEEN(90,105)/100 -> 0.17722008 | AR25: =AR13*RANDBETWEEN(90,105)/100 -> 0.17359443 | AS25: =AS13*RANDBETWEEN(90,105)/100 -> 0.0050519693 | ... AX25: =AX13*RANDBETWEEN(90,105)/100 -> 0.14904958
A26: =B26&E26 -> NetflixPAID | B26: Netflix | C26: Hindi,English,Tamil,Telugu,Malayalam,Kannada,Bengali | D26: All India | E26: PAID | F26: SVOD | H26: 17.44 | I26: 0.49 | J26: 0.51 | K26: 0.58 | L26: 0.42 | M26: 0.07 | N26: =H26*K26*5+H26*L26*1.5-H26*M26*5 -> 55.4592 | O26: =VLOOKUP(B:B,'[1]Revenue share'!$C$6:$J$16,8,0) -> 48 | T26: F 18 - 24 | U26: =U14*RANDBETWEEN(90,105)/100 -> 0.14797171 | V26: =V14*RANDBETWEEN(80,110)/100 -> 0.15098997 | W26: =W14*RANDBETWEEN(95,115)/100 -> 0.20206791 | X26: =X14*RANDBETWEEN(98,118)/100 -> 0.19690678 | Y26: =Y14*RANDBETWEEN(90,105)/100 -> 0.14154264 | Z26: =Z14*RANDBETWEEN(90,105)/100 -> 0.20626115 | AA26: =AA14*RANDBETWEEN(90,105)/100 -> 0.11455886 | AB26: =AB14*RANDBETWEEN(90,105)/100 -> 0.11671962 | AC26: =AC14*RANDBETWEEN(90,105)/100 -> 0.087001915 | AD26: =AD14*RANDBETWEEN(90,105)/100 -> 0.15611738 | AE26: =AE14*RANDBETWEEN(90,105)/100 -> 0.09654442 | AF26: =AF14*RANDBETWEEN(90,105)/100 -> 0.22695644 | AG26: =AG14*RANDBETWEEN(90,105)/100 -> 0.09697168 | AK26: West - T2 & beyond | AL26: =AL14*RANDBETWEEN(90,105)/100 -> 0.11586055 | AM26: =AM14*RANDBETWEEN(90,105)/100 -> 0.075207373 | AN26: =AN14*RANDBETWEEN(90,105)/100 -> 0.064968376 | AO26: =AO14*RANDBETWEEN(90,105)/100 -> 0.071366575 | AP26: =AP14*RANDBETWEEN(90,105)/100 -> 0.097942946 | AQ26: =AQ14*RANDBETWEEN(90,105)/100 -> 0.097374517 | AR26: =AR14*RANDBETWEEN(90,105)/100 -> 0.10131213 | AS26: =AS14*RANDBETWEEN(90,105)/100 -> 0.00089876339 | ... AX26: =AX14*RANDBETWEEN(90,105)/100 -> 0.093533139
A27: =B27&E27 -> Saina PlayPAID | B27: Saina Play | C27: Malayalam | D27: Kerala | E27: PAID | F27: SVOD | H27: 0.05 | I27: 0.7 | J27: 0.3 | K27: 0.4 | L27: 0.6 | M27: 0.04 | N27: =H27*K27*3+H27*L27*1.1-H27*M27*3 -> 0.087 | O27: =VLOOKUP(B:B,'[1]Revenue share'!$C$6:$J$16,8,0) -> #N/A | T27: F 25 - 35 | U27: =U15*RANDBETWEEN(90,105)/100 -> 0.11830868 | V27: =V15*RANDBETWEEN(80,110)/100 -> 0.16322938 | W27: =W15*RANDBETWEEN(95,115)/100 -> 0.15527738 | X27: =X15*RANDBETWEEN(98,118)/100 -> 0.11706927 | Y27: =Y15*RANDBETWEEN(90,105)/100 -> 0.19048147 | Z27: =Z15*RANDBETWEEN(90,105)/100 -> 0.17557779 | AA27: =AA15*RANDBETWEEN(90,105)/100 -> 0.067191239 | AB27: =AB15*RANDBETWEEN(90,105)/100 -> 0.11310595 | AC27: =AC15*RANDBETWEEN(90,105)/100 -> 0.098019334 | AD27: =AD15*RANDBETWEEN(90,105)/100 -> 0.084148586 | AE27: =AE15*RANDBETWEEN(90,105)/100 -> 0.078550986 | AF27: =AF15*RANDBETWEEN(90,105)/100 -> 0.08144988 | AG27: =AG15*RANDBETWEEN(90,105)/100 -> 0.11232107 | AK27: East - Metro & T1 | AL27: =AL15*RANDBETWEEN(90,105)/100 -> 0.096156522 | AM27: =AM15*RANDBETWEEN(90,105)/100 -> 0.097510519 | AN27: =AN15*RANDBETWEEN(90,105)/100 -> 0.068106451 | AO27: =AO15*RANDBETWEEN(90,105)/100 -> 0.067513949 | AP27: =AP15*RANDBETWEEN(90,105)/100 -> 0.062426742 | AQ27: =AQ15*RANDBETWEEN(90,105)/100 -> 0.077559846 | AR27: =AR15*RANDBETWEEN(90,105)/100 -> 0.065442346 | AS27: =AS15*RANDBETWEEN(90,105)/100 -> 0.0011064434 | ... AX27: =AX15*RANDBETWEEN(90,105)/100 -> 0.076737403
A28: =B28&E28 -> Shemaroo MePAID | B28: Shemaroo Me | C28: Gujarati,Hindi,Marathi | D28: Gujrat,Maharastra | E28: PAID | F28: SVOD | H28: 10 | I28: 0.75 | J28: 0.25 | K28: 0.38 | L28: 0.62 | M28: 0.08 | N28: =H28*K28*3+H28*L28*1.1-H28*M28*3 -> 15.82 | O28: =VLOOKUP(B:B,'[1]Revenue share'!$C$6:$J$16,8,0) -> #N/A | T28: F 35 + | U28: =U16*RANDBETWEEN(90,105)/100 -> 0.13404259 | V28: =V16*RANDBETWEEN(80,110)/100 -> 0.10714876 | W28: =W16*RANDBETWEEN(95,115)/100 -> 0.058731616 | X28: =X16*RANDBETWEEN(98,118)/100 -> 0.034201147 | Y28: =Y16*RANDBETWEEN(90,105)/100 -> 0.074764827 | Z28: =Z16*RANDBETWEEN(90,105)/100 -> 0.10320266 | AA28: =AA16*RANDBETWEEN(90,105)/100 -> 0.076953776 | AB28: =AB16*RANDBETWEEN(90,105)/100 -> 0.10572332 | AC28: =AC16*RANDBETWEEN(90,105)/100 -> 0.073685958 | AD28: =AD16*RANDBETWEEN(90,105)/100 -> 0.15553353 | AE28: =AE16*RANDBETWEEN(90,105)/100 -> 0.077457935 | AF28: =AF16*RANDBETWEEN(90,105)/100 -> 0.070067867 | AG28: =AG16*RANDBETWEEN(90,105)/100 -> 0.074122022 | AK28: East - T2 & beyond | AL28: =AL16*RANDBETWEEN(90,105)/100 -> 0.070310318 | AM28: =AM16*RANDBETWEEN(90,105)/100 -> 0.039270687 | AN28: =AN16*RANDBETWEEN(90,105)/100 -> 0.018772015 | AO28: =AO16*RANDBETWEEN(90,105)/100 -> 0.060579222 | AP28: =AP16*RANDBETWEEN(90,105)/100 -> 0.041839705 | AQ28: =AQ16*RANDBETWEEN(90,105)/100 -> 0.039752896 | AR28: =AR16*RANDBETWEEN(90,105)/100 -> 0.039725646 | AS28: =AS16*RANDBETWEEN(90,105)/100 -> 0.00096493304 | ... AX28: =AX16*RANDBETWEEN(90,105)/100 -> 0.049683194
A29: =B29&E29 -> Shemaroo MeFREE | B29: Shemaroo Me | C29: Gujarati,Hindi,Marathi | D29: Gujrat,Maharastra | E29: FREE | F29: AVOD | H29: 2 | I29: 0.73 | J29: 0.27 | K29: 0.38 | L29: 0.62 | M29: 0.06 | N29: =H29*K29*3+H29*L29*1.1-H29*M29*3 -> 3.284 | O29: =VLOOKUP(B:B,'[1]Revenue share'!$C$6:$J$16,8,0) -> #N/A | U29: =SUM(U21:U28) -> 1.0190537 | V29: =SUM(V21:V28) -> 0.99425536 | W29: =SUM(W21:W28) -> 1.0238913 | X29: =SUM(X21:X28) -> 1.1232473 | Y29: =SUM(Y21:Y28) -> 0.94243415 | Z29: =SUM(Z21:Z28) -> 0.9738788 | AA29: =SUM(AA21:AA28) -> 0.98994869 | AB29: =SUM(AB21:AB28) -> 0.97327802 | ... AG29: =SUM(AG21:AG28) -> 0.92799947
A30: =B30&E30 -> Sony LivPAID | B30: Sony Liv | C30: Hindi,English,Tamil,Telugu,Malayalam,Kannada,Bengali | D30: All India | E30: PAID | F30: SVOD | H30: 12.14 | I30: 0.65 | J30: 0.35 | K30: 0.44 | L30: 0.56 | M30: 0.05 | N30: =H30*K30*3+H30*L30*1.1-H30*M30*3 -> 21.68204 | O30: =VLOOKUP(B:B,'[1]Revenue share'!$C$6:$J$16,8,0) -> 35.1
A31: =B31&E31 -> Sony LivFREE | B31: Sony Liv | C31: Hindi,English,Tamil,Telugu,Malayalam,Kannada,Bengali | D31: All India | E31: FREE | F31: AVOD | H31: 3 | I31: 0.66 | J31: 0.34 | K31: 0.44 | L31: 0.56 | M31: 0.06 | N31: =H31*K31*3+H31*L31*1.1-H31*M31*3 -> 5.268 | O31: =VLOOKUP(B:B,'[1]Revenue share'!$C$6:$J$16,8,0) -> 35.1 | T31: Demographic Profile | U31: Jio Hotstar | V31: Amazon Prime Video | W31: Netflix | X31: Amazon MX Player | Y31: Zee5 | Z31: Sony Liv | AA31: Alt Balaji | AB31: Sun NXT | AC31: Hoichoi | AD31: Aha Video | AE31: Stage | AF31: Other OTT (Non Regional) | AG31: Other OTT (Regional)
A32: =B32&E32 -> Sun NxtPAID | B32: Sun Nxt | C32: Telugu,Tamil,Malyalam,Kannada | D32: South | E32: PAID | F32: SVOD | H32: 8.53 | I32: 0.78 | J32: 0.22 | K32: 0.28 | L32: 0.72 | M32: 0.05 | N32: =H32*K32*3+H32*L32*1.1-H32*M32*3 -> 12.64146 | O32: =VLOOKUP(B:B,'[1]Revenue share'!$C$6:$J$16,8,0) -> 30.4 | T32: M <18 | U32: =U21/U$29 -> 0.10694159 | V32: =V21/V$29 -> 0.032600385 | W32: =W21/W$29 -> 0.036872801 | X32: =X21/X$29 -> 0.079273754 | Y32: =Y21/Y$29 -> 0.015406892 | Z32: =Z21/Z$29 -> 0.041113362 | AA32: =AA21/AA$29 -> 0.033005946 | AB32: =AB21/AB$29 -> 0.033199615 | ... AG32: =AG21/AG$29 -> 0.051598458
A33: =B33&E33 -> Sun NxtFREE | B33: Sun Nxt | C33: Telugu,Tamil,Malyalam,Kannada | D33: South | E33: FREE | F33: AVOD | H33: 3.4 | I33: 0.74 | J33: 0.26 | K33: 0.28 | L33: 0.72 | M33: 0.09 | N33: =H33*K33*3+H33*L33*1.1-H33*M33*3 -> 4.6308 | O33: =VLOOKUP(B:B,'[1]Revenue share'!$C$6:$J$16,8,0) -> 30.4 | T33: M 18 - 24 | U33: =U22/U$29 -> 0.13929492 | V33: =V22/V$29 -> 0.19231752 | W33: =W22/W$29 -> 0.24114273 | X33: =X22/X$29 -> 0.29241419 | Y33: =Y22/Y$29 -> 0.11026815 | Z33: =Z22/Z$29 -> 0.12429952 | AA33: =AA22/AA$29 -> 0.21181361 | AB33: =AB22/AB$29 -> 0.1687786 | ... AG33: =AG22/AG$29 -> 0.23419879
A34: =B34&E34 -> TVF PlayFREE | B34: TVF Play | C34: Hindi,English | D34: All India | E34: FREE | F34: AVOD | H34: 1 | I34: 0.68 | J34: 0.32 | K34: 0.2 | L34: 0.8 | M34: 0.09 | N34: =H34*K34*3+H34*L34*1.1-H34*M34*3 -> 1.21 | O34: =VLOOKUP(B:B,'[1]Revenue share'!$C$6:$J$16,8,0) -> #N/A | T34: M 25 - 35 | U34: =U23/U$29 -> 0.17914724 | V34: =V23/V$29 -> 0.17681574 | W34: =W23/W$29 -> 0.16675006 | X34: =X23/X$29 -> 0.20928444 | Y34: =Y23/Y$29 -> 0.31539267 | Z34: =Z23/Z$29 -> 0.21637249 | AA34: =AA23/AA$29 -> 0.37377537 | AB34: =AB23/AB$29 -> 0.1988647 | ... AG34: =AG23/AG$29 -> 0.23778033
A35: =B35&E35 -> UlluPAID | B35: Ullu | C35: Hindi,Telugu,Tamil | D35: All India | E35: PAID | F35: SVOD | H35: 2.9 | I35: 0.8 | J35: 0.2 | K35: 0.27 | L35: 0.73 | M35: 0.05 | N35: =H35*K35*3+H35*L35*1.1-H35*M35*3 -> 4.2427 | O35: =VLOOKUP(B:B,'[1]Revenue share'!$C$6:$J$16,8,0) -> #N/A | T35: M 35 + | U35: =U24/U$29 -> 0.11218214 | V35: =V24/V$29 -> 0.11648173 | W35: =W24/W$29 -> 0.091920306 | X35: =X24/X$29 -> 0.064323022 | Y35: =Y24/Y$29 -> 0.096059466 | Z35: =Z24/Z$29 -> 0.033008134 | AA35: =AA24/AA$29 -> 0.078643971 | AB35: =AB24/AB$29 -> 0.079407897 | ... AG35: =AG24/AG$29 -> 0.10140851
A36: =B36&E36 -> Vr OttPAID | B36: Vr Ott | C36: Hindi,English,Tamil,Telugu | D36: Andhra Pradesh,Telangana,Tamilnadu | E36: PAID | F36: SVOD | H36: 0.05 | I36: 0.71 | J36: 0.29 | K36: 0.22 | L36: 0.78 | M36: 0.08 | N36: =H36*K36*3+H36*L36*1.1-H36*M36*3 -> 0.0639 | O36: =VLOOKUP(B:B,'[1]Revenue share'!$C$6:$J$16,8,0) -> #N/A | T36: F <18 | U36: =U25/U$29 -> 0.069596141 | V36: =V25/V$29 -> 0.057981917 | W36: =W25/W$29 -> 0.056945858 | X36: =X25/X$29 -> 0.044730826 | Y36: =Y25/Y$29 -> 0.031236363 | Z36: =Z25/Z$29 -> 0.087155199 | AA36: =AA25/AA$29 -> 0.04143052 | AB36: =AB25/AB$29 -> 0.17498758 | ... AG36: =AG25/AG$29 -> 0.069609891
A37: =B37&E37 -> STAGEPAID | B37: STAGE | C37: Haryanvi,Rajasthani | D37: HSM | E37: PAID | F37: SVOD | H37: 10.3 | I37: 0.6 | J37: 0.4 | K37: 0.11 | L37: 0.89 | M37: 0.08 | N37: =H37*K37*3+H37*L37*1.1-H37*M37*3 -> 11.0107 | O37: =VLOOKUP(B:B,'[1]Revenue share'!$C$6:$J$16,8,0) -> 0 | T37: F 18 - 24 | U37: =U26/U$29 -> 0.14520503 | V37: =V26/V$29 -> 0.15186237 | W37: =W26/W$29 -> 0.19735289 | X37: =X26/X$29 -> 0.17530136 | Y37: =Y26/Y$29 -> 0.15018837 | Z37: =Z26/Z$29 -> 0.21179345 | AA37: =AA26/AA$29 -> 0.11572202 | AB37: =AB26/AB$29 -> 0.11992424 | ... AG37: =AG26/AG$29 -> 0.1044954
A38: =B38&E38 -> Zee5PAID | B38: Zee5 | C38: Hindi,English,Tamil,Telugu,Malayalam,Kannada,Bengali | D38: All India | E38: PAID | F38: SVOD | H38: 41.2 | I38: 0.65 | J38: 0.35 | K38: 0.3 | L38: 0.7 | M38: 0.07 | N38: =H38*K38*3+H38*L38*1.1-H38*M38*3 -> 60.152 | O38: =VLOOKUP(B:B,'[1]Revenue share'!$C$6:$J$16,8,0) -> 85 | T38: F 25 - 35 | U38: =U27/U$29 -> 0.11609661 | V38: =V27/V$29 -> 0.16417249 | W38: =W27/W$29 -> 0.15165417 | X38: =X27/X$29 -> 0.10422395 | Y38: =Y27/Y$29 -> 0.20211648 | Z38: =Z27/Z$29 -> 0.18028711 | AA38: =AA27/AA$29 -> 0.067873456 | AB38: =AB27/AB$29 -> 0.11621135 | ... AG38: =AG27/AG$29 -> 0.12103571
A39: =B39&E39 -> Zee5RENT | B39: Zee5 | C39: Hindi,English,Tamil,Telugu,Malayalam,Kannada,Bengali | D39: All India | E39: RENT | F39: Rent | H39: 0.5 | I39: 0.75 | J39: 0.25 | K39: 0.3 | L39: 0.7 | M39: 0.09 | N39: =H39*K39*3+H39*L39*1.1-H39*M39*3 -> 0.7 | O39: =VLOOKUP(B:B,'[1]Revenue share'!$C$6:$J$16,8,0) -> 85 | T39: F 35 + | U39: =U28/U$29 -> 0.13153634 | V39: =V28/V$29 -> 0.10776785 | W39: =W28/W$29 -> 0.057361184 | X39: =X28/X$29 -> 0.030448458 | Y39: =Y28/Y$29 -> 0.079331619 | Z39: =Z28/Z$29 -> 0.10597075 | AA39: =AA28/AA$29 -> 0.077735116 | AB39: =AB28/AB$29 -> 0.10862603 | ... AG39: =AG28/AG$29 -> 0.079872914
A40: =B40&E40 -> Zee5FREE | B40: Zee5 | C40: Hindi,English,Tamil,Telugu,Malayalam,Kannada,Bengali | D40: All India | E40: FREE | F40: AVOD | H40: 16.73 | I40: 0.68 | J40: 0.32 | K40: 0.3 | L40: 0.7 | M40: 0.07 | N40: =H40*K40*3+H40*L40*1.1-H40*M40*3 -> 24.4258 | O40: =VLOOKUP(B:B,'[1]Revenue share'!$C$6:$J$16,8,0) -> 85
A41: =B41&E41 -> Apple TVPAID | B41: Apple TV | C41: English | D41: All India | E41: PAID | F41: SVOD | H41: 1 | I41: 0.6 | J41: 0.4 | K41: 0.41 | L41: 0.59 | M41: 0.07 | N41: =H41*K41*3+H41*L41*1.1-H41*M41*3 -> 1.669 | O41: =VLOOKUP(B:B,'[1]Revenue share'!$C$6:$J$16,8,0) -> #N/A
A42: =B42&E42 -> Etv WinFREE | B42: Etv Win | C42: Malayalam,Kannada,Telugu,Hindi,Tamil | D42: Kerala | E42: FREE | F42: SVOD | H42: 0.9 | I42: 0.75 | J42: 0.25 | K42: 0.2 | L42: 0.8 | M42: 0.07 | N42: =H42*K42*3+H42*L42*1.1-H42*M42*3 -> 1.143 | O42: =VLOOKUP(B:B,'[1]Revenue share'!$C$6:$J$16,8,0) -> #N/A
A43: =B43&E43 -> JioHotstarPAID | B43: JioHotstar | C43: Hindi,English,Tamil,Telugu,Malayalam,Kannada,Bengali | D43: All India | E43: PAID | F43: SVOD | H43: 88.46 | I43: 0.67 | J43: 0.33 | K43: 0.28 | L43: 0.72 | M43: 0.065 | N43: =H43*K43*3+H43*L43*1.1-H43*M43*3 -> 127.11702 | O43: =VLOOKUP(B:B,'[1]Revenue share'!$C$6:$J$16,8,0) -> 414
A44: =B44&E44 -> Jio Hotstar SparksFREE | B44: Jio Hotstar Sparks | C44: Hindi,English,Tamil,Telugu,Malayalam,Kannada,Bengali | D44: All India | E44: FREE | F44: AVOD | H44: 41 | I44: 0.625 | J44: 0.375 | K44: 0.28 | L44: 0.72 | M44: 0.065 | N44: =H44*K44*3+H44*L44*1.1-H44*M44*3 -> 58.917 | O44: =VLOOKUP(B:B,'[1]Revenue share'!$C$6:$J$16,8,0) -> #N/A
A45: =B45&E45 -> Manorama MaxFREE | B45: Manorama Max | C45: Malayalam,Tamil,Telugu | D45: Kerala,Tamil,Andra Pradesh | E45: FREE | F45: SVOD | H45: 0.1 | I45: 0.74 | J45: 0.26 | K45: 0.31 | L45: 0.69 | M45: 0.06 | N45: =H45*K45*3+H45*L45*1.1-H45*M45*3 -> 0.1509 | O45: =VLOOKUP(B:B,'[1]Revenue share'!$C$6:$J$16,8,0) -> #N/A | T45: M 35 + | U45: =U33*RANDBETWEEN(90,105)/100 -> 0.12536542 | V45: =V33*RANDBETWEEN(80,110)/100 -> 0.20962609 | W45: =W33*RANDBETWEEN(95,115)/100 -> 0.27490271 | X45: =X33*RANDBETWEEN(98,118)/100 -> 0.32457975 | Y45: =Y33*RANDBETWEEN(90,105)/100 -> 0.10254938 | Z45: =Z33*RANDBETWEEN(90,105)/100 -> 0.11311256 | AA45: =AA33*RANDBETWEEN(90,105)/100 -> 0.19275038 | AB45: =AB33*RANDBETWEEN(90,105)/100 -> 0.1687786 | AC45: =AC33*RANDBETWEEN(90,105)/100 -> 0.15853564 | AD45: =AD33*RANDBETWEEN(90,105)/100 -> 0.051402438 | AE45: =AE33*RANDBETWEEN(90,105)/100 -> 0.13744849 | AF45: =AF33*RANDBETWEEN(90,105)/100 -> 0.21246078 | AG45: =AG33*RANDBETWEEN(90,105)/100 -> 0.21780488 | AK45: South - T2 & beyond | AL45: =AL33*RANDBETWEEN(90,105)/100 -> 0 | AM45: =AM33*RANDBETWEEN(90,105)/100 -> 0 | AN45: =AN33*RANDBETWEEN(90,105)/100 -> 0 | AO45: =AO33*RANDBETWEEN(90,105)/100 -> 0 | AP45: =AP33*RANDBETWEEN(90,105)/100 -> 0 | AQ45: =AQ33*RANDBETWEEN(90,105)/100 -> 0 | AR45: =AR33*RANDBETWEEN(90,105)/100 -> 0 | AS45: =AS33*RANDBETWEEN(90,105)/100 -> 0 | ... AX45: =AX33*RANDBETWEEN(90,105)/100 -> 0

Sheet Genre Penetration
A1: GENRE | B1: Male | C1: Female | F1: GENRE | G1: Male | H1: Female | I1: 2-16 | J1: 17-24 | K1: 25-34 | L1: 35-44 | M1: 45+
A2: Action | B2: 0.7 | C2: 0.3 | F2: Action | G2: 0.7 | H2: 0.3 | I2: 0.15 | J2: 0.25 | K2: 0.3 | L2: 0.2 | M2: 0.1
A3: Action Thriller, Neo-Noir | B3: 0.7 | C3: 0.3 | F3: Action,Adventure,Comedy | G3: 0.6 | H3: 0.4 | I3: 0.1 | J3: 0.3 | K3: 0.25 | L3: 0.2 | M3: 0.15
A4: Action, Adventure | B4: 0.5 | C4: 0.5 | F4: Action,Adventure,Crime | G4: 0.65 | H4: 0.35 | I4: 0.05 | J4: 0.2 | K4: 0.35 | L4: 0.25 | M4: 0.15
A5: Action, Adventure, Comedy | B5: 0.55 | C5: 0.45 | F5: Action,Adventure,Drama | G5: 0.58 | H5: 0.42 | I5: 0.1 | J5: 0.25 | K5: 0.3 | L5: 0.2 | M5: 0.15
A6: Action, Comedy | B6: 0.55 | C6: 0.45 | F6: Action,Adventure,Fantasy | G6: 0.62 | H6: 0.38 | I6: 0.2 | J6: 0.3 | K6: 0.25 | L6: 0.15 | M6: 0.1
A7: Action, Comedy, Romance | B7: 0.6 | C7: 0.4 | F7: Action,Adventure,Sci-Fi | G7: 0.7 | H7: 0.3 | I7: 0.05 | J7: 0.2 | K7: 0.3 | L7: 0.25 | M7: 0.2
A8: Action, Comedy, Teen | B8: 0.55 | C8: 0.45 | F8: Action,Comedy,Crime | G8: 0.55 | H8: 0.45 | I8: 0.1 | J8: 0.25 | K8: 0.3 | L8: 0.2 | M8: 0.15
A9: Action, Dark Humor, Satire, Superheroes | B9: 0.6 | C9: 0.4 | F9: Action,Comedy,Drama | G9: 0.48 | H9: 0.52 | I9: 0.15 | J9: 0.3 | K9: 0.25 | L9: 0.2 | M9: 0.1
A10: Action, Drama | B10: 0.53 | C10: 0.47 | F10: Action,Comedy,Thriller | G10: 0.67 | H10: 0.33 | I10: 0.1 | J10: 0.25 | K10: 0.3 | L10: 0.2 | M10: 0.15
A11: Action, Drama, Crime | B11: 0.52 | C11: 0.48 | F11: Action,Crime | G11: 0.64 | H11: 0.36 | I11: 0.05 | J11: 0.15 | K11: 0.35 | L11: 0.3 | M11: 0.15
A12: Action, Drama, Fantasy | B12: 0.55 | C12: 0.45 | F12: Action,Crime,Drama | G12: 0.59 | H12: 0.41 | I12: 0.05 | J12: 0.2 | K12: 0.3 | L12: 0.25 | M12: 0.2
A13: Action, Drama, Social | B13: 0.55 | C13: 0.45 | F13: Action,Crime,Thriller | G13: 0.72 | H13: 0.28 | I13: 0.1 | J13: 0.2 | K13: 0.35 | L13: 0.2 | M13: 0.15
... A104: Action,Horror,Fantasy | B104: 0.5 | C104: 0.5 | F104: Mythology | G104: 0.58 | H104: 0.42 | I104: 0.05 | J104: 0.2 | K104: 0.3 | L104: 0.25 | M104: 0.2
A105: Action,horror,Thriller | B105: 0.65 | C105: 0.35
A106: Action,Mystery | B106: 0.55 | C106: 0.45
A107: Action,Mystery,Supernatural,Thriller | B107: 0.61 | C107: 0.39
A108: Action,Mystery,Thriller | B108: 0.53 | C108: 0.47
A109: Action,Patriotic,crime | B109: 0.68 | C109: 0.32
A110: Action,Political,Spy,Thriller | B110: 0.67 | C110: 0.33
A111: Action,Political,Thriller | B111: 0.67 | C111: 0.33
A112: Action,Romance | B112: 0.57 | C112: 0.43
A113: Action,Romance,Adventure,Mystery | B113: 0.59 | C113: 0.41
A114: Action,Romance,Drama | B114: 0.6 | C114: 0.4
A115: Action,Romance,Thriller | B115: 0.56 | C115: 0.44
A116: Action,Sci-Fi | B116: 0.66 | C116: 0.34
... A291: Comedy,Entertainment,Talk Show | B291: 0.4 | C291: 0.6
A292: Comedy,Event | B292: =AVERAGE(B6:B291) -> 0.5657462 | C292: =AVERAGE(C6:C291) -> 0.4342538
A293: Comedy,Family | B293: 0.58 | C293: 0.42
A294: Comedy,Family | B294: 0.55 | C294: 0.45
A295: Comedy,Family Drama | B295: 0.48 | C295: 0.52
A296: Comedy,Family,Animation | B296: 0.58 | C296: 0.42
A297: Comedy,Family,Drama | B297: 0.48 | C297: 0.52
A298: Comedy,Fantasy | B298: 0.53 | C298: 0.47
A299: Comedy,Fantasy,Horror | B299: 0.57 | C299: 0.43
A300: Comedy,Fantasy,Romance | B300: 0.55 | C300: 0.45
A301: Comedy,Horror | B301: 0.61 | C301: 0.39
A302: Comedy,Horror,Sci-Fi | B302: 0.54 | C302: 0.46
A303: Comedy,Horror,Thriller | B303: 0.655 | C303: 0.345
A304: Comedy,Kids | B304: 0.53 | C304: 0.47
... A688: Youth,Drama | B688: 0.48 | C688: 0.52

Sheet Language Penetration
A1: Type | B1: Market | C1: Hindi | D1: English | E1: English,Hindi | F1: English,Hindi,Telugu | G1: Tamil | H1: Telugu | I1: Tamil,Telugu | J1: Kannada | K1: Malayalam | L1: Kannada,Malayalam,Tamil,Telugu | M1: English,Hindi,Tamil,Telugu | N1: English,Hindi,Tamil,Telugu | O1: Marathi | P1: Gujarati | Q1: Hindi,Kannada,Malayalam,Tamil,Telugu | R1: English,Hindi,Tamil,Telugu | S1: Punjabi | T1: Bengali | U1: Bengali,Hindi,Kannada,Marathi,Tamil,Telugu | V1: Bengali,Hindi,Kannada,Malayalam,Marathi,Tamil,Telugu | W1: Bengali,Hindi,Kannada,Malayalam,Marathi,Tamil,Telugu | X1: Bengali,Hindi,Marathi,Tamil,Telugu | Y1: Kannada,Malayalam,Telugu | Z1: Bhojpuri | AA1: Haryanvi | AB1: Bangla,Bhojpuri,English,Haryanvi,Hindi,Kannada,Tamil,Telugu | AC1: Bangali,Hindi,Kannada,Malayalam,Marathi,Tamil,Telugu | AD1: Bengali,English,Hindi,Kannada,Marathi,Tamil,Telugu | AE1: Bengali,English,Hindi,Kannada,Malayalam,Tamil,Telugu | AF1: Hindi,Tamil,Telugu | AG1: Hindi,Malayalam,Tamil,Telugu | AH1: Bengali,Hindi,Marathi,Tamil,Telugu | AI1: Kannada,Malayalam,Tamil,Telugu | AJ1: Hindi,Kannada,Malayalam,Tamil,Telugu | AK1: English,Hindi,Marathi,Tamil,Telugu | AL1: English,Hindi,Kannada,Malayalam,Tamil,Telugu | AM1: English,Tamil,Telugu | AN1: Hindi,Marathi | AO1: Hindi,Tamil | AP1: Kannada,Malayalam,Tamil,Telugu,Telugu | AQ1: English,Hindi,Kannada,Tamil,Telugu | AR1: English,Gujarati,Hindi,Kannada,Malayalam,Marathi,Tamil,Telugu | AS1: Rajasthani | AT1: English,Telugu | AU1: English,Hindi,Tamil | AV1: Bengali,Bhojpuri,English,Hindi,Kannada,Marathi,Odia,Punjabi,Tamil,Telugu | AW1: Hindi,Kannada,Tamil,Telugu | AX1: Bengali,Hindi,Kannada,Marathi,Tamil,Telugu | AY1: English,Hindi,Malayalam | AZ1: Bengali,Bhojpuri,English,Haryanvi,Hindi,Kannada,Malayalam,Marathi,Tamil,Telugu | BA1: Odia | BB1: English,Hindi,Punjabi | BC1: Bengali,Hindi,Kannada,Punjabi,Tamil,Telugu | BD1: Bengali,Hindi,Kannada,Malayalam,Tamil,Telugu | BE1: Bengali,Bhojpuri,Gujarati,Haryanvi,Hindi,Kannada,Malayalam,Marathi,Odia,Rajasthani,Tamil,Telugu | BF1: Kannada,Tamil,Telugu | BG1: Bengali,Bhojpuri,English,Haryanvi,Hindi,Kannada,Tamil,Telugu | BH1: Bengali,English,Hindi,Malayalam | BI1: Hindi,Kannada,Malayalam,Tamil | BJ1: Hindi,Punjabi,Tamil,Telugu | BK1: Bengali,Bhojpuri,Haryanvi,Hindi,Kannada,Marathi,Tamil,Telugu | BL1: Bengali,Bhojpuri,Hindi,Kannada,Malayalam,Marathi,Tamil,Telugu
A2: Metro | B2: AHMADABAD | C2: 0.07 | D2: 0.06 | E2: =AVERAGE(C2,D2) -> 0.065 | F2: =AVERAGE(C2,D2,H2) -> 0.045 | G2: 0.01 | H2: 0.005 | I2: =AVERAGE(G2,H2) -> 0.0075 | J2: 0.01 | K2: 0.01 | L2: =AVERAGE(G2,H2,J2,K2) -> 0.00875 | M2: =AVERAGE(C2,G2,H2,D2) -> 0.03625 | N2: =AVERAGE(C2,D2,G2,H2) -> 0.03625 | O2: 0.01 | P2: 0.4 | Q2: =AVERAGE(C2,K2,G2,H2,J2) -> 0.021 | R2: =AVERAGE(C2,D2,H2,G2) -> 0.03625 | S2: 0.01 | T2: 0.01 | U2: =AVERAGE(C2,G2,H2,J2,O2,T2) -> 0.019166667 | V2: =AVERAGE(C2,K2,G2,H2,J2,T2,O2) -> 0.017857143 | W2: =AVERAGE(C2,K2,G2,H2,J2,T2,O2) -> 0.017857143 | X2: =AVERAGE(C2,G2,H2,O2,T2) -> 0.021 | Y2: =AVERAGE(K2,H2,J2) -> 0.0083333333 | Z2: 0.02 | AA2: 0.01 | AB2: =AVERAGE(C2,D2,Z2,AA2,H2,G2,T2,J2) -> 0.024375 | AC2: =AVERAGE(C2,H2,G2,T2,J2,O2,K2) -> 0.017857143 | AD2: =AVERAGE(C2,D2,G2,H2,J2,T2,O2) -> 0.025 | AE2: =AVERAGE(C2,D2,H2,T2,K2,J2,G2) -> 0.025 | AF2: =AVERAGE(C2,G2,H2) -> 0.028333333 | AG2: =AVERAGE(C2,G2,H2,K2) -> 0.02375 | AH2: =AVERAGE(C2,O2,G2,T2,H2) -> 0.021 | AI2: =AVERAGE(K2,G2,H2,J2) -> 0.00875 | AJ2: =AVERAGE(C2,G2,H2,K2,J2) -> 0.021 | AK2: =AVERAGE(C2,D2,O2,G2,H2) -> 0.031 | AL2: =AVERAGE(C2,D2,G2,H2,J2,K2) -> 0.0275 | AM2: =AVERAGE(D2,G2,H2) -> 0.025 | AN2: =AVERAGE(C2,O2) -> 0.04 | AO2: =AVERAGE(C2,G2) -> 0.04 | AP2: =AVERAGE(I2,J2,K2) -> 0.0091666667 | AQ2: =AVERAGE(N2,J2) -> 0.023125 | AR2: =AVERAGE(AL2,O2,P2) -> 0.14583333 | AS2: 0.01 | AT2: =AVERAGE(D2,H2) -> 0.0325 | AU2: =AVERAGE(C2,G2,H2) -> 0.028333333 | AV2: =AVERAGE(C2,D2,G2,H2,J2,O2,T2,Z2,S2) -> 0.022777778 | AW2: 0.021 | AX2: 0.013666667 | AY2: 0.046666667
A3: Metro | B3: BANGALORE | C3: 0.02 | D3: 0.12 | E3: =AVERAGE(C3,D3) -> 0.07 | F3: =AVERAGE(C3,D3,H3) -> 0.05 | G3: 0.3 | H3: 0.01 | I3: =AVERAGE(G3,H3) -> 0.155 | J3: 0.5 | K3: 0.03 | L3: =AVERAGE(G3,H3,J3,K3) -> 0.21 | M3: =AVERAGE(C3,G3,H3,D3) -> 0.1125 | N3: =AVERAGE(C3,D3,G3,H3) -> 0.1125 | O3: 0.01 | P3: 0.01 | Q3: =AVERAGE(C3,K3,G3,H3,J3) -> 0.172 | R3: =AVERAGE(C3,D3,H3,G3) -> 0.1125 | S3: 0.01 | T3: 0.01 | U3: =AVERAGE(C3,G3,H3,J3,O3,T3) -> 0.14166667 | V3: =AVERAGE(C3,K3,G3,H3,J3,T3,O3) -> 0.12571429 | W3: =AVERAGE(C3,K3,G3,H3,J3,T3,O3) -> 0.12571429 | X3: =AVERAGE(C3,G3,H3,O3,T3) -> 0.07 | Y3: =AVERAGE(K3,H3,J3) -> 0.18 | Z3: 0.01 | AA3: 0.005 | AB3: =AVERAGE(C3,D3,Z3,AA3,H3,G3,T3,J3) -> 0.121875 | AC3: =AVERAGE(C3,H3,G3,T3,J3,O3,K3) -> 0.12571429 | AD3: =AVERAGE(C3,D3,G3,H3,J3,T3,O3) -> 0.13857143 | AE3: =AVERAGE(C3,D3,H3,T3,K3,J3,G3) -> 0.14142857 | AF3: =AVERAGE(C3,G3,H3) -> 0.11 | AG3: =AVERAGE(C3,G3,H3,K3) -> 0.09 | AH3: =AVERAGE(C3,O3,G3,T3,H3) -> 0.07 | AI3: =AVERAGE(K3,G3,H3,J3) -> 0.21 | AJ3: =AVERAGE(C3,G3,H3,K3,J3) -> 0.172 | AK3: =AVERAGE(C3,D3,O3,G3,H3) -> 0.092 | AL3: =AVERAGE(C3,D3,G3,H3,J3,K3) -> 0.16333333 | AM3: =AVERAGE(D3,G3,H3) -> 0.14333333 | AN3: =AVERAGE(C3,O3) -> 0.015 | AO3: =AVERAGE(C3,G3) -> 0.16 | AP3: =AVERAGE(I3,J3,K3) -> 0.22833333 | AQ3: =AVERAGE(N3,J3) -> 0.30625 | AR3: =AVERAGE(AL3,O3,P3) -> 0.061111111 | AS3: 0.005 | AT3: =AVERAGE(D3,H3) -> 0.065 | AU3: =AVERAGE(C3,G3,H3) -> 0.11 | AV3: =AVERAGE(C3,D3,G3,H3,J3,O3,T3,Z3,S3) -> 0.11 | AW3: 0.172 | AX3: 0.064 | AY3: 0.056666667
A4: Metro | B4: CHENNAI | C4: 0.02 | D4: 0.12 | E4: =AVERAGE(C4,D4) -> 0.07 | F4: =AVERAGE(C4,D4,H4) -> 0.05 | G4: 0.3 | H4: 0.01 | I4: =AVERAGE(G4,H4) -> 0.155 | J4: 0.02 | K4: 0.14 | L4: =AVERAGE(G4,H4,J4,K4) -> 0.1175 | M4: =AVERAGE(C4,G4,H4,D4) -> 0.1125 | N4: =AVERAGE(C4,D4,G4,H4) -> 0.1125 | O4: 0.01 | P4: 0.01 | Q4: =AVERAGE(C4,K4,G4,H4,J4) -> 0.098 | R4: =AVERAGE(C4,D4,H4,G4) -> 0.1125 | S4: 0.01 | T4: 0.01 | U4: =AVERAGE(C4,G4,H4,J4,O4,T4) -> 0.061666667 | V4: =AVERAGE(C4,K4,G4,H4,J4,T4,O4) -> 0.072857143 | W4: =AVERAGE(C4,K4,G4,H4,J4,T4,O4) -> 0.072857143 | X4: =AVERAGE(C4,G4,H4,O4,T4) -> 0.07 | Y4: =AVERAGE(K4,H4,J4) -> 0.056666667 | Z4: 0.01 | AA4: 0.005 | AB4: =AVERAGE(C4,D4,Z4,AA4,H4,G4,T4,J4) -> 0.061875 | AC4: =AVERAGE(C4,H4,G4,T4,J4,O4,K4) -> 0.072857143 | AD4: =AVERAGE(C4,D4,G4,H4,J4,T4,O4) -> 0.07 | AE4: =AVERAGE(C4,D4,H4,T4,K4,J4,G4) -> 0.088571429 | AF4: =AVERAGE(C4,G4,H4) -> 0.11 | AG4: =AVERAGE(C4,G4,H4,K4) -> 0.1175 | AH4: =AVERAGE(C4,O4,G4,T4,H4) -> 0.07 | AI4: =AVERAGE(K4,G4,H4,J4) -> 0.1175 | AJ4: =AVERAGE(C4,G4,H4,K4,J4) -> 0.098 | AK4: =AVERAGE(C4,D4,O4,G4,H4) -> 0.092 | AL4: =AVERAGE(C4,D4,G4,H4,J4,K4) -> 0.10166667 | AM4: =AVERAGE(D4,G4,H4) -> 0.14333333 | AN4: =AVERAGE(C4,O4) -> 0.015 | AO4: =AVERAGE(C4,G4) -> 0.16 | AP4: =AVERAGE(I4,J4,K4) -> 0.105 | AQ4: =AVERAGE(N4,J4) -> 0.06625 | AR4: =AVERAGE(AL4,O4,P4) -> 0.040555556 | AS4: 0.005 | AT4: =AVERAGE(D4,H4) -> 0.065 | AU4: =AVERAGE(C4,G4,H4) -> 0.11 | AV4: =AVERAGE(C4,D4,G4,H4,J4,O4,T4,Z4,S4) -> 0.056666667 | AW4: 0.098 | AX4: 0.039333333 | AY4: 0.093333333
A5: Metro | B5: DELHI | C5: 0.13 | D5: 0.15 | E5: =AVERAGE(C5,D5) -> 0.14 | F5: =AVERAGE(C5,D5,H5) -> 0.096666667 | G5: 0.01 | H5: 0.01 | I5: =AVERAGE(G5,H5) -> 0.01 | J5: 0.02 | K5: 0.02 | L5: =AVERAGE(G5,H5,J5,K5) -> 0.015 | M5: =AVERAGE(C5,G5,H5,D5) -> 0.075 | N5: =AVERAGE(C5,D5,G5,H5) -> 0.075 | O5: 0.03 | P5: 0.05 | Q5: =AVERAGE(C5,K5,G5,H5,J5) -> 0.038 | R5: =AVERAGE(C5,D5,H5,G5) -> 0.075 | S5: 0.07 | T5: 0.06 | U5: =AVERAGE(C5,G5,H5,J5,O5,T5) -> 0.043333333 | V5: =AVERAGE(C5,K5,G5,H5,J5,T5,O5) -> 0.04 | W5: =AVERAGE(C5,K5,G5,H5,J5,T5,O5) -> 0.04 | X5: =AVERAGE(C5,G5,H5,O5,T5) -> 0.048 | Y5: =AVERAGE(K5,H5,J5) -> 0.016666667 | Z5: 0.04 | AA5: 0.04 | AB5: =AVERAGE(C5,D5,Z5,AA5,H5,G5,T5,J5) -> 0.0575 | AC5: =AVERAGE(C5,H5,G5,T5,J5,O5,K5) -> 0.04 | AD5: =AVERAGE(C5,D5,G5,H5,J5,T5,O5) -> 0.058571429 | AE5: =AVERAGE(C5,D5,H5,T5,K5,J5,G5) -> 0.057142857 | AF5: =AVERAGE(C5,G5,H5) -> 0.05 | AG5: =AVERAGE(C5,G5,H5,K5) -> 0.0425 | AH5: =AVERAGE(C5,O5,G5,T5,H5) -> 0.048 | AI5: =AVERAGE(K5,G5,H5,J5) -> 0.015 | AJ5: =AVERAGE(C5,G5,H5,K5,J5) -> 0.038 | AK5: =AVERAGE(C5,D5,O5,G5,H5) -> 0.066 | AL5: =AVERAGE(C5,D5,G5,H5,J5,K5) -> 0.056666667 | AM5: =AVERAGE(D5,G5,H5) -> 0.056666667 | AN5: =AVERAGE(C5,O5) -> 0.08 | AO5: =AVERAGE(C5,G5) -> 0.07 | AP5: =AVERAGE(I5,J5,K5) -> 0.016666667 | AQ5: =AVERAGE(N5,J5) -> 0.0475 | AR5: =AVERAGE(AL5,O5,P5) -> 0.045555556 | AS5: 0.04 | AT5: =AVERAGE(D5,H5) -> 0.08 | AU5: =AVERAGE(C5,G5,H5) -> 0.05 | AV5: =AVERAGE(C5,D5,G5,H5,J5,O5,T5,Z5,S5) -> 0.057777778 | AW5: 0.038 | AX5: 0.042666667 | AY5: 0.1
A6: Metro | B6: HYDERABAD | C6: 0.02 | D6: 0.11 | E6: =AVERAGE(C6,D6) -> 0.065 | F6: =AVERAGE(C6,D6,H6) -> 0.19333333 | G6: 0.03 | H6: 0.45 | I6: =AVERAGE(G6,H6) -> 0.24 | J6: 0.03 | K6: 0.04 | L6: =AVERAGE(G6,H6,J6,K6) -> 0.1375 | M6: =AVERAGE(C6,G6,H6,D6) -> 0.1525 | N6: =AVERAGE(C6,D6,G6,H6) -> 0.1525 | O6: 0.01 | P6: 0.01 | Q6: =AVERAGE(C6,K6,G6,H6,J6) -> 0.114 | R6: =AVERAGE(C6,D6,H6,G6) -> 0.1525 | S6: 0.01 | T6: 0.01 | U6: =AVERAGE(C6,G6,H6,J6,O6,T6) -> 0.091666667 | V6: =AVERAGE(C6,K6,G6,H6,J6,T6,O6) -> 0.084285714 | W6: =AVERAGE(C6,K6,G6,H6,J6,T6,O6) -> 0.084285714 | X6: =AVERAGE(C6,G6,H6,O6,T6) -> 0.104 | Y6: =AVERAGE(K6,H6,J6) -> 0.17333333 | Z6: 0.01 | AA6: 0.005 | AB6: =AVERAGE(C6,D6,Z6,AA6,H6,G6,T6,J6) -> 0.083125 | AC6: =AVERAGE(C6,H6,G6,T6,J6,O6,K6) -> 0.084285714 | AD6: =AVERAGE(C6,D6,G6,H6,J6,T6,O6) -> 0.094285714 | AE6: =AVERAGE(C6,D6,H6,T6,K6,J6,G6) -> 0.098571429 | AF6: =AVERAGE(C6,G6,H6) -> 0.16666667 | AG6: =AVERAGE(C6,G6,H6,K6) -> 0.135 | AH6: =AVERAGE(C6,O6,G6,T6,H6) -> 0.104 | AI6: =AVERAGE(K6,G6,H6,J6) -> 0.1375 | AJ6: =AVERAGE(C6,G6,H6,K6,J6) -> 0.114 | AK6: =AVERAGE(C6,D6,O6,G6,H6) -> 0.124 | AL6: =AVERAGE(C6,D6,G6,H6,J6,K6) -> 0.11333333 | AM6: =AVERAGE(D6,G6,H6) -> 0.19666667 | AN6: =AVERAGE(C6,O6) -> 0.015 | AO6: =AVERAGE(C6,G6) -> 0.025 | AP6: =AVERAGE(I6,J6,K6) -> 0.10333333 | AQ6: =AVERAGE(N6,J6) -> 0.09125 | AR6: =AVERAGE(AL6,O6,P6) -> 0.044444444 | AS6: 0.005 | AT6: =AVERAGE(D6,H6) -> 0.28 | AU6: =AVERAGE(C6,G6,H6) -> 0.16666667 | AV6: =AVERAGE(C6,D6,G6,H6,J6,O6,T6,Z6,S6) -> 0.075555556 | AW6: 0.114 | AX6: 0.044666667 | AY6: 0.056666667
A7: Metro | B7: KOLKATA | C7: 0.05 | D7: 0.1 | E7: =AVERAGE(C7,D7) -> 0.075 | F7: =AVERAGE(C7,D7,H7) -> 0.053333333 | G7: 0.01 | H7: 0.01 | I7: =AVERAGE(G7,H7) -> 0.01 | J7: 0.01 | K7: 0.02 | L7: =AVERAGE(G7,H7,J7,K7) -> 0.0125 | M7: =AVERAGE(C7,G7,H7,D7) -> 0.0425 | N7: =AVERAGE(C7,D7,G7,H7) -> 0.0425 | O7: 0.01 | P7: 0.01 | Q7: =AVERAGE(C7,K7,G7,H7,J7) -> 0.02 | R7: =AVERAGE(C7,D7,H7,G7) -> 0.0425 | S7: 0.01 | T7: 0.58 | U7: =AVERAGE(C7,G7,H7,J7,O7,T7) -> 0.11166667 | V7: =AVERAGE(C7,K7,G7,H7,J7,T7,O7) -> 0.098571429 | W7: =AVERAGE(C7,K7,G7,H7,J7,T7,O7) -> 0.098571429 | X7: =AVERAGE(C7,G7,H7,O7,T7) -> 0.132 | Y7: =AVERAGE(K7,H7,J7) -> 0.013333333 | Z7: 0.01 | AA7: 0.005 | AB7: =AVERAGE(C7,D7,Z7,AA7,H7,G7,T7,J7) -> 0.096875 | AC7: =AVERAGE(C7,H7,G7,T7,J7,O7,K7) -> 0.098571429 | AD7: =AVERAGE(C7,D7,G7,H7,J7,T7,O7) -> 0.11 | AE7: =AVERAGE(C7,D7,H7,T7,K7,J7,G7) -> 0.11142857 | AF7: =AVERAGE(C7,G7,H7) -> 0.023333333 | AG7: =AVERAGE(C7,G7,H7,K7) -> 0.0225 | AH7: =AVERAGE(C7,O7,G7,T7,H7) -> 0.132 | AI7: =AVERAGE(K7,G7,H7,J7) -> 0.0125 | AJ7: =AVERAGE(C7,G7,H7,K7,J7) -> 0.02 | AK7: =AVERAGE(C7,D7,O7,G7,H7) -> 0.036 | AL7: =AVERAGE(C7,D7,G7,H7,J7,K7) -> 0.033333333 | AM7: =AVERAGE(D7,G7,H7) -> 0.04 | AN7: =AVERAGE(C7,O7) -> 0.03 | AO7: =AVERAGE(C7,G7) -> 0.03 | AP7: =AVERAGE(I7,J7,K7) -> 0.013333333 | AQ7: =AVERAGE(N7,J7) -> 0.02625 | AR7: =AVERAGE(AL7,O7,P7) -> 0.017777778 | AS7: 0.005 | AT7: =AVERAGE(D7,H7) -> 0.055 | AU7: =AVERAGE(C7,G7,H7) -> 0.023333333 | AV7: =AVERAGE(C7,D7,G7,H7,J7,O7,T7,Z7,S7) -> 0.087777778 | AW7: 0.02 | AX7: 0.20333333 | AY7: 0.056666667
A8: Metro | B8: MUMBAI | C8: 0.11 | D8: 0.12 | E8: =AVERAGE(C8,D8) -> 0.115 | F8: =AVERAGE(C8,D8,H8) -> 0.08 | G8: 0.01 | H8: 0.01 | I8: =AVERAGE(G8,H8) -> 0.01 | J8: 0.01 | K8: 0.03 | L8: =AVERAGE(G8,H8,J8,K8) -> 0.015 | M8: =AVERAGE(C8,G8,H8,D8) -> 0.0625 | N8: =AVERAGE(C8,D8,G8,H8) -> 0.0625 | O8: 0.45 | P8: 0.03 | Q8: =AVERAGE(C8,K8,G8,H8,J8) -> 0.034 | R8: =AVERAGE(C8,D8,H8,G8) -> 0.0625 | S8: 0.05 | T8: 0.01 | U8: =AVERAGE(C8,G8,H8,J8,O8,T8) -> 0.1 | V8: =AVERAGE(C8,K8,G8,H8,J8,T8,O8) -> 0.09 | W8: =AVERAGE(C8,K8,G8,H8,J8,T8,O8) -> 0.09 | X8: =AVERAGE(C8,G8,H8,O8,T8) -> 0.118 | Y8: =AVERAGE(K8,H8,J8) -> 0.016666667 | Z8: 0.02 | AA8: 0.01 | AB8: =AVERAGE(C8,D8,Z8,AA8,H8,G8,T8,J8) -> 0.0375 | AC8: =AVERAGE(C8,H8,G8,T8,J8,O8,K8) -> 0.09 | AD8: =AVERAGE(C8,D8,G8,H8,J8,T8,O8) -> 0.10285714 | AE8: =AVERAGE(C8,D8,H8,T8,K8,J8,G8) -> 0.042857143 | AF8: =AVERAGE(C8,G8,H8) -> 0.043333333 | AG8: =AVERAGE(C8,G8,H8,K8) -> 0.04 | AH8: =AVERAGE(C8,O8,G8,T8,H8) -> 0.118 | AI8: =AVERAGE(K8,G8,H8,J8) -> 0.015 | AJ8: =AVERAGE(C8,G8,H8,K8,J8) -> 0.034 | AK8: =AVERAGE(C8,D8,O8,G8,H8) -> 0.14 | AL8: =AVERAGE(C8,D8,G8,H8,J8,K8) -> 0.048333333 | AM8: =AVERAGE(D8,G8,H8) -> 0.046666667 | AN8: =AVERAGE(C8,O8) -> 0.28 | AO8: =AVERAGE(C8,G8) -> 0.06 | AP8: =AVERAGE(I8,J8,K8) -> 0.016666667 | AQ8: =AVERAGE(N8,J8) -> 0.03625 | AR8: =AVERAGE(AL8,O8,P8) -> 0.17611111 | AS8: 0.01 | AT8: =AVERAGE(D8,H8) -> 0.065 | AU8: =AVERAGE(C8,G8,H8) -> 0.043333333 | AV8: =AVERAGE(C8,D8,G8,H8,J8,O8,T8,Z8,S8) -> 0.087777778 | AW8: 0.034 | AX8: 0.16466667 | AY8: 0.086666667
A9: Metro | B9: PUNE | C9: 0.07 | D9: 0.07 | E9: =AVERAGE(C9,D9) -> 0.07 | F9: =AVERAGE(C9,D9,H9) -> 0.05 | G9: 0.01 | H9: 0.01 | I9: =AVERAGE(G9,H9) -> 0.01 | J9: 0.01 | K9: 0.01 | L9: =AVERAGE(G9,H9,J9,K9) -> 0.01 | M9: =AVERAGE(C9,G9,H9,D9) -> 0.04 | N9: =AVERAGE(C9,D9,G9,H9) -> 0.04 | O9: 0.2 | P9: 0.02 | Q9: =AVERAGE(C9,K9,G9,H9,J9) -> 0.022 | R9: =AVERAGE(C9,D9,H9,G9) -> 0.04 | S9: 0.02 | T9: 0.01 | U9: =AVERAGE(C9,G9,H9,J9,O9,T9) -> 0.051666667 | V9: =AVERAGE(C9,K9,G9,H9,J9,T9,O9) -> 0.045714286 | W9: =AVERAGE(C9,K9,G9,H9,J9,T9,O9) -> 0.045714286 | X9: =AVERAGE(C9,G9,H9,O9,T9) -> 0.06 | Y9: =AVERAGE(K9,H9,J9) -> 0.01 | Z9: 0.01 | AA9: 0.01 | AB9: =AVERAGE(C9,D9,Z9,AA9,H9,G9,T9,J9) -> 0.025 | AC9: =AVERAGE(C9,H9,G9,T9,J9,O9,K9) -> 0.045714286 | AD9: =AVERAGE(C9,D9,G9,H9,J9,T9,O9) -> 0.054285714 | AE9: =AVERAGE(C9,D9,H9,T9,K9,J9,G9) -> 0.027142857 | AF9: =AVERAGE(C9,G9,H9) -> 0.03 | AG9: =AVERAGE(C9,G9,H9,K9) -> 0.025 | AH9: =AVERAGE(C9,O9,G9,T9,H9) -> 0.06 | AI9: =AVERAGE(K9,G9,H9,J9) -> 0.01 | AJ9: =AVERAGE(C9,G9,H9,K9,J9) -> 0.022 | AK9: =AVERAGE(C9,D9,O9,G9,H9) -> 0.072 | AL9: =AVERAGE(C9,D9,G9,H9,J9,K9) -> 0.03 | AM9: =AVERAGE(D9,G9,H9) -> 0.03 | AN9: =AVERAGE(C9,O9) -> 0.135 | AO9: =AVERAGE(C9,G9) -> 0.04 | AP9: =AVERAGE(I9,J9,K9) -> 0.01 | AQ9: =AVERAGE(N9,J9) -> 0.025 | AR9: =AVERAGE(AL9,O9,P9) -> 0.083333333 | AS9: 0.01 | AT9: =AVERAGE(D9,H9) -> 0.04 | AU9: =AVERAGE(C9,G9,H9) -> 0.03 | AV9: =AVERAGE(C9,D9,G9,H9,J9,O9,T9,Z9,S9) -> 0.045555556 | AW9: 0.022 | AX9: 0.077333333 | AY9: 0.05
A10: ALL INDIA | B10: ALL INDIA 10-75L | C10: 0.22 | D10: 0.05 | E10: =AVERAGE(C10,D10) -> 0.135 | F10: =AVERAGE(C10,D10,H10) -> 0.17333333 | G10: 0.1 | H10: 0.25 | I10: =AVERAGE(G10,H10) -> 0.175 | J10: 0.16 | K10: 0.3 | L10: =AVERAGE(G10,H10,J10,K10) -> 0.2025 | M10: =AVERAGE(C10,G10,H10,D10) -> 0.155 | N10: =AVERAGE(C10,D10,G10,H10) -> 0.155 | O10: 0.15 | P10: 0.18 | Q10: =AVERAGE(C10,K10,G10,H10,J10) -> 0.206 | R10: =AVERAGE(C10,D10,H10,G10) -> 0.155 | S10: 0.3 | T10: 0.14 | U10: =AVERAGE(C10,G10,H10,J10,O10,T10) -> 0.17 | V10: =AVERAGE(C10,K10,G10,H10,J10,T10,O10) -> 0.18857143 | W10: =AVERAGE(C10,K10,G10,H10,J10,T10,O10) -> 0.18857143 | X10: =AVERAGE(C10,G10,H10,O10,T10) -> 0.172 | Y10: =AVERAGE(K10,H10,J10) -> 0.23666667 | Z10: 0.35 | AA10: 0.36 | AB10: =AVERAGE(C10,D10,Z10,AA10,H10,G10,T10,J10) -> 0.20375 | AC10: =AVERAGE(C10,H10,G10,T10,J10,O10,K10) -> 0.18857143 | AD10: =AVERAGE(C10,D10,G10,H10,J10,T10,O10) -> 0.15285714 | AE10: =AVERAGE(C10,D10,H10,T10,K10,J10,G10) -> 0.17428571 | AF10: =AVERAGE(C10,G10,H10) -> 0.19 | AG10: =AVERAGE(C10,G10,H10,K10) -> 0.2175 | AH10: =AVERAGE(C10,O10,G10,T10,H10) -> 0.172 | AI10: =AVERAGE(K10,G10,H10,J10) -> 0.2025 | AJ10: =AVERAGE(C10,G10,H10,K10,J10) -> 0.206 | AK10: =AVERAGE(C10,D10,O10,G10,H10) -> 0.154 | AL10: =AVERAGE(C10,D10,G10,H10,J10,K10) -> 0.18 | AM10: =AVERAGE(D10,G10,H10) -> 0.13333333 | AN10: =AVERAGE(C10,O10) -> 0.185 | AO10: =AVERAGE(C10,G10) -> 0.16 | AP10: =AVERAGE(I10,J10,K10) -> 0.21166667 | AQ10: =AVERAGE(N10,J10) -> 0.1575 | AR10: =AVERAGE(AL10,O10,P10) -> 0.17 | AS10: 0.36 | AT10: =AVERAGE(D10,H10) -> 0.15 | AU10: =AVERAGE(C10,G10,H10) -> 0.19 | AV10: =AVERAGE(C10,D10,G10,H10,J10,O10,T10,Z10,S10) -> 0.19111111 | AW10: 0.206 | AX10: 0.16533333 | AY10: 0.19
A11: ALL INDIA | B11: ALL INDIA 1-10L | C11: 0.14 | D11: 0.05 | E11: =AVERAGE(C11,D11) -> 0.095 | F11: =AVERAGE(C11,D11,H11) -> 0.11333333 | G11: 0.12 | H11: 0.15 | I11: =AVERAGE(G11,H11) -> 0.135 | J11: 0.13 | K11: 0.25 | L11: =AVERAGE(G11,H11,J11,K11) -> 0.1625 | M11: =AVERAGE(C11,G11,H11,D11) -> 0.115 | N11: =AVERAGE(C11,D11,G11,H11) -> 0.115 | O11: 0.07 | P11: 0.16 | Q11: =AVERAGE(C11,K11,G11,H11,J11) -> 0.158 | R11: =AVERAGE(C11,D11,H11,G11) -> 0.115 | S11: 0.31 | T11: 0.1 | U11: =AVERAGE(C11,G11,H11,J11,O11,T11) -> 0.11833333 | V11: =AVERAGE(C11,K11,G11,H11,J11,T11,O11) -> 0.13714286 | W11: =AVERAGE(C11,K11,G11,H11,J11,T11,O11) -> 0.13714286 | X11: =AVERAGE(C11,G11,H11,O11,T11) -> 0.116 | Y11: =AVERAGE(K11,H11,J11) -> 0.17666667 | Z11: 0.25 | AA11: 0.3 | AB11: =AVERAGE(C11,D11,Z11,AA11,H11,G11,T11,J11) -> 0.155 | AC11: =AVERAGE(C11,H11,G11,T11,J11,O11,K11) -> 0.13714286 | AD11: =AVERAGE(C11,D11,G11,H11,J11,T11,O11) -> 0.10857143 | AE11: =AVERAGE(C11,D11,H11,T11,K11,J11,G11) -> 0.13428571 | AF11: =AVERAGE(C11,G11,H11) -> 0.13666667 | AG11: =AVERAGE(C11,G11,H11,K11) -> 0.165 | AH11: =AVERAGE(C11,O11,G11,T11,H11) -> 0.116 | AI11: =AVERAGE(K11,G11,H11,J11) -> 0.1625 | AJ11: =AVERAGE(C11,G11,H11,K11,J11) -> 0.158 | AK11: =AVERAGE(C11,D11,O11,G11,H11) -> 0.106 | AL11: =AVERAGE(C11,D11,G11,H11,J11,K11) -> 0.14 | AM11: =AVERAGE(D11,G11,H11) -> 0.10666667 | AN11: =AVERAGE(C11,O11) -> 0.105 | AO11: =AVERAGE(C11,G11) -> 0.13 | AP11: =AVERAGE(I11,J11,K11) -> 0.17166667 | AQ11: =AVERAGE(N11,J11) -> 0.1225 | AR11: =AVERAGE(AL11,O11,P11) -> 0.12333333 | AS11: 0.3 | AT11: =AVERAGE(D11,H11) -> 0.1 | AU11: =AVERAGE(C11,G11,H11) -> 0.13666667 | AV11: =AVERAGE(C11,D11,G11,H11,J11,O11,T11,Z11,S11) -> 0.14666667 | AW11: 0.158 | AX11: 0.10933333 | AY11: 0.14666667
A12: ALL INDIA | B12: RURAL | C12: 0.15 | D12: 0.05 | E12: =AVERAGE(C12,D12) -> 0.1 | F12: =AVERAGE(C12,D12,H12) -> 0.095 | G12: 0.1 | H12: 0.085 | I12: =AVERAGE(G12,H12) -> 0.0925 | J12: 0.1 | K12: 0.15 | L12: =AVERAGE(G12,H12,J12,K12) -> 0.10875 | M12: =AVERAGE(C12,G12,H12,D12) -> 0.09625 | N12: =AVERAGE(C12,D12,G12,H12) -> 0.09625 | O12: 0.05 | P12: 0.12 | Q12: =AVERAGE(C12,K12,G12,H12,J12) -> 0.117 | R12: =AVERAGE(C12,D12,H12,G12) -> 0.09625 | S12: 0.2 | T12: 0.06 | U12: =AVERAGE(C12,G12,H12,J12,O12,T12) -> 0.090833333 | V12: =AVERAGE(C12,K12,G12,H12,J12,T12,O12) -> 0.099285714 | W12: =AVERAGE(C12,K12,G12,H12,J12,T12,O12) -> 0.099285714 | X12: =AVERAGE(C12,G12,H12,O12,T12) -> 0.089 | Y12: =AVERAGE(K12,H12,J12) -> 0.11166667 | Z12: 0.27 | AA12: 0.25 | AB12: =AVERAGE(C12,D12,Z12,AA12,H12,G12,T12,J12) -> 0.133125 | AC12: =AVERAGE(C12,H12,G12,T12,J12,O12,K12) -> 0.099285714 | AD12: =AVERAGE(C12,D12,G12,H12,J12,T12,O12) -> 0.085 | AE12: =AVERAGE(C12,D12,H12,T12,K12,J12,G12) -> 0.099285714 | AF12: =AVERAGE(C12,G12,H12) -> 0.11166667 | AG12: =AVERAGE(C12,G12,H12,K12) -> 0.12125 | AH12: =AVERAGE(C12,O12,G12,T12,H12) -> 0.089 | AI12: =AVERAGE(K12,G12,H12,J12) -> 0.10875 | AJ12: =AVERAGE(C12,G12,H12,K12,J12) -> 0.117 | AK12: =AVERAGE(C12,D12,O12,G12,H12) -> 0.087 | AL12: =AVERAGE(C12,D12,G12,H12,J12,K12) -> 0.10583333 | AM12: =AVERAGE(D12,G12,H12) -> 0.078333333 | AN12: =AVERAGE(C12,O12) -> 0.1 | AO12: =AVERAGE(C12,G12) -> 0.125 | AP12: =AVERAGE(I12,J12,K12) -> 0.11416667 | AQ12: =AVERAGE(N12,J12) -> 0.098125 | AR12: =AVERAGE(AL12,O12,P12) -> 0.091944444 | AS12: 0.25 | AT12: =AVERAGE(D12,H12) -> 0.0675 | AU12: =AVERAGE(C12,G12,H12) -> 0.11166667 | AV12: =AVERAGE(C12,D12,G12,H12,J12,O12,T12,Z12,S12) -> 0.11833333 | AW12: 0.117 | AX12: 0.075666667 | AY12: 0.11666667
B13: - | C13: =SUM(C2:C12) -> 1 | D13: =SUM(D2:D12) -> 1 | E13: =SUM(E2:E12) -> 1 | F13: =AVERAGE(C13,D13,H13) -> 1 | G13: =SUM(G2:G12) -> 1 | H13: =SUM(H2:H12) -> 1 | I13: =AVERAGE(G13,H13) -> 1 | J13: =SUM(J2:J12) -> 1 | K13: =SUM(K2:K12) -> 1 | L13: =AVERAGE(G13,H13,J13,K13) -> 1 | M13: =AVERAGE(C13,G13,H13,D13) -> 1 | N13: =AVERAGE(C13,D13,G13,H13) -> 1 | O13: =SUM(O2:O12) -> 1 | P13: =SUM(P2:P12) -> 1 | Q13: =AVERAGE(C13,K13,G13,H13,J13) -> 1 | R13: =AVERAGE(C13,D13,H13,G13) -> 1 | S13: =SUM(S2:S12) -> 1 | T13: =SUM(T2:T12) -> 1 | U13: =AVERAGE(C13,G13,H13,J13,O13,T13) -> 1 | V13: =AVERAGE(C13,K13,G13,H13,J13,T13,O13) -> 1 | W13: =AVERAGE(C13,K13,G13,H13,J13,T13,O13) -> 1 | X13: =AVERAGE(C13,G13,H13,O13,T13) -> 1 | Y13: =AVERAGE(K13,H13,J13) -> 1 | Z13: =SUM(Z2:Z12) -> 1 | AA13: =SUM(AA2:AA12) -> 1 | AB13: =AVERAGE(C13,D13,Z13,AA13,H13,G13,T13,J13) -> 1 | AC13: =AVERAGE(C13,H13,G13,T13,J13,O13,K13) -> 1 | AD13: =AVERAGE(C13,D13,G13,H13,J13,T13,O13) -> 1 | AE13: =AVERAGE(C13,D13,H13,T13,K13,J13,G13) -> 1 | AF13: =AVERAGE(C13,G13,H13) -> 1 | AG13: =AVERAGE(C13,G13,H13,K13) -> 1 | AH13: =AVERAGE(C13,O13,G13,T13,H13) -> 1 | AI13: =AVERAGE(K13,G13,H13,J13) -> 1 | AJ13: =AVERAGE(C13,G13,H13,K13,J13) -> 1 | AK13: =AVERAGE(C13,D13,O13,G13,H13) -> 1 | AL13: =AVERAGE(C13,D13,G13,H13,J13,K13) -> 1 | AM13: =AVERAGE(D13,G13,H13) -> 1 | AN13: =AVERAGE(C13,O13) -> 1 | AO13: =AVERAGE(C13,G13) -> 1 | AP13: =AVERAGE(I13,J13,K13) -> 1 | AQ13: =AVERAGE(N13,J13) -> 1 | AR13: =AVERAGE(AL13,O13,P13) -> 1 | AS13: =SUM(AS2:AS12) -> 1 | AT13: =AVERAGE(D13,H13) -> 1 | AU13: =AVERAGE(C13,G13,H13) -> 1 | AV13: =AVERAGE(C13,D13,G13,H13,J13,O13,T13,Z13,S13) -> 1 | AW13: 1 | AX13: 1 | AY13: 1
A14: ALL India | B14: ALL India | C14: 0.6 | D14: 0.2 | E14: 0.4 | F14: 0.3 | G14: 0.1 | H14: 0.15 | I14: =AVERAGE(G14:H14) -> 0.125 | J14: 0.1 | K14: 0.07 | L14: =AVERAGE(K14,G14,H14,J14) -> 0.105 | M14: =AVERAGE(C14,D14,G14,H14) -> 0.2625 | N14: 0.26 | O14: 0.12 | P14: 0.15 | Q14: =AVERAGE(C14,K14,G14,H14,J14) -> 0.204 | R14: =AVERAGE(C14,D14,G14,H14) -> 0.2625 | S14: 0.09 | T14: 0.1 | U14: =AVERAGE(C14,G14,H14,J14,O14,T14) -> 0.195 | V14: =AVERAGE(C14,G14,H14,K14,J14,O14,T14) -> 0.17714286 | W14: =V14 -> 0.17714286 | X14: =AVERAGE(C14,G14,H14,O14,T14) -> 0.214 | Y14: =AVERAGE(K14,H14,J14) -> 0.10666667 | Z14: 0.1 | AA14: 0.1 | AE14: =AVERAGE(C14,D14,G14,H14,J14,K14,O14,T14) -> 0.18 | AF14: =AVERAGE(C14,G14,H14) -> 0.28333333 | AG14: =AVERAGE(C14,K14,G14,H14) -> 0.23 | AJ14: 0.7 | AK14: =AVERAGE(D14,C14,O14,G14,H14) -> 0.234 | AL14: =AVERAGE(C14,D14,G14,H14,J14,K14) -> 0.20333333 | AM14: =AVERAGE(D14,G14,H14) -> 0.15 | AN14: =AVERAGE(C14,O14) -> 0.36 | AO14: =AVERAGE(C14,G14) -> 0.35 | AQ14: =AVERAGE(D14,C14,J14,G14,H14) -> 0.23 | AS14: 0.1 | AT14: =AVERAGE(D14,H14) -> 0.175 | AU14: =AVERAGE(C14,D14,G14) -> 0.3 | AW14: =AVERAGE(C14,G14,H14,J14) -> 0.2375 | AX14: =AVERAGE(C14,G14,H14,J14,T14,O14) -> 0.195 | AY14: =AVERAGE(C14,D14,K14) -> 0.29 | AZ14: =AVERAGE(T14,Z14,AA14,C14,J14,K14,O14,G14,H14) -> 0.16 | BA14: 0.06 | BB14: =AVERAGE(C14,D14,S14) -> 0.29666667 | BC14: =AVERAGE(T14,C14,J14,S14,G14,H14) -> 0.19 | BD14: =AVERAGEA(T14,C14,G14,H14,K14,J14) -> 0.18666667 | BE14: =AVERAGE(T14,Z14,P14,AA14,C14,J14,K14,O14,BA14,AS14,G14,H14) -> 0.14583333 | BF14: =AVERAGE(J14,G14,H14) -> 0.11666667 | BG14: =AVERAGE(T14,Z14,D14,C14,J14,G14,H14) -> 0.19285714 | BH14: =AVERAGE(T14,D14,C14,K14) -> 0.2425 | BI14: 0.2 | BJ14: =AVERAGE(C14,S14,I14) -> 0.27166667 | BK14: 0.19 | BL14: 0.2
A15: =AVERAGE(G14,K14,H14,J14) -> 0.105 | C15: 0.6 | D15: 0.2 | G15: 0.1 | H15: 0.15 | K15: 0.07 | M15: =AVERAGE(C15,D15,G15,H15) -> 0.2625 | R15: =AVERAGE(C15,D15,G15,H15) -> 0.2625 | AF15: =AVERAGE(C15,G15,H15) -> 0.28333333 | AM15: =AVERAGE(D15,G15,H15) -> 0.15 | AO15: =AVERAGE(C15,G15) -> 0.35 | AT15: =AVERAGE(D15,H15) -> 0.175 | AU15: =AVERAGE(C15,D15,G15) -> 0.3
H16: =AVERAGE(H14,G14,D14,C14) -> 0.2625
C17: 0.7 | D17: 0.5 | E17: 0.8 | F17: 0.9 | G17: 0.1 | H17: 0.15 | I17: 0.25 | J17: 0.1 | K17: 0.07 | L17: 0.4 | M17: 1 | N17: 0.8 | O17: 0.12 | P17: 0.15 | Q17: 1 | R17: 0.8 | S17: 0.09 | T17: 0.1 | U17: 1 | V17: 1 | W17: 1 | X17: 0.8 | Y17: 0.25 | Z17: 0.2 | AA17: 0.1 | AB17: 1 | AC17: 1 | AD17: 1 | AE17: 1 | AF17: 0.75 | AG17: 0.8 | AH17: 0.8 | AI17: 0.8 | AJ17: 0.8 | AK17: 0.9 | AL17: 0.85 | AM17: 0.75 | AN17: =O17+C17 -> 0.82 | AO17: 0.6 | AP17: 0.7 | AQ17: 0.8 | AR17: 0.9 | AS17: 0.1 | AT17: =AVERAGE(D17,H17) -> 0.325 | AU17: 0.48 | AV17: 1 | AW17: 0.75 | AX17: 0.85 | AY17: 0.8
R20: =AVERAGE(J14,G14) -> 0.1

Sheet Sheet1
G1: WK-45, 2025 ( 08 Nov 2025-14 Nov 2025 )
M3: Genre Weightage%
A4: Week | B4: MARKET | C4: Platform | D4: Content format | E4: PAID/FREE | F4: Show Type | G4: Shows/Live Content | H4: Language | I4: Release Date | J4: Ranking | K4: Genre | L4: Total Viewers In Mn | M4: Male | N4: Female | O4: Language Weightage % | P4: Ranking Penetration | Q4: Reach | R4: Content format % | S4: Final Reach
A5: WK-45'2025 | B5: ALL INDIA | C5: Jio hotstar | D5: SVOD Originals Shows | E5: PAID | F5: Shows | G5: Stumble | H5: English | I5: 45969 | K5: Comedy | L5: =VLOOKUP($C5&$E5,'Updated SES'!A:N,14,0) -> #N/A | M5: =VLOOKUP($K5,'Genre Penetration'!A:B,2,0)*VLOOKUP($C5&$E5,'Updated SES'!A:I,9,0) -> #N/A | N5: =VLOOKUP(K:K,'Genre Penetration'!A:C,3,0)*VLOOKUP($C5&$E5,'Updated SES'!A:J,10,0) -> #N/A | O5: =VLOOKUP($B5,'Language Penetration'!$B$1:$AY$14,MATCH('Compile data Working'!#REF!,'Language Penetration'!$B$1:$AY$1,0),0) -> #REF! | P5: =IF(ISBLANK(J5),RANDBETWEEN(1,2)&"%",IF(J5=1,RANDBETWEEN(35,40)&"%",IF(J5=2,RANDBETWEEN(30,35)&"%",IF(J5=3,RANDBETWEEN(25,30)&"%",IF(J5=4,RANDBETWEEN(20,25)&"%",IF(J5=5,RANDBETWEEN(15,20)&"%",IF(J5=6,RANDBETWEEN(10,15)&"%",IF(J5=7,RANDBETWEEN(8,10)&"%",IF(J5=8,RANDBETWEEN(6,8)&"%",IF(J5=9,RANDBETWEEN(4,6)&"%",IF(J5=10,RANDBETWEEN(2,4)&"%",""))))))))))) -> 2% | Q5: =IFERROR(L5*(M5+N5)*O5*P5,RANDBETWEEN(1,2)%*L5*(M5+N5)*O5) -> #N/A | R5: =VLOOKUP(D:D,ranking!W:X,2,0) -> 0.6 | S5: 0.14735405
A6: WK-45'2025 | B6: ALL INDIA | C6: Amazon Prime Video | D6: Theatrical Movies | E6: PAID | F6: Movies | G6: Andhadhun | H6: Hindi | I6: 45970 | K6: Crime,Mystery,Thriller | L6: =VLOOKUP($C6&$E6,'Updated SES'!A:N,14,0) -> 36.49824 | M6: =VLOOKUP($K6,'Genre Penetration'!A:B,2,0)*VLOOKUP($C6&$E6,'Updated SES'!A:I,9,0) -> 0.3016 | N6: =VLOOKUP(K:K,'Genre Penetration'!A:C,3,0)*VLOOKUP($C6&$E6,'Updated SES'!A:J,10,0) -> 0.2016 | O6: =VLOOKUP($B6,'Language Penetration'!$B$1:$AY$14,MATCH('Compile data Working'!#REF!,'Language Penetration'!$B$1:$AY$1,0),0) -> #REF! | P6: =IF(ISBLANK(J6),RANDBETWEEN(1,2)&"%",IF(J6=1,RANDBETWEEN(35,40)&"%",IF(J6=2,RANDBETWEEN(30,35)&"%",IF(J6=3,RANDBETWEEN(25,30)&"%",IF(J6=4,RANDBETWEEN(20,25)&"%",IF(J6=5,RANDBETWEEN(15,20)&"%",IF(J6=6,RANDBETWEEN(10,15)&"%",IF(J6=7,RANDBETWEEN(8,10)&"%",IF(J6=8,RANDBETWEEN(6,8)&"%",IF(J6=9,RANDBETWEEN(4,6)&"%",IF(J6=10,RANDBETWEEN(2,4)&"%",""))))))))))) -> 1% | Q6: =IFERROR(L6*(M6+N6)*O6*P6,RANDBETWEEN(1,2)%*L6*(M6+N6)*O6) -> #REF! | R6: =VLOOKUP(D:D,ranking!W:X,2,0) -> 0.7 | S6: 0.07713684
A7: WK-45'2025 | B7: ALL INDIA | C7: Amazon Prime Video | D7: Theatrical Movies | E7: PAID | F7: Movies | G7: Everything’s Going to Be Great | H7: Hindi,English,Tamil,Telugu,Marathi | I7: 45970 | K7: Comedy,Drama | L7: =VLOOKUP($C7&$E7,'Updated SES'!A:N,14,0) -> 36.49824 | M7: =VLOOKUP($K7,'Genre Penetration'!A:B,2,0)*VLOOKUP($C7&$E7,'Updated SES'!A:I,9,0) -> 0.2444 | N7: =VLOOKUP(K:K,'Genre Penetration'!A:C,3,0)*VLOOKUP($C7&$E7,'Updated SES'!A:J,10,0) -> 0.2544 | O7: 0.7 | P7: =IF(ISBLANK(J7),RANDBETWEEN(1,2)&"%",IF(J7=1,RANDBETWEEN(35,40)&"%",IF(J7=2,RANDBETWEEN(30,35)&"%",IF(J7=3,RANDBETWEEN(25,30)&"%",IF(J7=4,RANDBETWEEN(20,25)&"%",IF(J7=5,RANDBETWEEN(15,20)&"%",IF(J7=6,RANDBETWEEN(10,15)&"%",IF(J7=7,RANDBETWEEN(8,10)&"%",IF(J7=8,RANDBETWEEN(6,8)&"%",IF(J7=9,RANDBETWEEN(4,6)&"%",IF(J7=10,RANDBETWEEN(2,4)&"%",""))))))))))) -> 1% | Q7: =IFERROR(L7*(M7+N7)*O7*P7,RANDBETWEEN(1,2)%*L7*(M7+N7)*O7) -> 0.12743725 | R7: =VLOOKUP(D:D,ranking!W:X,2,0) -> 0.7 | S7: 0.17841216
A8: WK-45'2025 | B8: ALL INDIA | C8: Jio hotstar | D8: SVOD Originals Shows | E8: PAID | F8: Shows | G8: Happy’s Place Season 2 | H8: English | I8: 45970 | K8: Comedy,Drama | L8: =VLOOKUP($C8&$E8,'Updated SES'!A:N,14,0) -> #N/A | M8: =VLOOKUP($K8,'Genre Penetration'!A:B,2,0)*VLOOKUP($C8&$E8,'Updated SES'!A:I,9,0) -> #N/A | N8: =VLOOKUP(K:K,'Genre Penetration'!A:C,3,0)*VLOOKUP($C8&$E8,'Updated SES'!A:J,10,0) -> #N/A | O8: =VLOOKUP($B8,'Language Penetration'!$B$1:$AY$14,MATCH('Compile data Working'!#REF!,'Language Penetration'!$B$1:$AY$1,0),0) -> #REF! | P8: =IF(ISBLANK(J8),RANDBETWEEN(1,2)&"%",IF(J8=1,RANDBETWEEN(35,40)&"%",IF(J8=2,RANDBETWEEN(30,35)&"%",IF(J8=3,RANDBETWEEN(25,30)&"%",IF(J8=4,RANDBETWEEN(20,25)&"%",IF(J8=5,RANDBETWEEN(15,20)&"%",IF(J8=6,RANDBETWEEN(10,15)&"%",IF(J8=7,RANDBETWEEN(8,10)&"%",IF(J8=8,RANDBETWEEN(6,8)&"%",IF(J8=9,RANDBETWEEN(4,6)&"%",IF(J8=10,RANDBETWEEN(2,4)&"%",""))))))))))) -> 2% | Q8: =IFERROR(L8*(M8+N8)*O8*P8,RANDBETWEEN(1,2)%*L8*(M8+N8)*O8) -> #N/A | R8: =VLOOKUP(D:D,ranking!W:X,2,0) -> 0.6 | S8: 0.1494286
A9: WK-45'2025 | B9: ALL INDIA | C9: Jio hotstar | D9: SVOD Originals Shows | E9: PAID | F9: Shows | G9: Caroline Flack: Search for the Truth | H9: English | I9: 45971 | K9: Documentary | L9: =VLOOKUP($C9&$E9,'Updated SES'!A:N,14,0) -> #N/A | M9: =VLOOKUP($K9,'Genre Penetration'!A:B,2,0)*VLOOKUP($C9&$E9,'Updated SES'!A:I,9,0) -> #N/A | N9: =VLOOKUP(K:K,'Genre Penetration'!A:C,3,0)*VLOOKUP($C9&$E9,'Updated SES'!A:J,10,0) -> #N/A | O9: =VLOOKUP($B9,'Language Penetration'!$B$1:$AY$14,MATCH('Compile data Working'!#REF!,'Language Penetration'!$B$1:$AY$1,0),0) -> #REF! | P9: =IF(ISBLANK(J9),RANDBETWEEN(1,2)&"%",IF(J9=1,RANDBETWEEN(35,40)&"%",IF(J9=2,RANDBETWEEN(30,35)&"%",IF(J9=3,RANDBETWEEN(25,30)&"%",IF(J9=4,RANDBETWEEN(20,25)&"%",IF(J9=5,RANDBETWEEN(15,20)&"%",IF(J9=6,RANDBETWEEN(10,15)&"%",IF(J9=7,RANDBETWEEN(8,10)&"%",IF(J9=8,RANDBETWEEN(6,8)&"%",IF(J9=9,RANDBETWEEN(4,6)&"%",IF(J9=10,RANDBETWEEN(2,4)&"%",""))))))))))) -> 2% | Q9: =IFERROR(L9*(M9+N9)*O9*P9,RANDBETWEEN(1,2)%*L9*(M9+N9)*O9) -> #N/A | R9: =VLOOKUP(D:D,ranking!W:X,2,0) -> 0.6 | S9: 0.14735405
A10: WK-45'2025 | B10: ALL INDIA | C10: Netflix | D10: SVOD Originals Shows | E10: PAID | F10: Shows | G10: MARINES | H10: Hindi,English | I10: 45971 | K10: Documentary | L10: =VLOOKUP($C10&$E10,'Updated SES'!A:N,14,0) -> 55.4592 | M10: =VLOOKUP($K10,'Genre Penetration'!A:B,2,0)*VLOOKUP($C10&$E10,'Updated SES'!A:I,9,0) -> 0.2205 | N10: =VLOOKUP(K:K,'Genre Penetration'!A:C,3,0)*VLOOKUP($C10&$E10,'Updated SES'!A:J,10,0) -> 0.2805 | O10: =VLOOKUP($B10,'Language Penetration'!$B$1:$AY$14,MATCH('Compile data Working'!$H6,'Language Penetration'!$B$1:$AY$1,0),0) -> #N/A | P10: =IF(ISBLANK(J10),RANDBETWEEN(1,2)&"%",IF(J10=1,RANDBETWEEN(35,40)&"%",IF(J10=2,RANDBETWEEN(30,35)&"%",IF(J10=3,RANDBETWEEN(25,30)&"%",IF(J10=4,RANDBETWEEN(20,25)&"%",IF(J10=5,RANDBETWEEN(15,20)&"%",IF(J10=6,RANDBETWEEN(10,15)&"%",IF(J10=7,RANDBETWEEN(8,10)&"%",IF(J10=8,RANDBETWEEN(6,8)&"%",IF(J10=9,RANDBETWEEN(4,6)&"%",IF(J10=10,RANDBETWEEN(2,4)&"%",""))))))))))) -> 1% | Q10: =IFERROR(L10*(M10+N10)*O10*P10,RANDBETWEEN(1,2)%*L10*(M10+N10)*O10) -> #N/A | R10: =VLOOKUP(D:D,ranking!W:X,2,0) -> 0.6 | S10: 0.13336828
A11: WK-45'2025 | B11: ALL INDIA | C11: Netflix | D11: SVOD Originals Movies | E11: PAID | F11: Movies | G11: Frankenstein: The Anatomy Lesson | H11: English | I11: 45972 | K11: Documentary | L11: =VLOOKUP($C11&$E11,'Updated SES'!A:N,14,0) -> 55.4592 | M11: =VLOOKUP($K11,'Genre Penetration'!A:B,2,0)*VLOOKUP($C11&$E11,'Updated SES'!A:I,9,0) -> 0.2205 | N11: =VLOOKUP(K:K,'Genre Penetration'!A:C,3,0)*VLOOKUP($C11&$E11,'Updated SES'!A:J,10,0) -> 0.2805 | O11: =VLOOKUP($B11,'Language Penetration'!$B$1:$AY$14,MATCH('Compile data Working'!#REF!,'Language Penetration'!$B$1:$AY$1,0),0) -> #REF! | P11: =IF(ISBLANK(J11),RANDBETWEEN(1,2)&"%",IF(J11=1,RANDBETWEEN(35,40)&"%",IF(J11=2,RANDBETWEEN(30,35)&"%",IF(J11=3,RANDBETWEEN(25,30)&"%",IF(J11=4,RANDBETWEEN(20,25)&"%",IF(J11=5,RANDBETWEEN(15,20)&"%",IF(J11=6,RANDBETWEEN(10,15)&"%",IF(J11=7,RANDBETWEEN(8,10)&"%",IF(J11=8,RANDBETWEEN(6,8)&"%",IF(J11=9,RANDBETWEEN(4,6)&"%",IF(J11=10,RANDBETWEEN(2,4)&"%",""))))))))))) -> 2% | Q11: =IFERROR(L11*(M11+N11)*O11*P11,RANDBETWEEN(1,2)%*L11*(M11+N11)*O11) -> #REF! | R11: =VLOOKUP(D:D,ranking!W:X,2,0) -> 0.8 | S11: 0.044456095
A12: WK-45'2025 | B12: ALL INDIA | C12: Amazon Prime Video | D12: Theatrical Movies | E12: RENT | F12: Movies | G12: Premachi Goshta 2 | H12: Marathi | I12: 45972 | K12: Romance | L12: =VLOOKUP($C12&$E12,'Updated SES'!A:N,14,0) -> 4.689 | M12: =VLOOKUP($K12,'Genre Penetration'!A:B,2,0)*VLOOKUP($C12&$E12,'Updated SES'!A:I,9,0) -> 0.306 | N12: =VLOOKUP(K:K,'Genre Penetration'!A:C,3,0)*VLOOKUP($C12&$E12,'Updated SES'!A:J,10,0) -> 0.176 | O12: =VLOOKUP($B12,'Language Penetration'!$B$1:$AY$14,MATCH('Compile data Working'!#REF!,'Language Penetration'!$B$1:$AY$1,0),0) -> #REF! | P12: =IF(ISBLANK(J12),RANDBETWEEN(1,2)&"%",IF(J12=1,RANDBETWEEN(35,40)&"%",IF(J12=2,RANDBETWEEN(30,35)&"%",IF(J12=3,RANDBETWEEN(25,30)&"%",IF(J12=4,RANDBETWEEN(20,25)&"%",IF(J12=5,RANDBETWEEN(15,20)&"%",IF(J12=6,RANDBETWEEN(10,15)&"%",IF(J12=7,RANDBETWEEN(8,10)&"%",IF(J12=8,RANDBETWEEN(6,8)&"%",IF(J12=9,RANDBETWEEN(4,6)&"%",IF(J12=10,RANDBETWEEN(2,4)&"%",""))))))))))) -> 2% | Q12: =IFERROR(L12*(M12+N12)*O12*P12,RANDBETWEEN(1,2)%*L12*(M12+N12)*O12) -> #REF! | R12: =VLOOKUP(D:D,ranking!W:X,2,0) -> 0.7 | S12: 0.0037969646
A13: WK-45'2025 | B13: ALL INDIA | C13: Amazon Prime Video | D13: Theatrical Movies | E13: PAID | F13: Movies | G13: 35-Chinna Katha Kaadu | H13: Telugu | I13: 45973 | K13: Comedy | L13: =VLOOKUP($C13&$E13,'Updated SES'!A:N,14,0) -> 36.49824 | M13: =VLOOKUP($K13,'Genre Penetration'!A:B,2,0)*VLOOKUP($C13&$E13,'Updated SES'!A:I,9,0) -> 0.234 | N13: =VLOOKUP(K:K,'Genre Penetration'!A:C,3,0)*VLOOKUP($C13&$E13,'Updated SES'!A:J,10,0) -> 0.264 | O13: =VLOOKUP($B13,'Language Penetration'!$B$1:$AY$14,MATCH('Compile data Working'!#REF!,'Language Penetration'!$B$1:$AY$1,0),0) -> #REF! | P13: =IF(ISBLANK(J13),RANDBETWEEN(1,2)&"%",IF(J13=1,RANDBETWEEN(35,40)&"%",IF(J13=2,RANDBETWEEN(30,35)&"%",IF(J13=3,RANDBETWEEN(25,30)&"%",IF(J13=4,RANDBETWEEN(20,25)&"%",IF(J13=5,RANDBETWEEN(15,20)&"%",IF(J13=6,RANDBETWEEN(10,15)&"%",IF(J13=7,RANDBETWEEN(8,10)&"%",IF(J13=8,RANDBETWEEN(6,8)&"%",IF(J13=9,RANDBETWEEN(4,6)&"%",IF(J13=10,RANDBETWEEN(2,4)&"%",""))))))))))) -> 1% | Q13: =IFERROR(L13*(M13+N13)*O13*P13,RANDBETWEEN(1,2)%*L13*(M13+N13)*O13) -> #REF! | R13: =VLOOKUP(D:D,ranking!W:X,2,0) -> 0.7 | S13: 0.01908493
