Workbook

Sheet Top 50 Shows & Movies
F1: WK-24, 2026 ( 13 Jun 2026 - 19 Jun 2026 )
A6: Week | B6: MARKET | C6: Platform | D6: Content format | E6: PAID/FREE | F6: Content Type | G6: Shows/Live Content | H6: Language | I6: Genre | J6: Release Date | K6: Rank | L6: Reach
A7: WK-24,2026 | B7: ALL INDIA | C7: JioHotstar | D7: Theatrical Movies | E7: PAID | F7: Movies | G7: Dhurandhar: The Revenge | H7: Hindi,Kannada,Malayalam,Tamil,Telugu | I7: Action,Crime,Thriller | J7: 46177 | K7: 1 | L7: 56.557616
A8: WK-24,2026 | B8: ALL INDIA | C8: JioHotstar | D8: Live Event | E8: PAID | F8: Sports | G8: AFGHANISTAN IN INDIA ODI SERIES 2026 | H8: Bengali,Bhojpuri,English,Haryanvi,Hindi,Kannada,Malayalam,Tamil,Telugu | I8: Sports | J8: 46186 | K8: =K7+1 -> 2 | L8: 46.138629
A9: WK-24,2026 | B9: ALL INDIA | C9: JioHotstar | D9: Live Event | E9: PAID | F9: Sports | G9: ICC Women's T20 World Cup 2026 | H9: Hindi | I9: Sport | J9: 46185 | K9: =K8+1 -> 3 | L9: 45.834995
A10: WK-24,2026 | B10: ALL INDIA | C10: Amazon Prime Video | D10: Theatrical Movies | E10: PAID | F10: Movies | G10: Karuppu | H10: Hindi,Kannada,Malayalam,Tamil | I10: Action,Comedy,Drama | J10: 46185 | K10: =K9+1 -> 4 | L10: 26.903316
A11: WK-24,2026 | B11: ALL INDIA | C11: Amazon Prime Video | D11: Svod Originals Shows | E11: PAID | F11: Shows | G11: Raakh | H11: Hindi,Tamil,Telugu | I11: Crime,Drama,Thriller | J11: 46185 | K11: =K10+1 -> 5 | L11: 26.705003
A12: WK-24,2026 | B12: ALL INDIA | C12: Netflix | D12: Theatrical Movies | E12: PAID | F12: Movies | G12: Bhooth Bangla | H12: Hindi | I12: Comedy,Horror | J12: 46185 | K12: =K11+1 -> 6 | L12: 19.527626
A13: WK-24,2026 | B13: ALL INDIA | C13: Amazon MX Player | D13: Avod Originals Shows | E13: FREE | F13: Shows | G13: Ab Hoga Hisaab | H13: Hindi | I13: Crime,Drama,Thriller | J13: 46191 | K13: =K12+1 -> 7 | L13: 24.870206
A14: WK-24,2026 | B14: ALL INDIA | C14: JioHotstar | D14: Tv Catch-Up | E14: PAID | F14: Tv catchup | G14: Laughter Chefs S3 | H14: Hindi | I14: Comedy,Reality-Tv | J14: 45983 | K14: =K13+1 -> 8 | L14: 21.996205
A15: WK-24,2026 | B15: ALL INDIA | C15: JioHotstar | D15: Svod Originals Shows | E15: PAID | F15: Shows | G15: Thukra Ke Mera Pyaar Season 2 | H15: Bengali,Bhojpuri,Hindi,Kannada,Malayalam,Marathi,Tamil,Telugu | I15: Romance | J15: 46192 | K15: =K14+1 -> 9 | L15: 21.448858
A16: WK-24,2026 | B16: ALL INDIA | C16: Amazon Prime Video | D16: SVOD Originals Movies | E16: PAID | F16: Movies | G16: Your Fault: London | H16: English,Hindi,Kannada,Malayalam,Tamil,Telugu | I16: Drama,Romance | J16: 46190 | K16: =K15+1 -> 10 | L16: 18.923245
A17: WK-24,2026 | B17: ALL INDIA | C17: JioHotstar | D17: Tv Catch-Up | E17: PAID | F17: Tv catchup | G17: Anupama | H17: Hindi | I17: Drama | J17: 44025 | K17: =K16+1 -> 11 | L17: 18.374668
A18: WK-24,2026 | B18: ALL INDIA | C18: Amazon Prime Video | D18: Svod Originals Shows | E18: PAID | F18: Shows | G18: From S4 | H18: English,Hindi | I18: Drama,Horror | J18: 46131 | K18: =K17+1 -> 12 | L18: 17.994455
A19: WK-24,2026 | B19: ALL INDIA | C19: Amazon Prime Video | D19: Svod Originals Shows | E19: PAID | F19: Shows | G19: The Pyramid Scheme | H19: Hindi | I19: Comedy,Drama | J19: 46178 | K19: =K18+1 -> 13 | L19: 17.507986
... A21: WK-24,2026 | B21: ALL INDIA | C21: Amazon Prime Video | D21: Theatrical Movies | E21: PAID | F21: Movies | G21: Mareechika | H21: Hindi | I21: Drama,Romance,Thriller | J21: 46192 | K21: =K20+1 -> 15 | L21: 16.624409
A22: WK-24,2026 | B22: ALL INDIA | C22: Netflix | D22: Theatrical Movies | E22: PAID | F22: Movies | G22: 29 | H22: Hindi,Kannada,Malayalam,Tamil,Telugu | I22: Comedy,Drama,Romance | J22: 46178 | K22: =K21+1 -> 16 | L22: 16.496989
A23: WK-24,2026 | B23: ALL INDIA | C23: Netflix | D23: SVOD Originals Shows | E23: PAID | F23: Shows | G23: My Love Story With Yamada-kun at Lv999 | H23: English | I23: Animation,Comedy,Romance | J23: 46188 | K23: =K22+1 -> 17 | L23: 16.496989
A24: WK-24,2026 | B24: ALL INDIA | C24: JioHotstar | D24: Theatrical Movies | E24: PAID | F24: Movies | G24: Kenatha Kanom | H24: Bengali,Hindi,Kannada,Malayalam,Marathi,Tamil,Telugu | I24: Comedy,Drama | J24: 46189 | K24: =K23+1 -> 18 | L24: 16.21064
A25: WK-24,2026 | B25: ALL INDIA | C25: Netflix | D25: Svod Originals Shows | E25: PAID | F25: Shows | G25: Teach You a Lesson | H25: English,Hindi,Tamil,Telugu | I25: Action,Drama | J25: 46178 | K25: =K24+1 -> 19 | L25: 16.16119
A26: WK-24,2026 | B26: ALL INDIA | C26: Netflix | D26: SVOD Originals Shows | E26: PAID | F26: Shows | G26: Horimiya Season 2 | H26: English | I26: Animation,Drama,Romance | J26: 46188 | K26: =K25+1 -> 20 | L26: 15.934591
A27: WK-24,2026 | B27: ALL INDIA | C27: Amazon Prime Video | D27: Theatrical Movies | E27: PAID | F27: Movies | G27: Dacoit | H27: Hindi | I27: Action,Drama,Thriller | J27: 46178 | K27: =K26+1 -> 21 | L27: 15.240957
A28: WK-24,2026 | B28: ALL INDIA | C28: JioHotstar | D28: SVOD Originals Shows | E28: PAID | F28: Shows | G28: Harry Potter: The Official Film Podcast | H28: English | I28: Talk Show | J28: 46190 | K28: =K27+1 -> 22 | L28: 14.736946
A29: WK-24,2026 | B29: ALL INDIA | C29: JioHotstar | D29: SVOD Originals Shows | E29: PAID | F29: Shows | G29: Save the Tigers Season 3 | H29: Bengali,Hindi,Kannada,Malayalam,Marathi,Tamil,Telugu | I29: Comedy,Drama,Thriller | J29: 46192 | K29: =K28+1 -> 23 | L29: 14.589576
A30: WK-24,2026 | B30: ALL INDIA | C30: JioHotstar | D30: Theatrical Movies | E30: PAID | F30: Movies | G30: Dridam | H30: Hindi,Kannada,Malayalam,Tamil,Telugu | I30: Crime,Drama,Thriller | J30: 46185 | K30: =K29+1 -> 24 | L30: 14.533046
A31: WK-24,2026 | B31: ALL INDIA | C31: Netflix | D31: Theatrical Movies | E31: PAID | F31: Movies | G31: Maa Behen | H31: English,Hindi,Tamil,Telugu | I31: Comedy,Crime,Drama | J31: 46177 | K31: =K30+1 -> 25 | L31: 14.305931
A32: WK-24,2026 | B32: ALL INDIA | C32: Sony Liv | D32: Svod Originals Shows | E32: PAID | F32: Shows | G32: Gullak Season 5 | H32: Hindi | I32: Comedy,Drama | J32: 46178 | K32: =K31+1 -> 26 | L32: 13.925057
A33: WK-24,2026 | B33: ALL INDIA | C33: Netflix | D33: SVOD Originals Shows | E33: PAID | F33: Shows | G33: Oasis | H33: English,Hindi,Tamil,Telugu | I33: Crime,Drama,Mystery | J33: 46192 | K33: =K32+1 -> 27 | L33: 13.809249
A34: WK-24,2026 | B34: ALL INDIA | C34: Amazon Prime Video | D34: Theatrical Movies | E34: PAID | F34: Movies | G34: A Snapshot of Forever | H34: English | I34: Comedy,Romance | J34: 46190 | K34: =K33+1 -> 28 | L34: 13.793016
... A56: WK-24,2026 | B56: ALL INDIA | C56: Lionsgate Play | D56: Theatrical Movies | E56: PAID | F56: Movies | G56: Motive For Murder (M4M) | H56: Hindi,Kannada,Malayalam,Tamil,Telugu | I56: Drama | J56: 46192 | K56: =K55+1 -> 50 | L56: 11.164489
C59: Gender
A60: PLATFORM | B60: Total Reach | C60: Male | D60: Female
A61: Amazon Prime Video | B61: 361.64643 | C61: =VLOOKUP(A:A,'Updated SES'!B:J,8,0) -> 0.52 | D61: =VLOOKUP(A:A,'Updated SES'!B:J,9,0) -> 0.48
A62: JioHotstar | B62: 329.92806 | C62: =VLOOKUP(A:A,'Updated SES'!B:J,8,0) -> 0.625 | D62: =VLOOKUP(A:A,'Updated SES'!B:J,9,0) -> 0.375
A63: Netflix | B63: 269.72524 | C63: =VLOOKUP(A:A,'Updated SES'!B:J,8,0) -> 0.49 | D63: =VLOOKUP(A:A,'Updated SES'!B:J,9,0) -> 0.51
A64: Sony Liv | B64: 90.716173 | C64: =VLOOKUP(A:A,'Updated SES'!B:J,8,0) -> 0.65 | D64: =VLOOKUP(A:A,'Updated SES'!B:J,9,0) -> 0.35
A65: Amazon MX Player | B65: 61.935932 | C65: =VLOOKUP(A:A,'Updated SES'!B:J,8,0) -> 0.8 | D65: =VLOOKUP(A:A,'Updated SES'!B:J,9,0) -> 0.2

Sheet Compile data Working
G1: WK-24, 2026 ( 13 Jun 2026 - 19 Jun 2026 )
M3: Genre Weightage%
A4: Week | B4: MARKET | C4: Platform | D4: Live Event | E4: PAID/FREE | F4: Show Type | G4: Shows/Live Content | H4: Language | I4: Release Date | J4: Ranking | K4: Genre | L4: Total Viewers In Mn | M4: Male | N4: Female | O4: Language Weightage % | P4: Ranking Penetration | Q4: Reach | R4: Content format % | S4: Final Reach | T4: WK-24 Reach
A5: Trending Top 10 | B5: ALL INDIA | C5: JioHotstar | D5: Theatrical Movies | E5: PAID | F5: Movies | G5: Dhurandhar: The Revenge | H5: Hindi,Kannada,Malayalam,Tamil,Telugu | I5: 46177 | J5: 3 | K5: Action,Crime,Thriller | L5: =VLOOKUP($C5&$E5,'Updated SES'!A:N,14,0) -> 127.11702 | M5: =VLOOKUP($K5,'Genre Penetration'!A:B,2,0)*VLOOKUP($C5&$E5,'Updated SES'!A:I,9,0) -> 0.4824 | N5: =VLOOKUP(K:K,'Genre Penetration'!A:C,3,0)*VLOOKUP($C5&$E5,'Updated SES'!A:J,10,0) -> 0.0924 | O5: =VLOOKUP($B5,'Language Penetration'!$B$1:$BE$14,MATCH('Compile data Working'!$H5,'Language Penetration'!$B$1:$BE$1,0),0) -> 0.204 | P5: =IF(ISBLANK(J5),RANDBETWEEN(1,2)&"%",IF(J5=1,RANDBETWEEN(35,40)&"%",IF(J5=2,RANDBETWEEN(30,35)&"%",IF(J5=3,RANDBETWEEN(25,30)&"%",IF(J5=4,RANDBETWEEN(20,25)&"%",IF(J5=5,RANDBETWEEN(15,20)&"%",IF(J5=6,RANDBETWEEN(10,15)&"%",IF(J5=7,RANDBETWEEN(8,10)&"%",IF(J5=8,RANDBETWEEN(6,8)&"%",IF(J5=9,RANDBETWEEN(4,6)&"%",IF(J5=10,RANDBETWEEN(2,4)&"%",""))))))))))) -> 27% | Q5: =IFERROR(L5*(M5+N5)*O5*P5,RANDBETWEEN(1,2)%*L5*(M5+N5)*O5) -> 4.0245228 | R5: =VLOOKUP(D:D,ranking!W:X,2,0) -> 0.7 | S5: =R5*Q5 -> 2.817166 | T5: 56.557616
A6: WK-24'2026 | B6: ALL INDIA | C6: JioHotstar | D6: Live Event | E6: PAID | F6: Sports | G6: AFGHANISTAN IN INDIA ODI SERIES 2026 | H6: Bengali,Bhojpuri,English,Haryanvi,Hindi,Kannada,Malayalam,Tamil,Telugu | I6: 46186 | K6: Sports | L6: =VLOOKUP($C6&$E6,'Updated SES'!A:N,14,0) -> 127.11702 | M6: =VLOOKUP($K6,'Genre Penetration'!A:B,2,0)*VLOOKUP($C6&$E6,'Updated SES'!A:I,9,0) -> 0.5025 | N6: =VLOOKUP(K:K,'Genre Penetration'!A:C,3,0)*VLOOKUP($C6&$E6,'Updated SES'!A:J,10,0) -> 0.0825 | O6: =VLOOKUP($B6,'Language Penetration'!$B$1:$BE$14,MATCH('Compile data Working'!$H6,'Language Penetration'!$B$1:$BE$1,0),0) -> #N/A | P6: =IF(ISBLANK(J6),RANDBETWEEN(1,2)&"%",IF(J6=1,RANDBETWEEN(35,40)&"%",IF(J6=2,RANDBETWEEN(30,35)&"%",IF(J6=3,RANDBETWEEN(25,30)&"%",IF(J6=4,RANDBETWEEN(20,25)&"%",IF(J6=5,RANDBETWEEN(15,20)&"%",IF(J6=6,RANDBETWEEN(10,15)&"%",IF(J6=7,RANDBETWEEN(8,10)&"%",IF(J6=8,RANDBETWEEN(6,8)&"%",IF(J6=9,RANDBETWEEN(4,6)&"%",IF(J6=10,RANDBETWEEN(2,4)&"%",""))))))))))) -> 2% | Q6: =IFERROR(L6*(M6+N6)*O6*P6,RANDBETWEEN(1,2)%*L6*(M6+N6)*O6) -> #N/A | R6: =VLOOKUP(D:D,ranking!W:X,2,0) -> 0.1 | S6: =R6*Q6 -> #N/A | T6: 46.138629
A7: Cott Data Servey | B7: ALL INDIA | C7: JioHotstar | D7: Live Event | E7: PAID | F7: Sports | G7: ICC Women's T20 World Cup 2026 | H7: Hindi | I7: 46185 | K7: Sport | L7: =VLOOKUP($C7&$E7,'Updated SES'!A:N,14,0) -> 127.11702 | M7: =VLOOKUP($K7,'Genre Penetration'!A:B,2,0)*VLOOKUP($C7&$E7,'Updated SES'!A:I,9,0) -> 0.5025 | N7: =VLOOKUP(K:K,'Genre Penetration'!A:C,3,0)*VLOOKUP($C7&$E7,'Updated SES'!A:J,10,0) -> 0.0825 | O7: =VLOOKUP($B7,'Language Penetration'!$B$1:$BE$14,MATCH('Compile data Working'!$H7,'Language Penetration'!$B$1:$BE$1,0),0) -> 0.6 | P7: =IF(ISBLANK(J7),RANDBETWEEN(1,2)&"%",IF(J7=1,RANDBETWEEN(35,40)&"%",IF(J7=2,RANDBETWEEN(30,35)&"%",IF(J7=3,RANDBETWEEN(25,30)&"%",IF(J7=4,RANDBETWEEN(20,25)&"%",IF(J7=5,RANDBETWEEN(15,20)&"%",IF(J7=6,RANDBETWEEN(10,15)&"%",IF(J7=7,RANDBETWEEN(8,10)&"%",IF(J7=8,RANDBETWEEN(6,8)&"%",IF(J7=9,RANDBETWEEN(4,6)&"%",IF(J7=10,RANDBETWEEN(2,4)&"%",""))))))))))) -> 1% | Q7: =IFERROR(L7*(M7+N7)*O7*P7,RANDBETWEEN(1,2)%*L7*(M7+N7)*O7) -> 0.44618074 | R7: =VLOOKUP(D:D,ranking!W:X,2,0) -> 0.1 | S7: =R7*Q7 -> 0.044618074 | T7: 45.834995
A8: Trending Top 10 | B8: ALL INDIA | C8: Amazon Prime Video | D8: Theatrical Movies | E8: PAID | F8: Movies | G8: Karuppu | H8: Hindi,Kannada,Malayalam,Tamil | I8: 46185 | J8: 3 | K8: Action,Comedy,Drama | L8: =VLOOKUP($C8&$E8,'Updated SES'!A:N,14,0) -> 36.49824 | M8: =VLOOKUP($K8,'Genre Penetration'!A:B,2,0)*VLOOKUP($C8&$E8,'Updated SES'!A:I,9,0) -> 0.2496 | N8: =VLOOKUP(K:K,'Genre Penetration'!A:C,3,0)*VLOOKUP($C8&$E8,'Updated SES'!A:J,10,0) -> 0.2496 | O8: =VLOOKUP($B8,'Language Penetration'!$B$1:$BE$14,MATCH('Compile data Working'!$H23,'Language Penetration'!$B$1:$BE$1,0),0) -> 0.17714286 | P8: =IF(ISBLANK(J8),RANDBETWEEN(1,2)&"%",IF(J8=1,RANDBETWEEN(35,40)&"%",IF(J8=2,RANDBETWEEN(30,35)&"%",IF(J8=3,RANDBETWEEN(25,30)&"%",IF(J8=4,RANDBETWEEN(20,25)&"%",IF(J8=5,RANDBETWEEN(15,20)&"%",IF(J8=6,RANDBETWEEN(10,15)&"%",IF(J8=7,RANDBETWEEN(8,10)&"%",IF(J8=8,RANDBETWEEN(6,8)&"%",IF(J8=9,RANDBETWEEN(4,6)&"%",IF(J8=10,RANDBETWEEN(2,4)&"%",""))))))))))) -> 30% | Q8: =IFERROR(L8*(M8+N8)*O8*P8,RANDBETWEEN(1,2)%*L8*(M8+N8)*O8) -> 0.96825868 | R8: =VLOOKUP(D:D,ranking!W:X,2,0) -> 0.7 | S8: =R8*Q8 -> 0.67778108 | T8: 26.903316
A9: Trending Top 10 | B9: ALL INDIA | C9: Amazon Prime Video | D9: Svod Originals Shows | E9: PAID | F9: Shows | G9: Raakh | H9: Hindi,Tamil,Telugu | I9: 46185 | J9: 1 | K9: Crime,Drama,Thriller | L9: =VLOOKUP($C9&$E9,'Updated SES'!A:N,14,0) -> 36.49824 | M9: =VLOOKUP($K9,'Genre Penetration'!A:B,2,0)*VLOOKUP($C9&$E9,'Updated SES'!A:I,9,0) -> 0.3744 | N9: =VLOOKUP(K:K,'Genre Penetration'!A:C,3,0)*VLOOKUP($C9&$E9,'Updated SES'!A:J,10,0) -> 0.1344 | O9: =VLOOKUP($B9,'Language Penetration'!$B$1:$BE$14,MATCH('Compile data Working'!$H13,'Language Penetration'!$B$1:$BE$1,0),0) -> 0.204 | P9: =IF(ISBLANK(J9),RANDBETWEEN(1,2)&"%",IF(J9=1,RANDBETWEEN(35,40)&"%",IF(J9=2,RANDBETWEEN(30,35)&"%",IF(J9=3,RANDBETWEEN(25,30)&"%",IF(J9=4,RANDBETWEEN(20,25)&"%",IF(J9=5,RANDBETWEEN(15,20)&"%",IF(J9=6,RANDBETWEEN(10,15)&"%",IF(J9=7,RANDBETWEEN(8,10)&"%",IF(J9=8,RANDBETWEEN(6,8)&"%",IF(J9=9,RANDBETWEEN(4,6)&"%",IF(J9=10,RANDBETWEEN(2,4)&"%",""))))))))))) -> 37% | Q9: =IFERROR(L9*(M9+N9)*O9*P9,RANDBETWEEN(1,2)%*L9*(M9+N9)*O9) -> 1.4016866 | R9: =VLOOKUP(D:D,ranking!W:X,2,0) -> 0.6 | S9: =R9*Q9 -> 0.84101195 | T9: 26.705003
A10: Trending Top 10 | B10: ALL INDIA | C10: Amazon MX Player | D10: Avod Originals Shows | E10: FREE | F10: Shows | G10: Ab Hoga Hisaab | H10: Hindi | I10: 46191 | J10: 1 | K10: Crime,Drama,Thriller | L10: =VLOOKUP($C10&$E10,'Updated SES'!A:N,14,0) -> 78.93987 | M10: =VLOOKUP($K10,'Genre Penetration'!A:B,2,0)*VLOOKUP($C10&$E10,'Updated SES'!A:I,9,0) -> 0.576 | N10: =VLOOKUP(K:K,'Genre Penetration'!A:C,3,0)*VLOOKUP($C10&$E10,'Updated SES'!A:J,10,0) -> 0.056 | O10: =VLOOKUP($B10,'Language Penetration'!$B$1:$BE$14,MATCH('Compile data Working'!$H9,'Language Penetration'!$B$1:$BE$1,0),0) -> 0.28333333 | P10: =IF(ISBLANK(J10),RANDBETWEEN(1,2)&"%",IF(J10=1,RANDBETWEEN(35,40)&"%",IF(J10=2,RANDBETWEEN(30,35)&"%",IF(J10=3,RANDBETWEEN(25,30)&"%",IF(J10=4,RANDBETWEEN(20,25)&"%",IF(J10=5,RANDBETWEEN(15,20)&"%",IF(J10=6,RANDBETWEEN(10,15)&"%",IF(J10=7,RANDBETWEEN(8,10)&"%",IF(J10=8,RANDBETWEEN(6,8)&"%",IF(J10=9,RANDBETWEEN(4,6)&"%",IF(J10=10,RANDBETWEEN(2,4)&"%",""))))))))))) -> 38% | Q10: =IFERROR(L10*(M10+N10)*O10*P10,RANDBETWEEN(1,2)%*L10*(M10+N10)*O10) -> 5.3714898 | R10: =VLOOKUP(D:D,ranking!W:X,2,0) -> 0.6 | S10: =R10*Q10 -> 3.2228939 | T10: 24.870206
A11: Cott Data Servey | B11: ALL INDIA | C11: JioHotstar | D11: Tv Catch-Up | E11: PAID | F11: Tv catchup | G11: Laughter Chefs S3 | H11: Hindi | I11: 45983 | J11: 2 | K11: Comedy,Reality-Tv | L11: =VLOOKUP($C11&$E11,'Updated SES'!A:N,14,0) -> 127.11702 | M11: =VLOOKUP($K11,'Genre Penetration'!A:B,2,0)*VLOOKUP($C11&$E11,'Updated SES'!A:I,9,0) -> 0.335 | N11: =VLOOKUP(K:K,'Genre Penetration'!A:C,3,0)*VLOOKUP($C11&$E11,'Updated SES'!A:J,10,0) -> 0.165 | O11: =VLOOKUP($B11,'Language Penetration'!$B$1:$BE$14,MATCH('Compile data Working'!$H10,'Language Penetration'!$B$1:$BE$1,0),0) -> 0.6 | P11: =IF(ISBLANK(J11),RANDBETWEEN(1,2)&"%",IF(J11=1,RANDBETWEEN(35,40)&"%",IF(J11=2,RANDBETWEEN(30,35)&"%",IF(J11=3,RANDBETWEEN(25,30)&"%",IF(J11=4,RANDBETWEEN(20,25)&"%",IF(J11=5,RANDBETWEEN(15,20)&"%",IF(J11=6,RANDBETWEEN(10,15)&"%",IF(J11=7,RANDBETWEEN(8,10)&"%",IF(J11=8,RANDBETWEEN(6,8)&"%",IF(J11=9,RANDBETWEEN(4,6)&"%",IF(J11=10,RANDBETWEEN(2,4)&"%",""))))))))))) -> 34% | Q11: =IFERROR(L11*(M11+N11)*O11*P11,RANDBETWEEN(1,2)%*L11*(M11+N11)*O11) -> 12.965936 | R11: =VLOOKUP(D:D,ranking!W:X,2,0) -> 0.3 | S11: =R11*Q11 -> 3.8897808 | T11: 21.996205
A12: Trending Top 10 | B12: ALL INDIA | C12: JioHotstar | D12: Svod Originals Shows | E12: PAID | F12: Shows | G12: Thukra Ke Mera Pyaar Season 2 | H12: Bengali,Bhojpuri,Hindi,Kannada,Malayalam,Marathi,Tamil,Telugu | I12: 46192 | J12: 1 | K12: Romance | L12: =VLOOKUP($C12&$E12,'Updated SES'!A:N,14,0) -> 127.11702 | M12: =VLOOKUP($K12,'Genre Penetration'!A:B,2,0)*VLOOKUP($C12&$E12,'Updated SES'!A:I,9,0) -> 0.3015 | N12: =VLOOKUP(K:K,'Genre Penetration'!A:C,3,0)*VLOOKUP($C12&$E12,'Updated SES'!A:J,10,0) -> 0.1815 | O12: =VLOOKUP($B12,'Language Penetration'!$B$1:$BE$14,MATCH('Compile data Working'!$H11,'Language Penetration'!$B$1:$BE$1,0),0) -> 0.6 | P12: =IF(ISBLANK(J12),RANDBETWEEN(1,2)&"%",IF(J12=1,RANDBETWEEN(35,40)&"%",IF(J12=2,RANDBETWEEN(30,35)&"%",IF(J12=3,RANDBETWEEN(25,30)&"%",IF(J12=4,RANDBETWEEN(20,25)&"%",IF(J12=5,RANDBETWEEN(15,20)&"%",IF(J12=6,RANDBETWEEN(10,15)&"%",IF(J12=7,RANDBETWEEN(8,10)&"%",IF(J12=8,RANDBETWEEN(6,8)&"%",IF(J12=9,RANDBETWEEN(4,6)&"%",IF(J12=10,RANDBETWEEN(2,4)&"%",""))))))))))) -> 37% | Q12: =IFERROR(L12*(M12+N12)*O12*P12,RANDBETWEEN(1,2)%*L12*(M12+N12)*O12) -> 13.63025 | R12: =VLOOKUP(D:D,ranking!W:X,2,0) -> 0.6 | S12: =R12*Q12 -> 8.1781498 | T12: 21.448858
A13: Trending Top 10 | B13: ALL INDIA | C13: Netflix | D13: Theatrical Movies | E13: PAID | F13: Movies | G13: Dhurandhar: The Revenge (Raw & Undekha) | H13: Hindi,Kannada,Malayalam,Tamil,Telugu | I13: 46192 | J13: 2 | K13: Action,Crime,Thriller | L13: =VLOOKUP($C13&$E13,'Updated SES'!A:N,14,0) -> 55.4592 | M13: =VLOOKUP($K13,'Genre Penetration'!A:B,2,0)*VLOOKUP($C13&$E13,'Updated SES'!A:I,9,0) -> 0.3528 | N13: =VLOOKUP(K:K,'Genre Penetration'!A:C,3,0)*VLOOKUP($C13&$E13,'Updated SES'!A:J,10,0) -> 0.1428 | O13: =VLOOKUP($B13,'Language Penetration'!$B$1:$BE$14,MATCH('Compile data Working'!$H12,'Language Penetration'!$B$1:$BE$1,0),0) -> #N/A | P13: =IF(ISBLANK(J13),RANDBETWEEN(1,2)&"%",IF(J13=1,RANDBETWEEN(35,40)&"%",IF(J13=2,RANDBETWEEN(30,35)&"%",IF(J13=3,RANDBETWEEN(25,30)&"%",IF(J13=4,RANDBETWEEN(20,25)&"%",IF(J13=5,RANDBETWEEN(15,20)&"%",IF(J13=6,RANDBETWEEN(10,15)&"%",IF(J13=7,RANDBETWEEN(8,10)&"%",IF(J13=8,RANDBETWEEN(6,8)&"%",IF(J13=9,RANDBETWEEN(4,6)&"%",IF(J13=10,RANDBETWEEN(2,4)&"%",""))))))))))) -> 35% | Q13: =IFERROR(L13*(M13+N13)*O13*P13,RANDBETWEEN(1,2)%*L13*(M13+N13)*O13) -> #N/A | R13: =VLOOKUP(D:D,ranking!W:X,2,0) -> 0.7 | S13: =R13*Q13 -> #N/A | T13: 21.295894
A14: Trending Top 10 | B14: ALL INDIA | C14: Netflix | D14: Theatrical Movies | E14: PAID | F14: Movies | G14: Bhooth Bangla | H14: Hindi | I14: 46185 | J14: 1 | K14: Comedy,Horror | L14: =VLOOKUP($C14&$E14,'Updated SES'!A:N,14,0) -> 55.4592 | M14: =VLOOKUP($K14,'Genre Penetration'!A:B,2,0)*VLOOKUP($C14&$E14,'Updated SES'!A:I,9,0) -> 0.2989 | N14: =VLOOKUP(K:K,'Genre Penetration'!A:C,3,0)*VLOOKUP($C14&$E14,'Updated SES'!A:J,10,0) -> 0.1989 | O14: =VLOOKUP($B14,'Language Penetration'!$B$1:$BE$14,MATCH('Compile data Working'!$H42,'Language Penetration'!$B$1:$BE$1,0),0) -> 0.2 | P14: =IF(ISBLANK(J14),RANDBETWEEN(1,2)&"%",IF(J14=1,RANDBETWEEN(35,40)&"%",IF(J14=2,RANDBETWEEN(30,35)&"%",IF(J14=3,RANDBETWEEN(25,30)&"%",IF(J14=4,RANDBETWEEN(20,25)&"%",IF(J14=5,RANDBETWEEN(15,20)&"%",IF(J14=6,RANDBETWEEN(10,15)&"%",IF(J14=7,RANDBETWEEN(8,10)&"%",IF(J14=8,RANDBETWEEN(6,8)&"%",IF(J14=9,RANDBETWEEN(4,6)&"%",IF(J14=10,RANDBETWEEN(2,4)&"%",""))))))))))) -> 37% | Q14: =IFERROR(L14*(M14+N14)*O14*P14,RANDBETWEEN(1,2)%*L14*(M14+N14)*O14) -> 2.0429616 | R14: =VLOOKUP(D:D,ranking!W:X,2,0) -> 0.7 | S14: =R14*Q14 -> 1.4300731 | T14: 19.527626
A15: Trending Top 10 | B15: ALL INDIA | C15: Amazon Prime Video | D15: SVOD Originals Movies | E15: PAID | F15: Movies | G15: Your Fault: London | H15: English,Hindi,Kannada,Malayalam,Tamil,Telugu | I15: 46190 | J15: 5 | K15: Drama,Romance | L15: =VLOOKUP($C15&$E15,'Updated SES'!A:N,14,0) -> 36.49824 | M15: =VLOOKUP($K15,'Genre Penetration'!A:B,2,0)*VLOOKUP($C15&$E15,'Updated SES'!A:I,9,0) -> 0.208 | N15: =VLOOKUP(K:K,'Genre Penetration'!A:C,3,0)*VLOOKUP($C15&$E15,'Updated SES'!A:J,10,0) -> 0.288 | O15: =VLOOKUP($B15,'Language Penetration'!$B$1:$BE$14,MATCH('Compile data Working'!$H8,'Language Penetration'!$B$1:$BE$1,0),0) -> #N/A | P15: =IF(ISBLANK(J15),RANDBETWEEN(1,2)&"%",IF(J15=1,RANDBETWEEN(35,40)&"%",IF(J15=2,RANDBETWEEN(30,35)&"%",IF(J15=3,RANDBETWEEN(25,30)&"%",IF(J15=4,RANDBETWEEN(20,25)&"%",IF(J15=5,RANDBETWEEN(15,20)&"%",IF(J15=6,RANDBETWEEN(10,15)&"%",IF(J15=7,RANDBETWEEN(8,10)&"%",IF(J15=8,RANDBETWEEN(6,8)&"%",IF(J15=9,RANDBETWEEN(4,6)&"%",IF(J15=10,RANDBETWEEN(2,4)&"%",""))))))))))) -> 19% | Q15: =IFERROR(L15*(M15+N15)*O15*P15,RANDBETWEEN(1,2)%*L15*(M15+N15)*O15) -> #N/A | R15: =VLOOKUP(D:D,ranking!W:X,2,0) -> 0.8 | S15: =R15*Q15 -> #N/A | T15: 18.923245
A16: Cott Data Servey | B16: ALL INDIA | C16: JioHotstar | D16: Tv Catch-Up | E16: PAID | F16: Tv catchup | G16: Anupama | H16: Hindi | I16: 44025 | K16: Drama | L16: =VLOOKUP($C16&$E16,'Updated SES'!A:N,14,0) -> 127.11702 | M16: =VLOOKUP($K16,'Genre Penetration'!A:B,2,0)*VLOOKUP($C16&$E16,'Updated SES'!A:I,9,0) -> 0.335 | N16: =VLOOKUP(K:K,'Genre Penetration'!A:C,3,0)*VLOOKUP($C16&$E16,'Updated SES'!A:J,10,0) -> 0.165 | O16: =VLOOKUP($B16,'Language Penetration'!$B$1:$BE$14,MATCH('Compile data Working'!$H17,'Language Penetration'!$B$1:$BE$1,0),0) -> 0.4 | P16: =IF(ISBLANK(J16),RANDBETWEEN(1,2)&"%",IF(J16=1,RANDBETWEEN(35,40)&"%",IF(J16=2,RANDBETWEEN(30,35)&"%",IF(J16=3,RANDBETWEEN(25,30)&"%",IF(J16=4,RANDBETWEEN(20,25)&"%",IF(J16=5,RANDBETWEEN(15,20)&"%",IF(J16=6,RANDBETWEEN(10,15)&"%",IF(J16=7,RANDBETWEEN(8,10)&"%",IF(J16=8,RANDBETWEEN(6,8)&"%",IF(J16=9,RANDBETWEEN(4,6)&"%",IF(J16=10,RANDBETWEEN(2,4)&"%",""))))))))))) -> 1% | Q16: =IFERROR(L16*(M16+N16)*O16*P16,RANDBETWEEN(1,2)%*L16*(M16+N16)*O16) -> 0.25423404 | R16: =VLOOKUP(D:D,ranking!W:X,2,0) -> 0.3 | S16: =R16*Q16 -> 0.076270212 | T16: 18.374668
A17: Trending Top 10 | B17: ALL INDIA | C17: Amazon Prime Video | D17: Svod Originals Shows | E17: PAID | F17: Shows | G17: From S4 | H17: English,Hindi | I17: 46131 | J17: 9 | K17: Drama,Horror | L17: =VLOOKUP($C17&$E17,'Updated SES'!A:N,14,0) -> 36.49824 | M17: =VLOOKUP($K17,'Genre Penetration'!A:B,2,0)*VLOOKUP($C17&$E17,'Updated SES'!A:I,9,0) -> 0.286 | N17: =VLOOKUP(K:K,'Genre Penetration'!A:C,3,0)*VLOOKUP($C17&$E17,'Updated SES'!A:J,10,0) -> 0.216 | O17: =VLOOKUP($B17,'Language Penetration'!$B$1:$BE$14,MATCH('Compile data Working'!$H18,'Language Penetration'!$B$1:$BE$1,0),0) -> 0.6 | P17: =IF(ISBLANK(J17),RANDBETWEEN(1,2)&"%",IF(J17=1,RANDBETWEEN(35,40)&"%",IF(J17=2,RANDBETWEEN(30,35)&"%",IF(J17=3,RANDBETWEEN(25,30)&"%",IF(J17=4,RANDBETWEEN(20,25)&"%",IF(J17=5,RANDBETWEEN(15,20)&"%",IF(J17=6,RANDBETWEEN(10,15)&"%",IF(J17=7,RANDBETWEEN(8,10)&"%",IF(J17=8,RANDBETWEEN(6,8)&"%",IF(J17=9,RANDBETWEEN(4,6)&"%",IF(J17=10,RANDBETWEEN(2,4)&"%",""))))))))))) -> 4% | Q17: =IFERROR(L17*(M17+N17)*O17*P17,RANDBETWEEN(1,2)%*L17*(M17+N17)*O17) -> 0.4397308 | R17: =VLOOKUP(D:D,ranking!W:X,2,0) -> 0.6 | S17: =R17*Q17 -> 0.26383848 | T17: 17.994455
A18: Trending Top 10 | B18: ALL INDIA | C18: Amazon Prime Video | D18: Svod Originals Shows | E18: PAID | F18: Shows | G18: The Pyramid Scheme | H18: Hindi | I18: 46178 | J18: 6 | K18: Comedy,Drama | L18: =VLOOKUP($C18&$E18,'Updated SES'!A:N,14,0) -> 36.49824 | M18: =VLOOKUP($K18,'Genre Penetration'!A:B,2,0)*VLOOKUP($C18&$E18,'Updated SES'!A:I,9,0) -> 0.2444 | N18: =VLOOKUP(K:K,'Genre Penetration'!A:C,3,0)*VLOOKUP($C18&$E18,'Updated SES'!A:J,10,0) -> 0.2544 | O18: =VLOOKUP($B18,'Language Penetration'!$B$1:$BE$14,MATCH('Compile data Working'!$H20,'Language Penetration'!$B$1:$BE$1,0),0) -> 0.6 | P18: =IF(ISBLANK(J18),RANDBETWEEN(1,2)&"%",IF(J18=1,RANDBETWEEN(35,40)&"%",IF(J18=2,RANDBETWEEN(30,35)&"%",IF(J18=3,RANDBETWEEN(25,30)&"%",IF(J18=4,RANDBETWEEN(20,25)&"%",IF(J18=5,RANDBETWEEN(15,20)&"%",IF(J18=6,RANDBETWEEN(10,15)&"%",IF(J18=7,RANDBETWEEN(8,10)&"%",IF(J18=8,RANDBETWEEN(6,8)&"%",IF(J18=9,RANDBETWEEN(4,6)&"%",IF(J18=10,RANDBETWEEN(2,4)&"%",""))))))))))) -> 10% | Q18: =IFERROR(L18*(M18+N18)*O18*P18,RANDBETWEEN(1,2)%*L18*(M18+N18)*O18) -> 1.0923193 | R18: =VLOOKUP(D:D,ranking!W:X,2,0) -> 0.6 | S18: =R18*Q18 -> 0.6553916 | T18: 17.507986
A19: Trending Top 10 | B19: ALL INDIA | C19: Amazon Prime Video | D19: Theatrical Movies | E19: PAID | F19: Movies | G19: Drishyam 3 | H19: Kannada,Malayalam,Tamil,Telugu | I19: 46191 | J19: 2 | K19: Crime,Drama,Thriller | L19: =VLOOKUP($C19&$E19,'Updated SES'!A:N,14,0) -> 36.49824 | M19: =VLOOKUP($K19,'Genre Penetration'!A:B,2,0)*VLOOKUP($C19&$E19,'Updated SES'!A:I,9,0) -> 0.3744 | N19: =VLOOKUP(K:K,'Genre Penetration'!A:C,3,0)*VLOOKUP($C19&$E19,'Updated SES'!A:J,10,0) -> 0.1344 | O19: =VLOOKUP($B19,'Language Penetration'!$B$1:$BE$14,MATCH('Compile data Working'!$H25,'Language Penetration'!$B$1:$BE$1,0),0) -> 0.2 | P19: =IF(ISBLANK(J19),RANDBETWEEN(1,2)&"%",IF(J19=1,RANDBETWEEN(35,40)&"%",IF(J19=2,RANDBETWEEN(30,35)&"%",IF(J19=3,RANDBETWEEN(25,30)&"%",IF(J19=4,RANDBETWEEN(20,25)&"%",IF(J19=5,RANDBETWEEN(15,20)&"%",IF(J19=6,RANDBETWEEN(10,15)&"%",IF(J19=7,RANDBETWEEN(8,10)&"%",IF(J19=8,RANDBETWEEN(6,8)&"%",IF(J19=9,RANDBETWEEN(4,6)&"%",IF(J19=10,RANDBETWEEN(2,4)&"%",""))))))))))) -> 35% | Q19: =IFERROR(L19*(M19+N19)*O19*P19,RANDBETWEEN(1,2)%*L19*(M19+N19)*O19) -> 1.2999213 | R19: =VLOOKUP(D:D,ranking!W:X,2,0) -> 0.7 | S19: =R19*Q19 -> 0.90994492 | T19: 16.858131
A20: Trending Top 10 | B20: ALL INDIA | C20: Amazon Prime Video | D20: Theatrical Movies | E20: PAID | F20: Movies | G20: Mareechika | H20: Hindi | I20: 46192 | J20: 7 | K20: Drama,Romance,Thriller | L20: =VLOOKUP($C20&$E20,'Updated SES'!A:N,14,0) -> 36.49824 | M20: =VLOOKUP($K20,'Genre Penetration'!A:B,2,0)*VLOOKUP($C20&$E20,'Updated SES'!A:I,9,0) -> 0.208 | N20: =VLOOKUP(K:K,'Genre Penetration'!A:C,3,0)*VLOOKUP($C20&$E20,'Updated SES'!A:J,10,0) -> 0.288 | O20: =VLOOKUP($B20,'Language Penetration'!$B$1:$BE$14,MATCH('Compile data Working'!$H26,'Language Penetration'!$B$1:$BE$1,0),0) -> 0.6 | P20: =IF(ISBLANK(J20),RANDBETWEEN(1,2)&"%",IF(J20=1,RANDBETWEEN(35,40)&"%",IF(J20=2,RANDBETWEEN(30,35)&"%",IF(J20=3,RANDBETWEEN(25,30)&"%",IF(J20=4,RANDBETWEEN(20,25)&"%",IF(J20=5,RANDBETWEEN(15,20)&"%",IF(J20=6,RANDBETWEEN(10,15)&"%",IF(J20=7,RANDBETWEEN(8,10)&"%",IF(J20=8,RANDBETWEEN(6,8)&"%",IF(J20=9,RANDBETWEEN(4,6)&"%",IF(J20=10,RANDBETWEEN(2,4)&"%",""))))))))))) -> 10% | Q20: =IFERROR(L20*(M20+N20)*O20*P20,RANDBETWEEN(1,2)%*L20*(M20+N20)*O20) -> 1.0861876 | R20: =VLOOKUP(D:D,ranking!W:X,2,0) -> 0.7 | S20: =R20*Q20 -> 0.76033134 | T20: 16.624409
A21: Trending Top 10 | B21: ALL INDIA | C21: Netflix | D21: Theatrical Movies | E21: PAID | F21: Movies | G21: 29 | H21: Hindi,Kannada,Malayalam,Tamil,Telugu | I21: 46178 | J21: 5 | K21: Comedy,Drama,Romance | L21: =VLOOKUP($C21&$E21,'Updated SES'!A:N,14,0) -> 55.4592 | M21: =VLOOKUP($K21,'Genre Penetration'!A:B,2,0)*VLOOKUP($C21&$E21,'Updated SES'!A:I,9,0) -> 0.1813 | N21: =VLOOKUP(K:K,'Genre Penetration'!A:C,3,0)*VLOOKUP($C21&$E21,'Updated SES'!A:J,10,0) -> 0.3213 | O21: =VLOOKUP($B21,'Language Penetration'!$B$1:$BE$14,MATCH('Compile data Working'!$H27,'Language Penetration'!$B$1:$BE$1,0),0) -> 0.2 | P21: =IF(ISBLANK(J21),RANDBETWEEN(1,2)&"%",IF(J21=1,RANDBETWEEN(35,40)&"%",IF(J21=2,RANDBETWEEN(30,35)&"%",IF(J21=3,RANDBETWEEN(25,30)&"%",IF(J21=4,RANDBETWEEN(20,25)&"%",IF(J21=5,RANDBETWEEN(15,20)&"%",IF(J21=6,RANDBETWEEN(10,15)&"%",IF(J21=7,RANDBETWEEN(8,10)&"%",IF(J21=8,RANDBETWEEN(6,8)&"%",IF(J21=9,RANDBETWEEN(4,6)&"%",IF(J21=10,RANDBETWEEN(2,4)&"%",""))))))))))) -> 15% | Q21: =IFERROR(L21*(M21+N21)*O21*P21,RANDBETWEEN(1,2)%*L21*(M21+N21)*O21) -> 0.83621382 | R21: =VLOOKUP(D:D,ranking!W:X,2,0) -> 0.7 | S21: =R21*Q21 -> 0.58534967 | T21: 16.496989
A22: WK-24'2026 | B22: ALL INDIA | C22: Netflix | D22: SVOD Originals Shows | E22: PAID | F22: Shows | G22: My Love Story With Yamada-kun at Lv999 | H22: English | I22: 46188 | K22: Animation,Comedy,Romance | L22: =VLOOKUP($C22&$E22,'Updated SES'!A:N,14,0) -> 55.4592 | M22: =VLOOKUP($K22,'Genre Penetration'!A:B,2,0)*VLOOKUP($C22&$E22,'Updated SES'!A:I,9,0) -> 0.2695 | N22: =VLOOKUP(K:K,'Genre Penetration'!A:C,3,0)*VLOOKUP($C22&$E22,'Updated SES'!A:J,10,0) -> 0.2295 | O22: =VLOOKUP($B22,'Language Penetration'!$B$1:$BE$14,MATCH('Compile data Working'!$H28,'Language Penetration'!$B$1:$BE$1,0),0) -> 0.17714286 | P22: =IF(ISBLANK(J22),RANDBETWEEN(1,2)&"%",IF(J22=1,RANDBETWEEN(35,40)&"%",IF(J22=2,RANDBETWEEN(30,35)&"%",IF(J22=3,RANDBETWEEN(25,30)&"%",IF(J22=4,RANDBETWEEN(20,25)&"%",IF(J22=5,RANDBETWEEN(15,20)&"%",IF(J22=6,RANDBETWEEN(10,15)&"%",IF(J22=7,RANDBETWEEN(8,10)&"%",IF(J22=8,RANDBETWEEN(6,8)&"%",IF(J22=9,RANDBETWEEN(4,6)&"%",IF(J22=10,RANDBETWEEN(2,4)&"%",""))))))))))) -> 2% | Q22: =IFERROR(L22*(M22+N22)*O22*P22,RANDBETWEEN(1,2)%*L22*(M22+N22)*O22) -> 0.098045527 | R22: =VLOOKUP(D:D,ranking!W:X,2,0) -> 0.6 | S22: =R22*Q22 -> 0.058827316 | T22: 16.496989
A23: WK-24'2026 | B23: ALL INDIA | C23: JioHotstar | D23: Theatrical Movies | E23: PAID | F23: Movies | G23: Kenatha Kanom | H23: Bengali,Hindi,Kannada,Malayalam,Marathi,Tamil,Telugu | I23: 46189 | K23: Comedy,Drama | L23: =VLOOKUP($C23&$E23,'Updated SES'!A:N,14,0) -> 127.11702 | M23: =VLOOKUP($K23,'Genre Penetration'!A:B,2,0)*VLOOKUP($C23&$E23,'Updated SES'!A:I,9,0) -> 0.3149 | N23: =VLOOKUP(K:K,'Genre Penetration'!A:C,3,0)*VLOOKUP($C23&$E23,'Updated SES'!A:J,10,0) -> 0.1749 | O23: =VLOOKUP($B23,'Language Penetration'!$B$1:$BE$14,MATCH('Compile data Working'!$H29,'Language Penetration'!$B$1:$BE$1,0),0) -> 0.204 | P23: =IF(ISBLANK(J23),RANDBETWEEN(1,2)&"%",IF(J23=1,RANDBETWEEN(35,40)&"%",IF(J23=2,RANDBETWEEN(30,35)&"%",IF(J23=3,RANDBETWEEN(25,30)&"%",IF(J23=4,RANDBETWEEN(20,25)&"%",IF(J23=5,RANDBETWEEN(15,20)&"%",IF(J23=6,RANDBETWEEN(10,15)&"%",IF(J23=7,RANDBETWEEN(8,10)&"%",IF(J23=8,RANDBETWEEN(6,8)&"%",IF(J23=9,RANDBETWEEN(4,6)&"%",IF(J23=10,RANDBETWEEN(2,4)&"%",""))))))))))) -> 1% | Q23: =IFERROR(L23*(M23+N23)*O23*P23,RANDBETWEEN(1,2)%*L23*(M23+N23)*O23) -> 0.12701431 | R23: =VLOOKUP(D:D,ranking!W:X,2,0) -> 0.7 | S23: =R23*Q23 -> 0.088910017 | T23: 16.21064
A24: Trending Top 10 | B24: ALL INDIA | C24: Netflix | D24: Svod Originals Shows | E24: PAID | F24: Shows | G24: Teach You a Lesson | H24: English,Hindi,Tamil,Telugu | I24: 46178 | J24: 1 | K24: Action,Drama | L24: =VLOOKUP($C24&$E24,'Updated SES'!A:N,14,0) -> 55.4592 | M24: =VLOOKUP($K24,'Genre Penetration'!A:B,2,0)*VLOOKUP($C24&$E24,'Updated SES'!A:I,9,0) -> 0.2597 | N24: =VLOOKUP(K:K,'Genre Penetration'!A:C,3,0)*VLOOKUP($C24&$E24,'Updated SES'!A:J,10,0) -> 0.2397 | O24: =VLOOKUP($B24,'Language Penetration'!$B$1:$BE$14,MATCH('Compile data Working'!$H30,'Language Penetration'!$B$1:$BE$1,0),0) -> 0.2625 | P24: =IF(ISBLANK(J24),RANDBETWEEN(1,2)&"%",IF(J24=1,RANDBETWEEN(35,40)&"%",IF(J24=2,RANDBETWEEN(30,35)&"%",IF(J24=3,RANDBETWEEN(25,30)&"%",IF(J24=4,RANDBETWEEN(20,25)&"%",IF(J24=5,RANDBETWEEN(15,20)&"%",IF(J24=6,RANDBETWEEN(10,15)&"%",IF(J24=7,RANDBETWEEN(8,10)&"%",IF(J24=8,RANDBETWEEN(6,8)&"%",IF(J24=9,RANDBETWEEN(4,6)&"%",IF(J24=10,RANDBETWEEN(2,4)&"%",""))))))))))) -> 36% | Q24: =IFERROR(L24*(M24+N24)*O24*P24,RANDBETWEEN(1,2)%*L24*(M24+N24)*O24) -> 2.6173027 | R24: =VLOOKUP(D:D,ranking!W:X,2,0) -> 0.6 | S24: =R24*Q24 -> 1.5703816 | T24: 16.16119
A25: WK-24'2026 | B25: ALL INDIA | C25: Netflix | D25: SVOD Originals Shows | E25: PAID | F25: Shows | G25: Horimiya Season 2 | H25: English | I25: 46188 | K25: Animation,Drama,Romance | L25: =VLOOKUP($C25&$E25,'Updated SES'!A:N,14,0) -> 55.4592 | M25: =VLOOKUP($K25,'Genre Penetration'!A:B,2,0)*VLOOKUP($C25&$E25,'Updated SES'!A:I,9,0) -> 0.2695 | N25: =VLOOKUP(K:K,'Genre Penetration'!A:C,3,0)*VLOOKUP($C25&$E25,'Updated SES'!A:J,10,0) -> 0.2295 | O25: =VLOOKUP($B25,'Language Penetration'!$B$1:$BE$14,MATCH('Compile data Working'!$H31,'Language Penetration'!$B$1:$BE$1,0),0) -> 0.6 | P25: =IF(ISBLANK(J25),RANDBETWEEN(1,2)&"%",IF(J25=1,RANDBETWEEN(35,40)&"%",IF(J25=2,RANDBETWEEN(30,35)&"%",IF(J25=3,RANDBETWEEN(25,30)&"%",IF(J25=4,RANDBETWEEN(20,25)&"%",IF(J25=5,RANDBETWEEN(15,20)&"%",IF(J25=6,RANDBETWEEN(10,15)&"%",IF(J25=7,RANDBETWEEN(8,10)&"%",IF(J25=8,RANDBETWEEN(6,8)&"%",IF(J25=9,RANDBETWEEN(4,6)&"%",IF(J25=10,RANDBETWEEN(2,4)&"%",""))))))))))) -> 1% | Q25: =IFERROR(L25*(M25+N25)*O25*P25,RANDBETWEEN(1,2)%*L25*(M25+N25)*O25) -> 0.16604484 | R25: =VLOOKUP(D:D,ranking!W:X,2,0) -> 0.6 | S25: =R25*Q25 -> 0.099626907 | T25: 15.934591
A26: Trending Top 10 | B26: ALL INDIA | C26: Amazon Prime Video | D26: Theatrical Movies | E26: PAID | F26: Movies | G26: Dacoit | H26: Hindi | I26: 46178 | J26: 10 | K26: Action,Drama,Thriller | L26: =VLOOKUP($C26&$E26,'Updated SES'!A:N,14,0) -> 36.49824 | M26: =VLOOKUP($K26,'Genre Penetration'!A:B,2,0)*VLOOKUP($C26&$E26,'Updated SES'!A:I,9,0) -> 0.3536 | N26: =VLOOKUP(K:K,'Genre Penetration'!A:C,3,0)*VLOOKUP($C26&$E26,'Updated SES'!A:J,10,0) -> 0.1536 | O26: =VLOOKUP($B26,'Language Penetration'!$B$1:$BE$14,MATCH('Compile data Working'!$H33,'Language Penetration'!$B$1:$BE$1,0),0) -> 0.2 | P26: =IF(ISBLANK(J26),RANDBETWEEN(1,2)&"%",IF(J26=1,RANDBETWEEN(35,40)&"%",IF(J26=2,RANDBETWEEN(30,35)&"%",IF(J26=3,RANDBETWEEN(25,30)&"%",IF(J26=4,RANDBETWEEN(20,25)&"%",IF(J26=5,RANDBETWEEN(15,20)&"%",IF(J26=6,RANDBETWEEN(10,15)&"%",IF(J26=7,RANDBETWEEN(8,10)&"%",IF(J26=8,RANDBETWEEN(6,8)&"%",IF(J26=9,RANDBETWEEN(4,6)&"%",IF(J26=10,RANDBETWEEN(2,4)&"%",""))))))))))) -> 3% | Q26: =IFERROR(L26*(M26+N26)*O26*P26,RANDBETWEEN(1,2)%*L26*(M26+N26)*O26) -> 0.11107144 | R26: =VLOOKUP(D:D,ranking!W:X,2,0) -> 0.7 | S26: =R26*Q26 -> 0.077750011 | T26: 15.240957
A27: WK-24'2026 | B27: ALL INDIA | C27: JioHotstar | D27: SVOD Originals Shows | E27: PAID | F27: Shows | G27: Harry Potter: The Official Film Podcast | H27: English | I27: 46190 | K27: Talk Show | L27: =VLOOKUP($C27&$E27,'Updated SES'!A:N,14,0) -> 127.11702 | M27: =VLOOKUP($K27,'Genre Penetration'!A:B,2,0)*VLOOKUP($C27&$E27,'Updated SES'!A:I,9,0) -> 0.335 | N27: =VLOOKUP(K:K,'Genre Penetration'!A:C,3,0)*VLOOKUP($C27&$E27,'Updated SES'!A:J,10,0) -> 0.165 | O27: =VLOOKUP($B27,'Language Penetration'!$B$1:$BE$14,MATCH('Compile data Working'!$H34,'Language Penetration'!$B$1:$BE$1,0),0) -> 0.2 | P27: =IF(ISBLANK(J27),RANDBETWEEN(1,2)&"%",IF(J27=1,RANDBETWEEN(35,40)&"%",IF(J27=2,RANDBETWEEN(30,35)&"%",IF(J27=3,RANDBETWEEN(25,30)&"%",IF(J27=4,RANDBETWEEN(20,25)&"%",IF(J27=5,RANDBETWEEN(15,20)&"%",IF(J27=6,RANDBETWEEN(10,15)&"%",IF(J27=7,RANDBETWEEN(8,10)&"%",IF(J27=8,RANDBETWEEN(6,8)&"%",IF(J27=9,RANDBETWEEN(4,6)&"%",IF(J27=10,RANDBETWEEN(2,4)&"%",""))))))))))) -> 2% | Q27: =IFERROR(L27*(M27+N27)*O27*P27,RANDBETWEEN(1,2)%*L27*(M27+N27)*O27) -> 0.25423404 | R27: =VLOOKUP(D:D,ranking!W:X,2,0) -> 0.6 | S27: =R27*Q27 -> 0.15254042 | T27: 14.736946
A28: WK-24'2026 | B28: ALL INDIA | C28: JioHotstar | D28: SVOD Originals Shows | E28: PAID | F28: Shows | G28: Save the Tigers Season 3 | H28: Bengali,Hindi,Kannada,Malayalam,Marathi,Tamil,Telugu | I28: 46192 | K28: Comedy,Drama,Thriller | L28: =VLOOKUP($C28&$E28,'Updated SES'!A:N,14,0) -> 127.11702 | M28: =VLOOKUP($K28,'Genre Penetration'!A:B,2,0)*VLOOKUP($C28&$E28,'Updated SES'!A:I,9,0) -> 0.3886 | N28: =VLOOKUP(K:K,'Genre Penetration'!A:C,3,0)*VLOOKUP($C28&$E28,'Updated SES'!A:J,10,0) -> 0.1386 | O28: =VLOOKUP($B28,'Language Penetration'!$B$1:$BE$14,MATCH('Compile data Working'!$H35,'Language Penetration'!$B$1:$BE$1,0),0) -> 0.2625 | P28: =IF(ISBLANK(J28),RANDBETWEEN(1,2)&"%",IF(J28=1,RANDBETWEEN(35,40)&"%",IF(J28=2,RANDBETWEEN(30,35)&"%",IF(J28=3,RANDBETWEEN(25,30)&"%",IF(J28=4,RANDBETWEEN(20,25)&"%",IF(J28=5,RANDBETWEEN(15,20)&"%",IF(J28=6,RANDBETWEEN(10,15)&"%",IF(J28=7,RANDBETWEEN(8,10)&"%",IF(J28=8,RANDBETWEEN(6,8)&"%",IF(J28=9,RANDBETWEEN(4,6)&"%",IF(J28=10,RANDBETWEEN(2,4)&"%",""))))))))))) -> 1% | Q28: =IFERROR(L28*(M28+N28)*O28*P28,RANDBETWEEN(1,2)%*L28*(M28+N28)*O28) -> 0.17591724 | R28: =VLOOKUP(D:D,ranking!W:X,2,0) -> 0.6 | S28: =R28*Q28 -> 0.10555035 | T28: 14.589576
A29: Trending Top 10 | B29: ALL INDIA | C29: JioHotstar | D29: Theatrical Movies | E29: PAID | F29: Movies | G29: Dridam | H29: Hindi,Kannada,Malayalam,Tamil,Telugu | I29: 46185 | J29: 5 | K29: Crime,Drama,Thriller | L29: =VLOOKUP($C29&$E29,'Updated SES'!A:N,14,0) -> 127.11702 | M29: =VLOOKUP($K29,'Genre Penetration'!A:B,2,0)*VLOOKUP($C29&$E29,'Updated SES'!A:I,9,0) -> 0.4824 | N29: =VLOOKUP(K:K,'Genre Penetration'!A:C,3,0)*VLOOKUP($C29&$E29,'Updated SES'!A:J,10,0) -> 0.0924 | O29: =VLOOKUP($B29,'Language Penetration'!$B$1:$BE$14,MATCH('Compile data Working'!$H36,'Language Penetration'!$B$1:$BE$1,0),0) -> 0.28333333 | P29: =IF(ISBLANK(J29),RANDBETWEEN(1,2)&"%",IF(J29=1,RANDBETWEEN(35,40)&"%",IF(J29=2,RANDBETWEEN(30,35)&"%",IF(J29=3,RANDBETWEEN(25,30)&"%",IF(J29=4,RANDBETWEEN(20,25)&"%",IF(J29=5,RANDBETWEEN(15,20)&"%",IF(J29=6,RANDBETWEEN(10,15)&"%",IF(J29=7,RANDBETWEEN(8,10)&"%",IF(J29=8,RANDBETWEEN(6,8)&"%",IF(J29=9,RANDBETWEEN(4,6)&"%",IF(J29=10,RANDBETWEEN(2,4)&"%",""))))))))))) -> 19% | Q29: =IFERROR(L29*(M29+N29)*O29*P29,RANDBETWEEN(1,2)%*L29*(M29+N29)*O29) -> 3.9334328 | R29: =VLOOKUP(D:D,ranking!W:X,2,0) -> 0.7 | S29: =R29*Q29 -> 2.753403 | T29: 14.533046
A30: Trending Top 10 | B30: ALL INDIA | C30: Netflix | D30: Theatrical Movies | E30: PAID | F30: Movies | G30: Maa Behen | H30: English,Hindi,Tamil,Telugu | I30: 46177 | J30: 3 | K30: Comedy,Crime,Drama | L30: =VLOOKUP($C30&$E30,'Updated SES'!A:N,14,0) -> 55.4592 | M30: =VLOOKUP($K30,'Genre Penetration'!A:B,2,0)*VLOOKUP($C30&$E30,'Updated SES'!A:I,9,0) -> 0.2744 | N30: =VLOOKUP(K:K,'Genre Penetration'!A:C,3,0)*VLOOKUP($C30&$E30,'Updated SES'!A:J,10,0) -> 0.2244 | O30: =VLOOKUP($B30,'Language Penetration'!$B$1:$BE$14,MATCH('Compile data Working'!$H37,'Language Penetration'!$B$1:$BE$1,0),0) -> 0.6 | P30: =IF(ISBLANK(J30),RANDBETWEEN(1,2)&"%",IF(J30=1,RANDBETWEEN(35,40)&"%",IF(J30=2,RANDBETWEEN(30,35)&"%",IF(J30=3,RANDBETWEEN(25,30)&"%",IF(J30=4,RANDBETWEEN(20,25)&"%",IF(J30=5,RANDBETWEEN(15,20)&"%",IF(J30=6,RANDBETWEEN(10,15)&"%",IF(J30=7,RANDBETWEEN(8,10)&"%",IF(J30=8,RANDBETWEEN(6,8)&"%",IF(J30=9,RANDBETWEEN(4,6)&"%",IF(J30=10,RANDBETWEEN(2,4)&"%",""))))))))))) -> 29% | Q30: =IFERROR(L30*(M30+N30)*O30*P30,RANDBETWEEN(1,2)%*L30*(M30+N30)*O30) -> 4.8133705 | R30: =VLOOKUP(D:D,ranking!W:X,2,0) -> 0.7 | S30: =R30*Q30 -> 3.3693594 | T30: 14.305931
A31: Trending Top 10 | B31: ALL INDIA | C31: Sony Liv | D31: Svod Originals Shows | E31: PAID | F31: Shows | G31: Gullak Season 5 | H31: Hindi | I31: 46178 | J31: 6 | K31: Comedy,Drama | L31: =VLOOKUP($C31&$E31,'Updated SES'!A:N,14,0) -> 21.68204 | M31: =VLOOKUP($K31,'Genre Penetration'!A:B,2,0)*VLOOKUP($C31&$E31,'Updated SES'!A:I,9,0) -> 0.3055 | N31: =VLOOKUP(K:K,'Genre Penetration'!A:C,3,0)*VLOOKUP($C31&$E31,'Updated SES'!A:J,10,0) -> 0.1855 | O31: =VLOOKUP($B31,'Language Penetration'!$B$1:$BE$14,MATCH('Compile data Working'!$H39,'Language Penetration'!$B$1:$BE$1,0),0) -> 0.2625 | P31: =IF(ISBLANK(J31),RANDBETWEEN(1,2)&"%",IF(J31=1,RANDBETWEEN(35,40)&"%",IF(J31=2,RANDBETWEEN(30,35)&"%",IF(J31=3,RANDBETWEEN(25,30)&"%",IF(J31=4,RANDBETWEEN(20,25)&"%",IF(J31=5,RANDBETWEEN(15,20)&"%",IF(J31=6,RANDBETWEEN(10,15)&"%",IF(J31=7,RANDBETWEEN(8,10)&"%",IF(J31=8,RANDBETWEEN(6,8)&"%",IF(J31=9,RANDBETWEEN(4,6)&"%",IF(J31=10,RANDBETWEEN(2,4)&"%",""))))))))))) -> 13% | Q31: =IFERROR(L31*(M31+N31)*O31*P31,RANDBETWEEN(1,2)%*L31*(M31+N31)*O31) -> 0.36329071 | R31: =VLOOKUP(D:D,ranking!W:X,2,0) -> 0.6 | S31: =R31*Q31 -> 0.21797443 | T31: 13.925057
A32: WK-24'2026 | B32: ALL INDIA | C32: Netflix | D32: SVOD Originals Shows | E32: PAID | F32: Shows | G32: Oasis | H32: English,Hindi,Tamil,Telugu | I32: 46192 | K32: Crime,Drama,Mystery | L32: =VLOOKUP($C32&$E32,'Updated SES'!A:N,14,0) -> 55.4592 | M32: =VLOOKUP($K32,'Genre Penetration'!A:B,2,0)*VLOOKUP($C32&$E32,'Updated SES'!A:I,9,0) -> 0.294 | N32: =VLOOKUP(K:K,'Genre Penetration'!A:C,3,0)*VLOOKUP($C32&$E32,'Updated SES'!A:J,10,0) -> 0.204 | O32: =VLOOKUP($B32,'Language Penetration'!$B$1:$BE$14,MATCH('Compile data Working'!$H19,'Language Penetration'!$B$1:$BE$1,0),0) -> 0.105 | P32: =IF(ISBLANK(J32),RANDBETWEEN(1,2)&"%",IF(J32=1,RANDBETWEEN(35,40)&"%",IF(J32=2,RANDBETWEEN(30,35)&"%",IF(J32=3,RANDBETWEEN(25,30)&"%",IF(J32=4,RANDBETWEEN(20,25)&"%",IF(J32=5,RANDBETWEEN(15,20)&"%",IF(J32=6,RANDBETWEEN(10,15)&"%",IF(J32=7,RANDBETWEEN(8,10)&"%",IF(J32=8,RANDBETWEEN(6,8)&"%",IF(J32=9,RANDBETWEEN(4,6)&"%",IF(J32=10,RANDBETWEEN(2,4)&"%",""))))))))))) -> 1% | Q32: =IFERROR(L32*(M32+N32)*O32*P32,RANDBETWEEN(1,2)%*L32*(M32+N32)*O32) -> 0.028999616 | R32: =VLOOKUP(D:D,ranking!W:X,2,0) -> 0.6 | S32: =R32*Q32 -> 0.017399769 | T32: 13.809249
A33: WK-24'2026 | B33: ALL INDIA | C33: Amazon Prime Video | D33: Theatrical Movies | E33: PAID | F33: Movies | G33: A Snapshot of Forever | H33: English | I33: 46190 | K33: Comedy,Romance | L33: =VLOOKUP($C33&$E33,'Updated SES'!A:N,14,0) -> 36.49824 | M33: =VLOOKUP($K33,'Genre Penetration'!A:B,2,0)*VLOOKUP($C33&$E33,'Updated SES'!A:I,9,0) -> 0.156 | N33: =VLOOKUP(K:K,'Genre Penetration'!A:C,3,0)*VLOOKUP($C33&$E33,'Updated SES'!A:J,10,0) -> 0.336 | O33: =VLOOKUP($B33,'Language Penetration'!$B$1:$BE$14,MATCH('Compile data Working'!$H40,'Language Penetration'!$B$1:$BE$1,0),0) -> 0.204 | P33: =IF(ISBLANK(J33),RANDBETWEEN(1,2)&"%",IF(J33=1,RANDBETWEEN(35,40)&"%",IF(J33=2,RANDBETWEEN(30,35)&"%",IF(J33=3,RANDBETWEEN(25,30)&"%",IF(J33=4,RANDBETWEEN(20,25)&"%",IF(J33=5,RANDBETWEEN(15,20)&"%",IF(J33=6,RANDBETWEEN(10,15)&"%",IF(J33=7,RANDBETWEEN(8,10)&"%",IF(J33=8,RANDBETWEEN(6,8)&"%",IF(J33=9,RANDBETWEEN(4,6)&"%",IF(J33=10,RANDBETWEEN(2,4)&"%",""))))))))))) -> 1% | Q33: =IFERROR(L33*(M33+N33)*O33*P33,RANDBETWEEN(1,2)%*L33*(M33+N33)*O33) -> 0.036632554 | R33: =VLOOKUP(D:D,ranking!W:X,2,0) -> 0.7 | S33: =R33*Q33 -> 0.025642787 | T33: 13.793016
A34: WK-24'2026 | B34: ALL INDIA | C34: JioHotstar | D34: SVOD Originals Movies | E34: PAID | F34: Movies | G34: Never Change! | H34: English | I34: 46190 | K34: Comedy | L34: =VLOOKUP($C34&$E34,'Updated SES'!A:N,14,0) -> 127.11702 | M34: =VLOOKUP($K34,'Genre Penetration'!A:B,2,0)*VLOOKUP($C34&$E34,'Updated SES'!A:I,9,0) -> 0.3015 | N34: =VLOOKUP(K:K,'Genre Penetration'!A:C,3,0)*VLOOKUP($C34&$E34,'Updated SES'!A:J,10,0) -> 0.1815 | O34: =VLOOKUP($B34,'Language Penetration'!$B$1:$BE$14,MATCH('Compile data Working'!$H41,'Language Penetration'!$B$1:$BE$1,0),0) -> 0.2 | P34: =IF(ISBLANK(J34),RANDBETWEEN(1,2)&"%",IF(J34=1,RANDBETWEEN(35,40)&"%",IF(J34=2,RANDBETWEEN(30,35)&"%",IF(J34=3,RANDBETWEEN(25,30)&"%",IF(J34=4,RANDBETWEEN(20,25)&"%",IF(J34=5,RANDBETWEEN(15,20)&"%",IF(J34=6,RANDBETWEEN(10,15)&"%",IF(J34=7,RANDBETWEEN(8,10)&"%",IF(J34=8,RANDBETWEEN(6,8)&"%",IF(J34=9,RANDBETWEEN(4,6)&"%",IF(J34=10,RANDBETWEEN(2,4)&"%",""))))))))))) -> 2% | Q34: =IFERROR(L34*(M34+N34)*O34*P34,RANDBETWEEN(1,2)%*L34*(M34+N34)*O34) -> 0.24559008 | R34: =VLOOKUP(D:D,ranking!W:X,2,0) -> 0.8 | S34: =R34*Q34 -> 0.19647207 | T34: 13.736946
A35: Trending Top 10 | B35: ALL INDIA | C35: Netflix | D35: SVOD Originals Movies | E35: PAID | F35: Movies | G35: Voicemails for Isabelle | H35: English,Hindi,Tamil,Telugu | I35: 46192 | J35: 6 | K35: Comedy,Drama,Romance | L35: =VLOOKUP($C35&$E35,'Updated SES'!A:N,14,0) -> 55.4592 | M35: =VLOOKUP($K35,'Genre Penetration'!A:B,2,0)*VLOOKUP($C35&$E35,'Updated SES'!A:I,9,0) -> 0.1813 | N35: =VLOOKUP(K:K,'Genre Penetration'!A:C,3,0)*VLOOKUP($C35&$E35,'Updated SES'!A:J,10,0) -> 0.3213 | O35: =VLOOKUP($B35,'Language Penetration'!$B$1:$BE$14,MATCH('Compile data Working'!$H32,'Language Penetration'!$B$1:$BE$1,0),0) -> 0.2625 | P35: =IF(ISBLANK(J35),RANDBETWEEN(1,2)&"%",IF(J35=1,RANDBETWEEN(35,40)&"%",IF(J35=2,RANDBETWEEN(30,35)&"%",IF(J35=3,RANDBETWEEN(25,30)&"%",IF(J35=4,RANDBETWEEN(20,25)&"%",IF(J35=5,RANDBETWEEN(15,20)&"%",IF(J35=6,RANDBETWEEN(10,15)&"%",IF(J35=7,RANDBETWEEN(8,10)&"%",IF(J35=8,RANDBETWEEN(6,8)&"%",IF(J35=9,RANDBETWEEN(4,6)&"%",IF(J35=10,RANDBETWEEN(2,4)&"%",""))))))))))) -> 13% | Q35: =IFERROR(L35*(M35+N35)*O35*P35,RANDBETWEEN(1,2)%*L35*(M35+N35)*O35) -> 0.95119322 | R35: =VLOOKUP(D:D,ranking!W:X,2,0) -> 0.8 | S35: =R35*Q35 -> 0.76095457 | T35: 13.721784
A36: WK-24'2026 | B36: ALL INDIA | C36: Amazon Prime Video | D36: Theatrical Movies | E36: PAID | F36: Movies | G36: Arco | H36: Hindi,Tamil,Telugu | I36: 46190 | K36: Adventure,Animation | L36: =VLOOKUP($C36&$E36,'Updated SES'!A:N,14,0) -> 36.49824 | M36: =VLOOKUP($K36,'Genre Penetration'!A:B,2,0)*VLOOKUP($C36&$E36,'Updated SES'!A:I,9,0) -> 0.286 | N36: =VLOOKUP(K:K,'Genre Penetration'!A:C,3,0)*VLOOKUP($C36&$E36,'Updated SES'!A:J,10,0) -> 0.216 | O36: =VLOOKUP($B36,'Language Penetration'!$B$1:$BE$14,MATCH('Compile data Working'!$H16,'Language Penetration'!$B$1:$BE$1,0),0) -> 0.6 | P36: =IF(ISBLANK(J36),RANDBETWEEN(1,2)&"%",IF(J36=1,RANDBETWEEN(35,40)&"%",IF(J36=2,RANDBETWEEN(30,35)&"%",IF(J36=3,RANDBETWEEN(25,30)&"%",IF(J36=4,RANDBETWEEN(20,25)&"%",IF(J36=5,RANDBETWEEN(15,20)&"%",IF(J36=6,RANDBETWEEN(10,15)&"%",IF(J36=7,RANDBETWEEN(8,10)&"%",IF(J36=8,RANDBETWEEN(6,8)&"%",IF(J36=9,RANDBETWEEN(4,6)&"%",IF(J36=10,RANDBETWEEN(2,4)&"%",""))))))))))) -> 2% | Q36: =IFERROR(L36*(M36+N36)*O36*P36,RANDBETWEEN(1,2)%*L36*(M36+N36)*O36) -> 0.2198654 | R36: =VLOOKUP(D:D,ranking!W:X,2,0) -> 0.7 | S36: =R36*Q36 -> 0.15390578 | T36: 13.390688
A37: Trending Top 10 | B37: ALL INDIA | C37: Sony Liv | D37: Tv Catch-Up | E37: FREE | F37: Shows | G37: Hastinapur Ke Veer | H37: Hindi | I37: 46175 | J37: 2 | K37: Mythology | L37: =VLOOKUP($C37&$E37,'Updated SES'!A:N,14,0) -> 5.268 | M37: =VLOOKUP($K37,'Genre Penetration'!A:B,2,0)*VLOOKUP($C37&$E37,'Updated SES'!A:I,9,0) -> 0.3828 | N37: =VLOOKUP(K:K,'Genre Penetration'!A:C,3,0)*VLOOKUP($C37&$E37,'Updated SES'!A:J,10,0) -> 0.1428 | O37: =VLOOKUP($B37,'Language Penetration'!$B$1:$BE$14,MATCH('Compile data Working'!$H43,'Language Penetration'!$B$1:$BE$1,0),0) -> 0.15 | P37: =IF(ISBLANK(J37),RANDBETWEEN(1,2)&"%",IF(J37=1,RANDBETWEEN(35,40)&"%",IF(J37=2,RANDBETWEEN(30,35)&"%",IF(J37=3,RANDBETWEEN(25,30)&"%",IF(J37=4,RANDBETWEEN(20,25)&"%",IF(J37=5,RANDBETWEEN(15,20)&"%",IF(J37=6,RANDBETWEEN(10,15)&"%",IF(J37=7,RANDBETWEEN(8,10)&"%",IF(J37=8,RANDBETWEEN(6,8)&"%",IF(J37=9,RANDBETWEEN(4,6)&"%",IF(J37=10,RANDBETWEEN(2,4)&"%",""))))))))))) -> 30% | Q37: =IFERROR(L37*(M37+N37)*O37*P37,RANDBETWEEN(1,2)%*L37*(M37+N37)*O37) -> 0.12459874 | R37: =VLOOKUP(D:D,ranking!W:X,2,0) -> 0.3 | S37: =R37*Q37 -> 0.037379621 | T37: 13.291294
A38: Trending Top 10 | B38: ALL INDIA | C38: Sony Liv | D38: Tv Catch-Up | E38: FREE | F38: Shows | G38: India's Best Dancer | H38: Hindi | I38: 46179 | J38: 5 | K38: Reality Tv | L38: =VLOOKUP($C38&$E38,'Updated SES'!A:N,14,0) -> 5.268 | M38: =VLOOKUP($K38,'Genre Penetration'!A:B,2,0)*VLOOKUP($C38&$E38,'Updated SES'!A:I,9,0) -> 0.264 | N38: =VLOOKUP(K:K,'Genre Penetration'!A:C,3,0)*VLOOKUP($C38&$E38,'Updated SES'!A:J,10,0) -> 0.204 | O38: =VLOOKUP($B38,'Language Penetration'!$B$1:$BE$14,MATCH('Compile data Working'!$H44,'Language Penetration'!$B$1:$BE$1,0),0) -> 0.2 | P38: =IF(ISBLANK(J38),RANDBETWEEN(1,2)&"%",IF(J38=1,RANDBETWEEN(35,40)&"%",IF(J38=2,RANDBETWEEN(30,35)&"%",IF(J38=3,RANDBETWEEN(25,30)&"%",IF(J38=4,RANDBETWEEN(20,25)&"%",IF(J38=5,RANDBETWEEN(15,20)&"%",IF(J38=6,RANDBETWEEN(10,15)&"%",IF(J38=7,RANDBETWEEN(8,10)&"%",IF(J38=8,RANDBETWEEN(6,8)&"%",IF(J38=9,RANDBETWEEN(4,6)&"%",IF(J38=10,RANDBETWEEN(2,4)&"%",""))))))))))) -> 19% | Q38: =IFERROR(L38*(M38+N38)*O38*P38,RANDBETWEEN(1,2)%*L38*(M38+N38)*O38) -> 0.093686112 | R38: =VLOOKUP(D:D,ranking!W:X,2,0) -> 0.3 | S38: =R38*Q38 -> 0.028105834 | T38: 13.131151
A39: Trending Top 10 | B39: ALL INDIA | C39: Netflix | D39: Svod Originals Shows | E39: PAID | F39: Shows | G39: I Will Find You | H39: English,Hindi,Tamil,Telugu | I39: 46191 | J39: 2 | K39: Crime,Drama,Thriller | L39: =VLOOKUP($C39&$E39,'Updated SES'!A:N,14,0) -> 55.4592 | M39: =VLOOKUP($K39,'Genre Penetration'!A:B,2,0)*VLOOKUP($C39&$E39,'Updated SES'!A:I,9,0) -> 0.3528 | N39: =VLOOKUP(K:K,'Genre Penetration'!A:C,3,0)*VLOOKUP($C39&$E39,'Updated SES'!A:J,10,0) -> 0.1428 | O39: =VLOOKUP($B39,'Language Penetration'!$B$1:$BE$14,MATCH('Compile data Working'!$H21,'Language Penetration'!$B$1:$BE$1,0),0) -> 0.204 | P39: =IF(ISBLANK(J39),RANDBETWEEN(1,2)&"%",IF(J39=1,RANDBETWEEN(35,40)&"%",IF(J39=2,RANDBETWEEN(30,35)&"%",IF(J39=3,RANDBETWEEN(25,30)&"%",IF(J39=4,RANDBETWEEN(20,25)&"%",IF(J39=5,RANDBETWEEN(15,20)&"%",IF(J39=6,RANDBETWEEN(10,15)&"%",IF(J39=7,RANDBETWEEN(8,10)&"%",IF(J39=8,RANDBETWEEN(6,8)&"%",IF(J39=9,RANDBETWEEN(4,6)&"%",IF(J39=10,RANDBETWEEN(2,4)&"%",""))))))))))) -> 35% | Q39: =IFERROR(L39*(M39+N39)*O39*P39,RANDBETWEEN(1,2)%*L39*(M39+N39)*O39) -> 1.9624704 | R39: =VLOOKUP(D:D,ranking!W:X,2,0) -> 0.6 | S39: =R39*Q39 -> 1.1774822 | T39: 13.120962
A40: Trending Top 10 | B40: ALL INDIA | C40: Sony Liv | D40: Theatrical Movies | E40: PAID | F40: Movies | G40: Athiradi | H40: Hindi,Kannada,Malayalam,Tamil,Telugu | I40: 46192 | J40: 1 | K40: Action,Comedy,Drama | L40: =VLOOKUP($C40&$E40,'Updated SES'!A:N,14,0) -> 21.68204 | M40: =VLOOKUP($K40,'Genre Penetration'!A:B,2,0)*VLOOKUP($C40&$E40,'Updated SES'!A:I,9,0) -> 0.312 | N40: =VLOOKUP(K:K,'Genre Penetration'!A:C,3,0)*VLOOKUP($C40&$E40,'Updated SES'!A:J,10,0) -> 0.182 | O40: =VLOOKUP($B40,'Language Penetration'!$B$1:$BE$14,MATCH('Compile data Working'!$H45,'Language Penetration'!$B$1:$BE$1,0),0) -> 0.2 | P40: =IF(ISBLANK(J40),RANDBETWEEN(1,2)&"%",IF(J40=1,RANDBETWEEN(35,40)&"%",IF(J40=2,RANDBETWEEN(30,35)&"%",IF(J40=3,RANDBETWEEN(25,30)&"%",IF(J40=4,RANDBETWEEN(20,25)&"%",IF(J40=5,RANDBETWEEN(15,20)&"%",IF(J40=6,RANDBETWEEN(10,15)&"%",IF(J40=7,RANDBETWEEN(8,10)&"%",IF(J40=8,RANDBETWEEN(6,8)&"%",IF(J40=9,RANDBETWEEN(4,6)&"%",IF(J40=10,RANDBETWEEN(2,4)&"%",""))))))))))) -> 35% | Q40: =IFERROR(L40*(M40+N40)*O40*P40,RANDBETWEEN(1,2)%*L40*(M40+N40)*O40) -> 0.74976494 | R40: =VLOOKUP(D:D,ranking!W:X,2,0) -> 0.7 | S40: =R40*Q40 -> 0.52483546 | T40: 12.946578
A41: WK-24'2026 | B41: ALL INDIA | C41: Netflix | D41: Theatrical Movies | E41: PAID | F41: Movies | G41: Color Book | H41: English | I41: 46192 | K41: Drama | L41: =VLOOKUP($C41&$E41,'Updated SES'!A:N,14,0) -> 55.4592 | M41: =VLOOKUP($K41,'Genre Penetration'!A:B,2,0)*VLOOKUP($C41&$E41,'Updated SES'!A:I,9,0) -> 0.245 | N41: =VLOOKUP(K:K,'Genre Penetration'!A:C,3,0)*VLOOKUP($C41&$E41,'Updated SES'!A:J,10,0) -> 0.255 | O41: =VLOOKUP($B41,'Language Penetration'!$B$1:$BE$14,MATCH('Compile data Working'!$H24,'Language Penetration'!$B$1:$BE$1,0),0) -> 0.2625 | P41: =IF(ISBLANK(J41),RANDBETWEEN(1,2)&"%",IF(J41=1,RANDBETWEEN(35,40)&"%",IF(J41=2,RANDBETWEEN(30,35)&"%",IF(J41=3,RANDBETWEEN(25,30)&"%",IF(J41=4,RANDBETWEEN(20,25)&"%",IF(J41=5,RANDBETWEEN(15,20)&"%",IF(J41=6,RANDBETWEEN(10,15)&"%",IF(J41=7,RANDBETWEEN(8,10)&"%",IF(J41=8,RANDBETWEEN(6,8)&"%",IF(J41=9,RANDBETWEEN(4,6)&"%",IF(J41=10,RANDBETWEEN(2,4)&"%",""))))))))))) -> 1% | Q41: =IFERROR(L41*(M41+N41)*O41*P41,RANDBETWEEN(1,2)%*L41*(M41+N41)*O41) -> 0.0727902 | R41: =VLOOKUP(D:D,ranking!W:X,2,0) -> 0.7 | S41: =R41*Q41 -> 0.05095314 | T41: 12.87192
A42: WK-24'2026 | B42: ALL INDIA | C42: Amazon Prime Video | D42: Theatrical Movies | E42: PAID | F42: Movies | G42: Meet Me in New York | H42: English | I42: 46190 | K42: Comedy,Romance | L42: =VLOOKUP($C42&$E42,'Updated SES'!A:N,14,0) -> 36.49824 | M42: =VLOOKUP($K42,'Genre Penetration'!A:B,2,0)*VLOOKUP($C42&$E42,'Updated SES'!A:I,9,0) -> 0.156 | N42: =VLOOKUP(K:K,'Genre Penetration'!A:C,3,0)*VLOOKUP($C42&$E42,'Updated SES'!A:J,10,0) -> 0.336 | O42: =VLOOKUP($B42,'Language Penetration'!$B$1:$BE$14,MATCH('Compile data Working'!$H46,'Language Penetration'!$B$1:$BE$1,0),0) -> 0.2 | P42: =IF(ISBLANK(J42),RANDBETWEEN(1,2)&"%",IF(J42=1,RANDBETWEEN(35,40)&"%",IF(J42=2,RANDBETWEEN(30,35)&"%",IF(J42=3,RANDBETWEEN(25,30)&"%",IF(J42=4,RANDBETWEEN(20,25)&"%",IF(J42=5,RANDBETWEEN(15,20)&"%",IF(J42=6,RANDBETWEEN(10,15)&"%",IF(J42=7,RANDBETWEEN(8,10)&"%",IF(J42=8,RANDBETWEEN(6,8)&"%",IF(J42=9,RANDBETWEEN(4,6)&"%",IF(J42=10,RANDBETWEEN(2,4)&"%",""))))))))))) -> 2% | Q42: =IFERROR(L42*(M42+N42)*O42*P42,RANDBETWEEN(1,2)%*L42*(M42+N42)*O42) -> 0.071828536 | R42: =VLOOKUP(D:D,ranking!W:X,2,0) -> 0.7 | S42: =R42*Q42 -> 0.050279975 | T42: 12.56697
A43: WK-24'2026 | B43: ALL INDIA | C43: Amazon Prime Video | D43: Theatrical Movies | E43: RENT | F43: Movies | G43: Identity | H43: Telugu | I43: 46188 | K43: Action,Crime,Thriller | L43: =VLOOKUP($C43&$E43,'Updated SES'!A:N,14,0) -> 4.689 | M43: =VLOOKUP($K43,'Genre Penetration'!A:B,2,0)*VLOOKUP($C43&$E43,'Updated SES'!A:I,9,0) -> 0.4896 | N43: =VLOOKUP(K:K,'Genre Penetration'!A:C,3,0)*VLOOKUP($C43&$E43,'Updated SES'!A:J,10,0) -> 0.0896 | O43: =VLOOKUP($B43,'Language Penetration'!$B$1:$BE$14,MATCH('Compile data Working'!$H47,'Language Penetration'!$B$1:$BE$1,0),0) -> 0.2 | P43: =IF(ISBLANK(J43),RANDBETWEEN(1,2)&"%",IF(J43=1,RANDBETWEEN(35,40)&"%",IF(J43=2,RANDBETWEEN(30,35)&"%",IF(J43=3,RANDBETWEEN(25,30)&"%",IF(J43=4,RANDBETWEEN(20,25)&"%",IF(J43=5,RANDBETWEEN(15,20)&"%",IF(J43=6,RANDBETWEEN(10,15)&"%",IF(J43=7,RANDBETWEEN(8,10)&"%",IF(J43=8,RANDBETWEEN(6,8)&"%",IF(J43=9,RANDBETWEEN(4,6)&"%",IF(J43=10,RANDBETWEEN(2,4)&"%",""))))))))))) -> 2% | Q43: =IFERROR(L43*(M43+N43)*O43*P43,RANDBETWEEN(1,2)%*L43*(M43+N43)*O43) -> 0.010863475 | R43: =VLOOKUP(D:D,ranking!W:X,2,0) -> 0.7 | S43: =R43*Q43 -> 0.0076044326 | T43: 12.260459
A44: WK-24'2026 | B44: ALL INDIA | C44: Netflix | D44: Theatrical Movies | E44: PAID | F44: Movies | G44: Per Aspera Ad Astra | H44: English | I44: 46191 | K44: Action,Adventure | L44: =VLOOKUP($C44&$E44,'Updated SES'!A:N,14,0) -> 55.4592 | M44: =VLOOKUP($K44,'Genre Penetration'!A:B,2,0)*VLOOKUP($C44&$E44,'Updated SES'!A:I,9,0) -> 0.2695 | N44: =VLOOKUP(K:K,'Genre Penetration'!A:C,3,0)*VLOOKUP($C44&$E44,'Updated SES'!A:J,10,0) -> 0.2295 | O44: =VLOOKUP($B44,'Language Penetration'!$B$1:$BE$14,MATCH('Compile data Working'!$H22,'Language Penetration'!$B$1:$BE$1,0),0) -> 0.2 | P44: =IF(ISBLANK(J44),RANDBETWEEN(1,2)&"%",IF(J44=1,RANDBETWEEN(35,40)&"%",IF(J44=2,RANDBETWEEN(30,35)&"%",IF(J44=3,RANDBETWEEN(25,30)&"%",IF(J44=4,RANDBETWEEN(20,25)&"%",IF(J44=5,RANDBETWEEN(15,20)&"%",IF(J44=6,RANDBETWEEN(10,15)&"%",IF(J44=7,RANDBETWEEN(8,10)&"%",IF(J44=8,RANDBETWEEN(6,8)&"%",IF(J44=9,RANDBETWEEN(4,6)&"%",IF(J44=10,RANDBETWEEN(2,4)&"%",""))))))))))) -> 2% | Q44: =IFERROR(L44*(M44+N44)*O44*P44,RANDBETWEEN(1,2)%*L44*(M44+N44)*O44) -> 0.11069656 | R44: =VLOOKUP(D:D,ranking!W:X,2,0) -> 0.7 | S44: =R44*Q44 -> 0.077487594 | T44: 12.059386
A45: WK-24'2026 | B45: ALL INDIA | C45: Amazon Prime Video | D45: Theatrical Movies | E45: PAID | F45: Movies | G45: A Match for the Prince | H45: English | I45: 46190 | K45: Comedy,Drama | L45: =VLOOKUP($C45&$E45,'Updated SES'!A:N,14,0) -> 36.49824 | M45: =VLOOKUP($K45,'Genre Penetration'!A:B,2,0)*VLOOKUP($C45&$E45,'Updated SES'!A:I,9,0) -> 0.2444 | N45: =VLOOKUP(K:K,'Genre Penetration'!A:C,3,0)*VLOOKUP($C45&$E45,'Updated SES'!A:J,10,0) -> 0.2544 | O45: =VLOOKUP($B45,'Language Penetration'!$B$1:$BE$14,MATCH('Compile data Working'!$H48,'Language Penetration'!$B$1:$BE$1,0),0) -> 0.2625 | P45: =IF(ISBLANK(J45),RANDBETWEEN(1,2)&"%",IF(J45=1,RANDBETWEEN(35,40)&"%",IF(J45=2,RANDBETWEEN(30,35)&"%",IF(J45=3,RANDBETWEEN(25,30)&"%",IF(J45=4,RANDBETWEEN(20,25)&"%",IF(J45=5,RANDBETWEEN(15,20)&"%",IF(J45=6,RANDBETWEEN(10,15)&"%",IF(J45=7,RANDBETWEEN(8,10)&"%",IF(J45=8,RANDBETWEEN(6,8)&"%",IF(J45=9,RANDBETWEEN(4,6)&"%",IF(J45=10,RANDBETWEEN(2,4)&"%",""))))))))))) -> 2% | Q45: =IFERROR(L45*(M45+N45)*O45*P45,RANDBETWEEN(1,2)%*L45*(M45+N45)*O45) -> 0.095577941 | R45: =VLOOKUP(D:D,ranking!W:X,2,0) -> 0.7 | S45: =R45*Q45 -> 0.066904559 | T45: 12
A46: WK-24'2026 | B46: ALL INDIA | C46: Amazon Prime Video | D46: Theatrical Movies | E46: PAID | F46: Movies | G46: The Love Hunt | H46: English | I46: 46190 | K46: Comedy,Drama,Romance | L46: =VLOOKUP($C46&$E46,'Updated SES'!A:N,14,0) -> 36.49824 | M46: =VLOOKUP($K46,'Genre Penetration'!A:B,2,0)*VLOOKUP($C46&$E46,'Updated SES'!A:I,9,0) -> 0.1924 | N46: =VLOOKUP(K:K,'Genre Penetration'!A:C,3,0)*VLOOKUP($C46&$E46,'Updated SES'!A:J,10,0) -> 0.3024 | O46: =VLOOKUP($B46,'Language Penetration'!$B$1:$BE$14,MATCH('Compile data Working'!$H49,'Language Penetration'!$B$1:$BE$1,0),0) -> 0.2 | P46: =IF(ISBLANK(J46),RANDBETWEEN(1,2)&"%",IF(J46=1,RANDBETWEEN(35,40)&"%",IF(J46=2,RANDBETWEEN(30,35)&"%",IF(J46=3,RANDBETWEEN(25,30)&"%",IF(J46=4,RANDBETWEEN(20,25)&"%",IF(J46=5,RANDBETWEEN(15,20)&"%",IF(J46=6,RANDBETWEEN(10,15)&"%",IF(J46=7,RANDBETWEEN(8,10)&"%",IF(J46=8,RANDBETWEEN(6,8)&"%",IF(J46=9,RANDBETWEEN(4,6)&"%",IF(J46=10,RANDBETWEEN(2,4)&"%",""))))))))))) -> 2% | Q46: =IFERROR(L46*(M46+N46)*O46*P46,RANDBETWEEN(1,2)%*L46*(M46+N46)*O46) -> 0.072237317 | R46: =VLOOKUP(D:D,ranking!W:X,2,0) -> 0.7 | S46: =R46*Q46 -> 0.050566122 | T46: 11.800691
A47: WK-24'2026 | B47: ALL INDIA | C47: Amazon Prime Video | D47: Theatrical Movies | E47: PAID | F47: Movies | G47: Let Love Grow | H47: English | I47: 46190 | K47: Drama,Romance | L47: =VLOOKUP($C47&$E47,'Updated SES'!A:N,14,0) -> 36.49824 | M47: =VLOOKUP($K47,'Genre Penetration'!A:B,2,0)*VLOOKUP($C47&$E47,'Updated SES'!A:I,9,0) -> 0.208 | N47: =VLOOKUP(K:K,'Genre Penetration'!A:C,3,0)*VLOOKUP($C47&$E47,'Updated SES'!A:J,10,0) -> 0.288 | O47: =VLOOKUP($B47,'Language Penetration'!$B$1:$BE$14,MATCH('Compile data Working'!$H50,'Language Penetration'!$B$1:$BE$1,0),0) -> 0.204 | P47: =IF(ISBLANK(J47),RANDBETWEEN(1,2)&"%",IF(J47=1,RANDBETWEEN(35,40)&"%",IF(J47=2,RANDBETWEEN(30,35)&"%",IF(J47=3,RANDBETWEEN(25,30)&"%",IF(J47=4,RANDBETWEEN(20,25)&"%",IF(J47=5,RANDBETWEEN(15,20)&"%",IF(J47=6,RANDBETWEEN(10,15)&"%",IF(J47=7,RANDBETWEEN(8,10)&"%",IF(J47=8,RANDBETWEEN(6,8)&"%",IF(J47=9,RANDBETWEEN(4,6)&"%",IF(J47=10,RANDBETWEEN(2,4)&"%",""))))))))))) -> 1% | Q47: =IFERROR(L47*(M47+N47)*O47*P47,RANDBETWEEN(1,2)%*L47*(M47+N47)*O47) -> 0.036930379 | R47: =VLOOKUP(D:D,ranking!W:X,2,0) -> 0.7 | S47: =R47*Q47 -> 0.025851265 | T47: 11.647436
A48: Trending Top 10 | B48: ALL INDIA | C48: Netflix | D48: SVOD Originals Movies | E48: PAID | F48: Movies | G48: Husbands in Action | H48: English,Hindi,Tamil,Telugu | I48: 46192 | J48: 8 | K48: Action,Comedy | L48: =VLOOKUP($C48&$E48,'Updated SES'!A:N,14,0) -> 55.4592 | M48: =VLOOKUP($K48,'Genre Penetration'!A:B,2,0)*VLOOKUP($C48&$E48,'Updated SES'!A:I,9,0) -> 0.3283 | N48: =VLOOKUP(K:K,'Genre Penetration'!A:C,3,0)*VLOOKUP($C48&$E48,'Updated SES'!A:J,10,0) -> 0.1683 | O48: =VLOOKUP($B48,'Language Penetration'!$B$1:$BE$14,MATCH('Compile data Working'!$H15,'Language Penetration'!$B$1:$BE$1,0),0) -> 0.20333333 | P48: =IF(ISBLANK(J48),RANDBETWEEN(1,2)&"%",IF(J48=1,RANDBETWEEN(35,40)&"%",IF(J48=2,RANDBETWEEN(30,35)&"%",IF(J48=3,RANDBETWEEN(25,30)&"%",IF(J48=4,RANDBETWEEN(20,25)&"%",IF(J48=5,RANDBETWEEN(15,20)&"%",IF(J48=6,RANDBETWEEN(10,15)&"%",IF(J48=7,RANDBETWEEN(8,10)&"%",IF(J48=8,RANDBETWEEN(6,8)&"%",IF(J48=9,RANDBETWEEN(4,6)&"%",IF(J48=10,RANDBETWEEN(2,4)&"%",""))))))))))) -> 8% | Q48: =IFERROR(L48*(M48+N48)*O48*P48,RANDBETWEEN(1,2)%*L48*(M48+N48)*O48) -> 0.4480009 | R48: =VLOOKUP(D:D,ranking!W:X,2,0) -> 0.8 | S48: =R48*Q48 -> 0.35840072 | T48: 11.621236
A49: WK-24'2026 | B49: ALL INDIA | C49: Amazon Prime Video | D49: SVOD Originals Shows | E49: PAID | F49: Shows | G49: In Plain Sight | H49: English | I49: 46188 | K49: Crime,Drama,Thriller | L49: =VLOOKUP($C49&$E49,'Updated SES'!A:N,14,0) -> 36.49824 | M49: =VLOOKUP($K49,'Genre Penetration'!A:B,2,0)*VLOOKUP($C49&$E49,'Updated SES'!A:I,9,0) -> 0.3744 | N49: =VLOOKUP(K:K,'Genre Penetration'!A:C,3,0)*VLOOKUP($C49&$E49,'Updated SES'!A:J,10,0) -> 0.1344 | O49: =VLOOKUP($B49,'Language Penetration'!$B$1:$BE$14,MATCH('Compile data Working'!$H51,'Language Penetration'!$B$1:$BE$1,0),0) -> 0.6 | P49: =IF(ISBLANK(J49),RANDBETWEEN(1,2)&"%",IF(J49=1,RANDBETWEEN(35,40)&"%",IF(J49=2,RANDBETWEEN(30,35)&"%",IF(J49=3,RANDBETWEEN(25,30)&"%",IF(J49=4,RANDBETWEEN(20,25)&"%",IF(J49=5,RANDBETWEEN(15,20)&"%",IF(J49=6,RANDBETWEEN(10,15)&"%",IF(J49=7,RANDBETWEEN(8,10)&"%",IF(J49=8,RANDBETWEEN(6,8)&"%",IF(J49=9,RANDBETWEEN(4,6)&"%",IF(J49=10,RANDBETWEEN(2,4)&"%",""))))))))))) -> 1% | Q49: =IFERROR(L49*(M49+N49)*O49*P49,RANDBETWEEN(1,2)%*L49*(M49+N49)*O49) -> 0.11142183 | R49: =VLOOKUP(D:D,ranking!W:X,2,0) -> 0.6 | S49: =R49*Q49 -> 0.066853096 | T49: 11.49418
A50: Trending Top 10 | B50: ALL INDIA | C50: Netflix | D50: SVOD Originals Movies | E50: PAID | F50: Movies | G50: Office Romance | H50: Hindi,Kannada,Malayalam,Tamil,Telugu | I50: 46178 | J50: 9 | K50: Comedy,Romance | L50: =VLOOKUP($C50&$E50,'Updated SES'!A:N,14,0) -> 55.4592 | M50: =VLOOKUP($K50,'Genre Penetration'!A:B,2,0)*VLOOKUP($C50&$E50,'Updated SES'!A:I,9,0) -> 0.147 | N50: =VLOOKUP(K:K,'Genre Penetration'!A:C,3,0)*VLOOKUP($C50&$E50,'Updated SES'!A:J,10,0) -> 0.357 | O50: =VLOOKUP($B50,'Language Penetration'!$B$1:$BE$14,MATCH('Compile data Working'!$H52,'Language Penetration'!$B$1:$BE$1,0),0) -> 0.6 | P50: =IF(ISBLANK(J50),RANDBETWEEN(1,2)&"%",IF(J50=1,RANDBETWEEN(35,40)&"%",IF(J50=2,RANDBETWEEN(30,35)&"%",IF(J50=3,RANDBETWEEN(25,30)&"%",IF(J50=4,RANDBETWEEN(20,25)&"%",IF(J50=5,RANDBETWEEN(15,20)&"%",IF(J50=6,RANDBETWEEN(10,15)&"%",IF(J50=7,RANDBETWEEN(8,10)&"%",IF(J50=8,RANDBETWEEN(6,8)&"%",IF(J50=9,RANDBETWEEN(4,6)&"%",IF(J50=10,RANDBETWEEN(2,4)&"%",""))))))))))) -> 4% | Q50: =IFERROR(L50*(M50+N50)*O50*P50,RANDBETWEEN(1,2)%*L50*(M50+N50)*O50) -> 0.67083448 | R50: =VLOOKUP(D:D,ranking!W:X,2,0) -> 0.8 | S50: =R50*Q50 -> 0.53666759 | T50: 11.483146
A51: Trending Top 10 | B51: ALL INDIA | C51: Netflix | D51: Theatrical Movies | E51: PAID | F51: Movies | G51: Kalank | H51: Hindi | I51: 46188 | J51: 7 | K51: Drama,Romance | L51: =VLOOKUP($C51&$E51,'Updated SES'!A:N,14,0) -> 55.4592 | M51: =VLOOKUP($K51,'Genre Penetration'!A:B,2,0)*VLOOKUP($C51&$E51,'Updated SES'!A:I,9,0) -> 0.196 | N51: =VLOOKUP(K:K,'Genre Penetration'!A:C,3,0)*VLOOKUP($C51&$E51,'Updated SES'!A:J,10,0) -> 0.306 | O51: =VLOOKUP($B51,'Language Penetration'!$B$1:$BE$14,MATCH('Compile data Working'!$H14,'Language Penetration'!$B$1:$BE$1,0),0) -> 0.6 | P51: =IF(ISBLANK(J51),RANDBETWEEN(1,2)&"%",IF(J51=1,RANDBETWEEN(35,40)&"%",IF(J51=2,RANDBETWEEN(30,35)&"%",IF(J51=3,RANDBETWEEN(25,30)&"%",IF(J51=4,RANDBETWEEN(20,25)&"%",IF(J51=5,RANDBETWEEN(15,20)&"%",IF(J51=6,RANDBETWEEN(10,15)&"%",IF(J51=7,RANDBETWEEN(8,10)&"%",IF(J51=8,RANDBETWEEN(6,8)&"%",IF(J51=9,RANDBETWEEN(4,6)&"%",IF(J51=10,RANDBETWEEN(2,4)&"%",""))))))))))) -> 9% | Q51: =IFERROR(L51*(M51+N51)*O51*P51,RANDBETWEEN(1,2)%*L51*(M51+N51)*O51) -> 1.503388 | R51: =VLOOKUP(D:D,ranking!W:X,2,0) -> 0.7 | S51: =R51*Q51 -> 1.0523716 | T51: 11.370552
A52: WK-24'2026 | B52: ALL INDIA | C52: Lionsgate Play | D52: Theatrical Movies | E52: PAID | F52: Movies | G52: Aliya Basu Gayab Hai | H52: Hindi | I52: 46192 | K52: Crime,Drama | L52: =VLOOKUP($C52&$E52,'Updated SES'!A:N,14,0) -> 25.34 | M52: =VLOOKUP($K52,'Genre Penetration'!A:B,2,0)*VLOOKUP($C52&$E52,'Updated SES'!A:I,9,0) -> 0.4756 | N52: =VLOOKUP(K:K,'Genre Penetration'!A:C,3,0)*VLOOKUP($C52&$E52,'Updated SES'!A:J,10,0) -> 0.0756 | O52: =VLOOKUP($B52,'Language Penetration'!$B$1:$BE$14,MATCH('Compile data Working'!$H53,'Language Penetration'!$B$1:$BE$1,0),0) -> 0.2 | P52: =IF(ISBLANK(J52),RANDBETWEEN(1,2)&"%",IF(J52=1,RANDBETWEEN(35,40)&"%",IF(J52=2,RANDBETWEEN(30,35)&"%",IF(J52=3,RANDBETWEEN(25,30)&"%",IF(J52=4,RANDBETWEEN(20,25)&"%",IF(J52=5,RANDBETWEEN(15,20)&"%",IF(J52=6,RANDBETWEEN(10,15)&"%",IF(J52=7,RANDBETWEEN(8,10)&"%",IF(J52=8,RANDBETWEEN(6,8)&"%",IF(J52=9,RANDBETWEEN(4,6)&"%",IF(J52=10,RANDBETWEEN(2,4)&"%",""))))))))))) -> 1% | Q52: =IFERROR(L52*(M52+N52)*O52*P52,RANDBETWEEN(1,2)%*L52*(M52+N52)*O52) -> 0.027934816 | R52: =VLOOKUP(D:D,ranking!W:X,2,0) -> 0.7 | S52: =R52*Q52 -> 0.019554371 | T52: 11.364489
A53: WK-24'2026 | B53: ALL INDIA | C53: Amazon Prime Video | D53: Theatrical Movies | E53: PAID | F53: Movies | G53: Steal Your Heart | H53: English | I53: 46190 | K53: Romance | L53: =VLOOKUP($C53&$E53,'Updated SES'!A:N,14,0) -> 36.49824 | M53: =VLOOKUP($K53,'Genre Penetration'!A:B,2,0)*VLOOKUP($C53&$E53,'Updated SES'!A:I,9,0) -> 0.234 | N53: =VLOOKUP(K:K,'Genre Penetration'!A:C,3,0)*VLOOKUP($C53&$E53,'Updated SES'!A:J,10,0) -> 0.264 | O53: =VLOOKUP($B53,'Language Penetration'!$B$1:$BE$14,MATCH('Compile data Working'!$H54,'Language Penetration'!$B$1:$BE$1,0),0) -> 0.204 | P53: =IF(ISBLANK(J53),RANDBETWEEN(1,2)&"%",IF(J53=1,RANDBETWEEN(35,40)&"%",IF(J53=2,RANDBETWEEN(30,35)&"%",IF(J53=3,RANDBETWEEN(25,30)&"%",IF(J53=4,RANDBETWEEN(20,25)&"%",IF(J53=5,RANDBETWEEN(15,20)&"%",IF(J53=6,RANDBETWEEN(10,15)&"%",IF(J53=7,RANDBETWEEN(8,10)&"%",IF(J53=8,RANDBETWEEN(6,8)&"%",IF(J53=9,RANDBETWEEN(4,6)&"%",IF(J53=10,RANDBETWEEN(2,4)&"%",""))))))))))) -> 2% | Q53: =IFERROR(L53*(M53+N53)*O53*P53,RANDBETWEEN(1,2)%*L53*(M53+N53)*O53) -> 0.074158584 | R53: =VLOOKUP(D:D,ranking!W:X,2,0) -> 0.7 | S53: =R53*Q53 -> 0.051911009 | T53: 11.187669
A54: WK-24'2026 | B54: ALL INDIA | C54: Lionsgate Play | D54: Theatrical Movies | E54: PAID | F54: Movies | G54: Motive For Murder (M4M) | H54: Hindi,Kannada,Malayalam,Tamil,Telugu | I54: 46192 | K54: Drama | L54: =VLOOKUP($C54&$E54,'Updated SES'!A:N,14,0) -> 25.34 | M54: =VLOOKUP($K54,'Genre Penetration'!A:B,2,0)*VLOOKUP($C54&$E54,'Updated SES'!A:I,9,0) -> 0.41 | N54: =VLOOKUP(K:K,'Genre Penetration'!A:C,3,0)*VLOOKUP($C54&$E54,'Updated SES'!A:J,10,0) -> 0.09 | O54: =VLOOKUP($B54,'Language Penetration'!$B$1:$BE$14,MATCH('Compile data Working'!$H38,'Language Penetration'!$B$1:$BE$1,0),0) -> 0.6 | P54: =IF(ISBLANK(J54),RANDBETWEEN(1,2)&"%",IF(J54=1,RANDBETWEEN(35,40)&"%",IF(J54=2,RANDBETWEEN(30,35)&"%",IF(J54=3,RANDBETWEEN(25,30)&"%",IF(J54=4,RANDBETWEEN(20,25)&"%",IF(J54=5,RANDBETWEEN(15,20)&"%",IF(J54=6,RANDBETWEEN(10,15)&"%",IF(J54=7,RANDBETWEEN(8,10)&"%",IF(J54=8,RANDBETWEEN(6,8)&"%",IF(J54=9,RANDBETWEEN(4,6)&"%",IF(J54=10,RANDBETWEEN(2,4)&"%",""))))))))))) -> 1% | Q54: =IFERROR(L54*(M54+N54)*O54*P54,RANDBETWEEN(1,2)%*L54*(M54+N54)*O54) -> 0.07602 | R54: =VLOOKUP(D:D,ranking!W:X,2,0) -> 0.7 | S54: =R54*Q54 -> 0.053214 | T54: 11.164489
A55: WK-24'2026 | B55: ALL INDIA | C55: Amazon Prime Video | D55: SVOD Originals Shows | E55: PAID | F55: Shows | G55: Royal Pains | H55: English | I55: 46188 | K55: Comedy,Drama | L55: =VLOOKUP($C55&$E55,'Updated SES'!A:N,14,0) -> 36.49824 | M55: =VLOOKUP($K55,'Genre Penetration'!A:B,2,0)*VLOOKUP($C55&$E55,'Updated SES'!A:I,9,0) -> 0.2444 | N55: =VLOOKUP(K:K,'Genre Penetration'!A:C,3,0)*VLOOKUP($C55&$E55,'Updated SES'!A:J,10,0) -> 0.2544 | O55: =VLOOKUP($B55,'Language Penetration'!$B$1:$BE$14,MATCH('Compile data Working'!$H55,'Language Penetration'!$B$1:$BE$1,0),0) -> 0.2 | P55: =IF(ISBLANK(J55),RANDBETWEEN(1,2)&"%",IF(J55=1,RANDBETWEEN(35,40)&"%",IF(J55=2,RANDBETWEEN(30,35)&"%",IF(J55=3,RANDBETWEEN(25,30)&"%",IF(J55=4,RANDBETWEEN(20,25)&"%",IF(J55=5,RANDBETWEEN(15,20)&"%",IF(J55=6,RANDBETWEEN(10,15)&"%",IF(J55=7,RANDBETWEEN(8,10)&"%",IF(J55=8,RANDBETWEEN(6,8)&"%",IF(J55=9,RANDBETWEEN(4,6)&"%",IF(J55=10,RANDBETWEEN(2,4)&"%",""))))))))))) -> 1% | Q55: =IFERROR(L55*(M55+N55)*O55*P55,RANDBETWEEN(1,2)%*L55*(M55+N55)*O55) -> 0.036410644 | R55: =VLOOKUP(D:D,ranking!W:X,2,0) -> 0.6 | S55: =R55*Q55 -> 0.021846387 | T55: 10.881157
A56: Trending Top 10 | B56: ALL INDIA | C56: Amazon MX Player | D56: Avod Originals Shows | E56: FREE | F56: Shows | G56: Vimal Khanna | H56: Hindi | I56: 46157 | J56: 3 | K56: Crime,Thriller | L56: =VLOOKUP($C56&$E56,'Updated SES'!A:N,14,0) -> 78.93987 | M56: =VLOOKUP($K56,'Genre Penetration'!A:B,2,0)*VLOOKUP($C56&$E56,'Updated SES'!A:I,9,0) -> 0.496 | N56: =VLOOKUP(K:K,'Genre Penetration'!A:C,3,0)*VLOOKUP($C56&$E56,'Updated SES'!A:J,10,0) -> 0.076 | O56: =VLOOKUP($B56,'Language Penetration'!$B$1:$BE$14,MATCH('Compile data Working'!$H73,'Language Penetration'!$B$1:$BE$1,0),0) -> 0.6 | P56: =IF(ISBLANK(J56),RANDBETWEEN(1,2)&"%",IF(J56=1,RANDBETWEEN(35,40)&"%",IF(J56=2,RANDBETWEEN(30,35)&"%",IF(J56=3,RANDBETWEEN(25,30)&"%",IF(J56=4,RANDBETWEEN(20,25)&"%",IF(J56=5,RANDBETWEEN(15,20)&"%",IF(J56=6,RANDBETWEEN(10,15)&"%",IF(J56=7,RANDBETWEEN(8,10)&"%",IF(J56=8,RANDBETWEEN(6,8)&"%",IF(J56=9,RANDBETWEEN(4,6)&"%",IF(J56=10,RANDBETWEEN(2,4)&"%",""))))))))))) -> 25% | Q56: =IFERROR(L56*(M56+N56)*O56*P56,RANDBETWEEN(1,2)%*L56*(M56+N56)*O56) -> 6.7730408 | R56: =VLOOKUP(D:D,ranking!W:X,2,0) -> 0.6 | S56: =R56*Q56 -> 4.0638245 | T56: 10.935849
A57: Trending Top 10 | B57: ALL INDIA | C57: Sony Liv | D57: Tv Catch-Up | E57: FREE | F57: Shows | G57: Taarak Mehta Ka Ooltah Chashmah | H57: Hindi | I57: - | J57: 3 | K57: Comedy | L57: =VLOOKUP($C57&$E57,'Updated SES'!A:N,14,0) -> 5.268 | M57: =VLOOKUP($K57,'Genre Penetration'!A:B,2,0)*VLOOKUP($C57&$E57,'Updated SES'!A:I,9,0) -> 0.297 | N57: =VLOOKUP(K:K,'Genre Penetration'!A:C,3,0)*VLOOKUP($C57&$E57,'Updated SES'!A:J,10,0) -> 0.187 | O57: =VLOOKUP($B57,'Language Penetration'!$B$1:$BE$14,MATCH('Compile data Working'!$H57,'Language Penetration'!$B$1:$BE$1,0),0) -> 0.6 | P57: =IF(ISBLANK(J57),RANDBETWEEN(1,2)&"%",IF(J57=1,RANDBETWEEN(35,40)&"%",IF(J57=2,RANDBETWEEN(30,35)&"%",IF(J57=3,RANDBETWEEN(25,30)&"%",IF(J57=4,RANDBETWEEN(20,25)&"%",IF(J57=5,RANDBETWEEN(15,20)&"%",IF(J57=6,RANDBETWEEN(10,15)&"%",IF(J57=7,RANDBETWEEN(8,10)&"%",IF(J57=8,RANDBETWEEN(6,8)&"%",IF(J57=9,RANDBETWEEN(4,6)&"%",IF(J57=10,RANDBETWEEN(2,4)&"%",""))))))))))) -> 25% | Q57: =IFERROR(L57*(M57+N57)*O57*P57,RANDBETWEEN(1,2)%*L57*(M57+N57)*O57) -> 0.3824568 | R57: =VLOOKUP(D:D,ranking!W:X,2,0) -> 0.3 | S57: =R57*Q57 -> 0.11473704 | T57: 10.762711
A58: WK-24'2026 | B58: ALL INDIA | C58: Amazon Prime Video | D58: SVOD Originals Shows | E58: PAID | F58: Shows | G58: Friday Night Lights | H58: English | I58: 46189 | K58: Drama | L58: =VLOOKUP($C58&$E58,'Updated SES'!A:N,14,0) -> 36.49824 | M58: =VLOOKUP($K58,'Genre Penetration'!A:B,2,0)*VLOOKUP($C58&$E58,'Updated SES'!A:I,9,0) -> 0.26 | N58: =VLOOKUP(K:K,'Genre Penetration'!A:C,3,0)*VLOOKUP($C58&$E58,'Updated SES'!A:J,10,0) -> 0.24 | O58: =VLOOKUP($B58,'Language Penetration'!$B$1:$BE$14,MATCH('Compile data Working'!$H58,'Language Penetration'!$B$1:$BE$1,0),0) -> 0.2 | P58: =IF(ISBLANK(J58),RANDBETWEEN(1,2)&"%",IF(J58=1,RANDBETWEEN(35,40)&"%",IF(J58=2,RANDBETWEEN(30,35)&"%",IF(J58=3,RANDBETWEEN(25,30)&"%",IF(J58=4,RANDBETWEEN(20,25)&"%",IF(J58=5,RANDBETWEEN(15,20)&"%",IF(J58=6,RANDBETWEEN(10,15)&"%",IF(J58=7,RANDBETWEEN(8,10)&"%",IF(J58=8,RANDBETWEEN(6,8)&"%",IF(J58=9,RANDBETWEEN(4,6)&"%",IF(J58=10,RANDBETWEEN(2,4)&"%",""))))))))))) -> 2% | Q58: =IFERROR(L58*(M58+N58)*O58*P58,RANDBETWEEN(1,2)%*L58*(M58+N58)*O58) -> 0.07299648 | R58: =VLOOKUP(D:D,ranking!W:X,2,0) -> 0.6 | S58: =R58*Q58 -> 0.043797888 | T58: 10.727901
A59: WK-24'2026 | B59: ALL INDIA | C59: Amazon Prime Video | D59: Theatrical Movies | E59: PAID | F59: Movies | G59: The Soulmate Search | H59: English | I59: 46190 | K59: Romance | L59: =VLOOKUP($C59&$E59,'Updated SES'!A:N,14,0) -> 36.49824 | M59: =VLOOKUP($K59,'Genre Penetration'!A:B,2,0)*VLOOKUP($C59&$E59,'Updated SES'!A:I,9,0) -> 0.234 | N59: =VLOOKUP(K:K,'Genre Penetration'!A:C,3,0)*VLOOKUP($C59&$E59,'Updated SES'!A:J,10,0) -> 0.264 | O59: =VLOOKUP($B59,'Language Penetration'!$B$1:$BE$14,MATCH('Compile data Working'!$H59,'Language Penetration'!$B$1:$BE$1,0),0) -> 0.2 | P59: =IF(ISBLANK(J59),RANDBETWEEN(1,2)&"%",IF(J59=1,RANDBETWEEN(35,40)&"%",IF(J59=2,RANDBETWEEN(30,35)&"%",IF(J59=3,RANDBETWEEN(25,30)&"%",IF(J59=4,RANDBETWEEN(20,25)&"%",IF(J59=5,RANDBETWEEN(15,20)&"%",IF(J59=6,RANDBETWEEN(10,15)&"%",IF(J59=7,RANDBETWEEN(8,10)&"%",IF(J59=8,RANDBETWEEN(6,8)&"%",IF(J59=9,RANDBETWEEN(4,6)&"%",IF(J59=10,RANDBETWEEN(2,4)&"%",""))))))))))) -> 2% | Q59: =IFERROR(L59*(M59+N59)*O59*P59,RANDBETWEEN(1,2)%*L59*(M59+N59)*O59) -> 0.072704494 | R59: =VLOOKUP(D:D,ranking!W:X,2,0) -> 0.7 | S59: =R59*Q59 -> 0.050893146 | T59: 10.574646
A60: Cott Data Servey | B60: ALL INDIA | C60: Amazon Mx Player | D60: AVOD Originals Shows | E60: FREE | F60: Shows | G60: Made in India – A Titan Story | H60: Hindi | I60: 46176 | J60: 2 | K60: Drama | L60: =VLOOKUP($C60&$E60,'Updated SES'!A:N,14,0) -> 78.93987 | M60: =VLOOKUP($K60,'Genre Penetration'!A:B,2,0)*VLOOKUP($C60&$E60,'Updated SES'!A:I,9,0) -> 0.4 | N60: =VLOOKUP(K:K,'Genre Penetration'!A:C,3,0)*VLOOKUP($C60&$E60,'Updated SES'!A:J,10,0) -> 0.1 | O60: =VLOOKUP($B60,'Language Penetration'!$B$1:$BE$14,MATCH('Compile data Working'!$H60,'Language Penetration'!$B$1:$BE$1,0),0) -> 0.6 | P60: =IF(ISBLANK(J60),RANDBETWEEN(1,2)&"%",IF(J60=1,RANDBETWEEN(35,40)&"%",IF(J60=2,RANDBETWEEN(30,35)&"%",IF(J60=3,RANDBETWEEN(25,30)&"%",IF(J60=4,RANDBETWEEN(20,25)&"%",IF(J60=5,RANDBETWEEN(15,20)&"%",IF(J60=6,RANDBETWEEN(10,15)&"%",IF(J60=7,RANDBETWEEN(8,10)&"%",IF(J60=8,RANDBETWEEN(6,8)&"%",IF(J60=9,RANDBETWEEN(4,6)&"%",IF(J60=10,RANDBETWEEN(2,4)&"%",""))))))))))) -> 33% | Q60: =IFERROR(L60*(M60+N60)*O60*P60,RANDBETWEEN(1,2)%*L60*(M60+N60)*O60) -> 7.8150471 | R60: =VLOOKUP(D:D,ranking!W:X,2,0) -> 0.6 | S60: =R60*Q60 -> 4.6890283 | T60: 10.483854
A61: WK-24'2026 | B61: ALL INDIA | C61: Amazon Prime Video | D61: Theatrical Movies | E61: RENT | F61: Movies | G61: Mortal Kombat II | H61: English,Hindi,Tamil,Telugu | I61: 46192 | K61: Action,Adventure,Sci-Fi | L61: =VLOOKUP($C61&$E61,'Updated SES'!A:N,14,0) -> 4.689 | M61: =VLOOKUP($K61,'Genre Penetration'!A:B,2,0)*VLOOKUP($C61&$E61,'Updated SES'!A:I,9,0) -> 0.476 | N61: =VLOOKUP(K:K,'Genre Penetration'!A:C,3,0)*VLOOKUP($C61&$E61,'Updated SES'!A:J,10,0) -> 0.096 | O61: =VLOOKUP($B61,'Language Penetration'!$B$1:$BE$14,MATCH('Compile data Working'!$H61,'Language Penetration'!$B$1:$BE$1,0),0) -> 0.2625 | P61: =IF(ISBLANK(J61),RANDBETWEEN(1,2)&"%",IF(J61=1,RANDBETWEEN(35,40)&"%",IF(J61=2,RANDBETWEEN(30,35)&"%",IF(J61=3,RANDBETWEEN(25,30)&"%",IF(J61=4,RANDBETWEEN(20,25)&"%",IF(J61=5,RANDBETWEEN(15,20)&"%",IF(J61=6,RANDBETWEEN(10,15)&"%",IF(J61=7,RANDBETWEEN(8,10)&"%",IF(J61=8,RANDBETWEEN(6,8)&"%",IF(J61=9,RANDBETWEEN(4,6)&"%",IF(J61=10,RANDBETWEEN(2,4)&"%",""))))))))))) -> 2% | Q61: =IFERROR(L61*(M61+N61)*O61*P61,RANDBETWEEN(1,2)%*L61*(M61+N61)*O61) -> 0.014081067 | R61: =VLOOKUP(D:D,ranking!W:X,2,0) -> 0.7 | S61: =R61*Q61 -> 0.0098567469 | T61: 10.42139
A62: WK-24'2026 | B62: ALL INDIA | C62: Amazon Prime Video | D62: Theatrical Movies | E62: PAID | F62: Movies | G62: The Wedding in the Hamptons | H62: English | I62: 46190 | K62: Romance | L62: =VLOOKUP($C62&$E62,'Updated SES'!A:N,14,0) -> 36.49824 | M62: =VLOOKUP($K62,'Genre Penetration'!A:B,2,0)*VLOOKUP($C62&$E62,'Updated SES'!A:I,9,0) -> 0.234 | N62: =VLOOKUP(K:K,'Genre Penetration'!A:C,3,0)*VLOOKUP($C62&$E62,'Updated SES'!A:J,10,0) -> 0.264 | O62: =VLOOKUP($B62,'Language Penetration'!$B$1:$BE$14,MATCH('Compile data Working'!$H62,'Language Penetration'!$B$1:$BE$1,0),0) -> 0.2 | P62: =IF(ISBLANK(J62),RANDBETWEEN(1,2)&"%",IF(J62=1,RANDBETWEEN(35,40)&"%",IF(J62=2,RANDBETWEEN(30,35)&"%",IF(J62=3,RANDBETWEEN(25,30)&"%",IF(J62=4,RANDBETWEEN(20,25)&"%",IF(J62=5,RANDBETWEEN(15,20)&"%",IF(J62=6,RANDBETWEEN(10,15)&"%",IF(J62=7,RANDBETWEEN(8,10)&"%",IF(J62=8,RANDBETWEEN(6,8)&"%",IF(J62=9,RANDBETWEEN(4,6)&"%",IF(J62=10,RANDBETWEEN(2,4)&"%",""))))))))))) -> 1% | Q62: =IFERROR(L62*(M62+N62)*O62*P62,RANDBETWEEN(1,2)%*L62*(M62+N62)*O62) -> 0.036352247 | R62: =VLOOKUP(D:D,ranking!W:X,2,0) -> 0.7 | S62: =R62*Q62 -> 0.025446573 | T62: 10.114878
A63: WK-24'2026 | B63: ALL INDIA | C63: Lionsgate Play | D63: Theatrical Movies | E63: PAID | F63: Movies | G63: Match Point | H63: English | I63: 46192 | K63: Drama,Romance,Thriller | L63: =VLOOKUP($C63&$E63,'Updated SES'!A:N,14,0) -> 25.34 | M63: =VLOOKUP($K63,'Genre Penetration'!A:B,2,0)*VLOOKUP($C63&$E63,'Updated SES'!A:I,9,0) -> 0.328 | N63: =VLOOKUP(K:K,'Genre Penetration'!A:C,3,0)*VLOOKUP($C63&$E63,'Updated SES'!A:J,10,0) -> 0.108 | O63: =VLOOKUP($B63,'Language Penetration'!$B$1:$BE$14,MATCH('Compile data Working'!$H63,'Language Penetration'!$B$1:$BE$1,0),0) -> 0.2 | P63: =IF(ISBLANK(J63),RANDBETWEEN(1,2)&"%",IF(J63=1,RANDBETWEEN(35,40)&"%",IF(J63=2,RANDBETWEEN(30,35)&"%",IF(J63=3,RANDBETWEEN(25,30)&"%",IF(J63=4,RANDBETWEEN(20,25)&"%",IF(J63=5,RANDBETWEEN(15,20)&"%",IF(J63=6,RANDBETWEEN(10,15)&"%",IF(J63=7,RANDBETWEEN(8,10)&"%",IF(J63=8,RANDBETWEEN(6,8)&"%",IF(J63=9,RANDBETWEEN(4,6)&"%",IF(J63=10,RANDBETWEEN(2,4)&"%",""))))))))))) -> 1% | Q63: =IFERROR(L63*(M63+N63)*O63*P63,RANDBETWEEN(1,2)%*L63*(M63+N63)*O63) -> 0.02209648 | R63: =VLOOKUP(D:D,ranking!W:X,2,0) -> 0.7 | S63: =R63*Q63 -> 0.015467536 | T63: 9.9644887
A64: Trending Top 10 | B64: ALL INDIA | C64: Sony Liv | D64: Tv Catch-Up | E64: FREE | F64: Shows | G64: Indian Idol S16 | H64: Hindi | I64: 45948 | J64: 4 | K64: Reality Tv | L64: =VLOOKUP($C64&$E64,'Updated SES'!A:N,14,0) -> 5.268 | M64: =VLOOKUP($K64,'Genre Penetration'!A:B,2,0)*VLOOKUP($C64&$E64,'Updated SES'!A:I,9,0) -> 0.264 | N64: =VLOOKUP(K:K,'Genre Penetration'!A:C,3,0)*VLOOKUP($C64&$E64,'Updated SES'!A:J,10,0) -> 0.204 | O64: =VLOOKUP($B64,'Language Penetration'!$B$1:$BE$14,MATCH('Compile data Working'!$H64,'Language Penetration'!$B$1:$BE$1,0),0) -> 0.6 | P64: =IF(ISBLANK(J64),RANDBETWEEN(1,2)&"%",IF(J64=1,RANDBETWEEN(35,40)&"%",IF(J64=2,RANDBETWEEN(30,35)&"%",IF(J64=3,RANDBETWEEN(25,30)&"%",IF(J64=4,RANDBETWEEN(20,25)&"%",IF(J64=5,RANDBETWEEN(15,20)&"%",IF(J64=6,RANDBETWEEN(10,15)&"%",IF(J64=7,RANDBETWEEN(8,10)&"%",IF(J64=8,RANDBETWEEN(6,8)&"%",IF(J64=9,RANDBETWEEN(4,6)&"%",IF(J64=10,RANDBETWEEN(2,4)&"%",""))))))))))) -> 21% | Q64: =IFERROR(L64*(M64+N64)*O64*P64,RANDBETWEEN(1,2)%*L64*(M64+N64)*O64) -> 0.31064342 | R64: =VLOOKUP(D:D,ranking!W:X,2,0) -> 0.3 | S64: =R64*Q64 -> 0.093193027 | T64: 9.6945088
A65: WK-24'2026 | B65: ALL INDIA | C65: Amazon Prime Video | D65: Theatrical Movies | E65: PAID | F65: Movies | G65: Three Dates to Forever | H65: English | I65: 46190 | K65: Comedy,Romance | L65: =VLOOKUP($C65&$E65,'Updated SES'!A:N,14,0) -> 36.49824 | M65: =VLOOKUP($K65,'Genre Penetration'!A:B,2,0)*VLOOKUP($C65&$E65,'Updated SES'!A:I,9,0) -> 0.156 | N65: =VLOOKUP(K:K,'Genre Penetration'!A:C,3,0)*VLOOKUP($C65&$E65,'Updated SES'!A:J,10,0) -> 0.336 | O65: =VLOOKUP($B65,'Language Penetration'!$B$1:$BE$14,MATCH('Compile data Working'!$H65,'Language Penetration'!$B$1:$BE$1,0),0) -> 0.2 | P65: =IF(ISBLANK(J65),RANDBETWEEN(1,2)&"%",IF(J65=1,RANDBETWEEN(35,40)&"%",IF(J65=2,RANDBETWEEN(30,35)&"%",IF(J65=3,RANDBETWEEN(25,30)&"%",IF(J65=4,RANDBETWEEN(20,25)&"%",IF(J65=5,RANDBETWEEN(15,20)&"%",IF(J65=6,RANDBETWEEN(10,15)&"%",IF(J65=7,RANDBETWEEN(8,10)&"%",IF(J65=8,RANDBETWEEN(6,8)&"%",IF(J65=9,RANDBETWEEN(4,6)&"%",IF(J65=10,RANDBETWEEN(2,4)&"%",""))))))))))) -> 1% | Q65: =IFERROR(L65*(M65+N65)*O65*P65,RANDBETWEEN(1,2)%*L65*(M65+N65)*O65) -> 0.035914268 | R65: =VLOOKUP(D:D,ranking!W:X,2,0) -> 0.7 | S65: =R65*Q65 -> 0.025139988 | T65: 9.6551112
A66: WK-24'2026 | B66: ALL INDIA | C66: Apple Tv | D66: SVOD Originals Shows | E66: PAID | F66: Shows | G66: Sugar Season 2 | H66: English | I66: 46192 | K66: Action,Crime,Drama | L66: =VLOOKUP($C66&$E66,'Updated SES'!A:N,14,0) -> 1.669 | M66: =VLOOKUP($K66,'Genre Penetration'!A:B,2,0)*VLOOKUP($C66&$E66,'Updated SES'!A:I,9,0) -> 0.366 | N66: =VLOOKUP(K:K,'Genre Penetration'!A:C,3,0)*VLOOKUP($C66&$E66,'Updated SES'!A:J,10,0) -> 0.156 | O66: =VLOOKUP($B66,'Language Penetration'!$B$1:$BE$14,MATCH('Compile data Working'!$H66,'Language Penetration'!$B$1:$BE$1,0),0) -> 0.2 | P66: =IF(ISBLANK(J66),RANDBETWEEN(1,2)&"%",IF(J66=1,RANDBETWEEN(35,40)&"%",IF(J66=2,RANDBETWEEN(30,35)&"%",IF(J66=3,RANDBETWEEN(25,30)&"%",IF(J66=4,RANDBETWEEN(20,25)&"%",IF(J66=5,RANDBETWEEN(15,20)&"%",IF(J66=6,RANDBETWEEN(10,15)&"%",IF(J66=7,RANDBETWEEN(8,10)&"%",IF(J66=8,RANDBETWEEN(6,8)&"%",IF(J66=9,RANDBETWEEN(4,6)&"%",IF(J66=10,RANDBETWEEN(2,4)&"%",""))))))))))) -> 2% | Q66: =IFERROR(L66*(M66+N66)*O66*P66,RANDBETWEEN(1,2)%*L66*(M66+N66)*O66) -> 0.003484872 | R66: =VLOOKUP(D:D,ranking!W:X,2,0) -> 0.6 | S66: =R66*Q66 -> 0.0020909232 | T66: 9.5473728
A67: Cott Data Servey | B67: ALL INDIA | C67: JioHotstar | D67: Tv Catch-Up | E67: PAID | F67: Tv catchup | G67: Kyunki Saas Bhi Kabhi Bahu Thi | H67: Hindi | I67: 36710 | K67: Drama | L67: =VLOOKUP($C67&$E67,'Updated SES'!A:N,14,0) -> 127.11702 | M67: =VLOOKUP($K67,'Genre Penetration'!A:B,2,0)*VLOOKUP($C67&$E67,'Updated SES'!A:I,9,0) -> 0.335 | N67: =VLOOKUP(K:K,'Genre Penetration'!A:C,3,0)*VLOOKUP($C67&$E67,'Updated SES'!A:J,10,0) -> 0.165 | O67: =VLOOKUP($B67,'Language Penetration'!$B$1:$BE$14,MATCH('Compile data Working'!$H67,'Language Penetration'!$B$1:$BE$1,0),0) -> 0.6 | P67: =IF(ISBLANK(J67),RANDBETWEEN(1,2)&"%",IF(J67=1,RANDBETWEEN(35,40)&"%",IF(J67=2,RANDBETWEEN(30,35)&"%",IF(J67=3,RANDBETWEEN(25,30)&"%",IF(J67=4,RANDBETWEEN(20,25)&"%",IF(J67=5,RANDBETWEEN(15,20)&"%",IF(J67=6,RANDBETWEEN(10,15)&"%",IF(J67=7,RANDBETWEEN(8,10)&"%",IF(J67=8,RANDBETWEEN(6,8)&"%",IF(J67=9,RANDBETWEEN(4,6)&"%",IF(J67=10,RANDBETWEEN(2,4)&"%",""))))))))))) -> 2% | Q67: =IFERROR(L67*(M67+N67)*O67*P67,RANDBETWEEN(1,2)%*L67*(M67+N67)*O67) -> 0.76270212 | R67: =VLOOKUP(D:D,ranking!W:X,2,0) -> 0.3 | S67: =R67*Q67 -> 0.22881064 | T67: 9.52558
A68: WK-24'2026 | B68: ALL INDIA | C68: Amazon Prime Video | D68: Theatrical Movies | E68: PAID | F68: Movies | G68: You, Me, and that Mountain Retreat | H68: English | I68: 46190 | K68: Comedy,Romance | L68: =VLOOKUP($C68&$E68,'Updated SES'!A:N,14,0) -> 36.49824 | M68: =VLOOKUP($K68,'Genre Penetration'!A:B,2,0)*VLOOKUP($C68&$E68,'Updated SES'!A:I,9,0) -> 0.156 | N68: =VLOOKUP(K:K,'Genre Penetration'!A:C,3,0)*VLOOKUP($C68&$E68,'Updated SES'!A:J,10,0) -> 0.336 | O68: =VLOOKUP($B68,'Language Penetration'!$B$1:$BE$14,MATCH('Compile data Working'!$H68,'Language Penetration'!$B$1:$BE$1,0),0) -> 0.2 | P68: =IF(ISBLANK(J68),RANDBETWEEN(1,2)&"%",IF(J68=1,RANDBETWEEN(35,40)&"%",IF(J68=2,RANDBETWEEN(30,35)&"%",IF(J68=3,RANDBETWEEN(25,30)&"%",IF(J68=4,RANDBETWEEN(20,25)&"%",IF(J68=5,RANDBETWEEN(15,20)&"%",IF(J68=6,RANDBETWEEN(10,15)&"%",IF(J68=7,RANDBETWEEN(8,10)&"%",IF(J68=8,RANDBETWEEN(6,8)&"%",IF(J68=9,RANDBETWEEN(4,6)&"%",IF(J68=10,RANDBETWEEN(2,4)&"%",""))))))))))) -> 1% | Q68: =IFERROR(L68*(M68+N68)*O68*P68,RANDBETWEEN(1,2)%*L68*(M68+N68)*O68) -> 0.035914268 | R68: =VLOOKUP(D:D,ranking!W:X,2,0) -> 0.7 | S68: =R68*Q68 -> 0.025139988 | T68: 9.5018555
A69: WK-24'2026 | B69: ALL INDIA | C69: Amazon Prime Video | D69: Theatrical Movies | E69: RENT | F69: Movies | G69: Dark Tracking | H69: Malayalam | I69: 46188 | K69: Mystery | L69: =VLOOKUP($C69&$E69,'Updated SES'!A:N,14,0) -> 4.689 | M69: =VLOOKUP($K69,'Genre Penetration'!A:B,2,0)*VLOOKUP($C69&$E69,'Updated SES'!A:I,9,0) -> 0.374 | N69: =VLOOKUP(K:K,'Genre Penetration'!A:C,3,0)*VLOOKUP($C69&$E69,'Updated SES'!A:J,10,0) -> 0.144 | O69: =VLOOKUP($B69,'Language Penetration'!$B$1:$BE$14,MATCH('Compile data Working'!$H69,'Language Penetration'!$B$1:$BE$1,0),0) -> 0.07 | P69: =IF(ISBLANK(J69),RANDBETWEEN(1,2)&"%",IF(J69=1,RANDBETWEEN(35,40)&"%",IF(J69=2,RANDBETWEEN(30,35)&"%",IF(J69=3,RANDBETWEEN(25,30)&"%",IF(J69=4,RANDBETWEEN(20,25)&"%",IF(J69=5,RANDBETWEEN(15,20)&"%",IF(J69=6,RANDBETWEEN(10,15)&"%",IF(J69=7,RANDBETWEEN(8,10)&"%",IF(J69=8,RANDBETWEEN(6,8)&"%",IF(J69=9,RANDBETWEEN(4,6)&"%",IF(J69=10,RANDBETWEEN(2,4)&"%",""))))))))))) -> 1% | Q69: =IFERROR(L69*(M69+N69)*O69*P69,RANDBETWEEN(1,2)%*L69*(M69+N69)*O69) -> 0.0017002314 | R69: =VLOOKUP(D:D,ranking!W:X,2,0) -> 0.7 | S69: =R69*Q69 -> 0.001190162 | T69: 9.195344
A70: Trending Top 10 | B70: ALL INDIA | C70: Netflix | D70: Svod Originals Shows | E70: PAID | F70: Shows | G70: Berlin and the Lady with an Ermine | H70: English,Hindi,Tamil,Telugu | I70: 46157 | J70: 5 | K70: Crime,Drama,Thriller | L70: =VLOOKUP($C70&$E70,'Updated SES'!A:N,14,0) -> 55.4592 | M70: =VLOOKUP($K70,'Genre Penetration'!A:B,2,0)*VLOOKUP($C70&$E70,'Updated SES'!A:I,9,0) -> 0.3528 | N70: =VLOOKUP(K:K,'Genre Penetration'!A:C,3,0)*VLOOKUP($C70&$E70,'Updated SES'!A:J,10,0) -> 0.1428 | O70: =VLOOKUP($B70,'Language Penetration'!$B$1:$BE$14,MATCH('Compile data Working'!$H70,'Language Penetration'!$B$1:$BE$1,0),0) -> 0.2625 | P70: =IF(ISBLANK(J70),RANDBETWEEN(1,2)&"%",IF(J70=1,RANDBETWEEN(35,40)&"%",IF(J70=2,RANDBETWEEN(30,35)&"%",IF(J70=3,RANDBETWEEN(25,30)&"%",IF(J70=4,RANDBETWEEN(20,25)&"%",IF(J70=5,RANDBETWEEN(15,20)&"%",IF(J70=6,RANDBETWEEN(10,15)&"%",IF(J70=7,RANDBETWEEN(8,10)&"%",IF(J70=8,RANDBETWEEN(6,8)&"%",IF(J70=9,RANDBETWEEN(4,6)&"%",IF(J70=10,RANDBETWEEN(2,4)&"%",""))))))))))) -> 19% | Q70: =IFERROR(L70*(M70+N70)*O70*P70,RANDBETWEEN(1,2)%*L70*(M70+N70)*O70) -> 1.3708433 | R70: =VLOOKUP(D:D,ranking!W:X,2,0) -> 0.6 | S70: =R70*Q70 -> 0.82250597 | T70: 8.9568392
A71: Trending Top 10 | B71: ALL INDIA | C71: Amazon Prime Video | D71: Svod Originals Shows | E71: PAID | F71: Shows | G71: Off Campus | H71: English,Hindi,Kannada,Malayalam,Tamil,Telugu | I71: 46155 | J71: 4 | K71: Drama,Romance | L71: =VLOOKUP($C71&$E71,'Updated SES'!A:N,14,0) -> 36.49824 | M71: =VLOOKUP($K71,'Genre Penetration'!A:B,2,0)*VLOOKUP($C71&$E71,'Updated SES'!A:I,9,0) -> 0.208 | N71: =VLOOKUP(K:K,'Genre Penetration'!A:C,3,0)*VLOOKUP($C71&$E71,'Updated SES'!A:J,10,0) -> 0.288 | O71: =VLOOKUP($B71,'Language Penetration'!$B$1:$BE$14,MATCH('Compile data Working'!$H71,'Language Penetration'!$B$1:$BE$1,0),0) -> 0.20333333 | P71: =IF(ISBLANK(J71),RANDBETWEEN(1,2)&"%",IF(J71=1,RANDBETWEEN(35,40)&"%",IF(J71=2,RANDBETWEEN(30,35)&"%",IF(J71=3,RANDBETWEEN(25,30)&"%",IF(J71=4,RANDBETWEEN(20,25)&"%",IF(J71=5,RANDBETWEEN(15,20)&"%",IF(J71=6,RANDBETWEEN(10,15)&"%",IF(J71=7,RANDBETWEEN(8,10)&"%",IF(J71=8,RANDBETWEEN(6,8)&"%",IF(J71=9,RANDBETWEEN(4,6)&"%",IF(J71=10,RANDBETWEEN(2,4)&"%",""))))))))))) -> 23% | Q71: =IFERROR(L71*(M71+N71)*O71*P71,RANDBETWEEN(1,2)%*L71*(M71+N71)*O71) -> 0.84662291 | R71: =VLOOKUP(D:D,ranking!W:X,2,0) -> 0.6 | S71: =R71*Q71 -> 0.50797374 | T71: 8.6180274
A72: Cott Data Servey | B72: ALL INDIA | C72: JioHotstar | D72: Tv Catch-Up | E72: PAID | F72: Tv catchup | G72: Yeh Rishta Kya Kehlata Hai | H72: Hindi | I72: 39825 | K72: Drama | L72: =VLOOKUP($C72&$E72,'Updated SES'!A:N,14,0) -> 127.11702 | M72: =VLOOKUP($K72,'Genre Penetration'!A:B,2,0)*VLOOKUP($C72&$E72,'Updated SES'!A:I,9,0) -> 0.335 | N72: =VLOOKUP(K:K,'Genre Penetration'!A:C,3,0)*VLOOKUP($C72&$E72,'Updated SES'!A:J,10,0) -> 0.165 | O72: =VLOOKUP($B72,'Language Penetration'!$B$1:$BE$14,MATCH('Compile data Working'!$H72,'Language Penetration'!$B$1:$BE$1,0),0) -> 0.6 | P72: =IF(ISBLANK(J72),RANDBETWEEN(1,2)&"%",IF(J72=1,RANDBETWEEN(35,40)&"%",IF(J72=2,RANDBETWEEN(30,35)&"%",IF(J72=3,RANDBETWEEN(25,30)&"%",IF(J72=4,RANDBETWEEN(20,25)&"%",IF(J72=5,RANDBETWEEN(15,20)&"%",IF(J72=6,RANDBETWEEN(10,15)&"%",IF(J72=7,RANDBETWEEN(8,10)&"%",IF(J72=8,RANDBETWEEN(6,8)&"%",IF(J72=9,RANDBETWEEN(4,6)&"%",IF(J72=10,RANDBETWEEN(2,4)&"%",""))))))))))) -> 2% | Q72: =IFERROR(L72*(M72+N72)*O72*P72,RANDBETWEEN(1,2)%*L72*(M72+N72)*O72) -> 0.76270212 | R72: =VLOOKUP(D:D,ranking!W:X,2,0) -> 0.3 | S72: =R72*Q72 -> 0.22881064 | T72: 8.0671479
A73: Trending Top 10 | B73: ALL INDIA | C73: Amazon MX Player | D73: Avod Originals Shows | E73: FREE | F73: Shows | G73: Taarak Mehta Ka Ooltah Chashmah | H73: Hindi | I73: 46095 | J73: 8 | K73: Comedy,Drama | L73: =VLOOKUP($C73&$E73,'Updated SES'!A:N,14,0) -> 78.93987 | M73: =VLOOKUP($K73,'Genre Penetration'!A:B,2,0)*VLOOKUP($C73&$E73,'Updated SES'!A:I,9,0) -> 0.376 | N73: =VLOOKUP(K:K,'Genre Penetration'!A:C,3,0)*VLOOKUP($C73&$E73,'Updated SES'!A:J,10,0) -> 0.106 | O73: =VLOOKUP($B73,'Language Penetration'!$B$1:$BE$14,MATCH('Compile data Working'!$H56,'Language Penetration'!$B$1:$BE$1,0),0) -> 0.6 | P73: =IF(ISBLANK(J73),RANDBETWEEN(1,2)&"%",IF(J73=1,RANDBETWEEN(35,40)&"%",IF(J73=2,RANDBETWEEN(30,35)&"%",IF(J73=3,RANDBETWEEN(25,30)&"%",IF(J73=4,RANDBETWEEN(20,25)&"%",IF(J73=5,RANDBETWEEN(15,20)&"%",IF(J73=6,RANDBETWEEN(10,15)&"%",IF(J73=7,RANDBETWEEN(8,10)&"%",IF(J73=8,RANDBETWEEN(6,8)&"%",IF(J73=9,RANDBETWEEN(4,6)&"%",IF(J73=10,RANDBETWEEN(2,4)&"%",""))))))))))) -> 6% | Q73: =IFERROR(L73*(M73+N73)*O73*P73,RANDBETWEEN(1,2)%*L73*(M73+N73)*O73) -> 1.3697646 | R73: =VLOOKUP(D:D,ranking!W:X,2,0) -> 0.6 | S73: =R73*Q73 -> 0.82185877 | T73: 8.7627106
A74: Cott Data Servey | B74: ALL INDIA | C74: JioHotstar | D74: Tv Catch-Up | E74: PAID | F74: Tv catchup | G74: Thai Maaman | H74: Tamil | I74: - | K74: Drama | L74: =VLOOKUP($C74&$E74,'Updated SES'!A:N,14,0) -> 127.11702 | M74: =VLOOKUP($K74,'Genre Penetration'!A:B,2,0)*VLOOKUP($C74&$E74,'Updated SES'!A:I,9,0) -> 0.335 | N74: =VLOOKUP(K:K,'Genre Penetration'!A:C,3,0)*VLOOKUP($C74&$E74,'Updated SES'!A:J,10,0) -> 0.165 | O74: =VLOOKUP($B74,'Language Penetration'!$B$1:$BE$14,MATCH('Compile data Working'!$H74,'Language Penetration'!$B$1:$BE$1,0),0) -> 0.1 | P74: =IF(ISBLANK(J74),RANDBETWEEN(1,2)&"%",IF(J74=1,RANDBETWEEN(35,40)&"%",IF(J74=2,RANDBETWEEN(30,35)&"%",IF(J74=3,RANDBETWEEN(25,30)&"%",IF(J74=4,RANDBETWEEN(20,25)&"%",IF(J74=5,RANDBETWEEN(15,20)&"%",IF(J74=6,RANDBETWEEN(10,15)&"%",IF(J74=7,RANDBETWEEN(8,10)&"%",IF(J74=8,RANDBETWEEN(6,8)&"%",IF(J74=9,RANDBETWEEN(4,6)&"%",IF(J74=10,RANDBETWEEN(2,4)&"%",""))))))))))) -> 1% | Q74: =IFERROR(L74*(M74+N74)*O74*P74,RANDBETWEEN(1,2)%*L74*(M74+N74)*O74) -> 0.06355851 | R74: =VLOOKUP(D:D,ranking!W:X,2,0) -> 0.3 | S74: =R74*Q74 -> 0.019067553 | T74: 7.9256791
A75: Trending Top 10 | B75: ALL INDIA | C75: Netflix | D75: Theatrical Movies | E75: PAID | F75: Movies | G75: Kara | H75: Hindi,Kannada,Malayalam,Tamil,Telugu | I75: 46170 | J75: 4 | K75: Action,Crime,Thriller | L75: =VLOOKUP($C75&$E75,'Updated SES'!A:N,14,0) -> 55.4592 | M75: =VLOOKUP($K75,'Genre Penetration'!A:B,2,0)*VLOOKUP($C75&$E75,'Updated SES'!A:I,9,0) -> 0.3528 | N75: =VLOOKUP(K:K,'Genre Penetration'!A:C,3,0)*VLOOKUP($C75&$E75,'Updated SES'!A:J,10,0) -> 0.1428 | O75: =VLOOKUP($B75,'Language Penetration'!$B$1:$BE$14,MATCH('Compile data Working'!$H75,'Language Penetration'!$B$1:$BE$1,0),0) -> 0.204 | P75: =IF(ISBLANK(J75),RANDBETWEEN(1,2)&"%",IF(J75=1,RANDBETWEEN(35,40)&"%",IF(J75=2,RANDBETWEEN(30,35)&"%",IF(J75=3,RANDBETWEEN(25,30)&"%",IF(J75=4,RANDBETWEEN(20,25)&"%",IF(J75=5,RANDBETWEEN(15,20)&"%",IF(J75=6,RANDBETWEEN(10,15)&"%",IF(J75=7,RANDBETWEEN(8,10)&"%",IF(J75=8,RANDBETWEEN(6,8)&"%",IF(J75=9,RANDBETWEEN(4,6)&"%",IF(J75=10,RANDBETWEEN(2,4)&"%",""))))))))))) -> 25% | Q75: =IFERROR(L75*(M75+N75)*O75*P75,RANDBETWEEN(1,2)%*L75*(M75+N75)*O75) -> 1.4017646 | R75: =VLOOKUP(D:D,ranking!W:X,2,0) -> 0.7 | S75: =R75*Q75 -> 0.98123519 | T75: 7.9029149
A76: Trending Top 10 | B76: ALL INDIA | C76: Netflix | D76: Svod Originals Shows | E76: PAID | F76: Shows | G76: Viral Hit | H76: English | I76: 46184 | J76: 4 | K76: Action,Drama,Thriller | L76: =VLOOKUP($C76&$E76,'Updated SES'!A:N,14,0) -> 55.4592 | M76: =VLOOKUP($K76,'Genre Penetration'!A:B,2,0)*VLOOKUP($C76&$E76,'Updated SES'!A:I,9,0) -> 0.3332 | N76: =VLOOKUP(K:K,'Genre Penetration'!A:C,3,0)*VLOOKUP($C76&$E76,'Updated SES'!A:J,10,0) -> 0.1632 | O76: =VLOOKUP($B76,'Language Penetration'!$B$1:$BE$14,MATCH('Compile data Working'!$H76,'Language Penetration'!$B$1:$BE$1,0),0) -> 0.2 | P76: =IF(ISBLANK(J76),RANDBETWEEN(1,2)&"%",IF(J76=1,RANDBETWEEN(35,40)&"%",IF(J76=2,RANDBETWEEN(30,35)&"%",IF(J76=3,RANDBETWEEN(25,30)&"%",IF(J76=4,RANDBETWEEN(20,25)&"%",IF(J76=5,RANDBETWEEN(15,20)&"%",IF(J76=6,RANDBETWEEN(10,15)&"%",IF(J76=7,RANDBETWEEN(8,10)&"%",IF(J76=8,RANDBETWEEN(6,8)&"%",IF(J76=9,RANDBETWEEN(4,6)&"%",IF(J76=10,RANDBETWEEN(2,4)&"%",""))))))))))) -> 25% | Q76: =IFERROR(L76*(M76+N76)*O76*P76,RANDBETWEEN(1,2)%*L76*(M76+N76)*O76) -> 1.3764973 | R76: =VLOOKUP(D:D,ranking!W:X,2,0) -> 0.6 | S76: =R76*Q76 -> 0.82589841 | T76: 7.7869262
A77: Cott Data Servey | B77: ALL INDIA | C77: JioHotstar | D77: Tv Catch-Up | E77: PAID | F77: Tv catchup | G77: Siragadikka Aasai | H77: Tamil | I77: 44949 | K77: Drama | L77: =VLOOKUP($C77&$E77,'Updated SES'!A:N,14,0) -> 127.11702 | M77: =VLOOKUP($K77,'Genre Penetration'!A:B,2,0)*VLOOKUP($C77&$E77,'Updated SES'!A:I,9,0) -> 0.335 | N77: =VLOOKUP(K:K,'Genre Penetration'!A:C,3,0)*VLOOKUP($C77&$E77,'Updated SES'!A:J,10,0) -> 0.165 | O77: =VLOOKUP($B77,'Language Penetration'!$B$1:$BE$14,MATCH('Compile data Working'!$H77,'Language Penetration'!$B$1:$BE$1,0),0) -> 0.1 | P77: =IF(ISBLANK(J77),RANDBETWEEN(1,2)&"%",IF(J77=1,RANDBETWEEN(35,40)&"%",IF(J77=2,RANDBETWEEN(30,35)&"%",IF(J77=3,RANDBETWEEN(25,30)&"%",IF(J77=4,RANDBETWEEN(20,25)&"%",IF(J77=5,RANDBETWEEN(15,20)&"%",IF(J77=6,RANDBETWEEN(10,15)&"%",IF(J77=7,RANDBETWEEN(8,10)&"%",IF(J77=8,RANDBETWEEN(6,8)&"%",IF(J77=9,RANDBETWEEN(4,6)&"%",IF(J77=10,RANDBETWEEN(2,4)&"%",""))))))))))) -> 1% | Q77: =IFERROR(L77*(M77+N77)*O77*P77,RANDBETWEEN(1,2)%*L77*(M77+N77)*O77) -> 0.06355851 | R77: =VLOOKUP(D:D,ranking!W:X,2,0) -> 0.3 | S77: =R77*Q77 -> 0.019067553 | T77: 7.6841973
A78: Trending Top 10 | B78: ALL INDIA | C78: Sony Liv | D78: Svod Originals Shows | E78: PAID | F78: Shows | G78: Manvat Murders | H78: Hindi | I78: 45568 | J78: 8 | K78: Crime,Thriller | L78: =VLOOKUP($C78&$E78,'Updated SES'!A:N,14,0) -> 21.68204 | M78: =VLOOKUP($K78,'Genre Penetration'!A:B,2,0)*VLOOKUP($C78&$E78,'Updated SES'!A:I,9,0) -> 0.403 | N78: =VLOOKUP(K:K,'Genre Penetration'!A:C,3,0)*VLOOKUP($C78&$E78,'Updated SES'!A:J,10,0) -> 0.133 | O78: =VLOOKUP($B78,'Language Penetration'!$B$1:$BE$14,MATCH('Compile data Working'!$H78,'Language Penetration'!$B$1:$BE$1,0),0) -> 0.6 | P78: =IF(ISBLANK(J78),RANDBETWEEN(1,2)&"%",IF(J78=1,RANDBETWEEN(35,40)&"%",IF(J78=2,RANDBETWEEN(30,35)&"%",IF(J78=3,RANDBETWEEN(25,30)&"%",IF(J78=4,RANDBETWEEN(20,25)&"%",IF(J78=5,RANDBETWEEN(15,20)&"%",IF(J78=6,RANDBETWEEN(10,15)&"%",IF(J78=7,RANDBETWEEN(8,10)&"%",IF(J78=8,RANDBETWEEN(6,8)&"%",IF(J78=9,RANDBETWEEN(4,6)&"%",IF(J78=10,RANDBETWEEN(2,4)&"%",""))))))))))) -> 6% | Q78: =IFERROR(L78*(M78+N78)*O78*P78,RANDBETWEEN(1,2)%*L78*(M78+N78)*O78) -> 0.41837664 | R78: =VLOOKUP(D:D,ranking!W:X,2,0) -> 0.6 | S78: =R78*Q78 -> 0.25102599 | T78: 7.2621646
A79: WK-24'2026 | B79: ALL INDIA | C79: Manorama Max | D79: Theatrical Movies | E79: PAID | F79: Movies | G79: Kolahalamedu | H79: Malayalam | I79: 46189 | K79: Thriller | L79: =VLOOKUP($C79&$E79,'Updated SES'!A:N,14,0) -> 0.1509 | M79: =VLOOKUP($K79,'Genre Penetration'!A:B,2,0)*VLOOKUP($C79&$E79,'Updated SES'!A:I,9,0) -> 0.4736 | N79: =VLOOKUP(K:K,'Genre Penetration'!A:C,3,0)*VLOOKUP($C79&$E79,'Updated SES'!A:J,10,0) -> 0.0936 | O79: =VLOOKUP($B79,'Language Penetration'!$B$1:$BE$14,MATCH('Compile data Working'!$H79,'Language Penetration'!$B$1:$BE$1,0),0) -> 0.07 | P79: =IF(ISBLANK(J79),RANDBETWEEN(1,2)&"%",IF(J79=1,RANDBETWEEN(35,40)&"%",IF(J79=2,RANDBETWEEN(30,35)&"%",IF(J79=3,RANDBETWEEN(25,30)&"%",IF(J79=4,RANDBETWEEN(20,25)&"%",IF(J79=5,RANDBETWEEN(15,20)&"%",IF(J79=6,RANDBETWEEN(10,15)&"%",IF(J79=7,RANDBETWEEN(8,10)&"%",IF(J79=8,RANDBETWEEN(6,8)&"%",IF(J79=9,RANDBETWEEN(4,6)&"%",IF(J79=10,RANDBETWEEN(2,4)&"%",""))))))))))) -> 2% | Q79: =IFERROR(L79*(M79+N79)*O79*P79,RANDBETWEEN(1,2)%*L79*(M79+N79)*O79) -> 0.00011982667 | R79: =VLOOKUP(D:D,ranking!W:X,2,0) -> 0.7 | S79: =R79*Q79 -> 8.387867e-05 | T79: 7.1644391
A80: Trending Top 10 | B80: ALL INDIA | C80: Sony Liv | D80: Svod Originals Shows | E80: PAID | F80: Shows | G80: Undekhi S4 | H80: Bengali,Hindi,Kannada,Malayalam,Marathi,Tamil,Telugu | I80: 46143 | J80: 10 | K80: Crime,Drama,Thriller | L80: =VLOOKUP($C80&$E80,'Updated SES'!A:N,14,0) -> 21.68204 | M80: =VLOOKUP($K80,'Genre Penetration'!A:B,2,0)*VLOOKUP($C80&$E80,'Updated SES'!A:I,9,0) -> 0.468 | N80: =VLOOKUP(K:K,'Genre Penetration'!A:C,3,0)*VLOOKUP($C80&$E80,'Updated SES'!A:J,10,0) -> 0.098 | O80: =VLOOKUP($B80,'Language Penetration'!$B$1:$BE$14,MATCH('Compile data Working'!$H80,'Language Penetration'!$B$1:$BE$1,0),0) -> 0.17714286 | P80: =IF(ISBLANK(J80),RANDBETWEEN(1,2)&"%",IF(J80=1,RANDBETWEEN(35,40)&"%",IF(J80=2,RANDBETWEEN(30,35)&"%",IF(J80=3,RANDBETWEEN(25,30)&"%",IF(J80=4,RANDBETWEEN(20,25)&"%",IF(J80=5,RANDBETWEEN(15,20)&"%",IF(J80=6,RANDBETWEEN(10,15)&"%",IF(J80=7,RANDBETWEEN(8,10)&"%",IF(J80=8,RANDBETWEEN(6,8)&"%",IF(J80=9,RANDBETWEEN(4,6)&"%",IF(J80=10,RANDBETWEEN(2,4)&"%",""))))))))))) -> 4% | Q80: =IFERROR(L80*(M80+N80)*O80*P80,RANDBETWEEN(1,2)%*L80*(M80+N80)*O80) -> 0.086956131 | R80: =VLOOKUP(D:D,ranking!W:X,2,0) -> 0.6 | S80: =R80*Q80 -> 0.052173679 | T80: 6.7719951
A81: Trending Top 10 | B81: ALL INDIA | C81: Zee5 | D81: Svod Originals Shows | E81: PAID | F81: Shows | G81: Satrangi: Badle ka Khel | H81: Hindi | I81: 46164 | J81: 3 | K81: Action,Crime | L81: =VLOOKUP($C81&$E81,'Updated SES'!A:N,14,0) -> 60.152 | M81: =VLOOKUP($K81,'Genre Penetration'!A:B,2,0)*VLOOKUP($C81&$E81,'Updated SES'!A:I,9,0) -> 0.416 | N81: =VLOOKUP(K:K,'Genre Penetration'!A:C,3,0)*VLOOKUP($C81&$E81,'Updated SES'!A:J,10,0) -> 0.126 | O81: =VLOOKUP($B81,'Language Penetration'!$B$1:$BE$14,MATCH('Compile data Working'!$H81,'Language Penetration'!$B$1:$BE$1,0),0) -> 0.6 | P81: =IF(ISBLANK(J81),RANDBETWEEN(1,2)&"%",IF(J81=1,RANDBETWEEN(35,40)&"%",IF(J81=2,RANDBETWEEN(30,35)&"%",IF(J81=3,RANDBETWEEN(25,30)&"%",IF(J81=4,RANDBETWEEN(20,25)&"%",IF(J81=5,RANDBETWEEN(15,20)&"%",IF(J81=6,RANDBETWEEN(10,15)&"%",IF(J81=7,RANDBETWEEN(8,10)&"%",IF(J81=8,RANDBETWEEN(6,8)&"%",IF(J81=9,RANDBETWEEN(4,6)&"%",IF(J81=10,RANDBETWEEN(2,4)&"%",""))))))))))) -> 29% | Q81: =IFERROR(L81*(M81+N81)*O81*P81,RANDBETWEEN(1,2)%*L81*(M81+N81)*O81) -> 5.6728148 | R81: =VLOOKUP(D:D,ranking!W:X,2,0) -> 0.6 | S81: =R81*Q81 -> 3.4036889 | T81: 6.0138544
A82: Cott Data Servey | B82: ALL INDIA | C82: JioHotstar | D82: Tv Catch-Up | E82: PAID | F82: Tv catchup | G82: Dr. Aarambhi | H82: Hindi | I82: - | K82: Drama | L82: =VLOOKUP($C82&$E82,'Updated SES'!A:N,14,0) -> 127.11702 | M82: =VLOOKUP($K82,'Genre Penetration'!A:B,2,0)*VLOOKUP($C82&$E82,'Updated SES'!A:I,9,0) -> 0.335 | N82: =VLOOKUP(K:K,'Genre Penetration'!A:C,3,0)*VLOOKUP($C82&$E82,'Updated SES'!A:J,10,0) -> 0.165 | O82: =VLOOKUP($B82,'Language Penetration'!$B$1:$BE$14,MATCH('Compile data Working'!$H82,'Language Penetration'!$B$1:$BE$1,0),0) -> 0.6 | P82: =IF(ISBLANK(J82),RANDBETWEEN(1,2)&"%",IF(J82=1,RANDBETWEEN(35,40)&"%",IF(J82=2,RANDBETWEEN(30,35)&"%",IF(J82=3,RANDBETWEEN(25,30)&"%",IF(J82=4,RANDBETWEEN(20,25)&"%",IF(J82=5,RANDBETWEEN(15,20)&"%",IF(J82=6,RANDBETWEEN(10,15)&"%",IF(J82=7,RANDBETWEEN(8,10)&"%",IF(J82=8,RANDBETWEEN(6,8)&"%",IF(J82=9,RANDBETWEEN(4,6)&"%",IF(J82=10,RANDBETWEEN(2,4)&"%",""))))))))))) -> 2% | Q82: =IFERROR(L82*(M82+N82)*O82*P82,RANDBETWEEN(1,2)%*L82*(M82+N82)*O82) -> 0.76270212 | R82: =VLOOKUP(D:D,ranking!W:X,2,0) -> 0.3 | S82: =R82*Q82 -> 0.22881064 | T82: 5.6976606
A83: Trending Top 10 | B83: ALL INDIA | C83: Netflix | D83: Svod Originals Shows | E83: PAID | F83: Shows | G83: Desi Bling | H83: English,Hindi,Tamil,Telugu | I83: 46162 | J83: 10 | K83: Reality Tv | L83: =VLOOKUP($C83&$E83,'Updated SES'!A:N,14,0) -> 55.4592 | M83: =VLOOKUP($K83,'Genre Penetration'!A:B,2,0)*VLOOKUP($C83&$E83,'Updated SES'!A:I,9,0) -> 0.196 | N83: =VLOOKUP(K:K,'Genre Penetration'!A:C,3,0)*VLOOKUP($C83&$E83,'Updated SES'!A:J,10,0) -> 0.306 | O83: =VLOOKUP($B83,'Language Penetration'!$B$1:$BE$14,MATCH('Compile data Working'!$H83,'Language Penetration'!$B$1:$BE$1,0),0) -> 0.2625 | P83: =IF(ISBLANK(J83),RANDBETWEEN(1,2)&"%",IF(J83=1,RANDBETWEEN(35,40)&"%",IF(J83=2,RANDBETWEEN(30,35)&"%",IF(J83=3,RANDBETWEEN(25,30)&"%",IF(J83=4,RANDBETWEEN(20,25)&"%",IF(J83=5,RANDBETWEEN(15,20)&"%",IF(J83=6,RANDBETWEEN(10,15)&"%",IF(J83=7,RANDBETWEEN(8,10)&"%",IF(J83=8,RANDBETWEEN(6,8)&"%",IF(J83=9,RANDBETWEEN(4,6)&"%",IF(J83=10,RANDBETWEEN(2,4)&"%",""))))))))))) -> 4% | Q83: =IFERROR(L83*(M83+N83)*O83*P83,RANDBETWEEN(1,2)%*L83*(M83+N83)*O83) -> 0.29232544 | R83: =VLOOKUP(D:D,ranking!W:X,2,0) -> 0.6 | S83: =R83*Q83 -> 0.17539527 | T83: 5.5513662
A84: WK-24'2026 | B84: ALL INDIA | C84: Aha Video | D84: Theatrical Movies | E84: PAID | F84: Movies | G84: Razor | H84: Telugu | I84: 46192 | K84: Action,Drama,Thriller | L84: =VLOOKUP($C84&$E84,'Updated SES'!A:N,14,0) -> 12.62664 | M84: =VLOOKUP($K84,'Genre Penetration'!A:B,2,0)*VLOOKUP($C84&$E84,'Updated SES'!A:I,9,0) -> 0.5168 | N84: =VLOOKUP(K:K,'Genre Penetration'!A:C,3,0)*VLOOKUP($C84&$E84,'Updated SES'!A:J,10,0) -> 0.0768 | O84: =VLOOKUP($B84,'Language Penetration'!$B$1:$BE$14,MATCH('Compile data Working'!$H84,'Language Penetration'!$B$1:$BE$1,0),0) -> 0.15 | P84: =IF(ISBLANK(J84),RANDBETWEEN(1,2)&"%",IF(J84=1,RANDBETWEEN(35,40)&"%",IF(J84=2,RANDBETWEEN(30,35)&"%",IF(J84=3,RANDBETWEEN(25,30)&"%",IF(J84=4,RANDBETWEEN(20,25)&"%",IF(J84=5,RANDBETWEEN(15,20)&"%",IF(J84=6,RANDBETWEEN(10,15)&"%",IF(J84=7,RANDBETWEEN(8,10)&"%",IF(J84=8,RANDBETWEEN(6,8)&"%",IF(J84=9,RANDBETWEEN(4,6)&"%",IF(J84=10,RANDBETWEEN(2,4)&"%",""))))))))))) -> 2% | Q84: =IFERROR(L84*(M84+N84)*O84*P84,RANDBETWEEN(1,2)%*L84*(M84+N84)*O84) -> 0.022485521 | R84: =VLOOKUP(D:D,ranking!W:X,2,0) -> 0.7 | S84: =R84*Q84 -> 0.015739864 | T84: 5.4103648
A85: Trending Top 10 | B85: ALL INDIA | C85: Amazon Prime Video | D85: Theatrical Movies | E85: PAID | F85: Movies | G85: Veerabhadrudu | H85: Telugu | I85: 46185 | J85: 8 | K85: Action,Comedy,Drama | L85: =VLOOKUP($C85&$E85,'Updated SES'!A:N,14,0) -> 36.49824 | M85: =VLOOKUP($K85,'Genre Penetration'!A:B,2,0)*VLOOKUP($C85&$E85,'Updated SES'!A:I,9,0) -> 0.2496 | N85: =VLOOKUP(K:K,'Genre Penetration'!A:C,3,0)*VLOOKUP($C85&$E85,'Updated SES'!A:J,10,0) -> 0.2496 | O85: =VLOOKUP($B85,'Language Penetration'!$B$1:$BE$14,MATCH('Compile data Working'!$H85,'Language Penetration'!$B$1:$BE$1,0),0) -> 0.15 | P85: =IF(ISBLANK(J85),RANDBETWEEN(1,2)&"%",IF(J85=1,RANDBETWEEN(35,40)&"%",IF(J85=2,RANDBETWEEN(30,35)&"%",IF(J85=3,RANDBETWEEN(25,30)&"%",IF(J85=4,RANDBETWEEN(20,25)&"%",IF(J85=5,RANDBETWEEN(15,20)&"%",IF(J85=6,RANDBETWEEN(10,15)&"%",IF(J85=7,RANDBETWEEN(8,10)&"%",IF(J85=8,RANDBETWEEN(6,8)&"%",IF(J85=9,RANDBETWEEN(4,6)&"%",IF(J85=10,RANDBETWEEN(2,4)&"%",""))))))))))) -> 6% | Q85: =IFERROR(L85*(M85+N85)*O85*P85,RANDBETWEEN(1,2)%*L85*(M85+N85)*O85) -> 0.16397929 | R85: =VLOOKUP(D:D,ranking!W:X,2,0) -> 0.7 | S85: =R85*Q85 -> 0.1147855 | T85: 5.057512
A86: Trending Top 10 | B86: ALL INDIA | C86: Netflix | D86: Svod Originals Shows | E86: PAID | F86: Shows | G86: If Wishes Could Kill | H86: English,Hindi,Telugu | I86: 46136 | J86: 9 | K86: Drama,Mystery,Thriller | L86: =VLOOKUP($C86&$E86,'Updated SES'!A:N,14,0) -> 55.4592 | M86: =VLOOKUP($K86,'Genre Penetration'!A:B,2,0)*VLOOKUP($C86&$E86,'Updated SES'!A:I,9,0) -> 0.26705 | N86: =VLOOKUP(K:K,'Genre Penetration'!A:C,3,0)*VLOOKUP($C86&$E86,'Updated SES'!A:J,10,0) -> 0.23205 | O86: =VLOOKUP($B86,'Language Penetration'!$B$1:$BE$14,MATCH('Compile data Working'!$H86,'Language Penetration'!$B$1:$BE$1,0),0) -> 0.3 | P86: =IF(ISBLANK(J86),RANDBETWEEN(1,2)&"%",IF(J86=1,RANDBETWEEN(35,40)&"%",IF(J86=2,RANDBETWEEN(30,35)&"%",IF(J86=3,RANDBETWEEN(25,30)&"%",IF(J86=4,RANDBETWEEN(20,25)&"%",IF(J86=5,RANDBETWEEN(15,20)&"%",IF(J86=6,RANDBETWEEN(10,15)&"%",IF(J86=7,RANDBETWEEN(8,10)&"%",IF(J86=8,RANDBETWEEN(6,8)&"%",IF(J86=9,RANDBETWEEN(4,6)&"%",IF(J86=10,RANDBETWEEN(2,4)&"%",""))))))))))) -> 6% | Q86: =IFERROR(L86*(M86+N86)*O86*P86,RANDBETWEEN(1,2)%*L86*(M86+N86)*O86) -> 0.49823436 | R86: =VLOOKUP(D:D,ranking!W:X,2,0) -> 0.6 | S86: =R86*Q86 -> 0.29894062 | T86: 4.6157571
A87: Trending Top 10 | B87: ALL INDIA | C87: Zee5 | D87: Avod Originals Shows | E87: FREE | F87: Shows | G87: Hathras 16 days | H87: Hindi | I87: 46157 | J87: 4 | K87: Crime,Documentary | L87: =VLOOKUP($C87&$E87,'Updated SES'!A:N,14,0) -> 24.4258 | M87: =VLOOKUP($K87,'Genre Penetration'!A:B,2,0)*VLOOKUP($C87&$E87,'Updated SES'!A:I,9,0) -> 0.374 | N87: =VLOOKUP(K:K,'Genre Penetration'!A:C,3,0)*VLOOKUP($C87&$E87,'Updated SES'!A:J,10,0) -> 0.144 | O87: =VLOOKUP($B87,'Language Penetration'!$B$1:$BE$14,MATCH('Compile data Working'!$H87,'Language Penetration'!$B$1:$BE$1,0),0) -> 0.6 | P87: =IF(ISBLANK(J87),RANDBETWEEN(1,2)&"%",IF(J87=1,RANDBETWEEN(35,40)&"%",IF(J87=2,RANDBETWEEN(30,35)&"%",IF(J87=3,RANDBETWEEN(25,30)&"%",IF(J87=4,RANDBETWEEN(20,25)&"%",IF(J87=5,RANDBETWEEN(15,20)&"%",IF(J87=6,RANDBETWEEN(10,15)&"%",IF(J87=7,RANDBETWEEN(8,10)&"%",IF(J87=8,RANDBETWEEN(6,8)&"%",IF(J87=9,RANDBETWEEN(4,6)&"%",IF(J87=10,RANDBETWEEN(2,4)&"%",""))))))))))) -> 24% | Q87: =IFERROR(L87*(M87+N87)*O87*P87,RANDBETWEEN(1,2)%*L87*(M87+N87)*O87) -> 1.8219693 | R87: =VLOOKUP(D:D,ranking!W:X,2,0) -> 0.6 | S87: =R87*Q87 -> 1.0931816 | T87: 4.4662613
A88: Trending Top 10 | B88: ALL INDIA | C88: Zee5 | D88: Svod Originals Shows | E88: PAID | F88: Shows | G88: Maa Hai Na | H88: Hindi | I88: 46185 | J88: 1 | K88: Reality Tv | L88: =VLOOKUP($C88&$E88,'Updated SES'!A:N,14,0) -> 60.152 | M88: =VLOOKUP($K88,'Genre Penetration'!A:B,2,0)*VLOOKUP($C88&$E88,'Updated SES'!A:I,9,0) -> 0.26 | N88: =VLOOKUP(K:K,'Genre Penetration'!A:C,3,0)*VLOOKUP($C88&$E88,'Updated SES'!A:J,10,0) -> 0.21 | O88: =VLOOKUP($B88,'Language Penetration'!$B$1:$BE$14,MATCH('Compile data Working'!$H88,'Language Penetration'!$B$1:$BE$1,0),0) -> 0.6 | P88: =IF(ISBLANK(J88),RANDBETWEEN(1,2)&"%",IF(J88=1,RANDBETWEEN(35,40)&"%",IF(J88=2,RANDBETWEEN(30,35)&"%",IF(J88=3,RANDBETWEEN(25,30)&"%",IF(J88=4,RANDBETWEEN(20,25)&"%",IF(J88=5,RANDBETWEEN(15,20)&"%",IF(J88=6,RANDBETWEEN(10,15)&"%",IF(J88=7,RANDBETWEEN(8,10)&"%",IF(J88=8,RANDBETWEEN(6,8)&"%",IF(J88=9,RANDBETWEEN(4,6)&"%",IF(J88=10,RANDBETWEEN(2,4)&"%",""))))))))))) -> 39% | Q88: =IFERROR(L88*(M88+N88)*O88*P88,RANDBETWEEN(1,2)%*L88*(M88+N88)*O88) -> 6.615517 | R88: =VLOOKUP(D:D,ranking!W:X,2,0) -> 0.6 | S88: =R88*Q88 -> 3.9693102 | T88: 4.4561729
A89: Trending Top 10 | B89: ALL INDIA | C89: Netflix | D89: SVOD Originals Movies | E89: PAID | F89: Movies | G89: Kartavya? | H89: English,Hindi,Tamil,Telugu | I89: 46157 | J89: 10 | K89: Drama | L89: =VLOOKUP($C89&$E89,'Updated SES'!A:N,14,0) -> 55.4592 | M89: =VLOOKUP($K89,'Genre Penetration'!A:B,2,0)*VLOOKUP($C89&$E89,'Updated SES'!A:I,9,0) -> 0.245 | N89: =VLOOKUP(K:K,'Genre Penetration'!A:C,3,0)*VLOOKUP($C89&$E89,'Updated SES'!A:J,10,0) -> 0.255 | O89: =VLOOKUP($B89,'Language Penetration'!$B$1:$BE$14,MATCH('Compile data Working'!$H89,'Language Penetration'!$B$1:$BE$1,0),0) -> 0.2625 | P89: =IF(ISBLANK(J89),RANDBETWEEN(1,2)&"%",IF(J89=1,RANDBETWEEN(35,40)&"%",IF(J89=2,RANDBETWEEN(30,35)&"%",IF(J89=3,RANDBETWEEN(25,30)&"%",IF(J89=4,RANDBETWEEN(20,25)&"%",IF(J89=5,RANDBETWEEN(15,20)&"%",IF(J89=6,RANDBETWEEN(10,15)&"%",IF(J89=7,RANDBETWEEN(8,10)&"%",IF(J89=8,RANDBETWEEN(6,8)&"%",IF(J89=9,RANDBETWEEN(4,6)&"%",IF(J89=10,RANDBETWEEN(2,4)&"%",""))))))))))) -> 4% | Q89: =IFERROR(L89*(M89+N89)*O89*P89,RANDBETWEEN(1,2)%*L89*(M89+N89)*O89) -> 0.2911608 | R89: =VLOOKUP(D:D,ranking!W:X,2,0) -> 0.8 | S89: =R89*Q89 -> 0.23292864 | T89: 4.3003529
A90: Trending Top 10 | B90: ALL INDIA | C90: Netflix | D90: Svod Originals Shows | E90: PAID | F90: Shows | G90: Glory | H90: Hindi,Tamil,Telugu | I90: 46143 | J90: 8 | K90: Action,Drama,Thriller | L90: =VLOOKUP($C90&$E90,'Updated SES'!A:N,14,0) -> 55.4592 | M90: =VLOOKUP($K90,'Genre Penetration'!A:B,2,0)*VLOOKUP($C90&$E90,'Updated SES'!A:I,9,0) -> 0.3332 | N90: =VLOOKUP(K:K,'Genre Penetration'!A:C,3,0)*VLOOKUP($C90&$E90,'Updated SES'!A:J,10,0) -> 0.1632 | O90: =VLOOKUP($B90,'Language Penetration'!$B$1:$BE$14,MATCH('Compile data Working'!$H90,'Language Penetration'!$B$1:$BE$1,0),0) -> 0.28333333 | P90: =IF(ISBLANK(J90),RANDBETWEEN(1,2)&"%",IF(J90=1,RANDBETWEEN(35,40)&"%",IF(J90=2,RANDBETWEEN(30,35)&"%",IF(J90=3,RANDBETWEEN(25,30)&"%",IF(J90=4,RANDBETWEEN(20,25)&"%",IF(J90=5,RANDBETWEEN(15,20)&"%",IF(J90=6,RANDBETWEEN(10,15)&"%",IF(J90=7,RANDBETWEEN(8,10)&"%",IF(J90=8,RANDBETWEEN(6,8)&"%",IF(J90=9,RANDBETWEEN(4,6)&"%",IF(J90=10,RANDBETWEEN(2,4)&"%",""))))))))))) -> 7% | Q90: =IFERROR(L90*(M90+N90)*O90*P90,RANDBETWEEN(1,2)%*L90*(M90+N90)*O90) -> 0.54601061 | R90: =VLOOKUP(D:D,ranking!W:X,2,0) -> 0.6 | S90: =R90*Q90 -> 0.32760637 | T90: 4.2437273
A91: Trending Top 10 | B91: ALL INDIA | C91: Zee5 | D91: Theatrical Movies | E91: PAID | F91: Movies | G91: KD: The Devil | H91: Kannada,Malayalam,Tamil,Telugu | I91: 46178 | J91: 2 | K91: Action,Crime,Thriller | L91: =VLOOKUP($C91&$E91,'Updated SES'!A:N,14,0) -> 60.152 | M91: =VLOOKUP($K91,'Genre Penetration'!A:B,2,0)*VLOOKUP($C91&$E91,'Updated SES'!A:I,9,0) -> 0.468 | N91: =VLOOKUP(K:K,'Genre Penetration'!A:C,3,0)*VLOOKUP($C91&$E91,'Updated SES'!A:J,10,0) -> 0.098 | O91: =VLOOKUP($B91,'Language Penetration'!$B$1:$BE$14,MATCH('Compile data Working'!$H91,'Language Penetration'!$B$1:$BE$1,0),0) -> 0.105 | P91: =IF(ISBLANK(J91),RANDBETWEEN(1,2)&"%",IF(J91=1,RANDBETWEEN(35,40)&"%",IF(J91=2,RANDBETWEEN(30,35)&"%",IF(J91=3,RANDBETWEEN(25,30)&"%",IF(J91=4,RANDBETWEEN(20,25)&"%",IF(J91=5,RANDBETWEEN(15,20)&"%",IF(J91=6,RANDBETWEEN(10,15)&"%",IF(J91=7,RANDBETWEEN(8,10)&"%",IF(J91=8,RANDBETWEEN(6,8)&"%",IF(J91=9,RANDBETWEEN(4,6)&"%",IF(J91=10,RANDBETWEEN(2,4)&"%",""))))))))))) -> 35% | Q91: =IFERROR(L91*(M91+N91)*O91*P91,RANDBETWEEN(1,2)%*L91*(M91+N91)*O91) -> 1.2511917 | R91: =VLOOKUP(D:D,ranking!W:X,2,0) -> 0.7 | S91: =R91*Q91 -> 0.87583417 | T91: 3.832951
A92: Cott Data Servey | B92: ALL INDIA | C92: JioHotstar | D92: Tv Catch-Up | E92: PAID | F92: Tv catchup | G92: Me Savitribai Jyotirao Phule | H92: Marathi | I92: - | K92: Drama | L92: =VLOOKUP($C92&$E92,'Updated SES'!A:N,14,0) -> 127.11702 | M92: =VLOOKUP($K92,'Genre Penetration'!A:B,2,0)*VLOOKUP($C92&$E92,'Updated SES'!A:I,9,0) -> 0.335 | N92: =VLOOKUP(K:K,'Genre Penetration'!A:C,3,0)*VLOOKUP($C92&$E92,'Updated SES'!A:J,10,0) -> 0.165 | O92: =VLOOKUP($B92,'Language Penetration'!$B$1:$BE$14,MATCH('Compile data Working'!$H92,'Language Penetration'!$B$1:$BE$1,0),0) -> 0.12 | P92: =IF(ISBLANK(J92),RANDBETWEEN(1,2)&"%",IF(J92=1,RANDBETWEEN(35,40)&"%",IF(J92=2,RANDBETWEEN(30,35)&"%",IF(J92=3,RANDBETWEEN(25,30)&"%",IF(J92=4,RANDBETWEEN(20,25)&"%",IF(J92=5,RANDBETWEEN(15,20)&"%",IF(J92=6,RANDBETWEEN(10,15)&"%",IF(J92=7,RANDBETWEEN(8,10)&"%",IF(J92=8,RANDBETWEEN(6,8)&"%",IF(J92=9,RANDBETWEEN(4,6)&"%",IF(J92=10,RANDBETWEEN(2,4)&"%",""))))))))))) -> 2% | Q92: =IFERROR(L92*(M92+N92)*O92*P92,RANDBETWEEN(1,2)%*L92*(M92+N92)*O92) -> 0.15254042 | R92: =VLOOKUP(D:D,ranking!W:X,2,0) -> 0.3 | S92: =R92*Q92 -> 0.045762127 | T92: 3.7831345
A93: Trending Top 10 | B93: ALL INDIA | C93: Amazon MX Player | D93: Avod Originals Shows | E93: FREE | F93: Shows | G93: Campus Beats Season 6 | H93: Hindi | I93: 46141 | J93: 5 | K93: Comedy,Romance | L93: =VLOOKUP($C93&$E93,'Updated SES'!A:N,14,0) -> 78.93987 | M93: =VLOOKUP($K93,'Genre Penetration'!A:B,2,0)*VLOOKUP($C93&$E93,'Updated SES'!A:I,9,0) -> 0.24 | N93: =VLOOKUP(K:K,'Genre Penetration'!A:C,3,0)*VLOOKUP($C93&$E93,'Updated SES'!A:J,10,0) -> 0.14 | O93: =VLOOKUP($B93,'Language Penetration'!$B$1:$BE$14,MATCH('Compile data Working'!$H93,'Language Penetration'!$B$1:$BE$1,0),0) -> 0.6 | P93: =IF(ISBLANK(J93),RANDBETWEEN(1,2)&"%",IF(J93=1,RANDBETWEEN(35,40)&"%",IF(J93=2,RANDBETWEEN(30,35)&"%",IF(J93=3,RANDBETWEEN(25,30)&"%",IF(J93=4,RANDBETWEEN(20,25)&"%",IF(J93=5,RANDBETWEEN(15,20)&"%",IF(J93=6,RANDBETWEEN(10,15)&"%",IF(J93=7,RANDBETWEEN(8,10)&"%",IF(J93=8,RANDBETWEEN(6,8)&"%",IF(J93=9,RANDBETWEEN(4,6)&"%",IF(J93=10,RANDBETWEEN(2,4)&"%",""))))))))))) -> 17% | Q93: =IFERROR(L93*(M93+N93)*O93*P93,RANDBETWEEN(1,2)%*L93*(M93+N93)*O93) -> 3.0597094 | R93: =VLOOKUP(D:D,ranking!W:X,2,0) -> 0.6 | S93: =R93*Q93 -> 1.8358256 | T93: 3.3832174
A94: Trending Top 10 | B94: ALL INDIA | C94: Netflix | D94: Svod Originals Shows | E94: PAID | F94: Shows | G94: Baki-Dou: The Invincible Samurai | H94: English,Hindi | I94: 46079 | J94: 7 | K94: Action,Animation,Drama | L94: =VLOOKUP($C94&$E94,'Updated SES'!A:N,14,0) -> 55.4592 | M94: =VLOOKUP($K94,'Genre Penetration'!A:B,2,0)*VLOOKUP($C94&$E94,'Updated SES'!A:I,9,0) -> 0.2597 | N94: =VLOOKUP(K:K,'Genre Penetration'!A:C,3,0)*VLOOKUP($C94&$E94,'Updated SES'!A:J,10,0) -> 0.2397 | O94: =VLOOKUP($B94,'Language Penetration'!$B$1:$BE$14,MATCH('Compile data Working'!$H94,'Language Penetration'!$B$1:$BE$1,0),0) -> 0.4 | P94: =IF(ISBLANK(J94),RANDBETWEEN(1,2)&"%",IF(J94=1,RANDBETWEEN(35,40)&"%",IF(J94=2,RANDBETWEEN(30,35)&"%",IF(J94=3,RANDBETWEEN(25,30)&"%",IF(J94=4,RANDBETWEEN(20,25)&"%",IF(J94=5,RANDBETWEEN(15,20)&"%",IF(J94=6,RANDBETWEEN(10,15)&"%",IF(J94=7,RANDBETWEEN(8,10)&"%",IF(J94=8,RANDBETWEEN(6,8)&"%",IF(J94=9,RANDBETWEEN(4,6)&"%",IF(J94=10,RANDBETWEEN(2,4)&"%",""))))))))))) -> 8% | Q94: =IFERROR(L94*(M94+N94)*O94*P94,RANDBETWEEN(1,2)%*L94*(M94+N94)*O94) -> 0.88628238 | R94: =VLOOKUP(D:D,ranking!W:X,2,0) -> 0.6 | S94: =R94*Q94 -> 0.53176943 | T94: 3.1964812
A95: Trending Top 10 | B95: ALL INDIA | C95: Zee5 | D95: Theatrical Movies | E95: PAID | F95: Movies | G95: Patriot | H95: Hindi,Kannada,Malayalam,Tamil,Telugu | I95: 46178 | J95: 1 | K95: Comedy,Drama,Thriller | L95: =VLOOKUP($C95&$E95,'Updated SES'!A:N,14,0) -> 60.152 | M95: =VLOOKUP($K95,'Genre Penetration'!A:B,2,0)*VLOOKUP($C95&$E95,'Updated SES'!A:I,9,0) -> 0.377 | N95: =VLOOKUP(K:K,'Genre Penetration'!A:C,3,0)*VLOOKUP($C95&$E95,'Updated SES'!A:J,10,0) -> 0.147 | O95: =VLOOKUP($B95,'Language Penetration'!$B$1:$BE$14,MATCH('Compile data Working'!$H95,'Language Penetration'!$B$1:$BE$1,0),0) -> 0.204 | P95: =IF(ISBLANK(J95),RANDBETWEEN(1,2)&"%",IF(J95=1,RANDBETWEEN(35,40)&"%",IF(J95=2,RANDBETWEEN(30,35)&"%",IF(J95=3,RANDBETWEEN(25,30)&"%",IF(J95=4,RANDBETWEEN(20,25)&"%",IF(J95=5,RANDBETWEEN(15,20)&"%",IF(J95=6,RANDBETWEEN(10,15)&"%",IF(J95=7,RANDBETWEEN(8,10)&"%",IF(J95=8,RANDBETWEEN(6,8)&"%",IF(J95=9,RANDBETWEEN(4,6)&"%",IF(J95=10,RANDBETWEEN(2,4)&"%",""))))))))))) -> 35% | Q95: =IFERROR(L95*(M95+N95)*O95*P95,RANDBETWEEN(1,2)%*L95*(M95+N95)*O95) -> 2.2505029 | R95: =VLOOKUP(D:D,ranking!W:X,2,0) -> 0.7 | S95: =R95*Q95 -> 1.575352 | T95: 3.1306645
A96: Trending Top 10 | B96: ALL INDIA | C96: Zee5 | D96: Svod Originals Shows | E96: PAID | F96: Shows | G96: Brown | H96: Hindi | I96: 46178 | J96: 2 | K96: Crime,Drama,Thriller | L96: =VLOOKUP($C96&$E96,'Updated SES'!A:N,14,0) -> 60.152 | M96: =VLOOKUP($K96,'Genre Penetration'!A:B,2,0)*VLOOKUP($C96&$E96,'Updated SES'!A:I,9,0) -> 0.468 | N96: =VLOOKUP(K:K,'Genre Penetration'!A:C,3,0)*VLOOKUP($C96&$E96,'Updated SES'!A:J,10,0) -> 0.098 | O96: =VLOOKUP($B96,'Language Penetration'!$B$1:$BE$14,MATCH('Compile data Working'!$H96,'Language Penetration'!$B$1:$BE$1,0),0) -> 0.6 | P96: =IF(ISBLANK(J96),RANDBETWEEN(1,2)&"%",IF(J96=1,RANDBETWEEN(35,40)&"%",IF(J96=2,RANDBETWEEN(30,35)&"%",IF(J96=3,RANDBETWEEN(25,30)&"%",IF(J96=4,RANDBETWEEN(20,25)&"%",IF(J96=5,RANDBETWEEN(15,20)&"%",IF(J96=6,RANDBETWEEN(10,15)&"%",IF(J96=7,RANDBETWEEN(8,10)&"%",IF(J96=8,RANDBETWEEN(6,8)&"%",IF(J96=9,RANDBETWEEN(4,6)&"%",IF(J96=10,RANDBETWEEN(2,4)&"%",""))))))))))) -> 30% | Q96: =IFERROR(L96*(M96+N96)*O96*P96,RANDBETWEEN(1,2)%*L96*(M96+N96)*O96) -> 6.1282858 | R96: =VLOOKUP(D:D,ranking!W:X,2,0) -> 0.6 | S96: =R96*Q96 -> 3.6769715 | T96: 3.1037722
A97: Trending Top 10 | B97: ALL INDIA | C97: Sony Liv | D97: Tv Catch-Up | E97: PAID | F97: Shows | G97: Hui Gumm Yaadein Ek Doctor,Do Zindagiyaan | H97: Hindi | I97: 46118 | J97: 7 | K97: Drama | L97: =VLOOKUP($C97&$E97,'Updated SES'!A:N,14,0) -> 21.68204 | M97: =VLOOKUP($K97,'Genre Penetration'!A:B,2,0)*VLOOKUP($C97&$E97,'Updated SES'!A:I,9,0) -> 0.325 | N97: =VLOOKUP(K:K,'Genre Penetration'!A:C,3,0)*VLOOKUP($C97&$E97,'Updated SES'!A:J,10,0) -> 0.175 | O97: =VLOOKUP($B97,'Language Penetration'!$B$1:$BE$14,MATCH('Compile data Working'!$H97,'Language Penetration'!$B$1:$BE$1,0),0) -> 0.6 | P97: =IF(ISBLANK(J97),RANDBETWEEN(1,2)&"%",IF(J97=1,RANDBETWEEN(35,40)&"%",IF(J97=2,RANDBETWEEN(30,35)&"%",IF(J97=3,RANDBETWEEN(25,30)&"%",IF(J97=4,RANDBETWEEN(20,25)&"%",IF(J97=5,RANDBETWEEN(15,20)&"%",IF(J97=6,RANDBETWEEN(10,15)&"%",IF(J97=7,RANDBETWEEN(8,10)&"%",IF(J97=8,RANDBETWEEN(6,8)&"%",IF(J97=9,RANDBETWEEN(4,6)&"%",IF(J97=10,RANDBETWEEN(2,4)&"%",""))))))))))) -> 9% | Q97: =IFERROR(L97*(M97+N97)*O97*P97,RANDBETWEEN(1,2)%*L97*(M97+N97)*O97) -> 0.58541508 | R97: =VLOOKUP(D:D,ranking!W:X,2,0) -> 0.3 | S97: =R97*Q97 -> 0.17562452 | T97: 2.9307141
A98: Trending Top 10 | B98: ALL INDIA | C98: Zee5 | D98: Theatrical Movies | E98: FREE | F98: Movies | G98: Unbroken- The Unmukt Chand Story | H98: Hindi | I98: 46169 | J98: 8 | K98: Documentary,Sports | L98: =VLOOKUP($C98&$E98,'Updated SES'!A:N,14,0) -> 24.4258 | M98: =VLOOKUP($K98,'Genre Penetration'!A:B,2,0)*VLOOKUP($C98&$E98,'Updated SES'!A:I,9,0) -> 0.34 | N98: =VLOOKUP(K:K,'Genre Penetration'!A:C,3,0)*VLOOKUP($C98&$E98,'Updated SES'!A:J,10,0) -> 0.16 | O98: =VLOOKUP($B98,'Language Penetration'!$B$1:$BE$14,MATCH('Compile data Working'!$H98,'Language Penetration'!$B$1:$BE$1,0),0) -> 0.6 | P98: =IF(ISBLANK(J98),RANDBETWEEN(1,2)&"%",IF(J98=1,RANDBETWEEN(35,40)&"%",IF(J98=2,RANDBETWEEN(30,35)&"%",IF(J98=3,RANDBETWEEN(25,30)&"%",IF(J98=4,RANDBETWEEN(20,25)&"%",IF(J98=5,RANDBETWEEN(15,20)&"%",IF(J98=6,RANDBETWEEN(10,15)&"%",IF(J98=7,RANDBETWEEN(8,10)&"%",IF(J98=8,RANDBETWEEN(6,8)&"%",IF(J98=9,RANDBETWEEN(4,6)&"%",IF(J98=10,RANDBETWEEN(2,4)&"%",""))))))))))) -> 6% | Q98: =IFERROR(L98*(M98+N98)*O98*P98,RANDBETWEEN(1,2)%*L98*(M98+N98)*O98) -> 0.4396644 | R98: =VLOOKUP(D:D,ranking!W:X,2,0) -> 0.7 | S98: =R98*Q98 -> 0.30776508 | T98: 2.5044502
A99: Trending Top 10 | B99: ALL INDIA | C99: Netflix | D99: Svod Originals Shows | E99: PAID | F99: Shows | G99: The WONDERfools | H99: English,Hindi,Tamil,Telugu | I99: 46157 | J99: 3 | K99: Action,Adventure,Comedy | L99: =VLOOKUP($C99&$E99,'Updated SES'!A:N,14,0) -> 55.4592 | M99: =VLOOKUP($K99,'Genre Penetration'!A:B,2,0)*VLOOKUP($C99&$E99,'Updated SES'!A:I,9,0) -> 0.294 | N99: =VLOOKUP(K:K,'Genre Penetration'!A:C,3,0)*VLOOKUP($C99&$E99,'Updated SES'!A:J,10,0) -> 0.204 | O99: =VLOOKUP($B99,'Language Penetration'!$B$1:$BE$14,MATCH('Compile data Working'!$H99,'Language Penetration'!$B$1:$BE$1,0),0) -> 0.2625 | P99: =IF(ISBLANK(J99),RANDBETWEEN(1,2)&"%",IF(J99=1,RANDBETWEEN(35,40)&"%",IF(J99=2,RANDBETWEEN(30,35)&"%",IF(J99=3,RANDBETWEEN(25,30)&"%",IF(J99=4,RANDBETWEEN(20,25)&"%",IF(J99=5,RANDBETWEEN(15,20)&"%",IF(J99=6,RANDBETWEEN(10,15)&"%",IF(J99=7,RANDBETWEEN(8,10)&"%",IF(J99=8,RANDBETWEEN(6,8)&"%",IF(J99=9,RANDBETWEEN(4,6)&"%",IF(J99=10,RANDBETWEEN(2,4)&"%",""))))))))))) -> 28% | Q99: =IFERROR(L99*(M99+N99)*O99*P99,RANDBETWEEN(1,2)%*L99*(M99+N99)*O99) -> 2.0299731 | R99: =VLOOKUP(D:D,ranking!W:X,2,0) -> 0.6 | S99: =R99*Q99 -> 1.2179839 | T99: 2.3831663
A100: Trending Top 10 | B100: ALL INDIA | C100: Zee5 | D100: Theatrical Movies | E100: PAID | F100: Movies | G100: Valavaara | H100: Kannada,Tamil,Telugu | I100: 46178 | J100: 7 | K100: Drama | L100: =VLOOKUP($C100&$E100,'Updated SES'!A:N,14,0) -> 60.152 | M100: =VLOOKUP($K100,'Genre Penetration'!A:B,2,0)*VLOOKUP($C100&$E100,'Updated SES'!A:I,9,0) -> 0.325 | N100: =VLOOKUP(K:K,'Genre Penetration'!A:C,3,0)*VLOOKUP($C100&$E100,'Updated SES'!A:J,10,0) -> 0.175 | O100: =VLOOKUP($B100,'Language Penetration'!$B$1:$BE$14,MATCH('Compile data Working'!$H100,'Language Penetration'!$B$1:$BE$1,0),0) -> #N/A | P100: =IF(ISBLANK(J100),RANDBETWEEN(1,2)&"%",IF(J100=1,RANDBETWEEN(35,40)&"%",IF(J100=2,RANDBETWEEN(30,35)&"%",IF(J100=3,RANDBETWEEN(25,30)&"%",IF(J100=4,RANDBETWEEN(20,25)&"%",IF(J100=5,RANDBETWEEN(15,20)&"%",IF(J100=6,RANDBETWEEN(10,15)&"%",IF(J100=7,RANDBETWEEN(8,10)&"%",IF(J100=8,RANDBETWEEN(6,8)&"%",IF(J100=9,RANDBETWEEN(4,6)&"%",IF(J100=10,RANDBETWEEN(2,4)&"%",""))))))))))) -> 8% | Q100: =IFERROR(L100*(M100+N100)*O100*P100,RANDBETWEEN(1,2)%*L100*(M100+N100)*O100) -> #N/A | R100: =VLOOKUP(D:D,ranking!W:X,2,0) -> 0.7 | S100: =R100*Q100 -> #N/A | T100: 2.1973998
A101: Trending Top 10 | B101: ALL INDIA | C101: JioHotstar | D101: SVOD Originals Shows | E101: PAID | F101: Shows | G101: 24 | H101: Hindi | I101: 46136 | J101: 4 | K101: Action,Crime,Drama | L101: =VLOOKUP($C101&$E101,'Updated SES'!A:N,14,0) -> 127.11702 | M101: =VLOOKUP($K101,'Genre Penetration'!A:B,2,0)*VLOOKUP($C101&$E101,'Updated SES'!A:I,9,0) -> 0.4087 | N101: =VLOOKUP(K:K,'Genre Penetration'!A:C,3,0)*VLOOKUP($C101&$E101,'Updated SES'!A:J,10,0) -> 0.1287 | O101: =VLOOKUP($B101,'Language Penetration'!$B$1:$BE$14,MATCH('Compile data Working'!$H101,'Language Penetration'!$B$1:$BE$1,0),0) -> 0.6 | P101: =IF(ISBLANK(J101),RANDBETWEEN(1,2)&"%",IF(J101=1,RANDBETWEEN(35,40)&"%",IF(J101=2,RANDBETWEEN(30,35)&"%",IF(J101=3,RANDBETWEEN(25,30)&"%",IF(J101=4,RANDBETWEEN(20,25)&"%",IF(J101=5,RANDBETWEEN(15,20)&"%",IF(J101=6,RANDBETWEEN(10,15)&"%",IF(J101=7,RANDBETWEEN(8,10)&"%",IF(J101=8,RANDBETWEEN(6,8)&"%",IF(J101=9,RANDBETWEEN(4,6)&"%",IF(J101=10,RANDBETWEEN(2,4)&"%",""))))))))))) -> 21% | Q101: =IFERROR(L101*(M101+N101)*O101*P101,RANDBETWEEN(1,2)%*L101*(M101+N101)*O101) -> 8.6073985 | R101: =VLOOKUP(D:D,ranking!W:X,2,0) -> 0.6 | S101: =R101*Q101 -> 5.1644391 | T101: 2.0986063
...

Sheet Sheet2
A1: ss | B1: ss
A2: Punjabi,Haryanvi | B2: 0.095
A3: Hindi,Kannada,Tamil | B3: 0.26666667
A4: English,Hindi,Kannada,Tamil,Telugu | B4: 0.23
A5: Hindi,Tamil,Telugu,Turkish | B5: #N/A
A6: Bengali,Hindi,Malayalam,Marathi,Tamil,Telugu | B6: 0.19
A7: Haryanvi,Rajasthani | B7: 0.1
A8: Hindi,English,Malayalam,Tamil,Telugu | B8: 0.224
A9: Hindi,Telugu | B9: 0.375
A10: English,Hindi,Kannada,Malayala,Marathi,Tamil,Telugu | B10: 0.19142857

Sheet ranking
A1: =B1&D1 -> OTT PLATFORMTop 10 | B1: OTT PLATFORM | C1: Content format | D1: Top 10 | E1: PAID/FREE | F1: Show/Movies | G1: Genre | H1: Language | I1: Average of Rank | J1: Round | L1: Rank | M1: Watching Percentage | O1: Rank | P1: Watching Percentage | S1: Rank | T1: Watching Percentage | AB1: 1) Original Shows - 80%
A2: =B2&D2 -> Adda TimesAbhishapto | B2: Adda Times | C2: Svod Originals Shows | D2: Abhishapto | E2: PAID | F2: Show | G2: Drama | H2: Bengali | I2: 9 | J2: 9 | L2: 7 | M2: 40-35% | O2: 7 | P2: 40-35% | S2: 1 | T2: 0.9 | W2: Content format | X2: Watching % | AB2: 2) Original Movies - 100%
A3: =B3&D3 -> Adda TimesBasanta Ese Geche | B3: Adda Times | C3: Svod Originals Shows | D3: Basanta Ese Geche | E3: PAID | F3: Show | G3: Drama | H3: Bengali | I3: 2 | J3: 2 | L3: 6 | M3: 35-30% | O3: 6 | P3: 35-30% | S3: 2 | T3: 0.85 | W3: Avod Originals Movies | X3: 0.8 | AB3: 3) Theatrical releases - 75% (conditions pl discuss)
A4: =B4&D4 -> Adda TimesCabaret | B4: Adda Times | C4: Svod Originals Shows | D4: Cabaret | E4: PAID | F4: Show | G4: Drama | H4: Bengali | I4: 4 | J4: 4 | L4: 5 | M4: 30-25% | O4: 5 | P4: 30-25% | S4: 3 | T4: 0.8 | W4: Avod Originals Shows | X4: 0.6 | AB4: 4) Catch up TV Shows - 30% (For bigg boss its also live and have highlights so higher)
A5: =B5&D5 -> Adda TimesGhoshbabur-retirement-plan | B5: Adda Times | C5: Svod Originals Shows | D5: Ghoshbabur-retirement-plan | E5: PAID | F5: Show | G5: Drama | H5: Bengali | I5: 7 | J5: 7 | L5: 4 | M5: 25-20% | O5: 4 | P5: 25-20% | S5: 4 | T5: 0.7 | W5: Live Event | X5: 0.1 | AB5: 5) Live sports - depending upon sports 100% for Cricket, Kabbadi 40%, rest sport 10-15%
A6: =B6&D6 -> Adda TimesKothamrita | B6: Adda Times | C6: Svod Originals Shows | D6: Kothamrita | E6: PAID | F6: Show | G6: Drama,Family | H6: Bengali | I6: 10 | J6: 10 | L6: 3 | M6: 20-15% | O6: 3 | P6: 20-15% | S6: 5 | T6: 0.65 | W6: Svod Originals Movies | X6: 0.8 | AB6: 4) Highlights - 10% of Live sports
A7: =B7&D7 -> Adda TimesNandini | B7: Adda Times | C7: Svod Originals Shows | D7: Nandini | E7: PAID | F7: Show | G7: Drama | H7: Bengali | I7: 8 | J7: 8 | L7: 2 | M7: 15-10% | O7: 2 | P7: 15-10% | S7: 6 | T7: 0.6 | W7: Svod Originals Shows | X7: 0.6
A8: =B8&D8 -> Adda TimesPetni | B8: Adda Times | C8: Svod Originals Shows | D8: Petni | E8: PAID | F8: Show | G8: Drama | H8: Bengali | I8: 5 | J8: 5 | L8: 1 | M8: 10-8% | O8: 1 | P8: 10-8% | S8: 7 | T8: 0.55 | W8: Theatrical releases | X8: 0.7
A9: =B9&D9 -> Adda TimesPreme Pora Baron | B9: Adda Times | C9: Svod Originals Shows | D9: Preme Pora Baron | E9: PAID | F9: Show | G9: Drama | H9: Bengali | I9: 3 | J9: 3 | L9: 8 | M9: 8-6% | S9: 8 | T9: 0.5 | W9: Tv Catch-Up | X9: 0.3
A10: =B10&D10 -> Adda TimesSIN - Whispers Of Guilt | B10: Adda Times | C10: Svod Originals Shows | D10: SIN - Whispers Of Guilt | E10: PAID | F10: Show | G10: Comedy | H10: Bengali | I10: 6 | J10: 6 | L10: 9 | M10: 6-4% | S10: 9 | T10: 0.45 | W10: Theatrical Movies | X10: 0.7
A11: =B11&D11 -> Adda TimesThe First Rain | B11: Adda Times | C11: Svod Originals Shows | D11: The First Rain | E11: PAID | F11: Show | G11: Drama,Romance | H11: Bengali | I11: 1 | J11: 1 | L11: 10 | M11: 4-2% | S11: 10 | T11: 0.4
A12: =B12&D12 -> Aha Video11th Hour | B12: Aha Video | C12: Svod Originals Shows | D12: 11th Hour | E12: PAID | F12: Show | G12: Drama,Thriller | H12: Telugu | I12: 8 | J12: 8 | S12: 11 | T12: =T11*90% -> 0.36
A13: =B13&D13 -> Aha VideoAkash Vaani | B13: Aha Video | C13: Svod Originals Shows | D13: Akash Vaani | E13: PAID | F13: Show | G13: Comedy,Romane | H13: Tamil,Telugu | I13: 5 | J13: 5 | S13: 12 | T13: =T12*90% -> 0.324
A14: =B14&D14 -> Aha VideoAmmuchi 2 | B14: Aha Video | C14: Svod Originals Shows | D14: Ammuchi 2 | E14: PAID | F14: Show | G14: Comedy | H14: Tamil | I14: 6 | J14: 6 | S14: 13 | T14: =T13*90% -> 0.2916
A15: =B15&D15 -> Aha VideoAnya's Tutorial | B15: Aha Video | C15: Svod Originals Shows | D15: Anya's Tutorial | E15: PAID | F15: Show | G15: Drama | H15: Tamil | I15: 10 | J15: 10 | S15: 14 | T15: =T14*90% -> 0.26244
A16: =B16&D16 -> Aha VideoEmoji | B16: Aha Video | C16: Svod Originals Shows | D16: Emoji | E16: PAID | F16: Show | G16: Romance | H16: Tamil | I16: 3 | J16: 3 | S16: 15 | T16: =T15*90% -> 0.236196
A17: =B17&D17 -> Aha VideoEP7 Youtubers | B17: Aha Video | C17: Svod Originals Shows | D17: EP7 Youtubers | E17: PAID | F17: Show | G17: Game Show | H17: Telugu | I17: 4 | J17: 4 | S17: 16 | T17: =T16*90% -> 0.2125764
A18: =B18&D18 -> Aha VideoIrai | B18: Aha Video | C18: Svod Originals Shows | D18: Irai | E18: PAID | F18: Show | G18: Action,Crime,Drama | H18: Tamil | I18: 2 | J18: 2 | S18: 17 | T18: =T17*90% -> 0.19131876
A19: =B19&D19 -> Aha VideoKuthukku Pathu | B19: Aha Video | C19: Svod Originals Shows | D19: Kuthukku Pathu | E19: PAID | F19: Show | G19: Comedy | H19: Tamil | I19: 7 | J19: 7 | S19: 18 | T19: =T18*90% -> 0.17218688
A20: =B20&D20 -> Aha VideoMad Company | B20: Aha Video | C20: Svod Originals Shows | D20: Mad Company | E20: PAID | F20: Show | G20: Comedy,Drama | H20: Tamil | I20: 9 | J20: 9 | S20: 19 | T20: =T19*90% -> 0.1549682
A21: =B21&D21 -> Aha VideoPettaikaali | B21: Aha Video | C21: Svod Originals Shows | D21: Pettaikaali | E21: PAID | F21: Show | G21: Action | H21: Tamil | I21: 1 | J21: 1 | S21: 20 | T21: =T20*90% -> 0.13947138
A22: =B22&D22 -> Aha VideoAyngaran | B22: Aha Video | C22: Theatrical releases | D22: Ayngaran | E22: PAID | F22: Movie | G22: Action,Drama | H22: Tamil | I22: 4 | J22: 4 | S22: 21 | T22: =T21*90% -> 0.12552424
A23: =B23&D23 -> Aha VideoDiary | B23: Aha Video | C23: Theatrical releases | D23: Diary | E23: PAID | F23: Movie | G23: Horror,Thriller | H23: Tamil | I23: 3 | J23: 3 | S23: 22 | T23: =T22*90% -> 0.11297181
... A92: =B92&D92 -> Apple TvBefore | B92: Apple Tv | C92: Svod Originals Shows | D92: Before | E92: PAID | F92: Show | G92: Drama,Thriller | H92: English | I92: 9 | J92: 9 | S92: 100 | T92: =T91*90% -> 7.865082e-05
A93: =B93&D93 -> Apple TvDisclaimer | B93: Apple Tv | C93: Svod Originals Shows | D93: Disclaimer | E93: PAID | F93: Show | G93: Drama,Mystery,Thriller | H93: English | I93: 5 | J93: 5
A94: =B94&D94 -> Apple TvPresumed Innocent | B94: Apple Tv | C94: Svod Originals Shows | D94: Presumed Innocent | E94: PAID | F94: Show | G94: Crime,Drama,Mystery | H94: English | I94: 7 | J94: 7
A95: =B95&D95 -> Apple TvSee | B95: Apple Tv | C95: Svod Originals Shows | D95: See | E95: PAID | F95: Show | G95: Action,Drama,Sci-Fi | H95: English | I95: 8 | J95: 8
A96: =B96&D96 -> Apple TvSeverance | B96: Apple Tv | C96: Svod Originals Shows | D96: Severance | E96: PAID | F96: Show | G96: Drama,Mystery,Thriller | H96: English | I96: 10 | J96: 10
A97: =B97&D97 -> Apple TvShrinking | B97: Apple Tv | C97: Svod Originals Shows | D97: Shrinking | E97: PAID | F97: Show | G97: Comedy,Drama | H97: English | I97: 3 | J97: 3
A98: =B98&D98 -> Apple TvSilo | B98: Apple Tv | C98: Svod Originals Shows | D98: Silo | E98: PAID | F98: Show | G98: Drama,Mystery,Sci-Fi | H98: English | I98: 1 | J98: 1
A99: =B99&D99 -> Apple TvSlow Horses | B99: Apple Tv | C99: Svod Originals Shows | D99: Slow Horses | E99: PAID | F99: Show | G99: Drama,Thriller | H99: English | I99: 6 | J99: 6
A100: =B100&D100 -> Apple TvTed Lasso | B100: Apple Tv | C100: Svod Originals Shows | D100: Ted Lasso | E100: PAID | F100: Show | G100: Comedy,Drama,Sport | H100: English | I100: 4 | J100: 4
A101: =B101&D101 -> Apple TvKillers of the Flower Moon | B101: Apple Tv | C101: Theatrical releases | D101: Killers of the Flower Moon | E101: PAID | F101: Movie | G101: Crime,Drama,Mystery | H101: English | I101: 8 | J101: 8
A102: =B102&D102 -> Apple TvLuck | B102: Apple Tv | C102: Theatrical releases | D102: Luck | E102: PAID | F102: Movie | G102: Animation,Adventure,Comedy | H102: English | I102: 4 | J102: 4
A103: =B103&D103 -> Apple TvWolfs | B103: Apple Tv | C103: Theatrical releases | D103: Wolfs | E103: PAID | F103: Movie | G103: Crime,Thriller | H103: English | I103: 1 | J103: 1
A104: =B104&D104 -> Chaupal TvJatt & Jullit 3 | B104: Chaupal Tv | C104: Svod Originals Movies | D104: Jatt & Jullit 3 | E104: PAID | F104: Movie | G104: Comedy,Romance | H104: Punjabi | I104: 3 | J104: 3
... A393: =B393&D393 -> Zee5Yek Number | B393: Zee5 | C393: Svod Originals Movies | D393: Yek Number | E393: PAID | F393: Movie | G393: Drama | H393: Marathi | I393: 4.6666667 | J393: 5
A394: =B394&D394 -> Zee52012 | B394: Zee5 | C394: Theatrical releases | D394: 2012 | E394: RENT | F394: Movie | G394: Action,Sci-Fi | H394: Hindi,English,Tamil, | I394: 9 | J394: 9
A395: =B395&D395 -> Zee5Bhaiyya Ji | B395: Zee5 | C395: Theatrical releases | D395: Bhaiyya Ji | E395: PAID | F395: Movie | G395: Action,Drama | H395: Hindi | I395: 7.3333333 | J395: 7
A396: =B396&D396 -> Zee5Fifty Shades Freed | B396: Zee5 | C396: Theatrical releases | D396: Fifty Shades Freed | E396: RENT | F396: Movie | G396: Romance,Drama,Thriller | H396: Hindi,English | I396: 6 | J396: 6
A397: =B397&D397 -> Zee5Fifty Shades of Grey | B397: Zee5 | C397: Theatrical releases | D397: Fifty Shades of Grey | E397: RENT | F397: Movie | G397: Romance,Drama,Thriller | H397: Hindi,English | I397: 4 | J397: 4
A398: =B398&D398 -> Zee5Gladiator | B398: Zee5 | C398: Theatrical releases | D398: Gladiator | E398: RENT | F398: Movie | G398: Action,Drama | H398: Hindi,English,Tamil,Telugu | I398: 8 | J398: 8
A399: =B399&D399 -> Zee5It Ends with Us | B399: Zee5 | C399: Theatrical releases | D399: It Ends with Us | E399: RENT | F399: Movie | G399: Drama,Romance | H399: Hindi,English | I399: 2 | J399: 2
A400: =B400&D400 -> Zee5Maa Nanna Superhero | B400: Zee5 | C400: Theatrical releases | D400: Maa Nanna Superhero | E400: PAID | F400: Movie | G400: Family,Drama,Romance | H400: Telegu | I400: 1.3333333 | J400: 1
A401: =B401&D401 -> Zee5Nunakkuzhi | B401: Zee5 | C401: Theatrical releases | D401: Nunakkuzhi | E401: PAID | F401: Movie | G401: Crime,Drama | H401: Malayalam,Telugu,Kannada | I401: 9 | J401: 9
A402: =B402&D402 -> Zee5Raghu Thatha | B402: Zee5 | C402: Theatrical releases | D402: Raghu Thatha | E402: PAID | F402: Movie | G402: Comedy | H402: Hindi,Tamil | I402: 7.3333333 | J402: 7
A403: =B403&D403 -> Zee5Simmba | B403: Zee5 | C403: Theatrical releases | D403: Simmba | E403: PAID | F403: Movie | G403: Action,Drama | H403: Hindi | I403: 9 | J403: 9
A404: =B404&D404 -> Zee5Spider-Man No Way Home | B404: Zee5 | C404: Theatrical releases | D404: Spider-Man No Way Home | E404: RENT | F404: Movie | G404: Adventure,Fantasy,Sci-Fi | H404: Hindi,English,Tamil,Telugu | I404: 10 | J404: 10
A405: =B405&D405 -> Zee5The Girl With The Dragon Tattoo | B405: Zee5 | C405: Theatrical releases | D405: The Girl With The Dragon Tattoo | E405: RENT | F405: Movie | G405: Crime,Drama,Mystery | H405: English | I405: 1 | J405: 1
A406: =B406&D406 -> Zee5The Pursuit of Happyness | B406: Zee5 | C406: Theatrical releases | D406: The Pursuit of Happyness | E406: RENT | F406: Movie | G406: Drama | H406: English,Telugu | I406: 3 | J406: 3
... A419: =B419&D419 -> Zee5Vasudha | B419: Zee5 | C419: Tv Catch-Up | D419: Vasudha | E419: FREE | F419: Tv-Shows | G419: Drama | H419: Hindi | I419: 5 | J419: 5

Sheet Updated SES
A2: OTT PlatformsTYPE | B2: OTT Platforms | C2: Language | D2: Region | E2: TYPE | F2: Show Type | G2: Top 10 | H2: Actual Subscribers | I2: Male % | J2: Female % | K2: CTV | L2: Mobile | M2: CTV+Mobile | N2: Total Viewers | V2: Category | W2: 2-24 | X2: 25-34 | Y2: 35-44 | Z2: 45+
A3: =B3&E3 -> Adda TimesPAID | B3: Adda Times | C3: Bengali | D3: West Bengali | E3: PAID | F3: SVOD | G3: NA | H3: 1.6 | I3: 0.8 | J3: 0.2 | K3: 0.13 | L3: 0.87 | M3: 0.06 | N3: =H3*K3*3+H3*L3*1.1-H3*M3*3 -> 1.8672 | V3: ALL INDIA | W3: 0.3 | X3: 0.33 | Y3: 0.2 | Z3: 0.17
A4: =B4&E4 -> Aha VideoPAID | B4: Aha Video | C4: Telugu & Tamil | D4: Andhra Pradesh,Telangana,Tamilnadu | E4: PAID | F4: SVOD | G4: Yes | H4: 9.23 | I4: 0.76 | J4: 0.24 | K4: 0.22 | L4: 0.78 | M4: 0.05 | N4: =H4*K4*3+H4*L4*1.1-H4*M4*3 -> 12.62664
A5: =B5&E5 -> Aha VideoFREE | B5: Aha Video | C5: Telugu & Tamil | D5: Andhra Pradesh,Telangana,Tamilnadu | E5: FREE | F5: AVOD | G5: Yes | H5: 3.75 | I5: 0.76 | J5: 0.24 | K5: 0.22 | L5: 0.78 | M5: 0.05 | N5: =H5*K5*3+H5*L5*1.1-H5*M5*3 -> 5.13
A6: =B6&E6 -> AlttPAID | B6: Altt | C6: Hindi | D6: All India | E6: PAID | F6: SVOD | G6: Yes | H6: 12.16 | I6: 0.65 | J6: 0.35 | K6: 0.26 | L6: 0.74 | M6: 0.07 | N6: =H6*K6*3+H6*L6*1.1-H6*M6*3 -> 16.82944
A7: =B7&E7 -> Amazon Prime VideoPAID | B7: Amazon Prime Video | C7: Hindi,English,Tamil,Telugu,Malayalam,Kannada,Bengali | D7: All India | E7: PAID | F7: SVOD | G7: Yes | H7: 22.08 | I7: 0.52 | J7: 0.48 | K7: 0.37 | L7: 0.63 | M7: 0.05 | N7: =H7*K7*3+H7*L7*1.1-H7*M7*3 -> 36.49824
A8: =B8&E8 -> Amazon Prime VideoFREE | B8: Amazon Prime Video | C8: Hindi,English,Tamil,Telugu,Malayalam,Kannada,Bengali | D8: All India | E8: FREE | F8: SVOD | G8: Yes | H8: 5.09 | I8: 0.52 | J8: 0.48 | K8: 0.37 | L8: 0.63 | M8: 0.05 | N8: =H8*K8*3+H8*L8*1.1-H8*M8*3 -> 8.41377 | T8: Demographic Profile | U8: Jio Hotstar | V8: Amazon Prime Video | W8: Netflix | X8: Amazon MX Player | Y8: Zee5 | Z8: Sony Liv | AA8: Alt Balaji | AB8: Sun NXT | AC8: Hoichoi | AD8: Aha Video | AE8: Stage | AF8: Other OTT (Non Regional) | AG8: Other OTT (Regional) | AK8: Location | AL8: Jio Hotstar | AM8: Amazon Prime Video | AN8: Netflix | AO8: Amazon MX Player | AP8: Zee5 | AQ8: Sony Liv | AR8: Alt Balaji | AS8: Sun NXT | AT8: Hoichoi | AU8: Aha Video | AV8: Stage | AW8: Other OTT (Non Regional) | AX8: Other OTT (Regional)
A9: =B9&E9 -> Amazon Prime VideoRENT | B9: Amazon Prime Video | C9: Hindi,English,Tamil,Telugu,Malayalam,Kannada,Bengali | D9: All India | E9: RENT | F9: Rent | G9: NA | H9: 3 | I9: 0.68 | J9: 0.32 | K9: 0.37 | L9: 0.63 | M9: 0.08 | N9: =H9*K9*3+H9*L9*1.1-H9*M9*3 -> 4.689 | T9: M <18 | U9: 0.10790021 | V9: 0.034482029 | W9: 0.035616735 | X9: 0.081691769 | Y9: 0.014519981 | Z9: 0.04214677 | AA9: 0.033684735 | AB9: 0.03331181 | AC9: 0.1309339 | AD9: 0.023882568 | AE9: 0.031394817 | AF9: 0.10547326 | AG9: 0.048860553 | AK9: North - Metro & T1 | AL9: 0.16111013 | AM9: 0.22260068 | AN9: 0.23109857 | AO9: 0.3575414 | AP9: 0.19018048 | AQ9: 0.2027027 | AR9: 0.1888668 | AS9: 0.0010650257 | AT9: 0.0044869546 | AU9: 0.0020714194 | AV9: 0.51032078 | AW9: 0.19978664 | AX9: 0.096550337
A10: =B10&E10 -> Chaupal TvPAID | B10: Chaupal Tv | C10: Punjabi,Haryanvi & Bhojpuri | D10: Punjab,Haryana | E10: PAID | F10: SVOD | G10: Yes | H10: 3 | I10: 0.75 | J10: 0.25 | K10: 0.21 | L10: 0.79 | M10: 0.04 | N10: =H10*K10*3+H10*L10*1.1-H10*M10*3 -> 4.137 | T10: M 18 - 24 | U10: 0.14054356 | V10: 0.18038936 | W10: 0.24206269 | X10: 0.295904 | Y10: 0.11419832 | Z10: 0.11639679 | AA10: 0.20357729 | AB10: 0.16104755 | AC10: 0.14952818 | AD10: 0.048690028 | AE10: 0.14162628 | AF10: 0.23500334 | AG10: 0.23623517 | AK10: North - T2 & beyond | AL10: 0.15261917 | AM10: 0.10118213 | AN10: 0.082514352 | AO10: 0.32232161 | AP10: 0.15864545 | AQ10: 0.11583012 | AR10: 0.14761431 | AS10: 0.00098613494 | AT10: 0.0035895637 | AU10: 0.0040654026 | AV10: 0.36247084 | AW10: 0.11870818 | AX10: 0.14331691
A11: =B11&E11 -> CrunchyrollPAID | B11: Crunchyroll | C11: English,Hindi,Tamil,Telugu | D11: All India | E11: PAID | F11: SVOD | H11: 0.5 | I11: 0.6 | J11: 0.4 | K11: 0.32 | L11: 0.68 | M11: 0.06 | N11: =H11*K11*3+H11*L11*1.1-H11*M11*3 -> 0.764 | T11: M 25 - 35 | U11: 0.17724335 | V11: 0.18505263 | W11: 0.17971993 | X11: 0.20620893 | Y11: 0.31960948 | Z11: 0.21284907 | AA11: 0.37756983 | AB11: 0.18975553 | AC11: 0.22169791 | AD11: 0.25680117 | AE11: 0.33298188 | AF11: 0.10881286 | AG11: 0.2451778 | AK11: South - Metro & T1 | AL11: 0.15557208 | AM11: 0.1731116 | AN11: 0.21835166 | AO11: 0.0051014082 | AP11: 0.14535222 | AQ11: 0.16679537 | AR11: 0.14890656 | AS11: 0.50588723 | AT11: 0.0023311853 | AU11: 0.53280006 | AV11: 0.0026036775 | AW11: 0.14693046 | AX11: 0.1971236
A12: =B12&E12 -> Dangal PlayPAID | B12: Dangal Play | C12: Hindi,Bhojpuri,Bengali | D12: All India | E12: PAID | F12: SVOD | H12: 21.05 | I12: 0.7 | J12: 0.3 | K12: 0.43 | L12: 0.57 | M12: 0.06 | N12: =H12*K12*3+H12*L12*1.1-H12*M12*3 -> 36.56385 | T12: M 35 + | U12: 0.10887583 | V12: 0.11939442 | W12: 0.08478955 | X12: 0.068160999 | Y12: 0.087892933 | Z12: 0.031209633 | AA12: 0.082822869 | AB12: 0.083103184 | AC12: 0.076042083 | AD12: 0.088082457 | AE12: 0.17890103 | AF12: 0.12446243 | AG12: 0.10011387 | AK12: South - T2 & beyond | AL12: 0.11018318 | AM12: 0.092867161 | AN12: 0.073562324 | AO12: 0.0034009388 | AP12: 0.12691636 | AQ12: 0.093822394 | AR12: 0.13439364 | AS12: 0.48369919 | AT12: 0.0039468582 | AU12: 0.45135843 | AV12: 0.0043430313 | AW12: 0.093104452 | AX12: 0.18103188
A13: =B13&E13 -> Dangal PlayFREE | B13: Dangal Play | C13: Hindi,Bhojpuri,Bengali | D13: All India | E13: FREE | F13: AVOD | H13: 10 | I13: 0.65 | J13: 0.35 | K13: 0.43 | L13: 0.57 | M13: 0.07 | N13: =H13*K13*3+H13*L13*1.1-H13*M13*3 -> 17.07 | T13: F <18 | U13: 0.067544954 | V13: 0.059431785 | W13: 0.05070119 | X13: 0.0429434 | Y13: 0.030664808 | Z13: 0.092259348 | AA13: 0.041851112 | AB13: 0.17740788 | AC13: 0.14823772 | AD13: 0.17170942 | AE13: 0.048995614 | AF13: 0.05055501 | AG13: 0.066595817 | AK13: West - Metro & T1 | AL13: 0.13111884 | AM13: 0.19635344 | AN13: 0.24394278 | AO13: 0.10746022 | AP13: 0.16766932 | AQ13: 0.1969112 | AR13: 0.17534791 | AS13: 0.0053744354 | AT13: 0.0037188175 | AU13: 0.0012544671 | AV13: 0.0030484926 | AW13: 0.22829987 | AX13: 0.1568943
A14: =B14&E14 -> Discovery+PAID | B14: Discovery+ | C14: Hindi,English,Tamil,Telugu,Malayalam,Kannada,Bengali | D14: All India | E14: PAID | F14: SVOD | H14: 0.5 | I14: 0.7 | J14: 0.3 | K14: 0.35 | L14: 0.65 | M14: 0.05 | N14: =H14*K14*3+H14*L14*1.1-H14*M14*3 -> 0.8075 | T14: F 18 - 24 | U14: 0.14650665 | V14: 0.15728122 | W14: 0.18709991 | X14: 0.17122328 | Y14: 0.14899226 | Z14: 0.217117 | AA14: 0.11122219 | AB14: 0.11223041 | AC14: 0.094567299 | AD14: 0.16786815 | AE14: 0.10609277 | AF14: 0.22034606 | AG14: 0.10207545 | AK14: West - T2 & beyond | AL14: 0.12195848 | AM14: 0.081747145 | AN14: 0.062469592 | AO14: 0.079296195 | AP14: 0.099941781 | AQ14: 0.1003861 | AR14: 0.097415507 | AS14: 0.00096641224 | AT14: 0.0046291338 | AU14: 0.0064368875 | AV14: 0.0039206029 | AW14: 0.099893318 | AX14: 0.10057327
A15: =B15&E15 -> Epic OnPAID | B15: Epic On | C15: Hindi,Bhojpuri,Punjabi | D15: Punjab,Haryana | E15: PAID | F15: SVOD | H15: 0.5 | I15: 0.76 | J15: 0.24 | K15: 0.34 | L15: 0.66 | M15: 0.06 | N15: =H15*K15*3+H15*L15*1.1-H15*M15*3 -> 0.783 | T15: F 25 - 35 | U15: 0.1159889 | V15: 0.16656059 | W15: 0.16007978 | X15: 0.10360112 | Y15: 0.20704508 | Z15: 0.18481873 | AA15: 0.066525979 | AB15: 0.12567328 | AC15: 0.098019334 | AD15: 0.090482351 | AE15: 0.080154068 | AF15: 0.083112123 | AG15: 0.12208812 | AK15: East - Metro & T1 | AL15: 0.0971278 | AM15: 0.092867161 | AN15: 0.06743213 | AO15: 0.064298999 | AP15: 0.068600815 | AQ15: 0.083397683 | AR15: 0.06888668 | AS15: 0.0010847484 | AT15: 0.62764313 | AU15: 0.0010163507 | AV15: 0.064726935 | AW15: 0.083018136 | AX15: 0.076737403
A16: =B16&E16 -> Epic OnFREE | B16: Epic On | C16: Hindi,Bhojpuri,Punjabi | D16: Punjab,Haryana | E16: FREE | F16: AVOD | H16: 0.8 | I16: 0.75 | J16: 0.25 | K16: 0.34 | L16: 0.66 | M16: 0.07 | N16: =H16*K16*3+H16*L16*1.1-H16*M16*3 -> 1.2288 | T16: F 35 + | U16: 0.13539655 | V16: 0.097407966 | W16: 0.059930221 | X16: 0.030266502 | Y16: 0.077077141 | Z16: 0.10320266 | AA16: 0.082745996 | AB16: 0.11747036 | AC16: 0.080973581 | AD16: 0.15248385 | AE16: 0.079853542 | AF16: 0.072234915 | AG16: 0.078853215 | AK16: East - T2 & beyond | AL16: 0.070310318 | AM16: 0.039270687 | AN16: 0.020628588 | AO16: 0.060579222 | AP16: 0.042693577 | AQ16: 0.04015444 | AR16: 0.038568588 | AS16: 0.0009368282 | AT16: 0.34965436 | AU16: 0.0009969916 | AV16: 0.048565641 | AW16: 0.030258947 | AX16: 0.047772302
A17: =B17&E17 -> Eros NowPAID | B17: Eros Now | C17: Hindi | D17: All India | E17: PAID | F17: SVOD | H17: 36.2 | I17: 0.75 | J17: 0.25 | K17: 0.24 | L17: 0.76 | M17: 0.06 | N17: =H17*K17*3+H17*L17*1.1-H17*M17*3 -> 49.8112
A18: =B18&E18 -> Etv WinPAID | B18: Etv Win | C18: Malayalam,Kannada,Telugu,Hindi,Tamil | D18: Kerala | E18: PAID | F18: SVOD | H18: 1.5 | I18: 0.78 | J18: 0.22 | K18: 0.18 | L18: 0.82 | M18: 0.07 | N18: =H18*K18*3+H18*L18*1.1-H18*M18*3 -> 1.848
A19: =B19&E19 -> HoichoiPAID | B19: Hoichoi | C19: Hindi,Bengali | D19: West Bengali | E19: PAID | F19: SVOD | H19: 10.13 | I19: 0.6 | J19: 0.4 | K19: 0.41 | L19: 0.59 | M19: 0.07 | N19: =H19*K19*3+H19*L19*1.1-H19*M19*3 -> 16.90697 | T19: Randbetween to change % Every time
A20: =B20&E20 -> Hr OttPAID | B20: Hr Ott | C20: Malayalam | D20: Kerala | E20: PAID | F20: SVOD | H20: 0 | I20: 0.8 | J20: 0.2 | K20: 0.36 | L20: 0.64 | M20: 0.07 | N20: =H20*K20*3+H20*L20*1.1-H20*M20*3 -> 0 | T20: Demographic Profile | U20: Jio Hotstar | V20: Amazon Prime Video | W20: Netflix | X20: Amazon MX Player | Y20: Zee5 | Z20: Sony Liv | AA20: Alt Balaji | AB20: Sun NXT | AC20: Hoichoi | AD20: Aha Video | AE20: Stage | AF20: Other OTT (Non Regional) | AG20: Other OTT (Regional) | AK20: Demographic Profile | AL20: Jio Hotstar | AM20: Amazon Prime Video | AN20: Netflix | AO20: Amazon MX Player | AP20: Zee5 | AQ20: Sony Liv | AR20: Alt Balaji | AS20: Sun NXT | AT20: Hoichoi | AU20: Aha Video | AV20: Stage | AW20: Other OTT (Non Regional) | AX20: Other OTT (Regional)
A21: =B21&E21 -> JioHotstarFREE | B21: JioHotstar | C21: Hindi,English,Tamil,Telugu,Malayalam,Kannada,Bengali | D21: All India | E21: FREE | F21: AVOD | H21: 39.06 | I21: 0.625 | J21: 0.375 | K21: 0.28 | L21: 0.72 | M21: 0.065 | N21: =H21*K21*3+H21*L21*1.1-H21*M21*3 -> 56.12922 | T21: M <18 | U21: =U9*RANDBETWEEN(90,105)/100 -> 0.099268197 | V21: =V9*RANDBETWEEN(80,110)/100 -> 0.036895771 | W21: =W9*RANDBETWEEN(95,115)/100 -> 0.035260568 | X21: =X9*RANDBETWEEN(98,118)/100 -> 0.089860946 | Y21: =Y9*RANDBETWEEN(90,105)/100 -> 0.013503583 | Z21: =Z9*RANDBETWEEN(90,105)/100 -> 0.039617964 | AA21: =AA9*RANDBETWEEN(90,105)/100 -> 0.032000498 | AB21: =AB9*RANDBETWEEN(90,105)/100 -> 0.033978046 | AC21: =AC9*RANDBETWEEN(90,105)/100 -> 0.11914985 | AD21: =AD9*RANDBETWEEN(90,105)/100 -> 0.023882568 | AE21: =AE9*RANDBETWEEN(90,105)/100 -> 0.032650609 | AF21: =AF9*RANDBETWEEN(90,105)/100 -> 0.10125433 | AG21: =AG9*RANDBETWEEN(90,105)/100 -> 0.04592892 | AK21: North - Metro & T1 | AL21: =AL9*RANDBETWEEN(90,105)/100 -> 0.15466572 | AM21: =AM9*RANDBETWEEN(90,105)/100 -> 0.22260068 | AN21: =AN9*RANDBETWEEN(90,105)/100 -> 0.22416561 | AO21: =AO9*RANDBETWEEN(90,105)/100 -> 0.33251351 | AP21: =AP9*RANDBETWEEN(90,105)/100 -> 0.17306423 | AQ21: =AQ9*RANDBETWEEN(90,105)/100 -> 0.18243243 | AR21: =AR9*RANDBETWEEN(90,105)/100 -> 0.16998012 | AS21: =AS9*RANDBETWEEN(90,105)/100 -> 0.0010224247 | ... AX21: =AX9*RANDBETWEEN(90,105)/100 -> 0.089791813
A22: =B22&E22 -> KlikkPAID | B22: Klikk | C22: Bengali | D22: West Bengali | E22: PAID | F22: SVOD | H22: 0.1 | I22: 0.85 | J22: 0.15 | K22: 0.31 | L22: 0.69 | M22: 0.06 | N22: =H22*K22*3+H22*L22*1.1-H22*M22*3 -> 0.1509 | T22: M 18 - 24 | U22: =U10*RANDBETWEEN(90,105)/100 -> 0.14194899 | V22: =V10*RANDBETWEEN(80,110)/100 -> 0.16776211 | W22: =W10*RANDBETWEEN(95,115)/100 -> 0.23722143 | X22: =X10*RANDBETWEEN(98,118)/100 -> 0.28998592 | Y22: =Y10*RANDBETWEEN(90,105)/100 -> 0.11419832 | Z22: =Z10*RANDBETWEEN(90,105)/100 -> 0.11406886 | AA22: =AA10*RANDBETWEEN(90,105)/100 -> 0.18932688 | AB22: =AB10*RANDBETWEEN(90,105)/100 -> 0.16748945 | AC22: =AC10*RANDBETWEEN(90,105)/100 -> 0.14653762 | AD22: =AD10*RANDBETWEEN(90,105)/100 -> 0.046742427 | AE22: =AE10*RANDBETWEEN(90,105)/100 -> 0.13454496 | AF22: =AF10*RANDBETWEEN(90,105)/100 -> 0.22090314 | AG22: =AG10*RANDBETWEEN(90,105)/100 -> 0.24804693 | AK22: North - T2 & beyond | AL22: =AL10*RANDBETWEEN(90,105)/100 -> 0.1480406 | AM22: =AM10*RANDBETWEEN(90,105)/100 -> 0.10320577 | AN22: =AN10*RANDBETWEEN(90,105)/100 -> 0.077563491 | AO22: =AO10*RANDBETWEEN(90,105)/100 -> 0.33843769 | AP22: =AP10*RANDBETWEEN(90,105)/100 -> 0.16657772 | AQ22: =AQ10*RANDBETWEEN(90,105)/100 -> 0.10540541 | AR22: =AR10*RANDBETWEEN(90,105)/100 -> 0.14761431 | AS22: =AS10*RANDBETWEEN(90,105)/100 -> 0.0009171055 | ... AX22: =AX10*RANDBETWEEN(90,105)/100 -> 0.13185155
A23: =B23&E23 -> Lionsgate PlayPAID | B23: Lionsgate Play | C23: English,Hindi,Tamil,Telugu,Kannada | D23: All India | E23: PAID | F23: SVOD | H23: 20 | I23: 0.82 | J23: 0.18 | K23: 0.23 | L23: 0.77 | M23: 0.09 | N23: =H23*K23*3+H23*L23*1.1-H23*M23*3 -> 25.34 | T23: M 25 - 35 | U23: =U11*RANDBETWEEN(90,105)/100 -> 0.16838118 | V23: =V11*RANDBETWEEN(80,110)/100 -> 0.19245474 | W23: =W11*RANDBETWEEN(95,115)/100 -> 0.17432833 | X23: =X11*RANDBETWEEN(98,118)/100 -> 0.21445728 | Y23: =Y11*RANDBETWEEN(90,105)/100 -> 0.32600167 | Z23: =Z11*RANDBETWEEN(90,105)/100 -> 0.20646359 | AA23: =AA11*RANDBETWEEN(90,105)/100 -> 0.36624274 | AB23: =AB11*RANDBETWEEN(90,105)/100 -> 0.19544819 | AC23: =AC11*RANDBETWEEN(90,105)/100 -> 0.22391489 | AD23: =AD11*RANDBETWEEN(90,105)/100 -> 0.24396112 | AE23: =AE11*RANDBETWEEN(90,105)/100 -> 0.31300297 | AF23: =AF11*RANDBETWEEN(90,105)/100 -> 0.11098912 | AG23: =AG11*RANDBETWEEN(90,105)/100 -> 0.22556357 | AK23: South - Metro & T1 | AL23: =AL11*RANDBETWEEN(90,105)/100 -> 0.15246064 | AM23: =AM11*RANDBETWEEN(90,105)/100 -> 0.17830495 | AN23: =AN11*RANDBETWEEN(90,105)/100 -> 0.21616814 | AO23: =AO11*RANDBETWEEN(90,105)/100 -> 0.0048463378 | AP23: =AP11*RANDBETWEEN(90,105)/100 -> 0.13227052 | AQ23: =AQ11*RANDBETWEEN(90,105)/100 -> 0.1584556 | AR23: =AR11*RANDBETWEEN(90,105)/100 -> 0.15039563 | AS23: =AS11*RANDBETWEEN(90,105)/100 -> 0.47047512 | ... AX23: =AX11*RANDBETWEEN(90,105)/100 -> 0.18726742
A24: =B24&E24 -> Manorama MaxPAID | B24: Manorama Max | C24: Malayalam,Tamil,Telugu | D24: Kerala,Tamil,Andra Pradesh | E24: PAID | F24: SVOD | H24: 0.1 | I24: 0.74 | J24: 0.26 | K24: 0.31 | L24: 0.69 | M24: 0.06 | N24: =H24*K24*3+H24*L24*1.1-H24*M24*3 -> 0.1509 | T24: M 35 + | U24: =U12*RANDBETWEEN(90,105)/100 -> 0.10125452 | V24: =V12*RANDBETWEEN(80,110)/100 -> 0.12297625 | W24: =W12*RANDBETWEEN(95,115)/100 -> 0.093268505 | X24: =X12*RANDBETWEEN(98,118)/100 -> 0.072250659 | Y24: =Y12*RANDBETWEEN(90,105)/100 -> 0.09140865 | Z24: =Z12*RANDBETWEEN(90,105)/100 -> 0.029961248 | AA24: =AA12*RANDBETWEEN(90,105)/100 -> 0.078681725 | AB24: =AB12*RANDBETWEEN(90,105)/100 -> 0.086427311 | AC24: =AC12*RANDBETWEEN(90,105)/100 -> 0.074521242 | AD24: =AD12*RANDBETWEEN(90,105)/100 -> 0.089844106 | AE24: =AE12*RANDBETWEEN(90,105)/100 -> 0.18426806 | AF24: =AF12*RANDBETWEEN(90,105)/100 -> 0.12944093 | AG24: =AG12*RANDBETWEEN(90,105)/100 -> 0.094107042 | AK24: South - T2 & beyond | AL24: =AL12*RANDBETWEEN(90,105)/100 -> 0.11569234 | AM24: =AM12*RANDBETWEEN(90,105)/100 -> 0.083580445 | AN24: =AN12*RANDBETWEEN(90,105)/100 -> 0.07724044 | AO24: =AO12*RANDBETWEEN(90,105)/100 -> 0.003502967 | AP24: =AP12*RANDBETWEEN(90,105)/100 -> 0.12183971 | AQ24: =AQ12*RANDBETWEEN(90,105)/100 -> 0.091945946 | AR24: =AR12*RANDBETWEEN(90,105)/100 -> 0.1330497 | AS24: =AS12*RANDBETWEEN(90,105)/100 -> 0.44984025 | ... AX24: =AX12*RANDBETWEEN(90,105)/100 -> 0.18465252
A25: =B25&E25 -> Amazon Mx PlayerFREE | B25: Amazon Mx Player | C25: Hindi,English,Tamil,Telugu,Malayalam,Kannada,Bengali | D25: All India | E25: FREE | F25: AVOD | H25: 72.89 | I25: 0.8 | J25: 0.2 | K25: 0.07 | L25: 0.93 | M25: 0.05 | N25: =H25*K25*3+H25*L25*1.1-H25*M25*3 -> 78.93987 | T25: F <18 | U25: =U13*RANDBETWEEN(90,105)/100 -> 0.067544954 | V25: =V13*RANDBETWEEN(80,110)/100 -> 0.048139746 | W25: =W13*RANDBETWEEN(95,115)/100 -> 0.057292344 | X25: =X13*RANDBETWEEN(98,118)/100 -> 0.048096608 | Y25: =Y13*RANDBETWEEN(90,105)/100 -> 0.027904975 | Z25: =Z13*RANDBETWEEN(90,105)/100 -> 0.083033413 | AA25: =AA13*RANDBETWEEN(90,105)/100 -> 0.038921534 | AB25: =AB13*RANDBETWEEN(90,105)/100 -> 0.16144117 | AC25: =AC13*RANDBETWEEN(90,105)/100 -> 0.13341394 | AD25: =AD13*RANDBETWEEN(90,105)/100 -> 0.17514361 | AE25: =AE13*RANDBETWEEN(90,105)/100 -> 0.045075965 | AF25: =AF13*RANDBETWEEN(90,105)/100 -> 0.045499509 | AG25: =AG13*RANDBETWEEN(90,105)/100 -> 0.068593691 | AK25: West - Metro & T1 | AL25: =AL13*RANDBETWEEN(90,105)/100 -> 0.12980766 | AM25: =AM13*RANDBETWEEN(90,105)/100 -> 0.19831697 | AN25: =AN13*RANDBETWEEN(90,105)/100 -> 0.21954851 | AO25: =AO13*RANDBETWEEN(90,105)/100 -> 0.10423641 | AP25: =AP13*RANDBETWEEN(90,105)/100 -> 0.17437609 | AQ25: =AQ13*RANDBETWEEN(90,105)/100 -> 0.20478764 | AR25: =AR13*RANDBETWEEN(90,105)/100 -> 0.168334 | AS25: =AS13*RANDBETWEEN(90,105)/100 -> 0.0053206911 | ... AX25: =AX13*RANDBETWEEN(90,105)/100 -> 0.14120487
A26: =B26&E26 -> NetflixPAID | B26: Netflix | C26: Hindi,English,Tamil,Telugu,Malayalam,Kannada,Bengali | D26: All India | E26: PAID | F26: SVOD | H26: 17.44 | I26: 0.49 | J26: 0.51 | K26: 0.58 | L26: 0.42 | M26: 0.07 | N26: =H26*K26*5+H26*L26*1.5-H26*M26*5 -> 55.4592 | T26: F 18 - 24 | U26: =U14*RANDBETWEEN(90,105)/100 -> 0.13771625 | V26: =V14*RANDBETWEEN(80,110)/100 -> 0.13368904 | W26: =W14*RANDBETWEEN(95,115)/100 -> 0.20019691 | X26: =X14*RANDBETWEEN(98,118)/100 -> 0.16951105 | Y26: =Y14*RANDBETWEEN(90,105)/100 -> 0.14750233 | Z26: =Z14*RANDBETWEEN(90,105)/100 -> 0.22797285 | AA26: =AA14*RANDBETWEEN(90,105)/100 -> 0.11233441 | AB26: =AB14*RANDBETWEEN(90,105)/100 -> 0.1099858 | AC26: =AC14*RANDBETWEEN(90,105)/100 -> 0.09173028 | AD26: =AD14*RANDBETWEEN(90,105)/100 -> 0.15611738 | AE26: =AE14*RANDBETWEEN(90,105)/100 -> 0.1071537 | AF26: =AF14*RANDBETWEEN(90,105)/100 -> 0.22254952 | AG26: =AG14*RANDBETWEEN(90,105)/100 -> 0.10003394 | AK26: West - T2 & beyond | AL26: =AL14*RANDBETWEEN(90,105)/100 -> 0.12195848 | AM26: =AM14*RANDBETWEEN(90,105)/100 -> 0.085017031 | AN26: =AN14*RANDBETWEEN(90,105)/100 -> 0.060595505 | AO26: =AO14*RANDBETWEEN(90,105)/100 -> 0.080089157 | AP26: =AP14*RANDBETWEEN(90,105)/100 -> 0.099941781 | AQ26: =AQ14*RANDBETWEEN(90,105)/100 -> 0.092355212 | AR26: =AR14*RANDBETWEEN(90,105)/100 -> 0.10033797 | AS26: =AS14*RANDBETWEEN(90,105)/100 -> 0.0010147329 | ... AX26: =AX14*RANDBETWEEN(90,105)/100 -> 0.099567535
A27: =B27&E27 -> Saina PlayPAID | B27: Saina Play | C27: Malayalam | D27: Kerala | E27: PAID | F27: SVOD | H27: 0.05 | I27: 0.7 | J27: 0.3 | K27: 0.4 | L27: 0.6 | M27: 0.04 | N27: =H27*K27*3+H27*L27*1.1-H27*M27*3 -> 0.087 | T27: F 25 - 35 | U27: =U15*RANDBETWEEN(90,105)/100 -> 0.12062845 | V27: =V15*RANDBETWEEN(80,110)/100 -> 0.18321665 | W27: =W15*RANDBETWEEN(95,115)/100 -> 0.15687818 | X27: =X15*RANDBETWEEN(98,118)/100 -> 0.10463713 | Y27: =Y15*RANDBETWEEN(90,105)/100 -> 0.21739733 | Z27: =Z15*RANDBETWEEN(90,105)/100 -> 0.17927416 | AA27: =AA15*RANDBETWEEN(90,105)/100 -> 0.066525979 | AB27: =AB15*RANDBETWEEN(90,105)/100 -> 0.11813288 | AC27: =AC15*RANDBETWEEN(90,105)/100 -> 0.10095991 | AD27: =AD15*RANDBETWEEN(90,105)/100 -> 0.090482351 | AE27: =AE15*RANDBETWEEN(90,105)/100 -> 0.080154068 | AF27: =AF15*RANDBETWEEN(90,105)/100 -> 0.083112123 | AG27: =AG15*RANDBETWEEN(90,105)/100 -> 0.12819253 | AK27: East - Metro & T1 | AL27: =AL15*RANDBETWEEN(90,105)/100 -> 0.09227141 | AM27: =AM15*RANDBETWEEN(90,105)/100 -> 0.084509116 | AN27: =AN15*RANDBETWEEN(90,105)/100 -> 0.068106451 | AO27: =AO15*RANDBETWEEN(90,105)/100 -> 0.064298999 | AP27: =AP15*RANDBETWEEN(90,105)/100 -> 0.061740734 | AQ27: =AQ15*RANDBETWEEN(90,105)/100 -> 0.08423166 | AR27: =AR15*RANDBETWEEN(90,105)/100 -> 0.06888668 | AS27: =AS15*RANDBETWEEN(90,105)/100 -> 0.00099796856 | ... AX27: =AX15*RANDBETWEEN(90,105)/100 -> 0.077504777
A28: =B28&E28 -> Shemaroo MePAID | B28: Shemaroo Me | C28: Gujarati,Hindi,Marathi | D28: Gujrat,Maharastra | E28: PAID | F28: SVOD | H28: 10 | I28: 0.75 | J28: 0.25 | K28: 0.38 | L28: 0.62 | M28: 0.08 | N28: =H28*K28*3+H28*L28*1.1-H28*M28*3 -> 15.82 | T28: F 35 + | U28: =U16*RANDBETWEEN(90,105)/100 -> 0.14216638 | V28: =V16*RANDBETWEEN(80,110)/100 -> 0.093511647 | W28: =W16*RANDBETWEEN(95,115)/100 -> 0.061728128 | X28: =X16*RANDBETWEEN(98,118)/100 -> 0.034503812 | Y28: =Y16*RANDBETWEEN(90,105)/100 -> 0.077847912 | Z28: =Z16*RANDBETWEEN(90,105)/100 -> 0.10320266 | AA28: =AA16*RANDBETWEEN(90,105)/100 -> 0.079436156 | AB28: =AB16*RANDBETWEEN(90,105)/100 -> 0.10689803 | AC28: =AC16*RANDBETWEEN(90,105)/100 -> 0.084212524 | AD28: =AD16*RANDBETWEEN(90,105)/100 -> 0.15095901 | AE28: =AE16*RANDBETWEEN(90,105)/100 -> 0.078256471 | AF28: =AF16*RANDBETWEEN(90,105)/100 -> 0.066456121 | AG28: =AG16*RANDBETWEEN(90,105)/100 -> 0.082795876 | AK28: East - T2 & beyond | AL28: =AL16*RANDBETWEEN(90,105)/100 -> 0.066794802 | AM28: =AM16*RANDBETWEEN(90,105)/100 -> 0.038485273 | AN28: =AN16*RANDBETWEEN(90,105)/100 -> 0.019184587 | AO28: =AO16*RANDBETWEEN(90,105)/100 -> 0.062396599 | AP28: =AP16*RANDBETWEEN(90,105)/100 -> 0.038851155 | AQ28: =AQ16*RANDBETWEEN(90,105)/100 -> 0.040957529 | AR28: =AR16*RANDBETWEEN(90,105)/100 -> 0.040497018 | AS28: =AS16*RANDBETWEEN(90,105)/100 -> 0.00096493304 | ... AX28: =AX16*RANDBETWEEN(90,105)/100 -> 0.046816856
A29: =B29&E29 -> Shemaroo MeFREE | B29: Shemaroo Me | C29: Gujarati,Hindi,Marathi | D29: Gujrat,Maharastra | E29: FREE | F29: AVOD | H29: 2 | I29: 0.73 | J29: 0.27 | K29: 0.38 | L29: 0.62 | M29: 0.06 | N29: =H29*K29*3+H29*L29*1.1-H29*M29*3 -> 3.284 | U29: =SUM(U21:U28) -> 0.97890893 | V29: =SUM(V21:V28) -> 0.97864594 | W29: =SUM(W21:W28) -> 1.0161744 | X29: =SUM(X21:X28) -> 1.0233034 | Y29: =SUM(Y21:Y28) -> 1.0157648 | Z29: =SUM(Z21:Z28) -> 0.98359475 | AA29: =SUM(AA21:AA28) -> 0.96346992 | AB29: =SUM(AB21:AB28) -> 0.97980088 | ... AG29: =SUM(AG21:AG28) -> 0.9932625
A30: =B30&E30 -> Sony LivPAID | B30: Sony Liv | C30: Hindi,English,Tamil,Telugu,Malayalam,Kannada,Bengali | D30: All India | E30: PAID | F30: SVOD | H30: 12.14 | I30: 0.65 | J30: 0.35 | K30: 0.44 | L30: 0.56 | M30: 0.05 | N30: =H30*K30*3+H30*L30*1.1-H30*M30*3 -> 21.68204
A31: =B31&E31 -> Sony LivFREE | B31: Sony Liv | C31: Hindi,English,Tamil,Telugu,Malayalam,Kannada,Bengali | D31: All India | E31: FREE | F31: AVOD | H31: 3 | I31: 0.66 | J31: 0.34 | K31: 0.44 | L31: 0.56 | M31: 0.06 | N31: =H31*K31*3+H31*L31*1.1-H31*M31*3 -> 5.268 | T31: Demographic Profile | U31: Jio Hotstar | V31: Amazon Prime Video | W31: Netflix | X31: Amazon MX Player | Y31: Zee5 | Z31: Sony Liv | AA31: Alt Balaji | AB31: Sun NXT | AC31: Hoichoi | AD31: Aha Video | AE31: Stage | AF31: Other OTT (Non Regional) | AG31: Other OTT (Regional)
A32: =B32&E32 -> Sun NxtPAID | B32: Sun Nxt | C32: Telugu,Tamil,Malyalam,Kannada | D32: South | E32: PAID | F32: SVOD | H32: 8.53 | I32: 0.78 | J32: 0.22 | K32: 0.28 | L32: 0.72 | M32: 0.05 | N32: =H32*K32*3+H32*L32*1.1-H32*M32*3 -> 12.64146 | T32: M <18 | U32: =U21/U$29 -> 0.10140698 | V32: =V21/V$29 -> 0.037700837 | W32: =W21/W$29 -> 0.034699327 | X32: =X21/X$29 -> 0.087814567 | Y32: =Y21/Y$29 -> 0.013294006 | Z32: =Z21/Z$29 -> 0.040278747 | AA32: =AA21/AA$29 -> 0.033213801 | AB32: =AB21/AB$29 -> 0.034678522 | ... AG32: =AG21/AG$29 -> 0.046240465
A33: =B33&E33 -> Sun NxtFREE | B33: Sun Nxt | C33: Telugu,Tamil,Malyalam,Kannada | D33: South | E33: FREE | F33: AVOD | H33: 3.4 | I33: 0.74 | J33: 0.26 | K33: 0.28 | L33: 0.72 | M33: 0.09 | N33: =H33*K33*3+H33*L33*1.1-H33*M33*3 -> 4.6308 | T33: M 18 - 24 | U33: =U22/U$29 -> 0.14500735 | V33: =V22/V$29 -> 0.17142268 | W33: =W22/W$29 -> 0.23344559 | X33: =X22/X$29 -> 0.28338215 | Y33: =Y22/Y$29 -> 0.11242595 | Z33: =Z22/Z$29 -> 0.1159714 | AA33: =AA22/AA$29 -> 0.19650523 | AB33: =AB22/AB$29 -> 0.17094234 | ... AG33: =AG22/AG$29 -> 0.24972948
A34: =B34&E34 -> TVF PlayFREE | B34: TVF Play | C34: Hindi,English | D34: All India | E34: FREE | F34: AVOD | H34: 1 | I34: 0.68 | J34: 0.32 | K34: 0.2 | L34: 0.8 | M34: 0.09 | N34: =H34*K34*3+H34*L34*1.1-H34*M34*3 -> 1.21 | T34: M 25 - 35 | U34: =U23/U$29 -> 0.17200904 | V34: =V23/V$29 -> 0.1966541 | W34: =W23/W$29 -> 0.17155355 | X34: =X23/X$29 -> 0.20957351 | Y34: =Y23/Y$29 -> 0.32094209 | Z34: =Z23/Z$29 -> 0.20990717 | AA34: =AA23/AA$29 -> 0.38012888 | AB34: =AB23/AB$29 -> 0.19947746 | ... AG34: =AG23/AG$29 -> 0.22709362
A35: =B35&E35 -> UlluPAID | B35: Ullu | C35: Hindi,Telugu,Tamil | D35: All India | E35: PAID | F35: SVOD | H35: 2.9 | I35: 0.8 | J35: 0.2 | K35: 0.27 | L35: 0.73 | M35: 0.05 | N35: =H35*K35*3+H35*L35*1.1-H35*M35*3 -> 4.2427 | T35: M 35 + | U35: =U24/U$29 -> 0.1034361 | V35: =V24/V$29 -> 0.12565959 | W35: =W24/W$29 -> 0.091783955 | X35: =X24/X$29 -> 0.070605314 | Y35: =Y24/Y$29 -> 0.089989978 | Z35: =Z24/Z$29 -> 0.030460967 | AA35: =AA24/AA$29 -> 0.081664953 | AB35: =AB24/AB$29 -> 0.088209056 | ... AG35: =AG24/AG$29 -> 0.094745389
A36: =B36&E36 -> Vr OttPAID | B36: Vr Ott | C36: Hindi,English,Tamil,Telugu | D36: Andhra Pradesh,Telangana,Tamilnadu | E36: PAID | F36: SVOD | H36: 0.05 | I36: 0.71 | J36: 0.29 | K36: 0.22 | L36: 0.78 | M36: 0.08 | N36: =H36*K36*3+H36*L36*1.1-H36*M36*3 -> 0.0639 | T36: F <18 | U36: =U25/U$29 -> 0.069000243 | V36: =V25/V$29 -> 0.049190155 | W36: =W25/W$29 -> 0.056380425 | X36: =X25/X$29 -> 0.047001317 | Y36: =Y25/Y$29 -> 0.027471887 | Z36: =Z25/Z$29 -> 0.084418316 | AA36: =AA25/AA$29 -> 0.040397248 | AB36: =AB25/AB$29 -> 0.16476937 | ... AG36: =AG25/AG$29 -> 0.069058976
A37: =B37&E37 -> STAGEPAID | B37: STAGE | C37: Haryanvi,Rajasthani | D37: HSM | E37: PAID | F37: SVOD | H37: 10.3 | I37: 0.6 | J37: 0.4 | K37: 0.11 | L37: 0.89 | M37: 0.08 | N37: =H37*K37*3+H37*L37*1.1-H37*M37*3 -> 11.0107 | T37: F 18 - 24 | U37: =U26/U$29 -> 0.14068341 | V37: =V26/V$29 -> 0.13660613 | W37: =W26/W$29 -> 0.19701038 | X37: =X26/X$29 -> 0.16565082 | Y37: =Y26/Y$29 -> 0.14521308 | Z37: =Z26/Z$29 -> 0.23177518 | AA37: =AA26/AA$29 -> 0.11659359 | AB37: =AB26/AB$29 -> 0.11225322 | ... AG37: =AG26/AG$29 -> 0.10071249
A38: =B38&E38 -> Zee5PAID | B38: Zee5 | C38: Hindi,English,Tamil,Telugu,Malayalam,Kannada,Bengali | D38: All India | E38: PAID | F38: SVOD | H38: 41.2 | I38: 0.65 | J38: 0.35 | K38: 0.3 | L38: 0.7 | M38: 0.07 | N38: =H38*K38*3+H38*L38*1.1-H38*M38*3 -> 60.152 | T38: F 25 - 35 | U38: =U27/U$29 -> 0.12322745 | V38: =V27/V$29 -> 0.18721443 | W38: =W27/W$29 -> 0.15438116 | X38: =X27/X$29 -> 0.10225426 | Y38: =Y27/Y$29 -> 0.2140233 | Z38: =Z27/Z$29 -> 0.18226425 | AA38: =AA27/AA$29 -> 0.069048319 | AB38: =AB27/AB$29 -> 0.12056825 | ... AG38: =AG27/AG$29 -> 0.12906208
A39: =B39&E39 -> Zee5RENT | B39: Zee5 | C39: Hindi,English,Tamil,Telugu,Malayalam,Kannada,Bengali | D39: All India | E39: RENT | F39: Rent | H39: 0.5 | I39: 0.75 | J39: 0.25 | K39: 0.3 | L39: 0.7 | M39: 0.09 | N39: =H39*K39*3+H39*L39*1.1-H39*M39*3 -> 0.7 | T39: F 35 + | U39: =U28/U$29 -> 0.14522943 | V39: =V28/V$29 -> 0.095552072 | W39: =W28/W$29 -> 0.060745604 | X39: =X28/X$29 -> 0.033718066 | Y39: =Y28/Y$29 -> 0.076639704 | Z39: =Z28/Z$29 -> 0.10492397 | AA39: =AA28/AA$29 -> 0.082447988 | AB39: =AB28/AB$29 -> 0.10910179 | ... AG39: =AG28/AG$29 -> 0.083357497
A40: =B40&E40 -> Zee5FREE | B40: Zee5 | C40: Hindi,English,Tamil,Telugu,Malayalam,Kannada,Bengali | D40: All India | E40: FREE | F40: AVOD | H40: 16.73 | I40: 0.68 | J40: 0.32 | K40: 0.3 | L40: 0.7 | M40: 0.07 | N40: =H40*K40*3+H40*L40*1.1-H40*M40*3 -> 24.4258
A41: =B41&E41 -> Apple TVPAID | B41: Apple TV | C41: English | D41: All India | E41: PAID | F41: SVOD | H41: 1 | I41: 0.6 | J41: 0.4 | K41: 0.41 | L41: 0.59 | M41: 0.07 | N41: =H41*K41*3+H41*L41*1.1-H41*M41*3 -> 1.669
A42: =B42&E42 -> Etv WinFREE | B42: Etv Win | C42: Malayalam,Kannada,Telugu,Hindi,Tamil | D42: Kerala | E42: FREE | F42: SVOD | H42: 0.9 | I42: 0.75 | J42: 0.25 | K42: 0.2 | L42: 0.8 | M42: 0.07 | N42: =H42*K42*3+H42*L42*1.1-H42*M42*3 -> 1.143
A43: =B43&E43 -> JioHotstarPAID | B43: JioHotstar | C43: Hindi,English,Tamil,Telugu,Malayalam,Kannada,Bengali | D43: All India | E43: PAID | F43: SVOD | H43: 88.46 | I43: 0.67 | J43: 0.33 | K43: 0.28 | L43: 0.72 | M43: 0.065 | N43: =H43*K43*3+H43*L43*1.1-H43*M43*3 -> 127.11702
A44: =B44&E44 -> Jio Hotstar SparksFREE | B44: Jio Hotstar Sparks | C44: Hindi,English,Tamil,Telugu,Malayalam,Kannada,Bengali | D44: All India | E44: FREE | F44: AVOD | H44: 41 | I44: 0.625 | J44: 0.375 | K44: 0.28 | L44: 0.72 | M44: 0.065 | N44: =H44*K44*3+H44*L44*1.1-H44*M44*3 -> 58.917
A45: =B45&E45 -> Manorama MaxFREE | B45: Manorama Max | C45: Malayalam,Tamil,Telugu | D45: Kerala,Tamil,Andra Pradesh | E45: FREE | F45: SVOD | H45: 0.1 | I45: 0.74 | J45: 0.26 | K45: 0.31 | L45: 0.69 | M45: 0.06 | N45: =H45*K45*3+H45*L45*1.1-H45*M45*3 -> 0.1509 | T45: M 35 + | U45: =U33*RANDBETWEEN(90,105)/100 -> 0.13050662 | V45: =V33*RANDBETWEEN(80,110)/100 -> 0.18856494 | W45: =W33*RANDBETWEEN(95,115)/100 -> 0.25912461 | X45: =X33*RANDBETWEEN(98,118)/100 -> 0.33439094 | Y45: =Y33*RANDBETWEEN(90,105)/100 -> 0.10230761 | Z45: =Z33*RANDBETWEEN(90,105)/100 -> 0.1078534 | AA45: =AA33*RANDBETWEEN(90,105)/100 -> 0.20633049 | AB45: =AB33*RANDBETWEEN(90,105)/100 -> 0.17778003 | AC45: =AC33*RANDBETWEEN(90,105)/100 -> 0.13534319 | AD45: =AD33*RANDBETWEEN(90,105)/100 -> 0.047357958 | AE45: =AE33*RANDBETWEEN(90,105)/100 -> 0.13108073 | AF45: =AF33*RANDBETWEEN(90,105)/100 -> 0.20508149 | AG45: =AG33*RANDBETWEEN(90,105)/100 -> 0.26221595 | AK45: South - T2 & beyond | AL45: =AL33*RANDBETWEEN(90,105)/100 -> 0 | AM45: =AM33*RANDBETWEEN(90,105)/100 -> 0 | AN45: =AN33*RANDBETWEEN(90,105)/100 -> 0 | AO45: =AO33*RANDBETWEEN(90,105)/100 -> 0 | AP45: =AP33*RANDBETWEEN(90,105)/100 -> 0 | AQ45: =AQ33*RANDBETWEEN(90,105)/100 -> 0 | AR45: =AR33*RANDBETWEEN(90,105)/100 -> 0 | AS45: =AS33*RANDBETWEEN(90,105)/100 -> 0 | ... AX45: =AX33*RANDBETWEEN(90,105)/100 -> 0

Sheet Genre Penetration
A1: GENRE | B1: Male | C1: Female | F1: GENRE | G1: Male | H1: Female | I1: 2-16 | J1: 17-24 | K1: 25-34 | L1: 35-44 | M1: 45+
A2: Action | B2: 0.7 | C2: 0.3 | F2: Action | G2: 0.7 | H2: 0.3 | I2: 0.15 | J2: 0.25 | K2: 0.3 | L2: 0.2 | M2: 0.1
A3: Action Thriller, Neo-Noir | B3: 0.7 | C3: 0.3 | F3: Action,Adventure,Comedy | G3: 0.6 | H3: 0.4 | I3: 0.1 | J3: 0.3 | K3: 0.25 | L3: 0.2 | M3: 0.15
A4: Action, Adventure | B4: 0.5 | C4: 0.5 | F4: Action,Adventure,Crime | G4: 0.65 | H4: 0.35 | I4: 0.05 | J4: 0.2 | K4: 0.35 | L4: 0.25 | M4: 0.15
A5: Action, Adventure, Comedy | B5: 0.55 | C5: 0.45 | F5: Action,Adventure,Drama | G5: 0.58 | H5: 0.42 | I5: 0.1 | J5: 0.25 | K5: 0.3 | L5: 0.2 | M5: 0.15
A6: Action, Comedy | B6: 0.55 | C6: 0.45 | F6: Action,Adventure,Fantasy | G6: 0.62 | H6: 0.38 | I6: 0.2 | J6: 0.3 | K6: 0.25 | L6: 0.15 | M6: 0.1
A7: Action, Comedy, Romance | B7: 0.6 | C7: 0.4 | F7: Action,Adventure,Sci-Fi | G7: 0.7 | H7: 0.3 | I7: 0.05 | J7: 0.2 | K7: 0.3 | L7: 0.25 | M7: 0.2
A8: Action, Comedy, Teen | B8: 0.55 | C8: 0.45 | F8: Action,Comedy,Crime | G8: 0.55 | H8: 0.45 | I8: 0.1 | J8: 0.25 | K8: 0.3 | L8: 0.2 | M8: 0.15
A9: Action, Dark Humor, Satire, Superheroes | B9: 0.6 | C9: 0.4 | F9: Action,Comedy,Drama | G9: 0.48 | H9: 0.52 | I9: 0.15 | J9: 0.3 | K9: 0.25 | L9: 0.2 | M9: 0.1
A10: Action, Drama | B10: 0.53 | C10: 0.47 | F10: Action,Comedy,Thriller | G10: 0.67 | H10: 0.33 | I10: 0.1 | J10: 0.25 | K10: 0.3 | L10: 0.2 | M10: 0.15
A11: Action, Drama, Crime | B11: 0.52 | C11: 0.48 | F11: Action,Crime | G11: 0.64 | H11: 0.36 | I11: 0.05 | J11: 0.15 | K11: 0.35 | L11: 0.3 | M11: 0.15
A12: Action, Drama, Fantasy | B12: 0.55 | C12: 0.45 | F12: Action,Crime,Drama | G12: 0.59 | H12: 0.41 | I12: 0.05 | J12: 0.2 | K12: 0.3 | L12: 0.25 | M12: 0.2
A13: Action, Drama, Social | B13: 0.55 | C13: 0.45 | F13: Action,Crime,Thriller | G13: 0.72 | H13: 0.28 | I13: 0.1 | J13: 0.2 | K13: 0.35 | L13: 0.2 | M13: 0.15
... A104: Action,Horror,Fantasy | B104: 0.5 | C104: 0.5 | F104: Mythology | G104: 0.58 | H104: 0.42 | I104: 0.05 | J104: 0.2 | K104: 0.3 | L104: 0.25 | M104: 0.2
A105: Action,horror,Thriller | B105: 0.65 | C105: 0.35
A106: Action,Mystery | B106: 0.55 | C106: 0.45
A107: Action,Mystery,Supernatural,Thriller | B107: 0.61 | C107: 0.39
A108: Action,Mystery,Thriller | B108: 0.53 | C108: 0.47
A109: Action,Patriotic,crime | B109: 0.68 | C109: 0.32
A110: Action,Political,Spy,Thriller | B110: 0.67 | C110: 0.33
A111: Action,Political,Thriller | B111: 0.67 | C111: 0.33
A112: Action,Romance | B112: 0.57 | C112: 0.43
A113: Action,Romance,Adventure,Mystery | B113: 0.59 | C113: 0.41
A114: Action,Romance,Drama | B114: 0.6 | C114: 0.4
A115: Action,Romance,Thriller | B115: 0.56 | C115: 0.44
A116: Action,Sci-Fi | B116: 0.66 | C116: 0.34
... A291: Comedy,Entertainment,Talk Show | B291: 0.4 | C291: 0.6
A292: Comedy,Event | B292: =AVERAGE(B6:B291) -> 0.5657462 | C292: =AVERAGE(C6:C291) -> 0.4342538
A293: Comedy,Family | B293: 0.58 | C293: 0.42
A294: Comedy,Family | B294: 0.55 | C294: 0.45
A295: Comedy,Family Drama | B295: 0.48 | C295: 0.52
A296: Comedy,Family,Animation | B296: 0.58 | C296: 0.42
A297: Comedy,Family,Drama | B297: 0.48 | C297: 0.52
A298: Comedy,Fantasy | B298: 0.53 | C298: 0.47
A299: Comedy,Fantasy,Horror | B299: 0.57 | C299: 0.43
A300: Comedy,Fantasy,Romance | B300: 0.55 | C300: 0.45
A301: Comedy,Horror | B301: 0.61 | C301: 0.39
A302: Comedy,Horror,Sci-Fi | B302: 0.54 | C302: 0.46
A303: Comedy,Horror,Thriller | B303: 0.655 | C303: 0.345
A304: Comedy,Kids | B304: 0.53 | C304: 0.47
... A688: Youth,Drama | B688: 0.48 | C688: 0.52

Sheet Language Penetration
A1: Type | B1: Market | C1: Hindi | D1: English | E1: English,Hindi | F1: English,Hindi,Telugu | G1: Tamil | H1: Telugu | I1: Tamil,Telugu | J1: Kannada | K1: Malayalam | L1: Kannada,Malayalam,Tamil,Telugu | M1: English,Hindi,Tamil,Telugu | N1: English,Hindi,Tamil,Telugu | O1: Marathi | P1: Gujarati | Q1: Hindi,Kannada,Malayalam,Tamil,Telugu | R1: English,Hindi,Tamil,Telugu | S1: Punjabi | T1: Bengali | U1: Bengali,Hindi,Kannada,Marathi,Tamil,Telugu | V1: Bengali,Hindi,Kannada,Malayalam,Marathi,Tamil,Telugu | W1: Bengali,Hindi,Kannada,Malayalam,Marathi,Tamil,Telugu | X1: Bengali,Hindi,Marathi,Tamil,Telugu | Y1: Kannada,Malayalam,Telugu | Z1: Bhojpuri | AA1: Haryanvi | AB1: Bangla,Bhojpuri,English,Haryanvi,Hindi,Kannada,Tamil,Telugu | AC1: Bangali,Hindi,Kannada,Malayalam,Marathi,Tamil,Telugu | AD1: Bengali,English,Hindi,Kannada,Marathi,Tamil,Telugu | AE1: Bengali,English,Hindi,Kannada,Malayalam,Tamil,Telugu | AF1: Hindi,Tamil,Telugu | AG1: Hindi,Malayalam,Tamil,Telugu | AH1: Bengali,Hindi,Marathi,Tamil,Telugu | AI1: Kannada,Malayalam,Tamil,Telugu | AJ1: Hindi,Kannada,Malayalam,Tamil,Telugu | AK1: English,Hindi,Marathi,Tamil,Telugu | AL1: English,Hindi,Kannada,Malayalam,Tamil,Telugu | AM1: English,Tamil,Telugu | AN1: Hindi,Marathi | AO1: Hindi,Tamil | AP1: Kannada,Malayalam,Tamil,Telugu,Telugu | AQ1: English,Hindi,Kannada,Tamil,Telugu | AR1: English,Gujarati,Hindi,Kannada,Malayalam,Marathi,Tamil,Telugu | AS1: Rajasthani | AT1: English,Telugu | AU1: English,Hindi,Tamil | AV1: Bengali,Bhojpuri,English,Hindi,Kannada,Marathi,Odia,Punjabi,Tamil,Telugu | AW1: Hindi,Kannada,Tamil,Telugu | AX1: Bengali,Hindi,Kannada,Marathi,Tamil,Telugu | AY1: English,Hindi,Malayalam | AZ1: Bengali,Bhojpuri,English,Haryanvi,Hindi,Kannada,Malayalam,Marathi,Tamil,Telugu | BA1: Odia | BB1: English,Hindi,Punjabi | BC1: Bengali,Hindi,Kannada,Punjabi,Tamil,Telugu | BD1: Bengali,Hindi,Kannada,Malayalam,Tamil,Telugu | BE1: Bengali,Bhojpuri,Gujarati,Haryanvi,Hindi,Kannada,Malayalam,Marathi,Odia,Rajasthani,Tamil,Telugu
A2: Metro | B2: AHMADABAD | C2: 0.07 | D2: 0.06 | E2: =AVERAGE(C2,D2) -> 0.065 | F2: =AVERAGE(C2,D2,H2) -> 0.045 | G2: 0.01 | H2: 0.005 | I2: =AVERAGE(G2,H2) -> 0.0075 | J2: 0.01 | K2: 0.01 | L2: =AVERAGE(G2,H2,J2,K2) -> 0.00875 | M2: =AVERAGE(C2,G2,H2,D2) -> 0.03625 | N2: =AVERAGE(C2,D2,G2,H2) -> 0.03625 | O2: 0.01 | P2: 0.4 | Q2: =AVERAGE(C2,K2,G2,H2,J2) -> 0.021 | R2: =AVERAGE(C2,D2,H2,G2) -> 0.03625 | S2: 0.01 | T2: 0.01 | U2: =AVERAGE(C2,G2,H2,J2,O2,T2) -> 0.019166667 | V2: =AVERAGE(C2,K2,G2,H2,J2,T2,O2) -> 0.017857143 | W2: =AVERAGE(C2,K2,G2,H2,J2,T2,O2) -> 0.017857143 | X2: =AVERAGE(C2,G2,H2,O2,T2) -> 0.021 | Y2: =AVERAGE(K2,H2,J2) -> 0.0083333333 | Z2: 0.02 | AA2: 0.01 | AB2: =AVERAGE(C2,D2,Z2,AA2,H2,G2,T2,J2) -> 0.024375 | AC2: =AVERAGE(C2,H2,G2,T2,J2,O2,K2) -> 0.017857143 | AD2: =AVERAGE(C2,D2,G2,H2,J2,T2,O2) -> 0.025 | AE2: =AVERAGE(C2,D2,H2,T2,K2,J2,G2) -> 0.025 | AF2: =AVERAGE(C2,G2,H2) -> 0.028333333 | AG2: =AVERAGE(C2,G2,H2,K2) -> 0.02375 | AH2: =AVERAGE(C2,O2,G2,T2,H2) -> 0.021 | AI2: =AVERAGE(K2,G2,H2,J2) -> 0.00875 | AJ2: =AVERAGE(C2,G2,H2,K2,J2) -> 0.021 | AK2: =AVERAGE(C2,D2,O2,G2,H2) -> 0.031 | AL2: =AVERAGE(C2,D2,G2,H2,J2,K2) -> 0.0275 | AM2: =AVERAGE(D2,G2,H2) -> 0.025 | AN2: =AVERAGE(C2,O2) -> 0.04 | AO2: =AVERAGE(C2,G2) -> 0.04 | AP2: =AVERAGE(I2,J2,K2) -> 0.0091666667 | AQ2: =AVERAGE(N2,J2) -> 0.023125 | AR2: =AVERAGE(AL2,O2,P2) -> 0.14583333 | AS2: 0.01 | AT2: =AVERAGE(D2,H2) -> 0.0325 | AU2: =AVERAGE(C2,G2,H2) -> 0.028333333 | AV2: =AVERAGE(C2,D2,G2,H2,J2,O2,T2,Z2,S2) -> 0.022777778 | AW2: 0.021 | AX2: 0.013666667 | AY2: 0.046666667
A3: Metro | B3: BANGALORE | C3: 0.02 | D3: 0.12 | E3: =AVERAGE(C3,D3) -> 0.07 | F3: =AVERAGE(C3,D3,H3) -> 0.05 | G3: 0.3 | H3: 0.01 | I3: =AVERAGE(G3,H3) -> 0.155 | J3: 0.5 | K3: 0.03 | L3: =AVERAGE(G3,H3,J3,K3) -> 0.21 | M3: =AVERAGE(C3,G3,H3,D3) -> 0.1125 | N3: =AVERAGE(C3,D3,G3,H3) -> 0.1125 | O3: 0.01 | P3: 0.01 | Q3: =AVERAGE(C3,K3,G3,H3,J3) -> 0.172 | R3: =AVERAGE(C3,D3,H3,G3) -> 0.1125 | S3: 0.01 | T3: 0.01 | U3: =AVERAGE(C3,G3,H3,J3,O3,T3) -> 0.14166667 | V3: =AVERAGE(C3,K3,G3,H3,J3,T3,O3) -> 0.12571429 | W3: =AVERAGE(C3,K3,G3,H3,J3,T3,O3) -> 0.12571429 | X3: =AVERAGE(C3,G3,H3,O3,T3) -> 0.07 | Y3: =AVERAGE(K3,H3,J3) -> 0.18 | Z3: 0.01 | AA3: 0.005 | AB3: =AVERAGE(C3,D3,Z3,AA3,H3,G3,T3,J3) -> 0.121875 | AC3: =AVERAGE(C3,H3,G3,T3,J3,O3,K3) -> 0.12571429 | AD3: =AVERAGE(C3,D3,G3,H3,J3,T3,O3) -> 0.13857143 | AE3: =AVERAGE(C3,D3,H3,T3,K3,J3,G3) -> 0.14142857 | AF3: =AVERAGE(C3,G3,H3) -> 0.11 | AG3: =AVERAGE(C3,G3,H3,K3) -> 0.09 | AH3: =AVERAGE(C3,O3,G3,T3,H3) -> 0.07 | AI3: =AVERAGE(K3,G3,H3,J3) -> 0.21 | AJ3: =AVERAGE(C3,G3,H3,K3,J3) -> 0.172 | AK3: =AVERAGE(C3,D3,O3,G3,H3) -> 0.092 | AL3: =AVERAGE(C3,D3,G3,H3,J3,K3) -> 0.16333333 | AM3: =AVERAGE(D3,G3,H3) -> 0.14333333 | AN3: =AVERAGE(C3,O3) -> 0.015 | AO3: =AVERAGE(C3,G3) -> 0.16 | AP3: =AVERAGE(I3,J3,K3) -> 0.22833333 | AQ3: =AVERAGE(N3,J3) -> 0.30625 | AR3: =AVERAGE(AL3,O3,P3) -> 0.061111111 | AS3: 0.005 | AT3: =AVERAGE(D3,H3) -> 0.065 | AU3: =AVERAGE(C3,G3,H3) -> 0.11 | AV3: =AVERAGE(C3,D3,G3,H3,J3,O3,T3,Z3,S3) -> 0.11 | AW3: 0.172 | AX3: 0.064 | AY3: 0.056666667
A4: Metro | B4: CHENNAI | C4: 0.02 | D4: 0.12 | E4: =AVERAGE(C4,D4) -> 0.07 | F4: =AVERAGE(C4,D4,H4) -> 0.05 | G4: 0.3 | H4: 0.01 | I4: =AVERAGE(G4,H4) -> 0.155 | J4: 0.02 | K4: 0.14 | L4: =AVERAGE(G4,H4,J4,K4) -> 0.1175 | M4: =AVERAGE(C4,G4,H4,D4) -> 0.1125 | N4: =AVERAGE(C4,D4,G4,H4) -> 0.1125 | O4: 0.01 | P4: 0.01 | Q4: =AVERAGE(C4,K4,G4,H4,J4) -> 0.098 | R4: =AVERAGE(C4,D4,H4,G4) -> 0.1125 | S4: 0.01 | T4: 0.01 | U4: =AVERAGE(C4,G4,H4,J4,O4,T4) -> 0.061666667 | V4: =AVERAGE(C4,K4,G4,H4,J4,T4,O4) -> 0.072857143 | W4: =AVERAGE(C4,K4,G4,H4,J4,T4,O4) -> 0.072857143 | X4: =AVERAGE(C4,G4,H4,O4,T4) -> 0.07 | Y4: =AVERAGE(K4,H4,J4) -> 0.056666667 | Z4: 0.01 | AA4: 0.005 | AB4: =AVERAGE(C4,D4,Z4,AA4,H4,G4,T4,J4) -> 0.061875 | AC4: =AVERAGE(C4,H4,G4,T4,J4,O4,K4) -> 0.072857143 | AD4: =AVERAGE(C4,D4,G4,H4,J4,T4,O4) -> 0.07 | AE4: =AVERAGE(C4,D4,H4,T4,K4,J4,G4) -> 0.088571429 | AF4: =AVERAGE(C4,G4,H4) -> 0.11 | AG4: =AVERAGE(C4,G4,H4,K4) -> 0.1175 | AH4: =AVERAGE(C4,O4,G4,T4,H4) -> 0.07 | AI4: =AVERAGE(K4,G4,H4,J4) -> 0.1175 | AJ4: =AVERAGE(C4,G4,H4,K4,J4) -> 0.098 | AK4: =AVERAGE(C4,D4,O4,G4,H4) -> 0.092 | AL4: =AVERAGE(C4,D4,G4,H4,J4,K4) -> 0.10166667 | AM4: =AVERAGE(D4,G4,H4) -> 0.14333333 | AN4: =AVERAGE(C4,O4) -> 0.015 | AO4: =AVERAGE(C4,G4) -> 0.16 | AP4: =AVERAGE(I4,J4,K4) -> 0.105 | AQ4: =AVERAGE(N4,J4) -> 0.06625 | AR4: =AVERAGE(AL4,O4,P4) -> 0.040555556 | AS4: 0.005 | AT4: =AVERAGE(D4,H4) -> 0.065 | AU4: =AVERAGE(C4,G4,H4) -> 0.11 | AV4: =AVERAGE(C4,D4,G4,H4,J4,O4,T4,Z4,S4) -> 0.056666667 | AW4: 0.098 | AX4: 0.039333333 | AY4: 0.093333333
A5: Metro | B5: DELHI | C5: 0.13 | D5: 0.15 | E5: =AVERAGE(C5,D5) -> 0.14 | F5: =AVERAGE(C5,D5,H5) -> 0.096666667 | G5: 0.01 | H5: 0.01 | I5: =AVERAGE(G5,H5) -> 0.01 | J5: 0.02 | K5: 0.02 | L5: =AVERAGE(G5,H5,J5,K5) -> 0.015 | M5: =AVERAGE(C5,G5,H5,D5) -> 0.075 | N5: =AVERAGE(C5,D5,G5,H5) -> 0.075 | O5: 0.03 | P5: 0.05 | Q5: =AVERAGE(C5,K5,G5,H5,J5) -> 0.038 | R5: =AVERAGE(C5,D5,H5,G5) -> 0.075 | S5: 0.07 | T5: 0.06 | U5: =AVERAGE(C5,G5,H5,J5,O5,T5) -> 0.043333333 | V5: =AVERAGE(C5,K5,G5,H5,J5,T5,O5) -> 0.04 | W5: =AVERAGE(C5,K5,G5,H5,J5,T5,O5) -> 0.04 | X5: =AVERAGE(C5,G5,H5,O5,T5) -> 0.048 | Y5: =AVERAGE(K5,H5,J5) -> 0.016666667 | Z5: 0.04 | AA5: 0.04 | AB5: =AVERAGE(C5,D5,Z5,AA5,H5,G5,T5,J5) -> 0.0575 | AC5: =AVERAGE(C5,H5,G5,T5,J5,O5,K5) -> 0.04 | AD5: =AVERAGE(C5,D5,G5,H5,J5,T5,O5) -> 0.058571429 | AE5: =AVERAGE(C5,D5,H5,T5,K5,J5,G5) -> 0.057142857 | AF5: =AVERAGE(C5,G5,H5) -> 0.05 | AG5: =AVERAGE(C5,G5,H5,K5) -> 0.0425 | AH5: =AVERAGE(C5,O5,G5,T5,H5) -> 0.048 | AI5: =AVERAGE(K5,G5,H5,J5) -> 0.015 | AJ5: =AVERAGE(C5,G5,H5,K5,J5) -> 0.038 | AK5: =AVERAGE(C5,D5,O5,G5,H5) -> 0.066 | AL5: =AVERAGE(C5,D5,G5,H5,J5,K5) -> 0.056666667 | AM5: =AVERAGE(D5,G5,H5) -> 0.056666667 | AN5: =AVERAGE(C5,O5) -> 0.08 | AO5: =AVERAGE(C5,G5) -> 0.07 | AP5: =AVERAGE(I5,J5,K5) -> 0.016666667 | AQ5: =AVERAGE(N5,J5) -> 0.0475 | AR5: =AVERAGE(AL5,O5,P5) -> 0.045555556 | AS5: 0.04 | AT5: =AVERAGE(D5,H5) -> 0.08 | AU5: =AVERAGE(C5,G5,H5) -> 0.05 | AV5: =AVERAGE(C5,D5,G5,H5,J5,O5,T5,Z5,S5) -> 0.057777778 | AW5: 0.038 | AX5: 0.042666667 | AY5: 0.1
A6: Metro | B6: HYDERABAD | C6: 0.02 | D6: 0.11 | E6: =AVERAGE(C6,D6) -> 0.065 | F6: =AVERAGE(C6,D6,H6) -> 0.19333333 | G6: 0.03 | H6: 0.45 | I6: =AVERAGE(G6,H6) -> 0.24 | J6: 0.03 | K6: 0.04 | L6: =AVERAGE(G6,H6,J6,K6) -> 0.1375 | M6: =AVERAGE(C6,G6,H6,D6) -> 0.1525 | N6: =AVERAGE(C6,D6,G6,H6) -> 0.1525 | O6: 0.01 | P6: 0.01 | Q6: =AVERAGE(C6,K6,G6,H6,J6) -> 0.114 | R6: =AVERAGE(C6,D6,H6,G6) -> 0.1525 | S6: 0.01 | T6: 0.01 | U6: =AVERAGE(C6,G6,H6,J6,O6,T6) -> 0.091666667 | V6: =AVERAGE(C6,K6,G6,H6,J6,T6,O6) -> 0.084285714 | W6: =AVERAGE(C6,K6,G6,H6,J6,T6,O6) -> 0.084285714 | X6: =AVERAGE(C6,G6,H6,O6,T6) -> 0.104 | Y6: =AVERAGE(K6,H6,J6) -> 0.17333333 | Z6: 0.01 | AA6: 0.005 | AB6: =AVERAGE(C6,D6,Z6,AA6,H6,G6,T6,J6) -> 0.083125 | AC6: =AVERAGE(C6,H6,G6,T6,J6,O6,K6) -> 0.084285714 | AD6: =AVERAGE(C6,D6,G6,H6,J6,T6,O6) -> 0.094285714 | AE6: =AVERAGE(C6,D6,H6,T6,K6,J6,G6) -> 0.098571429 | AF6: =AVERAGE(C6,G6,H6) -> 0.16666667 | AG6: =AVERAGE(C6,G6,H6,K6) -> 0.135 | AH6: =AVERAGE(C6,O6,G6,T6,H6) -> 0.104 | AI6: =AVERAGE(K6,G6,H6,J6) -> 0.1375 | AJ6: =AVERAGE(C6,G6,H6,K6,J6) -> 0.114 | AK6: =AVERAGE(C6,D6,O6,G6,H6) -> 0.124 | AL6: =AVERAGE(C6,D6,G6,H6,J6,K6) -> 0.11333333 | AM6: =AVERAGE(D6,G6,H6) -> 0.19666667 | AN6: =AVERAGE(C6,O6) -> 0.015 | AO6: =AVERAGE(C6,G6) -> 0.025 | AP6: =AVERAGE(I6,J6,K6) -> 0.10333333 | AQ6: =AVERAGE(N6,J6) -> 0.09125 | AR6: =AVERAGE(AL6,O6,P6) -> 0.044444444 | AS6: 0.005 | AT6: =AVERAGE(D6,H6) -> 0.28 | AU6: =AVERAGE(C6,G6,H6) -> 0.16666667 | AV6: =AVERAGE(C6,D6,G6,H6,J6,O6,T6,Z6,S6) -> 0.075555556 | AW6: 0.114 | AX6: 0.044666667 | AY6: 0.056666667
A7: Metro | B7: KOLKATA | C7: 0.05 | D7: 0.1 | E7: =AVERAGE(C7,D7) -> 0.075 | F7: =AVERAGE(C7,D7,H7) -> 0.053333333 | G7: 0.01 | H7: 0.01 | I7: =AVERAGE(G7,H7) -> 0.01 | J7: 0.01 | K7: 0.02 | L7: =AVERAGE(G7,H7,J7,K7) -> 0.0125 | M7: =AVERAGE(C7,G7,H7,D7) -> 0.0425 | N7: =AVERAGE(C7,D7,G7,H7) -> 0.0425 | O7: 0.01 | P7: 0.01 | Q7: =AVERAGE(C7,K7,G7,H7,J7) -> 0.02 | R7: =AVERAGE(C7,D7,H7,G7) -> 0.0425 | S7: 0.01 | T7: 0.58 | U7: =AVERAGE(C7,G7,H7,J7,O7,T7) -> 0.11166667 | V7: =AVERAGE(C7,K7,G7,H7,J7,T7,O7) -> 0.098571429 | W7: =AVERAGE(C7,K7,G7,H7,J7,T7,O7) -> 0.098571429 | X7: =AVERAGE(C7,G7,H7,O7,T7) -> 0.132 | Y7: =AVERAGE(K7,H7,J7) -> 0.013333333 | Z7: 0.01 | AA7: 0.005 | AB7: =AVERAGE(C7,D7,Z7,AA7,H7,G7,T7,J7) -> 0.096875 | AC7: =AVERAGE(C7,H7,G7,T7,J7,O7,K7) -> 0.098571429 | AD7: =AVERAGE(C7,D7,G7,H7,J7,T7,O7) -> 0.11 | AE7: =AVERAGE(C7,D7,H7,T7,K7,J7,G7) -> 0.11142857 | AF7: =AVERAGE(C7,G7,H7) -> 0.023333333 | AG7: =AVERAGE(C7,G7,H7,K7) -> 0.0225 | AH7: =AVERAGE(C7,O7,G7,T7,H7) -> 0.132 | AI7: =AVERAGE(K7,G7,H7,J7) -> 0.0125 | AJ7: =AVERAGE(C7,G7,H7,K7,J7) -> 0.02 | AK7: =AVERAGE(C7,D7,O7,G7,H7) -> 0.036 | AL7: =AVERAGE(C7,D7,G7,H7,J7,K7) -> 0.033333333 | AM7: =AVERAGE(D7,G7,H7) -> 0.04 | AN7: =AVERAGE(C7,O7) -> 0.03 | AO7: =AVERAGE(C7,G7) -> 0.03 | AP7: =AVERAGE(I7,J7,K7) -> 0.013333333 | AQ7: =AVERAGE(N7,J7) -> 0.02625 | AR7: =AVERAGE(AL7,O7,P7) -> 0.017777778 | AS7: 0.005 | AT7: =AVERAGE(D7,H7) -> 0.055 | AU7: =AVERAGE(C7,G7,H7) -> 0.023333333 | AV7: =AVERAGE(C7,D7,G7,H7,J7,O7,T7,Z7,S7) -> 0.087777778 | AW7: 0.02 | AX7: 0.20333333 | AY7: 0.056666667
A8: Metro | B8: MUMBAI | C8: 0.11 | D8: 0.12 | E8: =AVERAGE(C8,D8) -> 0.115 | F8: =AVERAGE(C8,D8,H8) -> 0.08 | G8: 0.01 | H8: 0.01 | I8: =AVERAGE(G8,H8) -> 0.01 | J8: 0.01 | K8: 0.03 | L8: =AVERAGE(G8,H8,J8,K8) -> 0.015 | M8: =AVERAGE(C8,G8,H8,D8) -> 0.0625 | N8: =AVERAGE(C8,D8,G8,H8) -> 0.0625 | O8: 0.45 | P8: 0.03 | Q8: =AVERAGE(C8,K8,G8,H8,J8) -> 0.034 | R8: =AVERAGE(C8,D8,H8,G8) -> 0.0625 | S8: 0.05 | T8: 0.01 | U8: =AVERAGE(C8,G8,H8,J8,O8,T8) -> 0.1 | V8: =AVERAGE(C8,K8,G8,H8,J8,T8,O8) -> 0.09 | W8: =AVERAGE(C8,K8,G8,H8,J8,T8,O8) -> 0.09 | X8: =AVERAGE(C8,G8,H8,O8,T8) -> 0.118 | Y8: =AVERAGE(K8,H8,J8) -> 0.016666667 | Z8: 0.02 | AA8: 0.01 | AB8: =AVERAGE(C8,D8,Z8,AA8,H8,G8,T8,J8) -> 0.0375 | AC8: =AVERAGE(C8,H8,G8,T8,J8,O8,K8) -> 0.09 | AD8: =AVERAGE(C8,D8,G8,H8,J8,T8,O8) -> 0.10285714 | AE8: =AVERAGE(C8,D8,H8,T8,K8,J8,G8) -> 0.042857143 | AF8: =AVERAGE(C8,G8,H8) -> 0.043333333 | AG8: =AVERAGE(C8,G8,H8,K8) -> 0.04 | AH8: =AVERAGE(C8,O8,G8,T8,H8) -> 0.118 | AI8: =AVERAGE(K8,G8,H8,J8) -> 0.015 | AJ8: =AVERAGE(C8,G8,H8,K8,J8) -> 0.034 | AK8: =AVERAGE(C8,D8,O8,G8,H8) -> 0.14 | AL8: =AVERAGE(C8,D8,G8,H8,J8,K8) -> 0.048333333 | AM8: =AVERAGE(D8,G8,H8) -> 0.046666667 | AN8: =AVERAGE(C8,O8) -> 0.28 | AO8: =AVERAGE(C8,G8) -> 0.06 | AP8: =AVERAGE(I8,J8,K8) -> 0.016666667 | AQ8: =AVERAGE(N8,J8) -> 0.03625 | AR8: =AVERAGE(AL8,O8,P8) -> 0.17611111 | AS8: 0.01 | AT8: =AVERAGE(D8,H8) -> 0.065 | AU8: =AVERAGE(C8,G8,H8) -> 0.043333333 | AV8: =AVERAGE(C8,D8,G8,H8,J8,O8,T8,Z8,S8) -> 0.087777778 | AW8: 0.034 | AX8: 0.16466667 | AY8: 0.086666667
A9: Metro | B9: PUNE | C9: 0.07 | D9: 0.07 | E9: =AVERAGE(C9,D9) -> 0.07 | F9: =AVERAGE(C9,D9,H9) -> 0.05 | G9: 0.01 | H9: 0.01 | I9: =AVERAGE(G9,H9) -> 0.01 | J9: 0.01 | K9: 0.01 | L9: =AVERAGE(G9,H9,J9,K9) -> 0.01 | M9: =AVERAGE(C9,G9,H9,D9) -> 0.04 | N9: =AVERAGE(C9,D9,G9,H9) -> 0.04 | O9: 0.2 | P9: 0.02 | Q9: =AVERAGE(C9,K9,G9,H9,J9) -> 0.022 | R9: =AVERAGE(C9,D9,H9,G9) -> 0.04 | S9: 0.02 | T9: 0.01 | U9: =AVERAGE(C9,G9,H9,J9,O9,T9) -> 0.051666667 | V9: =AVERAGE(C9,K9,G9,H9,J9,T9,O9) -> 0.045714286 | W9: =AVERAGE(C9,K9,G9,H9,J9,T9,O9) -> 0.045714286 | X9: =AVERAGE(C9,G9,H9,O9,T9) -> 0.06 | Y9: =AVERAGE(K9,H9,J9) -> 0.01 | Z9: 0.01 | AA9: 0.01 | AB9: =AVERAGE(C9,D9,Z9,AA9,H9,G9,T9,J9) -> 0.025 | AC9: =AVERAGE(C9,H9,G9,T9,J9,O9,K9) -> 0.045714286 | AD9: =AVERAGE(C9,D9,G9,H9,J9,T9,O9) -> 0.054285714 | AE9: =AVERAGE(C9,D9,H9,T9,K9,J9,G9) -> 0.027142857 | AF9: =AVERAGE(C9,G9,H9) -> 0.03 | AG9: =AVERAGE(C9,G9,H9,K9) -> 0.025 | AH9: =AVERAGE(C9,O9,G9,T9,H9) -> 0.06 | AI9: =AVERAGE(K9,G9,H9,J9) -> 0.01 | AJ9: =AVERAGE(C9,G9,H9,K9,J9) -> 0.022 | AK9: =AVERAGE(C9,D9,O9,G9,H9) -> 0.072 | AL9: =AVERAGE(C9,D9,G9,H9,J9,K9) -> 0.03 | AM9: =AVERAGE(D9,G9,H9) -> 0.03 | AN9: =AVERAGE(C9,O9) -> 0.135 | AO9: =AVERAGE(C9,G9) -> 0.04 | AP9: =AVERAGE(I9,J9,K9) -> 0.01 | AQ9: =AVERAGE(N9,J9) -> 0.025 | AR9: =AVERAGE(AL9,O9,P9) -> 0.083333333 | AS9: 0.01 | AT9: =AVERAGE(D9,H9) -> 0.04 | AU9: =AVERAGE(C9,G9,H9) -> 0.03 | AV9: =AVERAGE(C9,D9,G9,H9,J9,O9,T9,Z9,S9) -> 0.045555556 | AW9: 0.022 | AX9: 0.077333333 | AY9: 0.05
A10: ALL INDIA | B10: ALL INDIA 10-75L | C10: 0.22 | D10: 0.05 | E10: =AVERAGE(C10,D10) -> 0.135 | F10: =AVERAGE(C10,D10,H10) -> 0.17333333 | G10: 0.1 | H10: 0.25 | I10: =AVERAGE(G10,H10) -> 0.175 | J10: 0.16 | K10: 0.3 | L10: =AVERAGE(G10,H10,J10,K10) -> 0.2025 | M10: =AVERAGE(C10,G10,H10,D10) -> 0.155 | N10: =AVERAGE(C10,D10,G10,H10) -> 0.155 | O10: 0.15 | P10: 0.18 | Q10: =AVERAGE(C10,K10,G10,H10,J10) -> 0.206 | R10: =AVERAGE(C10,D10,H10,G10) -> 0.155 | S10: 0.3 | T10: 0.14 | U10: =AVERAGE(C10,G10,H10,J10,O10,T10) -> 0.17 | V10: =AVERAGE(C10,K10,G10,H10,J10,T10,O10) -> 0.18857143 | W10: =AVERAGE(C10,K10,G10,H10,J10,T10,O10) -> 0.18857143 | X10: =AVERAGE(C10,G10,H10,O10,T10) -> 0.172 | Y10: =AVERAGE(K10,H10,J10) -> 0.23666667 | Z10: 0.35 | AA10: 0.36 | AB10: =AVERAGE(C10,D10,Z10,AA10,H10,G10,T10,J10) -> 0.20375 | AC10: =AVERAGE(C10,H10,G10,T10,J10,O10,K10) -> 0.18857143 | AD10: =AVERAGE(C10,D10,G10,H10,J10,T10,O10) -> 0.15285714 | AE10: =AVERAGE(C10,D10,H10,T10,K10,J10,G10) -> 0.17428571 | AF10: =AVERAGE(C10,G10,H10) -> 0.19 | AG10: =AVERAGE(C10,G10,H10,K10) -> 0.2175 | AH10: =AVERAGE(C10,O10,G10,T10,H10) -> 0.172 | AI10: =AVERAGE(K10,G10,H10,J10) -> 0.2025 | AJ10: =AVERAGE(C10,G10,H10,K10,J10) -> 0.206 | AK10: =AVERAGE(C10,D10,O10,G10,H10) -> 0.154 | AL10: =AVERAGE(C10,D10,G10,H10,J10,K10) -> 0.18 | AM10: =AVERAGE(D10,G10,H10) -> 0.13333333 | AN10: =AVERAGE(C10,O10) -> 0.185 | AO10: =AVERAGE(C10,G10) -> 0.16 | AP10: =AVERAGE(I10,J10,K10) -> 0.21166667 | AQ10: =AVERAGE(N10,J10) -> 0.1575 | AR10: =AVERAGE(AL10,O10,P10) -> 0.17 | AS10: 0.36 | AT10: =AVERAGE(D10,H10) -> 0.15 | AU10: =AVERAGE(C10,G10,H10) -> 0.19 | AV10: =AVERAGE(C10,D10,G10,H10,J10,O10,T10,Z10,S10) -> 0.19111111 | AW10: 0.206 | AX10: 0.16533333 | AY10: 0.19
A11: ALL INDIA | B11: ALL INDIA 1-10L | C11: 0.14 | D11: 0.05 | E11: =AVERAGE(C11,D11) -> 0.095 | F11: =AVERAGE(C11,D11,H11) -> 0.11333333 | G11: 0.12 | H11: 0.15 | I11: =AVERAGE(G11,H11) -> 0.135 | J11: 0.13 | K11: 0.25 | L11: =AVERAGE(G11,H11,J11,K11) -> 0.1625 | M11: =AVERAGE(C11,G11,H11,D11) -> 0.115 | N11: =AVERAGE(C11,D11,G11,H11) -> 0.115 | O11: 0.07 | P11: 0.16 | Q11: =AVERAGE(C11,K11,G11,H11,J11) -> 0.158 | R11: =AVERAGE(C11,D11,H11,G11) -> 0.115 | S11: 0.31 | T11: 0.1 | U11: =AVERAGE(C11,G11,H11,J11,O11,T11) -> 0.11833333 | V11: =AVERAGE(C11,K11,G11,H11,J11,T11,O11) -> 0.13714286 | W11: =AVERAGE(C11,K11,G11,H11,J11,T11,O11) -> 0.13714286 | X11: =AVERAGE(C11,G11,H11,O11,T11) -> 0.116 | Y11: =AVERAGE(K11,H11,J11) -> 0.17666667 | Z11: 0.25 | AA11: 0.3 | AB11: =AVERAGE(C11,D11,Z11,AA11,H11,G11,T11,J11) -> 0.155 | AC11: =AVERAGE(C11,H11,G11,T11,J11,O11,K11) -> 0.13714286 | AD11: =AVERAGE(C11,D11,G11,H11,J11,T11,O11) -> 0.10857143 | AE11: =AVERAGE(C11,D11,H11,T11,K11,J11,G11) -> 0.13428571 | AF11: =AVERAGE(C11,G11,H11) -> 0.13666667 | AG11: =AVERAGE(C11,G11,H11,K11) -> 0.165 | AH11: =AVERAGE(C11,O11,G11,T11,H11) -> 0.116 | AI11: =AVERAGE(K11,G11,H11,J11) -> 0.1625 | AJ11: =AVERAGE(C11,G11,H11,K11,J11) -> 0.158 | AK11: =AVERAGE(C11,D11,O11,G11,H11) -> 0.106 | AL11: =AVERAGE(C11,D11,G11,H11,J11,K11) -> 0.14 | AM11: =AVERAGE(D11,G11,H11) -> 0.10666667 | AN11: =AVERAGE(C11,O11) -> 0.105 | AO11: =AVERAGE(C11,G11) -> 0.13 | AP11: =AVERAGE(I11,J11,K11) -> 0.17166667 | AQ11: =AVERAGE(N11,J11) -> 0.1225 | AR11: =AVERAGE(AL11,O11,P11) -> 0.12333333 | AS11: 0.3 | AT11: =AVERAGE(D11,H11) -> 0.1 | AU11: =AVERAGE(C11,G11,H11) -> 0.13666667 | AV11: =AVERAGE(C11,D11,G11,H11,J11,O11,T11,Z11,S11) -> 0.14666667 | AW11: 0.158 | AX11: 0.10933333 | AY11: 0.14666667
A12: ALL INDIA | B12: RURAL | C12: 0.15 | D12: 0.05 | E12: =AVERAGE(C12,D12) -> 0.1 | F12: =AVERAGE(C12,D12,H12) -> 0.095 | G12: 0.1 | H12: 0.085 | I12: =AVERAGE(G12,H12) -> 0.0925 | J12: 0.1 | K12: 0.15 | L12: =AVERAGE(G12,H12,J12,K12) -> 0.10875 | M12: =AVERAGE(C12,G12,H12,D12) -> 0.09625 | N12: =AVERAGE(C12,D12,G12,H12) -> 0.09625 | O12: 0.05 | P12: 0.12 | Q12: =AVERAGE(C12,K12,G12,H12,J12) -> 0.117 | R12: =AVERAGE(C12,D12,H12,G12) -> 0.09625 | S12: 0.2 | T12: 0.06 | U12: =AVERAGE(C12,G12,H12,J12,O12,T12) -> 0.090833333 | V12: =AVERAGE(C12,K12,G12,H12,J12,T12,O12) -> 0.099285714 | W12: =AVERAGE(C12,K12,G12,H12,J12,T12,O12) -> 0.099285714 | X12: =AVERAGE(C12,G12,H12,O12,T12) -> 0.089 | Y12: =AVERAGE(K12,H12,J12) -> 0.11166667 | Z12: 0.27 | AA12: 0.25 | AB12: =AVERAGE(C12,D12,Z12,AA12,H12,G12,T12,J12) -> 0.133125 | AC12: =AVERAGE(C12,H12,G12,T12,J12,O12,K12) -> 0.099285714 | AD12: =AVERAGE(C12,D12,G12,H12,J12,T12,O12) -> 0.085 | AE12: =AVERAGE(C12,D12,H12,T12,K12,J12,G12) -> 0.099285714 | AF12: =AVERAGE(C12,G12,H12) -> 0.11166667 | AG12: =AVERAGE(C12,G12,H12,K12) -> 0.12125 | AH12: =AVERAGE(C12,O12,G12,T12,H12) -> 0.089 | AI12: =AVERAGE(K12,G12,H12,J12) -> 0.10875 | AJ12: =AVERAGE(C12,G12,H12,K12,J12) -> 0.117 | AK12: =AVERAGE(C12,D12,O12,G12,H12) -> 0.087 | AL12: =AVERAGE(C12,D12,G12,H12,J12,K12) -> 0.10583333 | AM12: =AVERAGE(D12,G12,H12) -> 0.078333333 | AN12: =AVERAGE(C12,O12) -> 0.1 | AO12: =AVERAGE(C12,G12) -> 0.125 | AP12: =AVERAGE(I12,J12,K12) -> 0.11416667 | AQ12: =AVERAGE(N12,J12) -> 0.098125 | AR12: =AVERAGE(AL12,O12,P12) -> 0.091944444 | AS12: 0.25 | AT12: =AVERAGE(D12,H12) -> 0.0675 | AU12: =AVERAGE(C12,G12,H12) -> 0.11166667 | AV12: =AVERAGE(C12,D12,G12,H12,J12,O12,T12,Z12,S12) -> 0.11833333 | AW12: 0.117 | AX12: 0.075666667 | AY12: 0.11666667
B13: - | C13: =SUM(C2:C12) -> 1 | D13: =SUM(D2:D12) -> 1 | E13: =SUM(E2:E12) -> 1 | F13: =AVERAGE(C13,D13,H13) -> 1 | G13: =SUM(G2:G12) -> 1 | H13: =SUM(H2:H12) -> 1 | I13: =AVERAGE(G13,H13) -> 1 | J13: =SUM(J2:J12) -> 1 | K13: =SUM(K2:K12) -> 1 | L13: =AVERAGE(G13,H13,J13,K13) -> 1 | M13: =AVERAGE(C13,G13,H13,D13) -> 1 | N13: =AVERAGE(C13,D13,G13,H13) -> 1 | O13: =SUM(O2:O12) -> 1 | P13: =SUM(P2:P12) -> 1 | Q13: =AVERAGE(C13,K13,G13,H13,J13) -> 1 | R13: =AVERAGE(C13,D13,H13,G13) -> 1 | S13: =SUM(S2:S12) -> 1 | T13: =SUM(T2:T12) -> 1 | U13: =AVERAGE(C13,G13,H13,J13,O13,T13) -> 1 | V13: =AVERAGE(C13,K13,G13,H13,J13,T13,O13) -> 1 | W13: =AVERAGE(C13,K13,G13,H13,J13,T13,O13) -> 1 | X13: =AVERAGE(C13,G13,H13,O13,T13) -> 1 | Y13: =AVERAGE(K13,H13,J13) -> 1 | Z13: =SUM(Z2:Z12) -> 1 | AA13: =SUM(AA2:AA12) -> 1 | AB13: =AVERAGE(C13,D13,Z13,AA13,H13,G13,T13,J13) -> 1 | AC13: =AVERAGE(C13,H13,G13,T13,J13,O13,K13) -> 1 | AD13: =AVERAGE(C13,D13,G13,H13,J13,T13,O13) -> 1 | AE13: =AVERAGE(C13,D13,H13,T13,K13,J13,G13) -> 1 | AF13: =AVERAGE(C13,G13,H13) -> 1 | AG13: =AVERAGE(C13,G13,H13,K13) -> 1 | AH13: =AVERAGE(C13,O13,G13,T13,H13) -> 1 | AI13: =AVERAGE(K13,G13,H13,J13) -> 1 | AJ13: =AVERAGE(C13,G13,H13,K13,J13) -> 1 | AK13: =AVERAGE(C13,D13,O13,G13,H13) -> 1 | AL13: =AVERAGE(C13,D13,G13,H13,J13,K13) -> 1 | AM13: =AVERAGE(D13,G13,H13) -> 1 | AN13: =AVERAGE(C13,O13) -> 1 | AO13: =AVERAGE(C13,G13) -> 1 | AP13: =AVERAGE(I13,J13,K13) -> 1 | AQ13: =AVERAGE(N13,J13) -> 1 | AR13: =AVERAGE(AL13,O13,P13) -> 1 | AS13: =SUM(AS2:AS12) -> 1 | AT13: =AVERAGE(D13,H13) -> 1 | AU13: =AVERAGE(C13,G13,H13) -> 1 | AV13: =AVERAGE(C13,D13,G13,H13,J13,O13,T13,Z13,S13) -> 1 | AW13: 1 | AX13: 1 | AY13: 1
A14: ALL India | B14: ALL India | C14: 0.6 | D14: 0.2 | E14: 0.4 | F14: 0.3 | G14: 0.1 | H14: 0.15 | I14: =AVERAGE(G14:H14) -> 0.125 | J14: 0.1 | K14: 0.07 | L14: =AVERAGE(K14,G14,H14,J14) -> 0.105 | M14: =AVERAGE(C14,D14,G14,H14) -> 0.2625 | N14: 0.26 | O14: 0.12 | P14: 0.15 | Q14: =AVERAGE(C14,K14,G14,H14,J14) -> 0.204 | R14: =AVERAGE(C14,D14,G14,H14) -> 0.2625 | S14: 0.09 | T14: 0.1 | U14: =AVERAGE(C14,G14,H14,J14,O14,T14) -> 0.195 | V14: =AVERAGE(C14,G14,H14,K14,J14,O14,T14) -> 0.17714286 | W14: =V14 -> 0.17714286 | X14: =AVERAGE(C14,G14,H14,O14,T14) -> 0.214 | Y14: =AVERAGE(K14,H14,J14) -> 0.10666667 | Z14: 0.1 | AA14: 0.1 | AE14: =AVERAGE(C14,D14,G14,H14,J14,K14,O14,T14) -> 0.18 | AF14: =AVERAGE(C14,G14,H14) -> 0.28333333 | AG14: =AVERAGE(C14,K14,G14,H14) -> 0.23 | AJ14: 0.7 | AK14: =AVERAGE(D14,C14,O14,G14,H14) -> 0.234 | AL14: =AVERAGE(C14,D14,G14,H14,J14,K14) -> 0.20333333 | AM14: =AVERAGE(D14,G14,H14) -> 0.15 | AN14: =AVERAGE(C14,O14) -> 0.36 | AO14: =AVERAGE(C14,G14) -> 0.35 | AQ14: =AVERAGE(D14,C14,J14,G14,H14) -> 0.23 | AS14: 0.1 | AT14: =AVERAGE(D14,H14) -> 0.175 | AU14: =AVERAGE(C14,D14,G14) -> 0.3 | AW14: =AVERAGE(C14,G14,H14,J14) -> 0.2375 | AX14: =AVERAGE(C14,G14,H14,J14,T14,O14) -> 0.195 | AY14: =AVERAGE(C14,D14,K14) -> 0.29 | AZ14: =AVERAGE(T14,Z14,AA14,C14,J14,K14,O14,G14,H14) -> 0.16 | BA14: 0.06 | BB14: =AVERAGE(C14,D14,S14) -> 0.29666667 | BC14: =AVERAGE(T14,C14,J14,S14,G14,H14) -> 0.19 | BD14: =AVERAGEA(T14,C14,G14,H14,K14,J14) -> 0.18666667 | BE14: =AVERAGE(T14,Z14,P14,AA14,C14,J14,K14,O14,BA14,AS14,G14,H14) -> 0.14583333
A15: =AVERAGE(G14,K14,H14,J14) -> 0.105 | C15: 0.6 | D15: 0.2 | G15: 0.1 | H15: 0.15 | K15: 0.07 | M15: =AVERAGE(C15,D15,G15,H15) -> 0.2625 | R15: =AVERAGE(C15,D15,G15,H15) -> 0.2625 | AF15: =AVERAGE(C15,G15,H15) -> 0.28333333 | AM15: =AVERAGE(D15,G15,H15) -> 0.15 | AO15: =AVERAGE(C15,G15) -> 0.35 | AT15: =AVERAGE(D15,H15) -> 0.175 | AU15: =AVERAGE(C15,D15,G15) -> 0.3
H16: =AVERAGE(H14,G14,D14,C14) -> 0.2625
C17: 0.7 | D17: 0.5 | E17: 0.8 | F17: 0.9 | G17: 0.1 | H17: 0.15 | I17: 0.25 | J17: 0.1 | K17: 0.07 | L17: 0.4 | M17: 1 | N17: 0.8 | O17: 0.12 | P17: 0.15 | Q17: 1 | R17: 0.8 | S17: 0.09 | T17: 0.1 | U17: 1 | V17: 1 | W17: 1 | X17: 0.8 | Y17: 0.25 | Z17: 0.2 | AA17: 0.1 | AB17: 1 | AC17: 1 | AD17: 1 | AE17: 1 | AF17: 0.75 | AG17: 0.8 | AH17: 0.8 | AI17: 0.8 | AJ17: 0.8 | AK17: 0.9 | AL17: 0.85 | AM17: 0.75 | AN17: =O17+C17 -> 0.82 | AO17: 0.6 | AP17: 0.7 | AQ17: 0.8 | AR17: 0.9 | AS17: 0.1 | AT17: =AVERAGE(D17,H17) -> 0.325 | AU17: 0.48 | AV17: 1 | AW17: 0.75 | AX17: 0.85 | AY17: 0.8
R20: =AVERAGE(J14,G14) -> 0.1

Sheet Sheet1
G1: WK-45, 2025 ( 08 Nov 2025-14 Nov 2025 )
M3: Genre Weightage%
A4: Week | B4: MARKET | C4: Platform | D4: Content format | E4: PAID/FREE | F4: Show Type | G4: Shows/Live Content | H4: Language | I4: Release Date | J4: Ranking | K4: Genre | L4: Total Viewers In Mn | M4: Male | N4: Female | O4: Language Weightage % | P4: Ranking Penetration | Q4: Reach | R4: Content format % | S4: Final Reach
A5: WK-45'2025 | B5: ALL INDIA | C5: Jio hotstar | D5: SVOD Originals Shows | E5: PAID | F5: Shows | G5: Stumble | H5: English | I5: 45969 | K5: Comedy | L5: =VLOOKUP($C5&$E5,'Updated SES'!A:N,14,0) -> #N/A | M5: =VLOOKUP($K5,'Genre Penetration'!A:B,2,0)*VLOOKUP($C5&$E5,'Updated SES'!A:I,9,0) -> #N/A | N5: =VLOOKUP(K:K,'Genre Penetration'!A:C,3,0)*VLOOKUP($C5&$E5,'Updated SES'!A:J,10,0) -> #N/A | O5: =VLOOKUP($B5,'Language Penetration'!$B$1:$AY$14,MATCH('Compile data Working'!#REF!,'Language Penetration'!$B$1:$AY$1,0),0) -> #REF! | P5: =IF(ISBLANK(J5),RANDBETWEEN(1,2)&"%",IF(J5=1,RANDBETWEEN(35,40)&"%",IF(J5=2,RANDBETWEEN(30,35)&"%",IF(J5=3,RANDBETWEEN(25,30)&"%",IF(J5=4,RANDBETWEEN(20,25)&"%",IF(J5=5,RANDBETWEEN(15,20)&"%",IF(J5=6,RANDBETWEEN(10,15)&"%",IF(J5=7,RANDBETWEEN(8,10)&"%",IF(J5=8,RANDBETWEEN(6,8)&"%",IF(J5=9,RANDBETWEEN(4,6)&"%",IF(J5=10,RANDBETWEEN(2,4)&"%",""))))))))))) -> 2% | Q5: =IFERROR(L5*(M5+N5)*O5*P5,RANDBETWEEN(1,2)%*L5*(M5+N5)*O5) -> #N/A | R5: =VLOOKUP(D:D,ranking!W:X,2,0) -> 0.6 | S5: 0.14735405
A6: WK-45'2025 | B6: ALL INDIA | C6: Amazon Prime Video | D6: Theatrical Movies | E6: PAID | F6: Movies | G6: Andhadhun | H6: Hindi | I6: 45970 | K6: Crime,Mystery,Thriller | L6: =VLOOKUP($C6&$E6,'Updated SES'!A:N,14,0) -> 36.49824 | M6: =VLOOKUP($K6,'Genre Penetration'!A:B,2,0)*VLOOKUP($C6&$E6,'Updated SES'!A:I,9,0) -> 0.3016 | N6: =VLOOKUP(K:K,'Genre Penetration'!A:C,3,0)*VLOOKUP($C6&$E6,'Updated SES'!A:J,10,0) -> 0.2016 | O6: =VLOOKUP($B6,'Language Penetration'!$B$1:$AY$14,MATCH('Compile data Working'!#REF!,'Language Penetration'!$B$1:$AY$1,0),0) -> #REF! | P6: =IF(ISBLANK(J6),RANDBETWEEN(1,2)&"%",IF(J6=1,RANDBETWEEN(35,40)&"%",IF(J6=2,RANDBETWEEN(30,35)&"%",IF(J6=3,RANDBETWEEN(25,30)&"%",IF(J6=4,RANDBETWEEN(20,25)&"%",IF(J6=5,RANDBETWEEN(15,20)&"%",IF(J6=6,RANDBETWEEN(10,15)&"%",IF(J6=7,RANDBETWEEN(8,10)&"%",IF(J6=8,RANDBETWEEN(6,8)&"%",IF(J6=9,RANDBETWEEN(4,6)&"%",IF(J6=10,RANDBETWEEN(2,4)&"%",""))))))))))) -> 1% | Q6: =IFERROR(L6*(M6+N6)*O6*P6,RANDBETWEEN(1,2)%*L6*(M6+N6)*O6) -> #REF! | R6: =VLOOKUP(D:D,ranking!W:X,2,0) -> 0.7 | S6: 0.07713684
A7: WK-45'2025 | B7: ALL INDIA | C7: Amazon Prime Video | D7: Theatrical Movies | E7: PAID | F7: Movies | G7: Everything’s Going to Be Great | H7: Hindi,English,Tamil,Telugu,Marathi | I7: 45970 | K7: Comedy,Drama | L7: =VLOOKUP($C7&$E7,'Updated SES'!A:N,14,0) -> 36.49824 | M7: =VLOOKUP($K7,'Genre Penetration'!A:B,2,0)*VLOOKUP($C7&$E7,'Updated SES'!A:I,9,0) -> 0.2444 | N7: =VLOOKUP(K:K,'Genre Penetration'!A:C,3,0)*VLOOKUP($C7&$E7,'Updated SES'!A:J,10,0) -> 0.2544 | O7: 0.7 | P7: =IF(ISBLANK(J7),RANDBETWEEN(1,2)&"%",IF(J7=1,RANDBETWEEN(35,40)&"%",IF(J7=2,RANDBETWEEN(30,35)&"%",IF(J7=3,RANDBETWEEN(25,30)&"%",IF(J7=4,RANDBETWEEN(20,25)&"%",IF(J7=5,RANDBETWEEN(15,20)&"%",IF(J7=6,RANDBETWEEN(10,15)&"%",IF(J7=7,RANDBETWEEN(8,10)&"%",IF(J7=8,RANDBETWEEN(6,8)&"%",IF(J7=9,RANDBETWEEN(4,6)&"%",IF(J7=10,RANDBETWEEN(2,4)&"%",""))))))))))) -> 2% | Q7: =IFERROR(L7*(M7+N7)*O7*P7,RANDBETWEEN(1,2)%*L7*(M7+N7)*O7) -> 0.25487451 | R7: =VLOOKUP(D:D,ranking!W:X,2,0) -> 0.7 | S7: 0.17841216
A8: WK-45'2025 | B8: ALL INDIA | C8: Jio hotstar | D8: SVOD Originals Shows | E8: PAID | F8: Shows | G8: Happy’s Place Season 2 | H8: English | I8: 45970 | K8: Comedy,Drama | L8: =VLOOKUP($C8&$E8,'Updated SES'!A:N,14,0) -> #N/A | M8: =VLOOKUP($K8,'Genre Penetration'!A:B,2,0)*VLOOKUP($C8&$E8,'Updated SES'!A:I,9,0) -> #N/A | N8: =VLOOKUP(K:K,'Genre Penetration'!A:C,3,0)*VLOOKUP($C8&$E8,'Updated SES'!A:J,10,0) -> #N/A | O8: =VLOOKUP($B8,'Language Penetration'!$B$1:$AY$14,MATCH('Compile data Working'!$H6,'Language Penetration'!$B$1:$AY$1,0),0) -> #N/A | P8: =IF(ISBLANK(J8),RANDBETWEEN(1,2)&"%",IF(J8=1,RANDBETWEEN(35,40)&"%",IF(J8=2,RANDBETWEEN(30,35)&"%",IF(J8=3,RANDBETWEEN(25,30)&"%",IF(J8=4,RANDBETWEEN(20,25)&"%",IF(J8=5,RANDBETWEEN(15,20)&"%",IF(J8=6,RANDBETWEEN(10,15)&"%",IF(J8=7,RANDBETWEEN(8,10)&"%",IF(J8=8,RANDBETWEEN(6,8)&"%",IF(J8=9,RANDBETWEEN(4,6)&"%",IF(J8=10,RANDBETWEEN(2,4)&"%",""))))))))))) -> 2% | Q8: =IFERROR(L8*(M8+N8)*O8*P8,RANDBETWEEN(1,2)%*L8*(M8+N8)*O8) -> #N/A | R8: =VLOOKUP(D:D,ranking!W:X,2,0) -> 0.6 | S8: 0.1494286
A9: WK-45'2025 | B9: ALL INDIA | C9: Jio hotstar | D9: SVOD Originals Shows | E9: PAID | F9: Shows | G9: Caroline Flack: Search for the Truth | H9: English | I9: 45971 | K9: Documentary | L9: =VLOOKUP($C9&$E9,'Updated SES'!A:N,14,0) -> #N/A | M9: =VLOOKUP($K9,'Genre Penetration'!A:B,2,0)*VLOOKUP($C9&$E9,'Updated SES'!A:I,9,0) -> #N/A | N9: =VLOOKUP(K:K,'Genre Penetration'!A:C,3,0)*VLOOKUP($C9&$E9,'Updated SES'!A:J,10,0) -> #N/A | O9: =VLOOKUP($B9,'Language Penetration'!$B$1:$AY$14,MATCH('Compile data Working'!#REF!,'Language Penetration'!$B$1:$AY$1,0),0) -> #REF! | P9: =IF(ISBLANK(J9),RANDBETWEEN(1,2)&"%",IF(J9=1,RANDBETWEEN(35,40)&"%",IF(J9=2,RANDBETWEEN(30,35)&"%",IF(J9=3,RANDBETWEEN(25,30)&"%",IF(J9=4,RANDBETWEEN(20,25)&"%",IF(J9=5,RANDBETWEEN(15,20)&"%",IF(J9=6,RANDBETWEEN(10,15)&"%",IF(J9=7,RANDBETWEEN(8,10)&"%",IF(J9=8,RANDBETWEEN(6,8)&"%",IF(J9=9,RANDBETWEEN(4,6)&"%",IF(J9=10,RANDBETWEEN(2,4)&"%",""))))))))))) -> 1% | Q9: =IFERROR(L9*(M9+N9)*O9*P9,RANDBETWEEN(1,2)%*L9*(M9+N9)*O9) -> #N/A | R9: =VLOOKUP(D:D,ranking!W:X,2,0) -> 0.6 | S9: 0.14735405
A10: WK-45'2025 | B10: ALL INDIA | C10: Netflix | D10: SVOD Originals Shows | E10: PAID | F10: Shows | G10: MARINES | H10: Hindi,English | I10: 45971 | K10: Documentary | L10: =VLOOKUP($C10&$E10,'Updated SES'!A:N,14,0) -> 55.4592 | M10: =VLOOKUP($K10,'Genre Penetration'!A:B,2,0)*VLOOKUP($C10&$E10,'Updated SES'!A:I,9,0) -> 0.2205 | N10: =VLOOKUP(K:K,'Genre Penetration'!A:C,3,0)*VLOOKUP($C10&$E10,'Updated SES'!A:J,10,0) -> 0.2805 | O10: =VLOOKUP($B10,'Language Penetration'!$B$1:$AY$14,MATCH('Compile data Working'!$H7,'Language Penetration'!$B$1:$AY$1,0),0) -> 0.6 | P10: =IF(ISBLANK(J10),RANDBETWEEN(1,2)&"%",IF(J10=1,RANDBETWEEN(35,40)&"%",IF(J10=2,RANDBETWEEN(30,35)&"%",IF(J10=3,RANDBETWEEN(25,30)&"%",IF(J10=4,RANDBETWEEN(20,25)&"%",IF(J10=5,RANDBETWEEN(15,20)&"%",IF(J10=6,RANDBETWEEN(10,15)&"%",IF(J10=7,RANDBETWEEN(8,10)&"%",IF(J10=8,RANDBETWEEN(6,8)&"%",IF(J10=9,RANDBETWEEN(4,6)&"%",IF(J10=10,RANDBETWEEN(2,4)&"%",""))))))))))) -> 1% | Q10: =IFERROR(L10*(M10+N10)*O10*P10,RANDBETWEEN(1,2)%*L10*(M10+N10)*O10) -> 0.16671036 | R10: =VLOOKUP(D:D,ranking!W:X,2,0) -> 0.6 | S10: 0.13336828
A11: WK-45'2025 | B11: ALL INDIA | C11: Netflix | D11: SVOD Originals Movies | E11: PAID | F11: Movies | G11: Frankenstein: The Anatomy Lesson | H11: English | I11: 45972 | K11: Documentary | L11: =VLOOKUP($C11&$E11,'Updated SES'!A:N,14,0) -> 55.4592 | M11: =VLOOKUP($K11,'Genre Penetration'!A:B,2,0)*VLOOKUP($C11&$E11,'Updated SES'!A:I,9,0) -> 0.2205 | N11: =VLOOKUP(K:K,'Genre Penetration'!A:C,3,0)*VLOOKUP($C11&$E11,'Updated SES'!A:J,10,0) -> 0.2805 | O11: =VLOOKUP($B11,'Language Penetration'!$B$1:$AY$14,MATCH('Compile data Working'!$H8,'Language Penetration'!$B$1:$AY$1,0),0) -> #N/A | P11: =IF(ISBLANK(J11),RANDBETWEEN(1,2)&"%",IF(J11=1,RANDBETWEEN(35,40)&"%",IF(J11=2,RANDBETWEEN(30,35)&"%",IF(J11=3,RANDBETWEEN(25,30)&"%",IF(J11=4,RANDBETWEEN(20,25)&"%",IF(J11=5,RANDBETWEEN(15,20)&"%",IF(J11=6,RANDBETWEEN(10,15)&"%",IF(J11=7,RANDBETWEEN(8,10)&"%",IF(J11=8,RANDBETWEEN(6,8)&"%",IF(J11=9,RANDBETWEEN(4,6)&"%",IF(J11=10,RANDBETWEEN(2,4)&"%",""))))))))))) -> 1% | Q11: =IFERROR(L11*(M11+N11)*O11*P11,RANDBETWEEN(1,2)%*L11*(M11+N11)*O11) -> #N/A | R11: =VLOOKUP(D:D,ranking!W:X,2,0) -> 0.8 | S11: 0.044456095
A12: WK-45'2025 | B12: ALL INDIA | C12: Amazon Prime Video | D12: Theatrical Movies | E12: RENT | F12: Movies | G12: Premachi Goshta 2 | H12: Marathi | I12: 45972 | K12: Romance | L12: =VLOOKUP($C12&$E12,'Updated SES'!A:N,14,0) -> 4.689 | M12: =VLOOKUP($K12,'Genre Penetration'!A:B,2,0)*VLOOKUP($C12&$E12,'Updated SES'!A:I,9,0) -> 0.306 | N12: =VLOOKUP(K:K,'Genre Penetration'!A:C,3,0)*VLOOKUP($C12&$E12,'Updated SES'!A:J,10,0) -> 0.176 | O12: =VLOOKUP($B12,'Language Penetration'!$B$1:$AY$14,MATCH('Compile data Working'!#REF!,'Language Penetration'!$B$1:$AY$1,0),0) -> #REF! | P12: =IF(ISBLANK(J12),RANDBETWEEN(1,2)&"%",IF(J12=1,RANDBETWEEN(35,40)&"%",IF(J12=2,RANDBETWEEN(30,35)&"%",IF(J12=3,RANDBETWEEN(25,30)&"%",IF(J12=4,RANDBETWEEN(20,25)&"%",IF(J12=5,RANDBETWEEN(15,20)&"%",IF(J12=6,RANDBETWEEN(10,15)&"%",IF(J12=7,RANDBETWEEN(8,10)&"%",IF(J12=8,RANDBETWEEN(6,8)&"%",IF(J12=9,RANDBETWEEN(4,6)&"%",IF(J12=10,RANDBETWEEN(2,4)&"%",""))))))))))) -> 1% | Q12: =IFERROR(L12*(M12+N12)*O12*P12,RANDBETWEEN(1,2)%*L12*(M12+N12)*O12) -> #REF! | R12: =VLOOKUP(D:D,ranking!W:X,2,0) -> 0.7 | S12: 0.0037969646
A13: WK-45'2025 | B13: ALL INDIA | C13: Amazon Prime Video | D13: Theatrical Movies | E13: PAID | F13: Movies | G13: 35-Chinna Katha Kaadu | H13: Telugu | I13: 45973 | K13: Comedy | L13: =VLOOKUP($C13&$E13,'Updated SES'!A:N,14,0) -> 36.49824 | M13: =VLOOKUP($K13,'Genre Penetration'!A:B,2,0)*VLOOKUP($C13&$E13,'Updated SES'!A:I,9,0) -> 0.234 | N13: =VLOOKUP(K:K,'Genre Penetration'!A:C,3,0)*VLOOKUP($C13&$E13,'Updated SES'!A:J,10,0) -> 0.264 | O13: =VLOOKUP($B13,'Language Penetration'!$B$1:$AY$14,MATCH('Compile data Working'!#REF!,'Language Penetration'!$B$1:$AY$1,0),0) -> #REF! | P13: =IF(ISBLANK(J13),RANDBETWEEN(1,2)&"%",IF(J13=1,RANDBETWEEN(35,40)&"%",IF(J13=2,RANDBETWEEN(30,35)&"%",IF(J13=3,RANDBETWEEN(25,30)&"%",IF(J13=4,RANDBETWEEN(20,25)&"%",IF(J13=5,RANDBETWEEN(15,20)&"%",IF(J13=6,RANDBETWEEN(10,15)&"%",IF(J13=7,RANDBETWEEN(8,10)&"%",IF(J13=8,RANDBETWEEN(6,8)&"%",IF(J13=9,RANDBETWEEN(4,6)&"%",IF(J13=10,RANDBETWEEN(2,4)&"%",""))))))))))) -> 1% | Q13: =IFERROR(L13*(M13+N13)*O13*P13,RANDBETWEEN(1,2)%*L13*(M13+N13)*O13) -> #REF! | R13: =VLOOKUP(D:D,ranking!W:X,2,0) -> 0.7 | S13: 0.01908493
